Compiled from "Simple.java"
public class Simple {
  public Simple();
    Code:
       0: aload_0       
       1: invokespecial #1                  // Method java/lang/Object."<init>":()V
       4: getstatic     #2                  // Field enerj/rt/PrecisionRuntimeRoot.impl:Lenerj/rt/PrecisionRuntime;
       7: aload_0       
       8: invokeinterface #3,  2            // InterfaceMethod enerj/rt/PrecisionRuntime.enterConstructor:(Ljava/lang/Object;)Z
      13: pop           
      14: return        

  public static void main(java.lang.String[]);
    Code:
       0: new           #4                  // class enerj/rt/Reference
       3: dup           
       4: aload_0       
       5: iconst_0      
       6: iconst_0      
       7: invokespecial #5                  // Method enerj/rt/Reference."<init>":(Ljava/lang/Object;ZZ)V
      10: astore_1      
      11: new           #4                  // class enerj/rt/Reference
      14: dup           
      15: aconst_null   
      16: iconst_1      
      17: iconst_1      
      18: invokespecial #5                  // Method enerj/rt/Reference."<init>":(Ljava/lang/Object;ZZ)V
      21: astore_3      
      22: return        
}
