Compiled from "Intersection.java"
public class com.jme.intersection.Intersection {
  public static double EPSILON;

  public com.jme.intersection.Intersection();
    Code:
       0: aload_0       
       1: invokespecial #1                  // Method java/lang/Object."<init>":()V
       4: getstatic     #2                  // Field enerj/rt/PrecisionRuntimeRoot.impl:Lenerj/rt/PrecisionRuntime;
       7: aload_0       
       8: invokeinterface #3,  2            // InterfaceMethod enerj/rt/PrecisionRuntime.enterConstructor:(Ljava/lang/Object;)Z
      13: pop           
      14: return        

  public static boolean intersection(com.jme.math.Vector3f, com.jme.math.Vector3f, com.jme.math.Vector3f, com.jme.math.Vector3f, com.jme.math.Vector3f, com.jme.math.Vector3f);
    Code:
       0: new           #21                 // class enerj/rt/Reference
       3: dup           
       4: aload         5
       6: iconst_0      
       7: iconst_0      
       8: invokespecial #22                 // Method enerj/rt/Reference."<init>":(Ljava/lang/Object;ZZ)V
      11: astore        6
      13: new           #21                 // class enerj/rt/Reference
      16: dup           
      17: aload         4
      19: iconst_0      
      20: iconst_0      
      21: invokespecial #22                 // Method enerj/rt/Reference."<init>":(Ljava/lang/Object;ZZ)V
      24: astore        7
      26: new           #21                 // class enerj/rt/Reference
      29: dup           
      30: aload_3       
      31: iconst_0      
      32: iconst_0      
      33: invokespecial #22                 // Method enerj/rt/Reference."<init>":(Ljava/lang/Object;ZZ)V
      36: astore        8
      38: new           #21                 // class enerj/rt/Reference
      41: dup           
      42: aload_2       
      43: iconst_0      
      44: iconst_0      
      45: invokespecial #22                 // Method enerj/rt/Reference."<init>":(Ljava/lang/Object;ZZ)V
      48: astore        9
      50: new           #21                 // class enerj/rt/Reference
      53: dup           
      54: aload_1       
      55: iconst_0      
      56: iconst_0      
      57: invokespecial #22                 // Method enerj/rt/Reference."<init>":(Ljava/lang/Object;ZZ)V
      60: astore        10
      62: new           #21                 // class enerj/rt/Reference
      65: dup           
      66: aload_0       
      67: iconst_0      
      68: iconst_0      
      69: invokespecial #22                 // Method enerj/rt/Reference."<init>":(Ljava/lang/Object;ZZ)V
      72: astore        11
      74: getstatic     #2                  // Field enerj/rt/PrecisionRuntimeRoot.impl:Lenerj/rt/PrecisionRuntime;
      77: getstatic     #2                  // Field enerj/rt/PrecisionRuntimeRoot.impl:Lenerj/rt/PrecisionRuntime;
      80: ldc_w         #5                  // class com/jme/intersection/Intersection
      83: ldc           #23                 // String tempVa
      85: iconst_1      
      86: invokeinterface #24,  4           // InterfaceMethod enerj/rt/PrecisionRuntime.loadField:(Ljava/lang/Object;Ljava/lang/String;Z)Ljava/lang/Object;
      91: iconst_0      
      92: getstatic     #25                 // Field enerj/rt/PrecisionRuntime$MemKind.VARIABLE:Lenerj/rt/PrecisionRuntime$MemKind;
      95: invokeinterface #26,  4           // InterfaceMethod enerj/rt/PrecisionRuntime.storeValue:(Ljava/lang/Object;ZLenerj/rt/PrecisionRuntime$MemKind;)Ljava/lang/Object;
     100: checkcast     #9                  // class com/jme/math/Vector3f
     103: astore        12
     105: new           #21                 // class enerj/rt/Reference
     108: dup           
     109: aload         12
     111: iconst_0      
     112: iconst_0      
     113: invokespecial #22                 // Method enerj/rt/Reference."<init>":(Ljava/lang/Object;ZZ)V
     116: astore        13
     118: getstatic     #2                  // Field enerj/rt/PrecisionRuntimeRoot.impl:Lenerj/rt/PrecisionRuntime;
     121: getstatic     #2                  // Field enerj/rt/PrecisionRuntimeRoot.impl:Lenerj/rt/PrecisionRuntime;
     124: ldc_w         #5                  // class com/jme/intersection/Intersection
     127: ldc           #27                 // String tempVb
     129: iconst_1      
     130: invokeinterface #24,  4           // InterfaceMethod enerj/rt/PrecisionRuntime.loadField:(Ljava/lang/Object;Ljava/lang/String;Z)Ljava/lang/Object;
     135: iconst_0      
     136: getstatic     #25                 // Field enerj/rt/PrecisionRuntime$MemKind.VARIABLE:Lenerj/rt/PrecisionRuntime$MemKind;
     139: invokeinterface #26,  4           // InterfaceMethod enerj/rt/PrecisionRuntime.storeValue:(Ljava/lang/Object;ZLenerj/rt/PrecisionRuntime$MemKind;)Ljava/lang/Object;
     144: checkcast     #9                  // class com/jme/math/Vector3f
     147: astore        14
     149: new           #21                 // class enerj/rt/Reference
     152: dup           
     153: aload         14
     155: iconst_0      
     156: iconst_0      
     157: invokespecial #22                 // Method enerj/rt/Reference."<init>":(Ljava/lang/Object;ZZ)V
     160: astore        15
     162: getstatic     #2                  // Field enerj/rt/PrecisionRuntimeRoot.impl:Lenerj/rt/PrecisionRuntime;
     165: getstatic     #2                  // Field enerj/rt/PrecisionRuntimeRoot.impl:Lenerj/rt/PrecisionRuntime;
     168: ldc_w         #5                  // class com/jme/intersection/Intersection
     171: ldc           #6                  // String tempVc
     173: iconst_1      
     174: invokeinterface #24,  4           // InterfaceMethod enerj/rt/PrecisionRuntime.loadField:(Ljava/lang/Object;Ljava/lang/String;Z)Ljava/lang/Object;
     179: iconst_0      
     180: getstatic     #25                 // Field enerj/rt/PrecisionRuntime$MemKind.VARIABLE:Lenerj/rt/PrecisionRuntime$MemKind;
     183: invokeinterface #26,  4           // InterfaceMethod enerj/rt/PrecisionRuntime.storeValue:(Ljava/lang/Object;ZLenerj/rt/PrecisionRuntime$MemKind;)Ljava/lang/Object;
     188: checkcast     #9                  // class com/jme/math/Vector3f
     191: astore        16
     193: new           #21                 // class enerj/rt/Reference
     196: dup           
     197: aload         16
     199: iconst_0      
     200: iconst_0      
     201: invokespecial #22                 // Method enerj/rt/Reference."<init>":(Ljava/lang/Object;ZZ)V
     204: astore        17
     206: getstatic     #2                  // Field enerj/rt/PrecisionRuntimeRoot.impl:Lenerj/rt/PrecisionRuntime;
     209: getstatic     #2                  // Field enerj/rt/PrecisionRuntimeRoot.impl:Lenerj/rt/PrecisionRuntime;
     212: ldc_w         #5                  // class com/jme/intersection/Intersection
     215: ldc           #13                 // String tempVd
     217: iconst_1      
     218: invokeinterface #24,  4           // InterfaceMethod enerj/rt/PrecisionRuntime.loadField:(Ljava/lang/Object;Ljava/lang/String;Z)Ljava/lang/Object;
     223: iconst_0      
     224: getstatic     #25                 // Field enerj/rt/PrecisionRuntime$MemKind.VARIABLE:Lenerj/rt/PrecisionRuntime$MemKind;
     227: invokeinterface #26,  4           // InterfaceMethod enerj/rt/PrecisionRuntime.storeValue:(Ljava/lang/Object;ZLenerj/rt/PrecisionRuntime$MemKind;)Ljava/lang/Object;
     232: checkcast     #9                  // class com/jme/math/Vector3f
     235: astore        18
     237: new           #21                 // class enerj/rt/Reference
     240: dup           
     241: aload         18
     243: iconst_0      
     244: iconst_0      
     245: invokespecial #22                 // Method enerj/rt/Reference."<init>":(Ljava/lang/Object;ZZ)V
     248: astore        19
     250: new           #21                 // class enerj/rt/Reference
     253: dup           
     254: aconst_null   
     255: iconst_0      
     256: iconst_1      
     257: invokespecial #22                 // Method enerj/rt/Reference."<init>":(Ljava/lang/Object;ZZ)V
     260: astore        21
     262: new           #21                 // class enerj/rt/Reference
     265: dup           
     266: aconst_null   
     267: iconst_0      
     268: iconst_1      
     269: invokespecial #22                 // Method enerj/rt/Reference."<init>":(Ljava/lang/Object;ZZ)V
     272: astore        23
     274: new           #21                 // class enerj/rt/Reference
     277: dup           
     278: aconst_null   
     279: iconst_0      
     280: iconst_1      
     281: invokespecial #22                 // Method enerj/rt/Reference."<init>":(Ljava/lang/Object;ZZ)V
     284: astore        25
     286: new           #21                 // class enerj/rt/Reference
     289: dup           
     290: aconst_null   
     291: iconst_0      
     292: iconst_1      
     293: invokespecial #22                 // Method enerj/rt/Reference."<init>":(Ljava/lang/Object;ZZ)V
     296: astore        27
     298: new           #21                 // class enerj/rt/Reference
     301: dup           
     302: aconst_null   
     303: iconst_0      
     304: iconst_1      
     305: invokespecial #22                 // Method enerj/rt/Reference."<init>":(Ljava/lang/Object;ZZ)V
     308: astore        29
     310: new           #21                 // class enerj/rt/Reference
     313: dup           
     314: aconst_null   
     315: iconst_0      
     316: iconst_1      
     317: invokespecial #22                 // Method enerj/rt/Reference."<init>":(Ljava/lang/Object;ZZ)V
     320: astore        31
     322: new           #21                 // class enerj/rt/Reference
     325: dup           
     326: aconst_null   
     327: iconst_0      
     328: iconst_1      
     329: invokespecial #22                 // Method enerj/rt/Reference."<init>":(Ljava/lang/Object;ZZ)V
     332: astore        33
     334: new           #21                 // class enerj/rt/Reference
     337: dup           
     338: aconst_null   
     339: iconst_0      
     340: iconst_1      
     341: invokespecial #22                 // Method enerj/rt/Reference."<init>":(Ljava/lang/Object;ZZ)V
     344: astore        35
     346: getstatic     #2                  // Field enerj/rt/PrecisionRuntimeRoot.impl:Lenerj/rt/PrecisionRuntime;
     349: getstatic     #2                  // Field enerj/rt/PrecisionRuntimeRoot.impl:Lenerj/rt/PrecisionRuntime;
     352: ldc_w         #5                  // class com/jme/intersection/Intersection
     355: ldc           #15                 // String tempVe
     357: iconst_1      
     358: invokeinterface #24,  4           // InterfaceMethod enerj/rt/PrecisionRuntime.loadField:(Ljava/lang/Object;Ljava/lang/String;Z)Ljava/lang/Object;
     363: iconst_0      
     364: getstatic     #25                 // Field enerj/rt/PrecisionRuntime$MemKind.VARIABLE:Lenerj/rt/PrecisionRuntime$MemKind;
     367: invokeinterface #26,  4           // InterfaceMethod enerj/rt/PrecisionRuntime.storeValue:(Ljava/lang/Object;ZLenerj/rt/PrecisionRuntime$MemKind;)Ljava/lang/Object;
     372: checkcast     #9                  // class com/jme/math/Vector3f
     375: astore        36
     377: new           #21                 // class enerj/rt/Reference
     380: dup           
     381: aload         36
     383: iconst_0      
     384: iconst_0      
     385: invokespecial #22                 // Method enerj/rt/Reference."<init>":(Ljava/lang/Object;ZZ)V
     388: astore        37
     390: getstatic     #2                  // Field enerj/rt/PrecisionRuntimeRoot.impl:Lenerj/rt/PrecisionRuntime;
     393: getstatic     #2                  // Field enerj/rt/PrecisionRuntimeRoot.impl:Lenerj/rt/PrecisionRuntime;
     396: ldc_w         #5                  // class com/jme/intersection/Intersection
     399: ldc           #17                 // String tempFa
     401: iconst_0      
     402: invokeinterface #24,  4           // InterfaceMethod enerj/rt/PrecisionRuntime.loadField:(Ljava/lang/Object;Ljava/lang/String;Z)Ljava/lang/Object;
     407: iconst_0      
     408: getstatic     #25                 // Field enerj/rt/PrecisionRuntime$MemKind.VARIABLE:Lenerj/rt/PrecisionRuntime$MemKind;
     411: invokeinterface #26,  4           // InterfaceMethod enerj/rt/PrecisionRuntime.storeValue:(Ljava/lang/Object;ZLenerj/rt/PrecisionRuntime$MemKind;)Ljava/lang/Object;
     416: checkcast     #19                 // class "[F"
     419: checkcast     #19                 // class "[F"
     422: astore        38
     424: new           #21                 // class enerj/rt/Reference
     427: dup           
     428: aload         38
     430: iconst_0      
     431: iconst_0      
     432: invokespecial #22                 // Method enerj/rt/Reference."<init>":(Ljava/lang/Object;ZZ)V
     435: astore        39
     437: getstatic     #2                  // Field enerj/rt/PrecisionRuntimeRoot.impl:Lenerj/rt/PrecisionRuntime;
     440: getstatic     #2                  // Field enerj/rt/PrecisionRuntimeRoot.impl:Lenerj/rt/PrecisionRuntime;
     443: ldc_w         #5                  // class com/jme/intersection/Intersection
     446: ldc           #20                 // String tempFb
     448: iconst_0      
     449: invokeinterface #24,  4           // InterfaceMethod enerj/rt/PrecisionRuntime.loadField:(Ljava/lang/Object;Ljava/lang/String;Z)Ljava/lang/Object;
     454: iconst_0      
     455: getstatic     #25                 // Field enerj/rt/PrecisionRuntime$MemKind.VARIABLE:Lenerj/rt/PrecisionRuntime$MemKind;
     458: invokeinterface #26,  4           // InterfaceMethod enerj/rt/PrecisionRuntime.storeValue:(Ljava/lang/Object;ZLenerj/rt/PrecisionRuntime$MemKind;)Ljava/lang/Object;
     463: checkcast     #19                 // class "[F"
     466: checkcast     #19                 // class "[F"
     469: astore        40
     471: new           #21                 // class enerj/rt/Reference
     474: dup           
     475: aload         40
     477: iconst_0      
     478: iconst_0      
     479: invokespecial #22                 // Method enerj/rt/Reference."<init>":(Ljava/lang/Object;ZZ)V
     482: astore        41
     484: new           #21                 // class enerj/rt/Reference
     487: dup           
     488: aconst_null   
     489: iconst_0      
     490: iconst_1      
     491: invokespecial #22                 // Method enerj/rt/Reference."<init>":(Ljava/lang/Object;ZZ)V
     494: astore        43
     496: new           #21                 // class enerj/rt/Reference
     499: dup           
     500: aconst_null   
     501: iconst_0      
     502: iconst_1      
     503: invokespecial #22                 // Method enerj/rt/Reference."<init>":(Ljava/lang/Object;ZZ)V
     506: astore        45
     508: new           #21                 // class enerj/rt/Reference
     511: dup           
     512: aconst_null   
     513: iconst_0      
     514: iconst_1      
     515: invokespecial #22                 // Method enerj/rt/Reference."<init>":(Ljava/lang/Object;ZZ)V
     518: astore        47
     520: new           #21                 // class enerj/rt/Reference
     523: dup           
     524: aconst_null   
     525: iconst_0      
     526: iconst_1      
     527: invokespecial #22                 // Method enerj/rt/Reference."<init>":(Ljava/lang/Object;ZZ)V
     530: astore        49
     532: new           #21                 // class enerj/rt/Reference
     535: dup           
     536: aconst_null   
     537: iconst_0      
     538: iconst_1      
     539: invokespecial #22                 // Method enerj/rt/Reference."<init>":(Ljava/lang/Object;ZZ)V
     542: astore        51
     544: new           #21                 // class enerj/rt/Reference
     547: dup           
     548: aconst_null   
     549: iconst_0      
     550: iconst_1      
     551: invokespecial #22                 // Method enerj/rt/Reference."<init>":(Ljava/lang/Object;ZZ)V
     554: astore        53
     556: new           #21                 // class enerj/rt/Reference
     559: dup           
     560: aconst_null   
     561: iconst_0      
     562: iconst_1      
     563: invokespecial #22                 // Method enerj/rt/Reference."<init>":(Ljava/lang/Object;ZZ)V
     566: astore        55
     568: new           #21                 // class enerj/rt/Reference
     571: dup           
     572: aconst_null   
     573: iconst_0      
     574: iconst_1      
     575: invokespecial #22                 // Method enerj/rt/Reference."<init>":(Ljava/lang/Object;ZZ)V
     578: astore        57
     580: new           #21                 // class enerj/rt/Reference
     583: dup           
     584: aconst_null   
     585: iconst_0      
     586: iconst_1      
     587: invokespecial #22                 // Method enerj/rt/Reference."<init>":(Ljava/lang/Object;ZZ)V
     590: astore        59
     592: new           #21                 // class enerj/rt/Reference
     595: dup           
     596: aconst_null   
     597: iconst_0      
     598: iconst_1      
     599: invokespecial #22                 // Method enerj/rt/Reference."<init>":(Ljava/lang/Object;ZZ)V
     602: astore        61
     604: new           #21                 // class enerj/rt/Reference
     607: dup           
     608: aconst_null   
     609: iconst_0      
     610: iconst_1      
     611: invokespecial #22                 // Method enerj/rt/Reference."<init>":(Ljava/lang/Object;ZZ)V
     614: astore        63
     616: new           #21                 // class enerj/rt/Reference
     619: dup           
     620: aconst_null   
     621: iconst_0      
     622: iconst_1      
     623: invokespecial #22                 // Method enerj/rt/Reference."<init>":(Ljava/lang/Object;ZZ)V
     626: astore        65
     628: new           #21                 // class enerj/rt/Reference
     631: dup           
     632: aconst_null   
     633: iconst_0      
     634: iconst_1      
     635: invokespecial #22                 // Method enerj/rt/Reference."<init>":(Ljava/lang/Object;ZZ)V
     638: astore        67
     640: new           #21                 // class enerj/rt/Reference
     643: dup           
     644: aconst_null   
     645: iconst_0      
     646: iconst_1      
     647: invokespecial #22                 // Method enerj/rt/Reference."<init>":(Ljava/lang/Object;ZZ)V
     650: astore        69
     652: new           #21                 // class enerj/rt/Reference
     655: dup           
     656: aconst_null   
     657: iconst_0      
     658: iconst_1      
     659: invokespecial #22                 // Method enerj/rt/Reference."<init>":(Ljava/lang/Object;ZZ)V
     662: astore        71
     664: new           #21                 // class enerj/rt/Reference
     667: dup           
     668: aconst_null   
     669: iconst_0      
     670: iconst_1      
     671: invokespecial #22                 // Method enerj/rt/Reference."<init>":(Ljava/lang/Object;ZZ)V
     674: astore        73
     676: new           #21                 // class enerj/rt/Reference
     679: dup           
     680: aconst_null   
     681: iconst_0      
     682: iconst_1      
     683: invokespecial #22                 // Method enerj/rt/Reference."<init>":(Ljava/lang/Object;ZZ)V
     686: astore        75
     688: new           #21                 // class enerj/rt/Reference
     691: dup           
     692: aconst_null   
     693: iconst_0      
     694: iconst_1      
     695: invokespecial #22                 // Method enerj/rt/Reference."<init>":(Ljava/lang/Object;ZZ)V
     698: astore        77
     700: getstatic     #2                  // Field enerj/rt/PrecisionRuntimeRoot.impl:Lenerj/rt/PrecisionRuntime;
     703: aload         10
     705: iconst_1      
     706: invokeinterface #28,  3           // InterfaceMethod enerj/rt/PrecisionRuntime.loadLocal:(Lenerj/rt/Reference;Z)Ljava/lang/Object;
     711: checkcast     #9                  // class com/jme/math/Vector3f
     714: getstatic     #2                  // Field enerj/rt/PrecisionRuntimeRoot.impl:Lenerj/rt/PrecisionRuntime;
     717: aload         11
     719: iconst_1      
     720: invokeinterface #28,  3           // InterfaceMethod enerj/rt/PrecisionRuntime.loadLocal:(Lenerj/rt/Reference;Z)Ljava/lang/Object;
     725: checkcast     #9                  // class com/jme/math/Vector3f
     728: getstatic     #2                  // Field enerj/rt/PrecisionRuntimeRoot.impl:Lenerj/rt/PrecisionRuntime;
     731: aload         13
     733: iconst_1      
     734: invokeinterface #28,  3           // InterfaceMethod enerj/rt/PrecisionRuntime.loadLocal:(Lenerj/rt/Reference;Z)Ljava/lang/Object;
     739: checkcast     #9                  // class com/jme/math/Vector3f
     742: invokevirtual #29                 // Method com/jme/math/Vector3f.subtract:(Lcom/jme/math/Vector3f;Lcom/jme/math/Vector3f;)Lcom/jme/math/Vector3f;
     745: pop           
     746: getstatic     #2                  // Field enerj/rt/PrecisionRuntimeRoot.impl:Lenerj/rt/PrecisionRuntime;
     749: aload         9
     751: iconst_1      
     752: invokeinterface #28,  3           // InterfaceMethod enerj/rt/PrecisionRuntime.loadLocal:(Lenerj/rt/Reference;Z)Ljava/lang/Object;
     757: checkcast     #9                  // class com/jme/math/Vector3f
     760: getstatic     #2                  // Field enerj/rt/PrecisionRuntimeRoot.impl:Lenerj/rt/PrecisionRuntime;
     763: aload         11
     765: iconst_1      
     766: invokeinterface #28,  3           // InterfaceMethod enerj/rt/PrecisionRuntime.loadLocal:(Lenerj/rt/Reference;Z)Ljava/lang/Object;
     771: checkcast     #9                  // class com/jme/math/Vector3f
     774: getstatic     #2                  // Field enerj/rt/PrecisionRuntimeRoot.impl:Lenerj/rt/PrecisionRuntime;
     777: aload         15
     779: iconst_1      
     780: invokeinterface #28,  3           // InterfaceMethod enerj/rt/PrecisionRuntime.loadLocal:(Lenerj/rt/Reference;Z)Ljava/lang/Object;
     785: checkcast     #9                  // class com/jme/math/Vector3f
     788: invokevirtual #29                 // Method com/jme/math/Vector3f.subtract:(Lcom/jme/math/Vector3f;Lcom/jme/math/Vector3f;)Lcom/jme/math/Vector3f;
     791: pop           
     792: getstatic     #2                  // Field enerj/rt/PrecisionRuntimeRoot.impl:Lenerj/rt/PrecisionRuntime;
     795: aload         13
     797: iconst_1      
     798: invokeinterface #28,  3           // InterfaceMethod enerj/rt/PrecisionRuntime.loadLocal:(Lenerj/rt/Reference;Z)Ljava/lang/Object;
     803: checkcast     #9                  // class com/jme/math/Vector3f
     806: getstatic     #2                  // Field enerj/rt/PrecisionRuntimeRoot.impl:Lenerj/rt/PrecisionRuntime;
     809: aload         15
     811: iconst_1      
     812: invokeinterface #28,  3           // InterfaceMethod enerj/rt/PrecisionRuntime.loadLocal:(Lenerj/rt/Reference;Z)Ljava/lang/Object;
     817: checkcast     #9                  // class com/jme/math/Vector3f
     820: getstatic     #2                  // Field enerj/rt/PrecisionRuntimeRoot.impl:Lenerj/rt/PrecisionRuntime;
     823: aload         17
     825: iconst_1      
     826: invokeinterface #28,  3           // InterfaceMethod enerj/rt/PrecisionRuntime.loadLocal:(Lenerj/rt/Reference;Z)Ljava/lang/Object;
     831: checkcast     #9                  // class com/jme/math/Vector3f
     834: invokevirtual #30                 // Method com/jme/math/Vector3f.cross:(Lcom/jme/math/Vector3f;Lcom/jme/math/Vector3f;)Lcom/jme/math/Vector3f;
     837: pop           
     838: getstatic     #2                  // Field enerj/rt/PrecisionRuntimeRoot.impl:Lenerj/rt/PrecisionRuntime;
     841: aload         21
     843: iconst_1      
     844: getstatic     #2                  // Field enerj/rt/PrecisionRuntimeRoot.impl:Lenerj/rt/PrecisionRuntime;
     847: aload         17
     849: iconst_1      
     850: invokeinterface #28,  3           // InterfaceMethod enerj/rt/PrecisionRuntime.loadLocal:(Lenerj/rt/Reference;Z)Ljava/lang/Object;
     855: checkcast     #9                  // class com/jme/math/Vector3f
     858: getstatic     #2                  // Field enerj/rt/PrecisionRuntimeRoot.impl:Lenerj/rt/PrecisionRuntime;
     861: aload         11
     863: iconst_1      
     864: invokeinterface #28,  3           // InterfaceMethod enerj/rt/PrecisionRuntime.loadLocal:(Lenerj/rt/Reference;Z)Ljava/lang/Object;
     869: checkcast     #9                  // class com/jme/math/Vector3f
     872: invokevirtual #31                 // Method com/jme/math/Vector3f.dot:(Lcom/jme/math/Vector3f;)F
     875: fneg          
     876: invokestatic  #32                 // Method java/lang/Float.valueOf:(F)Ljava/lang/Float;
     879: invokeinterface #33,  4           // InterfaceMethod enerj/rt/PrecisionRuntime.storeLocal:(Lenerj/rt/Reference;ZLjava/lang/Object;)Ljava/lang/Object;
     884: pop           
     885: getstatic     #2                  // Field enerj/rt/PrecisionRuntimeRoot.impl:Lenerj/rt/PrecisionRuntime;
     888: aload         25
     890: iconst_1      
     891: getstatic     #2                  // Field enerj/rt/PrecisionRuntimeRoot.impl:Lenerj/rt/PrecisionRuntime;
     894: getstatic     #2                  // Field enerj/rt/PrecisionRuntimeRoot.impl:Lenerj/rt/PrecisionRuntime;
     897: aload         17
     899: iconst_1      
     900: invokeinterface #28,  3           // InterfaceMethod enerj/rt/PrecisionRuntime.loadLocal:(Lenerj/rt/Reference;Z)Ljava/lang/Object;
     905: checkcast     #9                  // class com/jme/math/Vector3f
     908: getstatic     #2                  // Field enerj/rt/PrecisionRuntimeRoot.impl:Lenerj/rt/PrecisionRuntime;
     911: aload         8
     913: iconst_1      
     914: invokeinterface #28,  3           // InterfaceMethod enerj/rt/PrecisionRuntime.loadLocal:(Lenerj/rt/Reference;Z)Ljava/lang/Object;
     919: checkcast     #9                  // class com/jme/math/Vector3f
     922: invokevirtual #31                 // Method com/jme/math/Vector3f.dot:(Lcom/jme/math/Vector3f;)F
     925: invokestatic  #32                 // Method java/lang/Float.valueOf:(F)Ljava/lang/Float;
     928: getstatic     #2                  // Field enerj/rt/PrecisionRuntimeRoot.impl:Lenerj/rt/PrecisionRuntime;
     931: aload         21
     933: iconst_1      
     934: invokeinterface #28,  3           // InterfaceMethod enerj/rt/PrecisionRuntime.loadLocal:(Lenerj/rt/Reference;Z)Ljava/lang/Object;
     939: checkcast     #34                 // class java/lang/Float
     942: invokevirtual #35                 // Method java/lang/Float.floatValue:()F
     945: invokestatic  #32                 // Method java/lang/Float.valueOf:(F)Ljava/lang/Float;
     948: getstatic     #36                 // Field enerj/rt/PrecisionRuntime$ArithOperator.PLUS:Lenerj/rt/PrecisionRuntime$ArithOperator;
     951: getstatic     #37                 // Field enerj/rt/PrecisionRuntime$NumberKind.FLOAT:Lenerj/rt/PrecisionRuntime$NumberKind;
     954: iconst_1      
     955: invokeinterface #38,  6           // InterfaceMethod enerj/rt/PrecisionRuntime.binaryOp:(Ljava/lang/Number;Ljava/lang/Number;Lenerj/rt/PrecisionRuntime$ArithOperator;Lenerj/rt/PrecisionRuntime$NumberKind;Z)Ljava/lang/Number;
     960: invokevirtual #39                 // Method java/lang/Number.floatValue:()F
     963: invokestatic  #32                 // Method java/lang/Float.valueOf:(F)Ljava/lang/Float;
     966: invokeinterface #33,  4           // InterfaceMethod enerj/rt/PrecisionRuntime.storeLocal:(Lenerj/rt/Reference;ZLjava/lang/Object;)Ljava/lang/Object;
     971: pop           
     972: getstatic     #2                  // Field enerj/rt/PrecisionRuntimeRoot.impl:Lenerj/rt/PrecisionRuntime;
     975: aload         27
     977: iconst_1      
     978: getstatic     #2                  // Field enerj/rt/PrecisionRuntimeRoot.impl:Lenerj/rt/PrecisionRuntime;
     981: getstatic     #2                  // Field enerj/rt/PrecisionRuntimeRoot.impl:Lenerj/rt/PrecisionRuntime;
     984: aload         17
     986: iconst_1      
     987: invokeinterface #28,  3           // InterfaceMethod enerj/rt/PrecisionRuntime.loadLocal:(Lenerj/rt/Reference;Z)Ljava/lang/Object;
     992: checkcast     #9                  // class com/jme/math/Vector3f
     995: getstatic     #2                  // Field enerj/rt/PrecisionRuntimeRoot.impl:Lenerj/rt/PrecisionRuntime;
     998: aload         7
    1000: iconst_1      
    1001: invokeinterface #28,  3           // InterfaceMethod enerj/rt/PrecisionRuntime.loadLocal:(Lenerj/rt/Reference;Z)Ljava/lang/Object;
    1006: checkcast     #9                  // class com/jme/math/Vector3f
    1009: invokevirtual #31                 // Method com/jme/math/Vector3f.dot:(Lcom/jme/math/Vector3f;)F
    1012: invokestatic  #32                 // Method java/lang/Float.valueOf:(F)Ljava/lang/Float;
    1015: getstatic     #2                  // Field enerj/rt/PrecisionRuntimeRoot.impl:Lenerj/rt/PrecisionRuntime;
    1018: aload         21
    1020: iconst_1      
    1021: invokeinterface #28,  3           // InterfaceMethod enerj/rt/PrecisionRuntime.loadLocal:(Lenerj/rt/Reference;Z)Ljava/lang/Object;
    1026: checkcast     #34                 // class java/lang/Float
    1029: invokevirtual #35                 // Method java/lang/Float.floatValue:()F
    1032: invokestatic  #32                 // Method java/lang/Float.valueOf:(F)Ljava/lang/Float;
    1035: getstatic     #36                 // Field enerj/rt/PrecisionRuntime$ArithOperator.PLUS:Lenerj/rt/PrecisionRuntime$ArithOperator;
    1038: getstatic     #37                 // Field enerj/rt/PrecisionRuntime$NumberKind.FLOAT:Lenerj/rt/PrecisionRuntime$NumberKind;
    1041: iconst_1      
    1042: invokeinterface #38,  6           // InterfaceMethod enerj/rt/PrecisionRuntime.binaryOp:(Ljava/lang/Number;Ljava/lang/Number;Lenerj/rt/PrecisionRuntime$ArithOperator;Lenerj/rt/PrecisionRuntime$NumberKind;Z)Ljava/lang/Number;
    1047: invokevirtual #39                 // Method java/lang/Number.floatValue:()F
    1050: invokestatic  #32                 // Method java/lang/Float.valueOf:(F)Ljava/lang/Float;
    1053: invokeinterface #33,  4           // InterfaceMethod enerj/rt/PrecisionRuntime.storeLocal:(Lenerj/rt/Reference;ZLjava/lang/Object;)Ljava/lang/Object;
    1058: pop           
    1059: getstatic     #2                  // Field enerj/rt/PrecisionRuntimeRoot.impl:Lenerj/rt/PrecisionRuntime;
    1062: aload         29
    1064: iconst_1      
    1065: getstatic     #2                  // Field enerj/rt/PrecisionRuntimeRoot.impl:Lenerj/rt/PrecisionRuntime;
    1068: getstatic     #2                  // Field enerj/rt/PrecisionRuntimeRoot.impl:Lenerj/rt/PrecisionRuntime;
    1071: aload         17
    1073: iconst_1      
    1074: invokeinterface #28,  3           // InterfaceMethod enerj/rt/PrecisionRuntime.loadLocal:(Lenerj/rt/Reference;Z)Ljava/lang/Object;
    1079: checkcast     #9                  // class com/jme/math/Vector3f
    1082: getstatic     #2                  // Field enerj/rt/PrecisionRuntimeRoot.impl:Lenerj/rt/PrecisionRuntime;
    1085: aload         6
    1087: iconst_1      
    1088: invokeinterface #28,  3           // InterfaceMethod enerj/rt/PrecisionRuntime.loadLocal:(Lenerj/rt/Reference;Z)Ljava/lang/Object;
    1093: checkcast     #9                  // class com/jme/math/Vector3f
    1096: invokevirtual #31                 // Method com/jme/math/Vector3f.dot:(Lcom/jme/math/Vector3f;)F
    1099: invokestatic  #32                 // Method java/lang/Float.valueOf:(F)Ljava/lang/Float;
    1102: getstatic     #2                  // Field enerj/rt/PrecisionRuntimeRoot.impl:Lenerj/rt/PrecisionRuntime;
    1105: aload         21
    1107: iconst_1      
    1108: invokeinterface #28,  3           // InterfaceMethod enerj/rt/PrecisionRuntime.loadLocal:(Lenerj/rt/Reference;Z)Ljava/lang/Object;
    1113: checkcast     #34                 // class java/lang/Float
    1116: invokevirtual #35                 // Method java/lang/Float.floatValue:()F
    1119: invokestatic  #32                 // Method java/lang/Float.valueOf:(F)Ljava/lang/Float;
    1122: getstatic     #36                 // Field enerj/rt/PrecisionRuntime$ArithOperator.PLUS:Lenerj/rt/PrecisionRuntime$ArithOperator;
    1125: getstatic     #37                 // Field enerj/rt/PrecisionRuntime$NumberKind.FLOAT:Lenerj/rt/PrecisionRuntime$NumberKind;
    1128: iconst_1      
    1129: invokeinterface #38,  6           // InterfaceMethod enerj/rt/PrecisionRuntime.binaryOp:(Ljava/lang/Number;Ljava/lang/Number;Lenerj/rt/PrecisionRuntime$ArithOperator;Lenerj/rt/PrecisionRuntime$NumberKind;Z)Ljava/lang/Number;
    1134: invokevirtual #39                 // Method java/lang/Number.floatValue:()F
    1137: invokestatic  #32                 // Method java/lang/Float.valueOf:(F)Ljava/lang/Float;
    1140: invokeinterface #33,  4           // InterfaceMethod enerj/rt/PrecisionRuntime.storeLocal:(Lenerj/rt/Reference;ZLjava/lang/Object;)Ljava/lang/Object;
    1145: pop           
    1146: getstatic     #2                  // Field enerj/rt/PrecisionRuntimeRoot.impl:Lenerj/rt/PrecisionRuntime;
    1149: aload         25
    1151: iconst_1      
    1152: getstatic     #2                  // Field enerj/rt/PrecisionRuntimeRoot.impl:Lenerj/rt/PrecisionRuntime;
    1155: aload         25
    1157: iconst_1      
    1158: invokeinterface #28,  3           // InterfaceMethod enerj/rt/PrecisionRuntime.loadLocal:(Lenerj/rt/Reference;Z)Ljava/lang/Object;
    1163: checkcast     #34                 // class java/lang/Float
    1166: invokevirtual #35                 // Method java/lang/Float.floatValue:()F
    1169: invokestatic  #40                 // Method accept:(F)F
    1172: invokestatic  #32                 // Method java/lang/Float.valueOf:(F)Ljava/lang/Float;
    1175: invokeinterface #33,  4           // InterfaceMethod enerj/rt/PrecisionRuntime.storeLocal:(Lenerj/rt/Reference;ZLjava/lang/Object;)Ljava/lang/Object;
    1180: pop           
    1181: getstatic     #2                  // Field enerj/rt/PrecisionRuntimeRoot.impl:Lenerj/rt/PrecisionRuntime;
    1184: aload         27
    1186: iconst_1      
    1187: getstatic     #2                  // Field enerj/rt/PrecisionRuntimeRoot.impl:Lenerj/rt/PrecisionRuntime;
    1190: aload         27
    1192: iconst_1      
    1193: invokeinterface #28,  3           // InterfaceMethod enerj/rt/PrecisionRuntime.loadLocal:(Lenerj/rt/Reference;Z)Ljava/lang/Object;
    1198: checkcast     #34                 // class java/lang/Float
    1201: invokevirtual #35                 // Method java/lang/Float.floatValue:()F
    1204: invokestatic  #40                 // Method accept:(F)F
    1207: invokestatic  #32                 // Method java/lang/Float.valueOf:(F)Ljava/lang/Float;
    1210: invokeinterface #33,  4           // InterfaceMethod enerj/rt/PrecisionRuntime.storeLocal:(Lenerj/rt/Reference;ZLjava/lang/Object;)Ljava/lang/Object;
    1215: pop           
    1216: getstatic     #2                  // Field enerj/rt/PrecisionRuntimeRoot.impl:Lenerj/rt/PrecisionRuntime;
    1219: aload         29
    1221: iconst_1      
    1222: getstatic     #2                  // Field enerj/rt/PrecisionRuntimeRoot.impl:Lenerj/rt/PrecisionRuntime;
    1225: aload         29
    1227: iconst_1      
    1228: invokeinterface #28,  3           // InterfaceMethod enerj/rt/PrecisionRuntime.loadLocal:(Lenerj/rt/Reference;Z)Ljava/lang/Object;
    1233: checkcast     #34                 // class java/lang/Float
    1236: invokevirtual #35                 // Method java/lang/Float.floatValue:()F
    1239: invokestatic  #40                 // Method accept:(F)F
    1242: invokestatic  #32                 // Method java/lang/Float.valueOf:(F)Ljava/lang/Float;
    1245: invokeinterface #33,  4           // InterfaceMethod enerj/rt/PrecisionRuntime.storeLocal:(Lenerj/rt/Reference;ZLjava/lang/Object;)Ljava/lang/Object;
    1250: pop           
    1251: getstatic     #2                  // Field enerj/rt/PrecisionRuntimeRoot.impl:Lenerj/rt/PrecisionRuntime;
    1254: getstatic     #2                  // Field enerj/rt/PrecisionRuntimeRoot.impl:Lenerj/rt/PrecisionRuntime;
    1257: aload         25
    1259: iconst_1      
    1260: invokeinterface #28,  3           // InterfaceMethod enerj/rt/PrecisionRuntime.loadLocal:(Lenerj/rt/Reference;Z)Ljava/lang/Object;
    1265: checkcast     #34                 // class java/lang/Float
    1268: invokevirtual #35                 // Method java/lang/Float.floatValue:()F
    1271: invokestatic  #41                 // Method com/jme/math/ApproxMath.abs:(F)F
    1274: f2d           
    1275: getstatic     #2                  // Field enerj/rt/PrecisionRuntimeRoot.impl:Lenerj/rt/PrecisionRuntime;
    1278: ldc_w         #5                  // class com/jme/intersection/Intersection
    1281: ldc           #42                 // String EPSILON
    1283: iconst_0      
    1284: invokeinterface #24,  4           // InterfaceMethod enerj/rt/PrecisionRuntime.loadField:(Ljava/lang/Object;Ljava/lang/String;Z)Ljava/lang/Object;
    1289: checkcast     #43                 // class java/lang/Double
    1292: invokevirtual #44                 // Method java/lang/Double.doubleValue:()D
    1295: dcmpg         
    1296: ifge          1303
    1299: iconst_1      
    1300: goto          1304
    1303: iconst_0      
    1304: invokestatic  #45                 // Method java/lang/Boolean.valueOf:(Z)Ljava/lang/Boolean;
    1307: invokeinterface #46,  2           // InterfaceMethod enerj/rt/PrecisionRuntime.countLogicalOp:(Ljava/lang/Object;)Ljava/lang/Object;
    1312: checkcast     #47                 // class java/lang/Boolean
    1315: invokevirtual #48                 // Method java/lang/Boolean.booleanValue:()Z
    1318: ifeq          1337
    1321: getstatic     #2                  // Field enerj/rt/PrecisionRuntimeRoot.impl:Lenerj/rt/PrecisionRuntime;
    1324: aload         25
    1326: iconst_1      
    1327: fconst_0      
    1328: invokestatic  #32                 // Method java/lang/Float.valueOf:(F)Ljava/lang/Float;
    1331: invokeinterface #33,  4           // InterfaceMethod enerj/rt/PrecisionRuntime.storeLocal:(Lenerj/rt/Reference;ZLjava/lang/Object;)Ljava/lang/Object;
    1336: pop           
    1337: getstatic     #2                  // Field enerj/rt/PrecisionRuntimeRoot.impl:Lenerj/rt/PrecisionRuntime;
    1340: getstatic     #2                  // Field enerj/rt/PrecisionRuntimeRoot.impl:Lenerj/rt/PrecisionRuntime;
    1343: aload         27
    1345: iconst_1      
    1346: invokeinterface #28,  3           // InterfaceMethod enerj/rt/PrecisionRuntime.loadLocal:(Lenerj/rt/Reference;Z)Ljava/lang/Object;
    1351: checkcast     #34                 // class java/lang/Float
    1354: invokevirtual #35                 // Method java/lang/Float.floatValue:()F
    1357: invokestatic  #41                 // Method com/jme/math/ApproxMath.abs:(F)F
    1360: f2d           
    1361: getstatic     #2                  // Field enerj/rt/PrecisionRuntimeRoot.impl:Lenerj/rt/PrecisionRuntime;
    1364: ldc_w         #5                  // class com/jme/intersection/Intersection
    1367: ldc           #42                 // String EPSILON
    1369: iconst_0      
    1370: invokeinterface #24,  4           // InterfaceMethod enerj/rt/PrecisionRuntime.loadField:(Ljava/lang/Object;Ljava/lang/String;Z)Ljava/lang/Object;
    1375: checkcast     #43                 // class java/lang/Double
    1378: invokevirtual #44                 // Method java/lang/Double.doubleValue:()D
    1381: dcmpg         
    1382: ifge          1389
    1385: iconst_1      
    1386: goto          1390
    1389: iconst_0      
    1390: invokestatic  #45                 // Method java/lang/Boolean.valueOf:(Z)Ljava/lang/Boolean;
    1393: invokeinterface #46,  2           // InterfaceMethod enerj/rt/PrecisionRuntime.countLogicalOp:(Ljava/lang/Object;)Ljava/lang/Object;
    1398: checkcast     #47                 // class java/lang/Boolean
    1401: invokevirtual #48                 // Method java/lang/Boolean.booleanValue:()Z
    1404: ifeq          1423
    1407: getstatic     #2                  // Field enerj/rt/PrecisionRuntimeRoot.impl:Lenerj/rt/PrecisionRuntime;
    1410: aload         27
    1412: iconst_1      
    1413: fconst_0      
    1414: invokestatic  #32                 // Method java/lang/Float.valueOf:(F)Ljava/lang/Float;
    1417: invokeinterface #33,  4           // InterfaceMethod enerj/rt/PrecisionRuntime.storeLocal:(Lenerj/rt/Reference;ZLjava/lang/Object;)Ljava/lang/Object;
    1422: pop           
    1423: getstatic     #2                  // Field enerj/rt/PrecisionRuntimeRoot.impl:Lenerj/rt/PrecisionRuntime;
    1426: getstatic     #2                  // Field enerj/rt/PrecisionRuntimeRoot.impl:Lenerj/rt/PrecisionRuntime;
    1429: aload         29
    1431: iconst_1      
    1432: invokeinterface #28,  3           // InterfaceMethod enerj/rt/PrecisionRuntime.loadLocal:(Lenerj/rt/Reference;Z)Ljava/lang/Object;
    1437: checkcast     #34                 // class java/lang/Float
    1440: invokevirtual #35                 // Method java/lang/Float.floatValue:()F
    1443: invokestatic  #41                 // Method com/jme/math/ApproxMath.abs:(F)F
    1446: f2d           
    1447: getstatic     #2                  // Field enerj/rt/PrecisionRuntimeRoot.impl:Lenerj/rt/PrecisionRuntime;
    1450: ldc_w         #5                  // class com/jme/intersection/Intersection
    1453: ldc           #42                 // String EPSILON
    1455: iconst_0      
    1456: invokeinterface #24,  4           // InterfaceMethod enerj/rt/PrecisionRuntime.loadField:(Ljava/lang/Object;Ljava/lang/String;Z)Ljava/lang/Object;
    1461: checkcast     #43                 // class java/lang/Double
    1464: invokevirtual #44                 // Method java/lang/Double.doubleValue:()D
    1467: dcmpg         
    1468: ifge          1475
    1471: iconst_1      
    1472: goto          1476
    1475: iconst_0      
    1476: invokestatic  #45                 // Method java/lang/Boolean.valueOf:(Z)Ljava/lang/Boolean;
    1479: invokeinterface #46,  2           // InterfaceMethod enerj/rt/PrecisionRuntime.countLogicalOp:(Ljava/lang/Object;)Ljava/lang/Object;
    1484: checkcast     #47                 // class java/lang/Boolean
    1487: invokevirtual #48                 // Method java/lang/Boolean.booleanValue:()Z
    1490: ifeq          1509
    1493: getstatic     #2                  // Field enerj/rt/PrecisionRuntimeRoot.impl:Lenerj/rt/PrecisionRuntime;
    1496: aload         29
    1498: iconst_1      
    1499: fconst_0      
    1500: invokestatic  #32                 // Method java/lang/Float.valueOf:(F)Ljava/lang/Float;
    1503: invokeinterface #33,  4           // InterfaceMethod enerj/rt/PrecisionRuntime.storeLocal:(Lenerj/rt/Reference;ZLjava/lang/Object;)Ljava/lang/Object;
    1508: pop           
    1509: getstatic     #2                  // Field enerj/rt/PrecisionRuntimeRoot.impl:Lenerj/rt/PrecisionRuntime;
    1512: aload         43
    1514: iconst_1      
    1515: getstatic     #2                  // Field enerj/rt/PrecisionRuntimeRoot.impl:Lenerj/rt/PrecisionRuntime;
    1518: getstatic     #2                  // Field enerj/rt/PrecisionRuntimeRoot.impl:Lenerj/rt/PrecisionRuntime;
    1521: aload         25
    1523: iconst_1      
    1524: invokeinterface #28,  3           // InterfaceMethod enerj/rt/PrecisionRuntime.loadLocal:(Lenerj/rt/Reference;Z)Ljava/lang/Object;
    1529: checkcast     #34                 // class java/lang/Float
    1532: invokevirtual #35                 // Method java/lang/Float.floatValue:()F
    1535: invokestatic  #32                 // Method java/lang/Float.valueOf:(F)Ljava/lang/Float;
    1538: getstatic     #2                  // Field enerj/rt/PrecisionRuntimeRoot.impl:Lenerj/rt/PrecisionRuntime;
    1541: aload         27
    1543: iconst_1      
    1544: invokeinterface #28,  3           // InterfaceMethod enerj/rt/PrecisionRuntime.loadLocal:(Lenerj/rt/Reference;Z)Ljava/lang/Object;
    1549: checkcast     #34                 // class java/lang/Float
    1552: invokevirtual #35                 // Method java/lang/Float.floatValue:()F
    1555: invokestatic  #32                 // Method java/lang/Float.valueOf:(F)Ljava/lang/Float;
    1558: getstatic     #49                 // Field enerj/rt/PrecisionRuntime$ArithOperator.MULTIPLY:Lenerj/rt/PrecisionRuntime$ArithOperator;
    1561: getstatic     #37                 // Field enerj/rt/PrecisionRuntime$NumberKind.FLOAT:Lenerj/rt/PrecisionRuntime$NumberKind;
    1564: iconst_1      
    1565: invokeinterface #38,  6           // InterfaceMethod enerj/rt/PrecisionRuntime.binaryOp:(Ljava/lang/Number;Ljava/lang/Number;Lenerj/rt/PrecisionRuntime$ArithOperator;Lenerj/rt/PrecisionRuntime$NumberKind;Z)Ljava/lang/Number;
    1570: invokevirtual #39                 // Method java/lang/Number.floatValue:()F
    1573: invokestatic  #32                 // Method java/lang/Float.valueOf:(F)Ljava/lang/Float;
    1576: invokeinterface #33,  4           // InterfaceMethod enerj/rt/PrecisionRuntime.storeLocal:(Lenerj/rt/Reference;ZLjava/lang/Object;)Ljava/lang/Object;
    1581: pop           
    1582: getstatic     #2                  // Field enerj/rt/PrecisionRuntimeRoot.impl:Lenerj/rt/PrecisionRuntime;
    1585: aload         45
    1587: iconst_1      
    1588: getstatic     #2                  // Field enerj/rt/PrecisionRuntimeRoot.impl:Lenerj/rt/PrecisionRuntime;
    1591: getstatic     #2                  // Field enerj/rt/PrecisionRuntimeRoot.impl:Lenerj/rt/PrecisionRuntime;
    1594: aload         25
    1596: iconst_1      
    1597: invokeinterface #28,  3           // InterfaceMethod enerj/rt/PrecisionRuntime.loadLocal:(Lenerj/rt/Reference;Z)Ljava/lang/Object;
    1602: checkcast     #34                 // class java/lang/Float
    1605: invokevirtual #35                 // Method java/lang/Float.floatValue:()F
    1608: invokestatic  #32                 // Method java/lang/Float.valueOf:(F)Ljava/lang/Float;
    1611: getstatic     #2                  // Field enerj/rt/PrecisionRuntimeRoot.impl:Lenerj/rt/PrecisionRuntime;
    1614: aload         29
    1616: iconst_1      
    1617: invokeinterface #28,  3           // InterfaceMethod enerj/rt/PrecisionRuntime.loadLocal:(Lenerj/rt/Reference;Z)Ljava/lang/Object;
    1622: checkcast     #34                 // class java/lang/Float
    1625: invokevirtual #35                 // Method java/lang/Float.floatValue:()F
    1628: invokestatic  #32                 // Method java/lang/Float.valueOf:(F)Ljava/lang/Float;
    1631: getstatic     #49                 // Field enerj/rt/PrecisionRuntime$ArithOperator.MULTIPLY:Lenerj/rt/PrecisionRuntime$ArithOperator;
    1634: getstatic     #37                 // Field enerj/rt/PrecisionRuntime$NumberKind.FLOAT:Lenerj/rt/PrecisionRuntime$NumberKind;
    1637: iconst_1      
    1638: invokeinterface #38,  6           // InterfaceMethod enerj/rt/PrecisionRuntime.binaryOp:(Ljava/lang/Number;Ljava/lang/Number;Lenerj/rt/PrecisionRuntime$ArithOperator;Lenerj/rt/PrecisionRuntime$NumberKind;Z)Ljava/lang/Number;
    1643: invokevirtual #39                 // Method java/lang/Number.floatValue:()F
    1646: invokestatic  #32                 // Method java/lang/Float.valueOf:(F)Ljava/lang/Float;
    1649: invokeinterface #33,  4           // InterfaceMethod enerj/rt/PrecisionRuntime.storeLocal:(Lenerj/rt/Reference;ZLjava/lang/Object;)Ljava/lang/Object;
    1654: pop           
    1655: getstatic     #2                  // Field enerj/rt/PrecisionRuntimeRoot.impl:Lenerj/rt/PrecisionRuntime;
    1658: aload         43
    1660: iconst_0      
    1661: getstatic     #2                  // Field enerj/rt/PrecisionRuntimeRoot.impl:Lenerj/rt/PrecisionRuntime;
    1664: aload         43
    1666: iconst_1      
    1667: invokeinterface #28,  3           // InterfaceMethod enerj/rt/PrecisionRuntime.loadLocal:(Lenerj/rt/Reference;Z)Ljava/lang/Object;
    1672: checkcast     #34                 // class java/lang/Float
    1675: invokevirtual #35                 // Method java/lang/Float.floatValue:()F
    1678: invokestatic  #40                 // Method accept:(F)F
    1681: invokestatic  #32                 // Method java/lang/Float.valueOf:(F)Ljava/lang/Float;
    1684: invokeinterface #33,  4           // InterfaceMethod enerj/rt/PrecisionRuntime.storeLocal:(Lenerj/rt/Reference;ZLjava/lang/Object;)Ljava/lang/Object;
    1689: pop           
    1690: getstatic     #2                  // Field enerj/rt/PrecisionRuntimeRoot.impl:Lenerj/rt/PrecisionRuntime;
    1693: aload         45
    1695: iconst_0      
    1696: getstatic     #2                  // Field enerj/rt/PrecisionRuntimeRoot.impl:Lenerj/rt/PrecisionRuntime;
    1699: aload         45
    1701: iconst_1      
    1702: invokeinterface #28,  3           // InterfaceMethod enerj/rt/PrecisionRuntime.loadLocal:(Lenerj/rt/Reference;Z)Ljava/lang/Object;
    1707: checkcast     #34                 // class java/lang/Float
    1710: invokevirtual #35                 // Method java/lang/Float.floatValue:()F
    1713: invokestatic  #40                 // Method accept:(F)F
    1716: invokestatic  #32                 // Method java/lang/Float.valueOf:(F)Ljava/lang/Float;
    1719: invokeinterface #33,  4           // InterfaceMethod enerj/rt/PrecisionRuntime.storeLocal:(Lenerj/rt/Reference;ZLjava/lang/Object;)Ljava/lang/Object;
    1724: pop           
    1725: getstatic     #2                  // Field enerj/rt/PrecisionRuntimeRoot.impl:Lenerj/rt/PrecisionRuntime;
    1728: getstatic     #2                  // Field enerj/rt/PrecisionRuntimeRoot.impl:Lenerj/rt/PrecisionRuntime;
    1731: getstatic     #2                  // Field enerj/rt/PrecisionRuntimeRoot.impl:Lenerj/rt/PrecisionRuntime;
    1734: aload         43
    1736: iconst_1      
    1737: invokeinterface #28,  3           // InterfaceMethod enerj/rt/PrecisionRuntime.loadLocal:(Lenerj/rt/Reference;Z)Ljava/lang/Object;
    1742: checkcast     #34                 // class java/lang/Float
    1745: invokevirtual #35                 // Method java/lang/Float.floatValue:()F
    1748: fconst_0      
    1749: fcmpl         
    1750: ifle          1757
    1753: iconst_1      
    1754: goto          1758
    1757: iconst_0      
    1758: invokestatic  #45                 // Method java/lang/Boolean.valueOf:(Z)Ljava/lang/Boolean;
    1761: invokeinterface #46,  2           // InterfaceMethod enerj/rt/PrecisionRuntime.countLogicalOp:(Ljava/lang/Object;)Ljava/lang/Object;
    1766: checkcast     #47                 // class java/lang/Boolean
    1769: invokevirtual #48                 // Method java/lang/Boolean.booleanValue:()Z
    1772: ifeq          1826
    1775: getstatic     #2                  // Field enerj/rt/PrecisionRuntimeRoot.impl:Lenerj/rt/PrecisionRuntime;
    1778: getstatic     #2                  // Field enerj/rt/PrecisionRuntimeRoot.impl:Lenerj/rt/PrecisionRuntime;
    1781: aload         45
    1783: iconst_1      
    1784: invokeinterface #28,  3           // InterfaceMethod enerj/rt/PrecisionRuntime.loadLocal:(Lenerj/rt/Reference;Z)Ljava/lang/Object;
    1789: checkcast     #34                 // class java/lang/Float
    1792: invokevirtual #35                 // Method java/lang/Float.floatValue:()F
    1795: fconst_0      
    1796: fcmpl         
    1797: ifle          1804
    1800: iconst_1      
    1801: goto          1805
    1804: iconst_0      
    1805: invokestatic  #45                 // Method java/lang/Boolean.valueOf:(Z)Ljava/lang/Boolean;
    1808: invokeinterface #46,  2           // InterfaceMethod enerj/rt/PrecisionRuntime.countLogicalOp:(Ljava/lang/Object;)Ljava/lang/Object;
    1813: checkcast     #47                 // class java/lang/Boolean
    1816: invokevirtual #48                 // Method java/lang/Boolean.booleanValue:()Z
    1819: ifeq          1826
    1822: iconst_1      
    1823: goto          1827
    1826: iconst_0      
    1827: invokestatic  #45                 // Method java/lang/Boolean.valueOf:(Z)Ljava/lang/Boolean;
    1830: invokeinterface #46,  2           // InterfaceMethod enerj/rt/PrecisionRuntime.countLogicalOp:(Ljava/lang/Object;)Ljava/lang/Object;
    1835: checkcast     #47                 // class java/lang/Boolean
    1838: invokevirtual #48                 // Method java/lang/Boolean.booleanValue:()Z
    1841: ifeq          1846
    1844: iconst_0      
    1845: ireturn       
    1846: getstatic     #2                  // Field enerj/rt/PrecisionRuntimeRoot.impl:Lenerj/rt/PrecisionRuntime;
    1849: aload         7
    1851: iconst_1      
    1852: invokeinterface #28,  3           // InterfaceMethod enerj/rt/PrecisionRuntime.loadLocal:(Lenerj/rt/Reference;Z)Ljava/lang/Object;
    1857: checkcast     #9                  // class com/jme/math/Vector3f
    1860: getstatic     #2                  // Field enerj/rt/PrecisionRuntimeRoot.impl:Lenerj/rt/PrecisionRuntime;
    1863: aload         8
    1865: iconst_1      
    1866: invokeinterface #28,  3           // InterfaceMethod enerj/rt/PrecisionRuntime.loadLocal:(Lenerj/rt/Reference;Z)Ljava/lang/Object;
    1871: checkcast     #9                  // class com/jme/math/Vector3f
    1874: getstatic     #2                  // Field enerj/rt/PrecisionRuntimeRoot.impl:Lenerj/rt/PrecisionRuntime;
    1877: aload         13
    1879: iconst_1      
    1880: invokeinterface #28,  3           // InterfaceMethod enerj/rt/PrecisionRuntime.loadLocal:(Lenerj/rt/Reference;Z)Ljava/lang/Object;
    1885: checkcast     #9                  // class com/jme/math/Vector3f
    1888: invokevirtual #29                 // Method com/jme/math/Vector3f.subtract:(Lcom/jme/math/Vector3f;Lcom/jme/math/Vector3f;)Lcom/jme/math/Vector3f;
    1891: pop           
    1892: getstatic     #2                  // Field enerj/rt/PrecisionRuntimeRoot.impl:Lenerj/rt/PrecisionRuntime;
    1895: aload         6
    1897: iconst_1      
    1898: invokeinterface #28,  3           // InterfaceMethod enerj/rt/PrecisionRuntime.loadLocal:(Lenerj/rt/Reference;Z)Ljava/lang/Object;
    1903: checkcast     #9                  // class com/jme/math/Vector3f
    1906: getstatic     #2                  // Field enerj/rt/PrecisionRuntimeRoot.impl:Lenerj/rt/PrecisionRuntime;
    1909: aload         8
    1911: iconst_1      
    1912: invokeinterface #28,  3           // InterfaceMethod enerj/rt/PrecisionRuntime.loadLocal:(Lenerj/rt/Reference;Z)Ljava/lang/Object;
    1917: checkcast     #9                  // class com/jme/math/Vector3f
    1920: getstatic     #2                  // Field enerj/rt/PrecisionRuntimeRoot.impl:Lenerj/rt/PrecisionRuntime;
    1923: aload         15
    1925: iconst_1      
    1926: invokeinterface #28,  3           // InterfaceMethod enerj/rt/PrecisionRuntime.loadLocal:(Lenerj/rt/Reference;Z)Ljava/lang/Object;
    1931: checkcast     #9                  // class com/jme/math/Vector3f
    1934: invokevirtual #29                 // Method com/jme/math/Vector3f.subtract:(Lcom/jme/math/Vector3f;Lcom/jme/math/Vector3f;)Lcom/jme/math/Vector3f;
    1937: pop           
    1938: getstatic     #2                  // Field enerj/rt/PrecisionRuntimeRoot.impl:Lenerj/rt/PrecisionRuntime;
    1941: aload         13
    1943: iconst_1      
    1944: invokeinterface #28,  3           // InterfaceMethod enerj/rt/PrecisionRuntime.loadLocal:(Lenerj/rt/Reference;Z)Ljava/lang/Object;
    1949: checkcast     #9                  // class com/jme/math/Vector3f
    1952: getstatic     #2                  // Field enerj/rt/PrecisionRuntimeRoot.impl:Lenerj/rt/PrecisionRuntime;
    1955: aload         15
    1957: iconst_1      
    1958: invokeinterface #28,  3           // InterfaceMethod enerj/rt/PrecisionRuntime.loadLocal:(Lenerj/rt/Reference;Z)Ljava/lang/Object;
    1963: checkcast     #9                  // class com/jme/math/Vector3f
    1966: getstatic     #2                  // Field enerj/rt/PrecisionRuntimeRoot.impl:Lenerj/rt/PrecisionRuntime;
    1969: aload         19
    1971: iconst_1      
    1972: invokeinterface #28,  3           // InterfaceMethod enerj/rt/PrecisionRuntime.loadLocal:(Lenerj/rt/Reference;Z)Ljava/lang/Object;
    1977: checkcast     #9                  // class com/jme/math/Vector3f
    1980: invokevirtual #30                 // Method com/jme/math/Vector3f.cross:(Lcom/jme/math/Vector3f;Lcom/jme/math/Vector3f;)Lcom/jme/math/Vector3f;
    1983: pop           
    1984: getstatic     #2                  // Field enerj/rt/PrecisionRuntimeRoot.impl:Lenerj/rt/PrecisionRuntime;
    1987: aload         23
    1989: iconst_1      
    1990: getstatic     #2                  // Field enerj/rt/PrecisionRuntimeRoot.impl:Lenerj/rt/PrecisionRuntime;
    1993: aload         19
    1995: iconst_1      
    1996: invokeinterface #28,  3           // InterfaceMethod enerj/rt/PrecisionRuntime.loadLocal:(Lenerj/rt/Reference;Z)Ljava/lang/Object;
    2001: checkcast     #9                  // class com/jme/math/Vector3f
    2004: getstatic     #2                  // Field enerj/rt/PrecisionRuntimeRoot.impl:Lenerj/rt/PrecisionRuntime;
    2007: aload         8
    2009: iconst_1      
    2010: invokeinterface #28,  3           // InterfaceMethod enerj/rt/PrecisionRuntime.loadLocal:(Lenerj/rt/Reference;Z)Ljava/lang/Object;
    2015: checkcast     #9                  // class com/jme/math/Vector3f
    2018: invokevirtual #31                 // Method com/jme/math/Vector3f.dot:(Lcom/jme/math/Vector3f;)F
    2021: fneg          
    2022: invokestatic  #32                 // Method java/lang/Float.valueOf:(F)Ljava/lang/Float;
    2025: invokeinterface #33,  4           // InterfaceMethod enerj/rt/PrecisionRuntime.storeLocal:(Lenerj/rt/Reference;ZLjava/lang/Object;)Ljava/lang/Object;
    2030: pop           
    2031: getstatic     #2                  // Field enerj/rt/PrecisionRuntimeRoot.impl:Lenerj/rt/PrecisionRuntime;
    2034: aload         31
    2036: iconst_1      
    2037: getstatic     #2                  // Field enerj/rt/PrecisionRuntimeRoot.impl:Lenerj/rt/PrecisionRuntime;
    2040: getstatic     #2                  // Field enerj/rt/PrecisionRuntimeRoot.impl:Lenerj/rt/PrecisionRuntime;
    2043: aload         19
    2045: iconst_1      
    2046: invokeinterface #28,  3           // InterfaceMethod enerj/rt/PrecisionRuntime.loadLocal:(Lenerj/rt/Reference;Z)Ljava/lang/Object;
    2051: checkcast     #9                  // class com/jme/math/Vector3f
    2054: getstatic     #2                  // Field enerj/rt/PrecisionRuntimeRoot.impl:Lenerj/rt/PrecisionRuntime;
    2057: aload         11
    2059: iconst_1      
    2060: invokeinterface #28,  3           // InterfaceMethod enerj/rt/PrecisionRuntime.loadLocal:(Lenerj/rt/Reference;Z)Ljava/lang/Object;
    2065: checkcast     #9                  // class com/jme/math/Vector3f
    2068: invokevirtual #31                 // Method com/jme/math/Vector3f.dot:(Lcom/jme/math/Vector3f;)F
    2071: invokestatic  #32                 // Method java/lang/Float.valueOf:(F)Ljava/lang/Float;
    2074: getstatic     #2                  // Field enerj/rt/PrecisionRuntimeRoot.impl:Lenerj/rt/PrecisionRuntime;
    2077: aload         23
    2079: iconst_1      
    2080: invokeinterface #28,  3           // InterfaceMethod enerj/rt/PrecisionRuntime.loadLocal:(Lenerj/rt/Reference;Z)Ljava/lang/Object;
    2085: checkcast     #34                 // class java/lang/Float
    2088: invokevirtual #35                 // Method java/lang/Float.floatValue:()F
    2091: invokestatic  #32                 // Method java/lang/Float.valueOf:(F)Ljava/lang/Float;
    2094: getstatic     #36                 // Field enerj/rt/PrecisionRuntime$ArithOperator.PLUS:Lenerj/rt/PrecisionRuntime$ArithOperator;
    2097: getstatic     #37                 // Field enerj/rt/PrecisionRuntime$NumberKind.FLOAT:Lenerj/rt/PrecisionRuntime$NumberKind;
    2100: iconst_1      
    2101: invokeinterface #38,  6           // InterfaceMethod enerj/rt/PrecisionRuntime.binaryOp:(Ljava/lang/Number;Ljava/lang/Number;Lenerj/rt/PrecisionRuntime$ArithOperator;Lenerj/rt/PrecisionRuntime$NumberKind;Z)Ljava/lang/Number;
    2106: invokevirtual #39                 // Method java/lang/Number.floatValue:()F
    2109: invokestatic  #32                 // Method java/lang/Float.valueOf:(F)Ljava/lang/Float;
    2112: invokeinterface #33,  4           // InterfaceMethod enerj/rt/PrecisionRuntime.storeLocal:(Lenerj/rt/Reference;ZLjava/lang/Object;)Ljava/lang/Object;
    2117: pop           
    2118: getstatic     #2                  // Field enerj/rt/PrecisionRuntimeRoot.impl:Lenerj/rt/PrecisionRuntime;
    2121: aload         33
    2123: iconst_1      
    2124: getstatic     #2                  // Field enerj/rt/PrecisionRuntimeRoot.impl:Lenerj/rt/PrecisionRuntime;
    2127: getstatic     #2                  // Field enerj/rt/PrecisionRuntimeRoot.impl:Lenerj/rt/PrecisionRuntime;
    2130: aload         19
    2132: iconst_1      
    2133: invokeinterface #28,  3           // InterfaceMethod enerj/rt/PrecisionRuntime.loadLocal:(Lenerj/rt/Reference;Z)Ljava/lang/Object;
    2138: checkcast     #9                  // class com/jme/math/Vector3f
    2141: getstatic     #2                  // Field enerj/rt/PrecisionRuntimeRoot.impl:Lenerj/rt/PrecisionRuntime;
    2144: aload         10
    2146: iconst_1      
    2147: invokeinterface #28,  3           // InterfaceMethod enerj/rt/PrecisionRuntime.loadLocal:(Lenerj/rt/Reference;Z)Ljava/lang/Object;
    2152: checkcast     #9                  // class com/jme/math/Vector3f
    2155: invokevirtual #31                 // Method com/jme/math/Vector3f.dot:(Lcom/jme/math/Vector3f;)F
    2158: invokestatic  #32                 // Method java/lang/Float.valueOf:(F)Ljava/lang/Float;
    2161: getstatic     #2                  // Field enerj/rt/PrecisionRuntimeRoot.impl:Lenerj/rt/PrecisionRuntime;
    2164: aload         23
    2166: iconst_1      
    2167: invokeinterface #28,  3           // InterfaceMethod enerj/rt/PrecisionRuntime.loadLocal:(Lenerj/rt/Reference;Z)Ljava/lang/Object;
    2172: checkcast     #34                 // class java/lang/Float
    2175: invokevirtual #35                 // Method java/lang/Float.floatValue:()F
    2178: invokestatic  #32                 // Method java/lang/Float.valueOf:(F)Ljava/lang/Float;
    2181: getstatic     #36                 // Field enerj/rt/PrecisionRuntime$ArithOperator.PLUS:Lenerj/rt/PrecisionRuntime$ArithOperator;
    2184: getstatic     #37                 // Field enerj/rt/PrecisionRuntime$NumberKind.FLOAT:Lenerj/rt/PrecisionRuntime$NumberKind;
    2187: iconst_1      
    2188: invokeinterface #38,  6           // InterfaceMethod enerj/rt/PrecisionRuntime.binaryOp:(Ljava/lang/Number;Ljava/lang/Number;Lenerj/rt/PrecisionRuntime$ArithOperator;Lenerj/rt/PrecisionRuntime$NumberKind;Z)Ljava/lang/Number;
    2193: invokevirtual #39                 // Method java/lang/Number.floatValue:()F
    2196: invokestatic  #32                 // Method java/lang/Float.valueOf:(F)Ljava/lang/Float;
    2199: invokeinterface #33,  4           // InterfaceMethod enerj/rt/PrecisionRuntime.storeLocal:(Lenerj/rt/Reference;ZLjava/lang/Object;)Ljava/lang/Object;
    2204: pop           
    2205: getstatic     #2                  // Field enerj/rt/PrecisionRuntimeRoot.impl:Lenerj/rt/PrecisionRuntime;
    2208: aload         35
    2210: iconst_1      
    2211: getstatic     #2                  // Field enerj/rt/PrecisionRuntimeRoot.impl:Lenerj/rt/PrecisionRuntime;
    2214: getstatic     #2                  // Field enerj/rt/PrecisionRuntimeRoot.impl:Lenerj/rt/PrecisionRuntime;
    2217: aload         19
    2219: iconst_1      
    2220: invokeinterface #28,  3           // InterfaceMethod enerj/rt/PrecisionRuntime.loadLocal:(Lenerj/rt/Reference;Z)Ljava/lang/Object;
    2225: checkcast     #9                  // class com/jme/math/Vector3f
    2228: getstatic     #2                  // Field enerj/rt/PrecisionRuntimeRoot.impl:Lenerj/rt/PrecisionRuntime;
    2231: aload         9
    2233: iconst_1      
    2234: invokeinterface #28,  3           // InterfaceMethod enerj/rt/PrecisionRuntime.loadLocal:(Lenerj/rt/Reference;Z)Ljava/lang/Object;
    2239: checkcast     #9                  // class com/jme/math/Vector3f
    2242: invokevirtual #31                 // Method com/jme/math/Vector3f.dot:(Lcom/jme/math/Vector3f;)F
    2245: invokestatic  #32                 // Method java/lang/Float.valueOf:(F)Ljava/lang/Float;
    2248: getstatic     #2                  // Field enerj/rt/PrecisionRuntimeRoot.impl:Lenerj/rt/PrecisionRuntime;
    2251: aload         23
    2253: iconst_1      
    2254: invokeinterface #28,  3           // InterfaceMethod enerj/rt/PrecisionRuntime.loadLocal:(Lenerj/rt/Reference;Z)Ljava/lang/Object;
    2259: checkcast     #34                 // class java/lang/Float
    2262: invokevirtual #35                 // Method java/lang/Float.floatValue:()F
    2265: invokestatic  #32                 // Method java/lang/Float.valueOf:(F)Ljava/lang/Float;
    2268: getstatic     #36                 // Field enerj/rt/PrecisionRuntime$ArithOperator.PLUS:Lenerj/rt/PrecisionRuntime$ArithOperator;
    2271: getstatic     #37                 // Field enerj/rt/PrecisionRuntime$NumberKind.FLOAT:Lenerj/rt/PrecisionRuntime$NumberKind;
    2274: iconst_1      
    2275: invokeinterface #38,  6           // InterfaceMethod enerj/rt/PrecisionRuntime.binaryOp:(Ljava/lang/Number;Ljava/lang/Number;Lenerj/rt/PrecisionRuntime$ArithOperator;Lenerj/rt/PrecisionRuntime$NumberKind;Z)Ljava/lang/Number;
    2280: invokevirtual #39                 // Method java/lang/Number.floatValue:()F
    2283: invokestatic  #32                 // Method java/lang/Float.valueOf:(F)Ljava/lang/Float;
    2286: invokeinterface #33,  4           // InterfaceMethod enerj/rt/PrecisionRuntime.storeLocal:(Lenerj/rt/Reference;ZLjava/lang/Object;)Ljava/lang/Object;
    2291: pop           
    2292: getstatic     #2                  // Field enerj/rt/PrecisionRuntimeRoot.impl:Lenerj/rt/PrecisionRuntime;
    2295: aload         31
    2297: iconst_1      
    2298: getstatic     #2                  // Field enerj/rt/PrecisionRuntimeRoot.impl:Lenerj/rt/PrecisionRuntime;
    2301: aload         31
    2303: iconst_1      
    2304: invokeinterface #28,  3           // InterfaceMethod enerj/rt/PrecisionRuntime.loadLocal:(Lenerj/rt/Reference;Z)Ljava/lang/Object;
    2309: checkcast     #34                 // class java/lang/Float
    2312: invokevirtual #35                 // Method java/lang/Float.floatValue:()F
    2315: invokestatic  #40                 // Method accept:(F)F
    2318: invokestatic  #32                 // Method java/lang/Float.valueOf:(F)Ljava/lang/Float;
    2321: invokeinterface #33,  4           // InterfaceMethod enerj/rt/PrecisionRuntime.storeLocal:(Lenerj/rt/Reference;ZLjava/lang/Object;)Ljava/lang/Object;
    2326: pop           
    2327: getstatic     #2                  // Field enerj/rt/PrecisionRuntimeRoot.impl:Lenerj/rt/PrecisionRuntime;
    2330: aload         33
    2332: iconst_1      
    2333: getstatic     #2                  // Field enerj/rt/PrecisionRuntimeRoot.impl:Lenerj/rt/PrecisionRuntime;
    2336: aload         33
    2338: iconst_1      
    2339: invokeinterface #28,  3           // InterfaceMethod enerj/rt/PrecisionRuntime.loadLocal:(Lenerj/rt/Reference;Z)Ljava/lang/Object;
    2344: checkcast     #34                 // class java/lang/Float
    2347: invokevirtual #35                 // Method java/lang/Float.floatValue:()F
    2350: invokestatic  #40                 // Method accept:(F)F
    2353: invokestatic  #32                 // Method java/lang/Float.valueOf:(F)Ljava/lang/Float;
    2356: invokeinterface #33,  4           // InterfaceMethod enerj/rt/PrecisionRuntime.storeLocal:(Lenerj/rt/Reference;ZLjava/lang/Object;)Ljava/lang/Object;
    2361: pop           
    2362: getstatic     #2                  // Field enerj/rt/PrecisionRuntimeRoot.impl:Lenerj/rt/PrecisionRuntime;
    2365: aload         35
    2367: iconst_0      
    2368: getstatic     #2                  // Field enerj/rt/PrecisionRuntimeRoot.impl:Lenerj/rt/PrecisionRuntime;
    2371: aload         35
    2373: iconst_1      
    2374: invokeinterface #28,  3           // InterfaceMethod enerj/rt/PrecisionRuntime.loadLocal:(Lenerj/rt/Reference;Z)Ljava/lang/Object;
    2379: checkcast     #34                 // class java/lang/Float
    2382: invokevirtual #35                 // Method java/lang/Float.floatValue:()F
    2385: invokestatic  #40                 // Method accept:(F)F
    2388: invokestatic  #32                 // Method java/lang/Float.valueOf:(F)Ljava/lang/Float;
    2391: invokeinterface #33,  4           // InterfaceMethod enerj/rt/PrecisionRuntime.storeLocal:(Lenerj/rt/Reference;ZLjava/lang/Object;)Ljava/lang/Object;
    2396: pop           
    2397: getstatic     #2                  // Field enerj/rt/PrecisionRuntimeRoot.impl:Lenerj/rt/PrecisionRuntime;
    2400: getstatic     #2                  // Field enerj/rt/PrecisionRuntimeRoot.impl:Lenerj/rt/PrecisionRuntime;
    2403: aload         31
    2405: iconst_1      
    2406: invokeinterface #28,  3           // InterfaceMethod enerj/rt/PrecisionRuntime.loadLocal:(Lenerj/rt/Reference;Z)Ljava/lang/Object;
    2411: checkcast     #34                 // class java/lang/Float
    2414: invokevirtual #35                 // Method java/lang/Float.floatValue:()F
    2417: invokestatic  #41                 // Method com/jme/math/ApproxMath.abs:(F)F
    2420: f2d           
    2421: getstatic     #2                  // Field enerj/rt/PrecisionRuntimeRoot.impl:Lenerj/rt/PrecisionRuntime;
    2424: ldc_w         #5                  // class com/jme/intersection/Intersection
    2427: ldc           #42                 // String EPSILON
    2429: iconst_0      
    2430: invokeinterface #24,  4           // InterfaceMethod enerj/rt/PrecisionRuntime.loadField:(Ljava/lang/Object;Ljava/lang/String;Z)Ljava/lang/Object;
    2435: checkcast     #43                 // class java/lang/Double
    2438: invokevirtual #44                 // Method java/lang/Double.doubleValue:()D
    2441: dcmpg         
    2442: ifge          2449
    2445: iconst_1      
    2446: goto          2450
    2449: iconst_0      
    2450: invokestatic  #45                 // Method java/lang/Boolean.valueOf:(Z)Ljava/lang/Boolean;
    2453: invokeinterface #46,  2           // InterfaceMethod enerj/rt/PrecisionRuntime.countLogicalOp:(Ljava/lang/Object;)Ljava/lang/Object;
    2458: checkcast     #47                 // class java/lang/Boolean
    2461: invokevirtual #48                 // Method java/lang/Boolean.booleanValue:()Z
    2464: ifeq          2483
    2467: getstatic     #2                  // Field enerj/rt/PrecisionRuntimeRoot.impl:Lenerj/rt/PrecisionRuntime;
    2470: aload         31
    2472: iconst_1      
    2473: fconst_0      
    2474: invokestatic  #32                 // Method java/lang/Float.valueOf:(F)Ljava/lang/Float;
    2477: invokeinterface #33,  4           // InterfaceMethod enerj/rt/PrecisionRuntime.storeLocal:(Lenerj/rt/Reference;ZLjava/lang/Object;)Ljava/lang/Object;
    2482: pop           
    2483: getstatic     #2                  // Field enerj/rt/PrecisionRuntimeRoot.impl:Lenerj/rt/PrecisionRuntime;
    2486: getstatic     #2                  // Field enerj/rt/PrecisionRuntimeRoot.impl:Lenerj/rt/PrecisionRuntime;
    2489: aload         33
    2491: iconst_1      
    2492: invokeinterface #28,  3           // InterfaceMethod enerj/rt/PrecisionRuntime.loadLocal:(Lenerj/rt/Reference;Z)Ljava/lang/Object;
    2497: checkcast     #34                 // class java/lang/Float
    2500: invokevirtual #35                 // Method java/lang/Float.floatValue:()F
    2503: invokestatic  #41                 // Method com/jme/math/ApproxMath.abs:(F)F
    2506: f2d           
    2507: getstatic     #2                  // Field enerj/rt/PrecisionRuntimeRoot.impl:Lenerj/rt/PrecisionRuntime;
    2510: ldc_w         #5                  // class com/jme/intersection/Intersection
    2513: ldc           #42                 // String EPSILON
    2515: iconst_0      
    2516: invokeinterface #24,  4           // InterfaceMethod enerj/rt/PrecisionRuntime.loadField:(Ljava/lang/Object;Ljava/lang/String;Z)Ljava/lang/Object;
    2521: checkcast     #43                 // class java/lang/Double
    2524: invokevirtual #44                 // Method java/lang/Double.doubleValue:()D
    2527: dcmpg         
    2528: ifge          2535
    2531: iconst_1      
    2532: goto          2536
    2535: iconst_0      
    2536: invokestatic  #45                 // Method java/lang/Boolean.valueOf:(Z)Ljava/lang/Boolean;
    2539: invokeinterface #46,  2           // InterfaceMethod enerj/rt/PrecisionRuntime.countLogicalOp:(Ljava/lang/Object;)Ljava/lang/Object;
    2544: checkcast     #47                 // class java/lang/Boolean
    2547: invokevirtual #48                 // Method java/lang/Boolean.booleanValue:()Z
    2550: ifeq          2569
    2553: getstatic     #2                  // Field enerj/rt/PrecisionRuntimeRoot.impl:Lenerj/rt/PrecisionRuntime;
    2556: aload         33
    2558: iconst_1      
    2559: fconst_0      
    2560: invokestatic  #32                 // Method java/lang/Float.valueOf:(F)Ljava/lang/Float;
    2563: invokeinterface #33,  4           // InterfaceMethod enerj/rt/PrecisionRuntime.storeLocal:(Lenerj/rt/Reference;ZLjava/lang/Object;)Ljava/lang/Object;
    2568: pop           
    2569: getstatic     #2                  // Field enerj/rt/PrecisionRuntimeRoot.impl:Lenerj/rt/PrecisionRuntime;
    2572: getstatic     #2                  // Field enerj/rt/PrecisionRuntimeRoot.impl:Lenerj/rt/PrecisionRuntime;
    2575: aload         35
    2577: iconst_1      
    2578: invokeinterface #28,  3           // InterfaceMethod enerj/rt/PrecisionRuntime.loadLocal:(Lenerj/rt/Reference;Z)Ljava/lang/Object;
    2583: checkcast     #34                 // class java/lang/Float
    2586: invokevirtual #35                 // Method java/lang/Float.floatValue:()F
    2589: invokestatic  #41                 // Method com/jme/math/ApproxMath.abs:(F)F
    2592: f2d           
    2593: getstatic     #2                  // Field enerj/rt/PrecisionRuntimeRoot.impl:Lenerj/rt/PrecisionRuntime;
    2596: ldc_w         #5                  // class com/jme/intersection/Intersection
    2599: ldc           #42                 // String EPSILON
    2601: iconst_0      
    2602: invokeinterface #24,  4           // InterfaceMethod enerj/rt/PrecisionRuntime.loadField:(Ljava/lang/Object;Ljava/lang/String;Z)Ljava/lang/Object;
    2607: checkcast     #43                 // class java/lang/Double
    2610: invokevirtual #44                 // Method java/lang/Double.doubleValue:()D
    2613: dcmpg         
    2614: ifge          2621
    2617: iconst_1      
    2618: goto          2622
    2621: iconst_0      
    2622: invokestatic  #45                 // Method java/lang/Boolean.valueOf:(Z)Ljava/lang/Boolean;
    2625: invokeinterface #46,  2           // InterfaceMethod enerj/rt/PrecisionRuntime.countLogicalOp:(Ljava/lang/Object;)Ljava/lang/Object;
    2630: checkcast     #47                 // class java/lang/Boolean
    2633: invokevirtual #48                 // Method java/lang/Boolean.booleanValue:()Z
    2636: ifeq          2655
    2639: getstatic     #2                  // Field enerj/rt/PrecisionRuntimeRoot.impl:Lenerj/rt/PrecisionRuntime;
    2642: aload         35
    2644: iconst_0      
    2645: fconst_0      
    2646: invokestatic  #32                 // Method java/lang/Float.valueOf:(F)Ljava/lang/Float;
    2649: invokeinterface #33,  4           // InterfaceMethod enerj/rt/PrecisionRuntime.storeLocal:(Lenerj/rt/Reference;ZLjava/lang/Object;)Ljava/lang/Object;
    2654: pop           
    2655: getstatic     #2                  // Field enerj/rt/PrecisionRuntimeRoot.impl:Lenerj/rt/PrecisionRuntime;
    2658: aload         47
    2660: iconst_1      
    2661: getstatic     #2                  // Field enerj/rt/PrecisionRuntimeRoot.impl:Lenerj/rt/PrecisionRuntime;
    2664: getstatic     #2                  // Field enerj/rt/PrecisionRuntimeRoot.impl:Lenerj/rt/PrecisionRuntime;
    2667: aload         31
    2669: iconst_1      
    2670: invokeinterface #28,  3           // InterfaceMethod enerj/rt/PrecisionRuntime.loadLocal:(Lenerj/rt/Reference;Z)Ljava/lang/Object;
    2675: checkcast     #34                 // class java/lang/Float
    2678: invokevirtual #35                 // Method java/lang/Float.floatValue:()F
    2681: invokestatic  #32                 // Method java/lang/Float.valueOf:(F)Ljava/lang/Float;
    2684: getstatic     #2                  // Field enerj/rt/PrecisionRuntimeRoot.impl:Lenerj/rt/PrecisionRuntime;
    2687: aload         33
    2689: iconst_1      
    2690: invokeinterface #28,  3           // InterfaceMethod enerj/rt/PrecisionRuntime.loadLocal:(Lenerj/rt/Reference;Z)Ljava/lang/Object;
    2695: checkcast     #34                 // class java/lang/Float
    2698: invokevirtual #35                 // Method java/lang/Float.floatValue:()F
    2701: invokestatic  #32                 // Method java/lang/Float.valueOf:(F)Ljava/lang/Float;
    2704: getstatic     #49                 // Field enerj/rt/PrecisionRuntime$ArithOperator.MULTIPLY:Lenerj/rt/PrecisionRuntime$ArithOperator;
    2707: getstatic     #37                 // Field enerj/rt/PrecisionRuntime$NumberKind.FLOAT:Lenerj/rt/PrecisionRuntime$NumberKind;
    2710: iconst_1      
    2711: invokeinterface #38,  6           // InterfaceMethod enerj/rt/PrecisionRuntime.binaryOp:(Ljava/lang/Number;Ljava/lang/Number;Lenerj/rt/PrecisionRuntime$ArithOperator;Lenerj/rt/PrecisionRuntime$NumberKind;Z)Ljava/lang/Number;
    2716: invokevirtual #39                 // Method java/lang/Number.floatValue:()F
    2719: invokestatic  #32                 // Method java/lang/Float.valueOf:(F)Ljava/lang/Float;
    2722: invokeinterface #33,  4           // InterfaceMethod enerj/rt/PrecisionRuntime.storeLocal:(Lenerj/rt/Reference;ZLjava/lang/Object;)Ljava/lang/Object;
    2727: pop           
    2728: getstatic     #2                  // Field enerj/rt/PrecisionRuntimeRoot.impl:Lenerj/rt/PrecisionRuntime;
    2731: aload         49
    2733: iconst_1      
    2734: getstatic     #2                  // Field enerj/rt/PrecisionRuntimeRoot.impl:Lenerj/rt/PrecisionRuntime;
    2737: getstatic     #2                  // Field enerj/rt/PrecisionRuntimeRoot.impl:Lenerj/rt/PrecisionRuntime;
    2740: aload         31
    2742: iconst_1      
    2743: invokeinterface #28,  3           // InterfaceMethod enerj/rt/PrecisionRuntime.loadLocal:(Lenerj/rt/Reference;Z)Ljava/lang/Object;
    2748: checkcast     #34                 // class java/lang/Float
    2751: invokevirtual #35                 // Method java/lang/Float.floatValue:()F
    2754: invokestatic  #32                 // Method java/lang/Float.valueOf:(F)Ljava/lang/Float;
    2757: getstatic     #2                  // Field enerj/rt/PrecisionRuntimeRoot.impl:Lenerj/rt/PrecisionRuntime;
    2760: aload         35
    2762: iconst_1      
    2763: invokeinterface #28,  3           // InterfaceMethod enerj/rt/PrecisionRuntime.loadLocal:(Lenerj/rt/Reference;Z)Ljava/lang/Object;
    2768: checkcast     #34                 // class java/lang/Float
    2771: invokevirtual #35                 // Method java/lang/Float.floatValue:()F
    2774: invokestatic  #32                 // Method java/lang/Float.valueOf:(F)Ljava/lang/Float;
    2777: getstatic     #49                 // Field enerj/rt/PrecisionRuntime$ArithOperator.MULTIPLY:Lenerj/rt/PrecisionRuntime$ArithOperator;
    2780: getstatic     #37                 // Field enerj/rt/PrecisionRuntime$NumberKind.FLOAT:Lenerj/rt/PrecisionRuntime$NumberKind;
    2783: iconst_1      
    2784: invokeinterface #38,  6           // InterfaceMethod enerj/rt/PrecisionRuntime.binaryOp:(Ljava/lang/Number;Ljava/lang/Number;Lenerj/rt/PrecisionRuntime$ArithOperator;Lenerj/rt/PrecisionRuntime$NumberKind;Z)Ljava/lang/Number;
    2789: invokevirtual #39                 // Method java/lang/Number.floatValue:()F
    2792: invokestatic  #32                 // Method java/lang/Float.valueOf:(F)Ljava/lang/Float;
    2795: invokeinterface #33,  4           // InterfaceMethod enerj/rt/PrecisionRuntime.storeLocal:(Lenerj/rt/Reference;ZLjava/lang/Object;)Ljava/lang/Object;
    2800: pop           
    2801: getstatic     #2                  // Field enerj/rt/PrecisionRuntimeRoot.impl:Lenerj/rt/PrecisionRuntime;
    2804: aload         47
    2806: iconst_0      
    2807: getstatic     #2                  // Field enerj/rt/PrecisionRuntimeRoot.impl:Lenerj/rt/PrecisionRuntime;
    2810: aload         47
    2812: iconst_1      
    2813: invokeinterface #28,  3           // InterfaceMethod enerj/rt/PrecisionRuntime.loadLocal:(Lenerj/rt/Reference;Z)Ljava/lang/Object;
    2818: checkcast     #34                 // class java/lang/Float
    2821: invokevirtual #35                 // Method java/lang/Float.floatValue:()F
    2824: invokestatic  #40                 // Method accept:(F)F
    2827: invokestatic  #32                 // Method java/lang/Float.valueOf:(F)Ljava/lang/Float;
    2830: invokeinterface #33,  4           // InterfaceMethod enerj/rt/PrecisionRuntime.storeLocal:(Lenerj/rt/Reference;ZLjava/lang/Object;)Ljava/lang/Object;
    2835: pop           
    2836: getstatic     #2                  // Field enerj/rt/PrecisionRuntimeRoot.impl:Lenerj/rt/PrecisionRuntime;
    2839: aload         49
    2841: iconst_0      
    2842: getstatic     #2                  // Field enerj/rt/PrecisionRuntimeRoot.impl:Lenerj/rt/PrecisionRuntime;
    2845: aload         49
    2847: iconst_1      
    2848: invokeinterface #28,  3           // InterfaceMethod enerj/rt/PrecisionRuntime.loadLocal:(Lenerj/rt/Reference;Z)Ljava/lang/Object;
    2853: checkcast     #34                 // class java/lang/Float
    2856: invokevirtual #35                 // Method java/lang/Float.floatValue:()F
    2859: invokestatic  #40                 // Method accept:(F)F
    2862: invokestatic  #32                 // Method java/lang/Float.valueOf:(F)Ljava/lang/Float;
    2865: invokeinterface #33,  4           // InterfaceMethod enerj/rt/PrecisionRuntime.storeLocal:(Lenerj/rt/Reference;ZLjava/lang/Object;)Ljava/lang/Object;
    2870: pop           
    2871: getstatic     #2                  // Field enerj/rt/PrecisionRuntimeRoot.impl:Lenerj/rt/PrecisionRuntime;
    2874: getstatic     #2                  // Field enerj/rt/PrecisionRuntimeRoot.impl:Lenerj/rt/PrecisionRuntime;
    2877: getstatic     #2                  // Field enerj/rt/PrecisionRuntimeRoot.impl:Lenerj/rt/PrecisionRuntime;
    2880: aload         47
    2882: iconst_1      
    2883: invokeinterface #28,  3           // InterfaceMethod enerj/rt/PrecisionRuntime.loadLocal:(Lenerj/rt/Reference;Z)Ljava/lang/Object;
    2888: checkcast     #34                 // class java/lang/Float
    2891: invokevirtual #35                 // Method java/lang/Float.floatValue:()F
    2894: fconst_0      
    2895: fcmpl         
    2896: ifle          2903
    2899: iconst_1      
    2900: goto          2904
    2903: iconst_0      
    2904: invokestatic  #45                 // Method java/lang/Boolean.valueOf:(Z)Ljava/lang/Boolean;
    2907: invokeinterface #46,  2           // InterfaceMethod enerj/rt/PrecisionRuntime.countLogicalOp:(Ljava/lang/Object;)Ljava/lang/Object;
    2912: checkcast     #47                 // class java/lang/Boolean
    2915: invokevirtual #48                 // Method java/lang/Boolean.booleanValue:()Z
    2918: ifeq          2972
    2921: getstatic     #2                  // Field enerj/rt/PrecisionRuntimeRoot.impl:Lenerj/rt/PrecisionRuntime;
    2924: getstatic     #2                  // Field enerj/rt/PrecisionRuntimeRoot.impl:Lenerj/rt/PrecisionRuntime;
    2927: aload         49
    2929: iconst_1      
    2930: invokeinterface #28,  3           // InterfaceMethod enerj/rt/PrecisionRuntime.loadLocal:(Lenerj/rt/Reference;Z)Ljava/lang/Object;
    2935: checkcast     #34                 // class java/lang/Float
    2938: invokevirtual #35                 // Method java/lang/Float.floatValue:()F
    2941: fconst_0      
    2942: fcmpl         
    2943: ifle          2950
    2946: iconst_1      
    2947: goto          2951
    2950: iconst_0      
    2951: invokestatic  #45                 // Method java/lang/Boolean.valueOf:(Z)Ljava/lang/Boolean;
    2954: invokeinterface #46,  2           // InterfaceMethod enerj/rt/PrecisionRuntime.countLogicalOp:(Ljava/lang/Object;)Ljava/lang/Object;
    2959: checkcast     #47                 // class java/lang/Boolean
    2962: invokevirtual #48                 // Method java/lang/Boolean.booleanValue:()Z
    2965: ifeq          2972
    2968: iconst_1      
    2969: goto          2973
    2972: iconst_0      
    2973: invokestatic  #45                 // Method java/lang/Boolean.valueOf:(Z)Ljava/lang/Boolean;
    2976: invokeinterface #46,  2           // InterfaceMethod enerj/rt/PrecisionRuntime.countLogicalOp:(Ljava/lang/Object;)Ljava/lang/Object;
    2981: checkcast     #47                 // class java/lang/Boolean
    2984: invokevirtual #48                 // Method java/lang/Boolean.booleanValue:()Z
    2987: ifeq          2992
    2990: iconst_0      
    2991: ireturn       
    2992: getstatic     #2                  // Field enerj/rt/PrecisionRuntimeRoot.impl:Lenerj/rt/PrecisionRuntime;
    2995: aload         17
    2997: iconst_1      
    2998: invokeinterface #28,  3           // InterfaceMethod enerj/rt/PrecisionRuntime.loadLocal:(Lenerj/rt/Reference;Z)Ljava/lang/Object;
    3003: checkcast     #9                  // class com/jme/math/Vector3f
    3006: getstatic     #2                  // Field enerj/rt/PrecisionRuntimeRoot.impl:Lenerj/rt/PrecisionRuntime;
    3009: aload         19
    3011: iconst_1      
    3012: invokeinterface #28,  3           // InterfaceMethod enerj/rt/PrecisionRuntime.loadLocal:(Lenerj/rt/Reference;Z)Ljava/lang/Object;
    3017: checkcast     #9                  // class com/jme/math/Vector3f
    3020: getstatic     #2                  // Field enerj/rt/PrecisionRuntimeRoot.impl:Lenerj/rt/PrecisionRuntime;
    3023: aload         37
    3025: iconst_1      
    3026: invokeinterface #28,  3           // InterfaceMethod enerj/rt/PrecisionRuntime.loadLocal:(Lenerj/rt/Reference;Z)Ljava/lang/Object;
    3031: checkcast     #9                  // class com/jme/math/Vector3f
    3034: invokevirtual #30                 // Method com/jme/math/Vector3f.cross:(Lcom/jme/math/Vector3f;Lcom/jme/math/Vector3f;)Lcom/jme/math/Vector3f;
    3037: pop           
    3038: getstatic     #2                  // Field enerj/rt/PrecisionRuntimeRoot.impl:Lenerj/rt/PrecisionRuntime;
    3041: aload         37
    3043: iconst_0      
    3044: getstatic     #2                  // Field enerj/rt/PrecisionRuntimeRoot.impl:Lenerj/rt/PrecisionRuntime;
    3047: aload         37
    3049: iconst_1      
    3050: invokeinterface #28,  3           // InterfaceMethod enerj/rt/PrecisionRuntime.loadLocal:(Lenerj/rt/Reference;Z)Ljava/lang/Object;
    3055: checkcast     #9                  // class com/jme/math/Vector3f
    3058: invokestatic  #50                 // Method accept_all_FIELD1_TAG1:(Lcom/jme/math/Vector3f;)Lcom/jme/math/Vector3f;
    3061: invokeinterface #33,  4           // InterfaceMethod enerj/rt/PrecisionRuntime.storeLocal:(Lenerj/rt/Reference;ZLjava/lang/Object;)Ljava/lang/Object;
    3066: pop           
    3067: getstatic     #2                  // Field enerj/rt/PrecisionRuntimeRoot.impl:Lenerj/rt/PrecisionRuntime;
    3070: aload         37
    3072: iconst_0      
    3073: getstatic     #2                  // Field enerj/rt/PrecisionRuntimeRoot.impl:Lenerj/rt/PrecisionRuntime;
    3076: aload         37
    3078: iconst_1      
    3079: invokeinterface #28,  3           // InterfaceMethod enerj/rt/PrecisionRuntime.loadLocal:(Lenerj/rt/Reference;Z)Ljava/lang/Object;
    3084: checkcast     #9                  // class com/jme/math/Vector3f
    3087: invokestatic  #51                 // Method accept_all_FIELD2_TAG1:(Lcom/jme/math/Vector3f;)Lcom/jme/math/Vector3f;
    3090: invokeinterface #33,  4           // InterfaceMethod enerj/rt/PrecisionRuntime.storeLocal:(Lenerj/rt/Reference;ZLjava/lang/Object;)Ljava/lang/Object;
    3095: pop           
    3096: getstatic     #2                  // Field enerj/rt/PrecisionRuntimeRoot.impl:Lenerj/rt/PrecisionRuntime;
    3099: aload         37
    3101: iconst_0      
    3102: getstatic     #2                  // Field enerj/rt/PrecisionRuntimeRoot.impl:Lenerj/rt/PrecisionRuntime;
    3105: aload         37
    3107: iconst_1      
    3108: invokeinterface #28,  3           // InterfaceMethod enerj/rt/PrecisionRuntime.loadLocal:(Lenerj/rt/Reference;Z)Ljava/lang/Object;
    3113: checkcast     #9                  // class com/jme/math/Vector3f
    3116: invokestatic  #52                 // Method accept_all_FIELD3_TAG1:(Lcom/jme/math/Vector3f;)Lcom/jme/math/Vector3f;
    3119: invokeinterface #33,  4           // InterfaceMethod enerj/rt/PrecisionRuntime.storeLocal:(Lenerj/rt/Reference;ZLjava/lang/Object;)Ljava/lang/Object;
    3124: pop           
    3125: getstatic     #2                  // Field enerj/rt/PrecisionRuntimeRoot.impl:Lenerj/rt/PrecisionRuntime;
    3128: aload         69
    3130: iconst_1      
    3131: getstatic     #2                  // Field enerj/rt/PrecisionRuntimeRoot.impl:Lenerj/rt/PrecisionRuntime;
    3134: aload         37
    3136: iconst_1      
    3137: invokeinterface #28,  3           // InterfaceMethod enerj/rt/PrecisionRuntime.loadLocal:(Lenerj/rt/Reference;Z)Ljava/lang/Object;
    3142: checkcast     #9                  // class com/jme/math/Vector3f
    3145: getfield      #53                 // Field com/jme/math/Vector3f.x:F
    3148: invokestatic  #41                 // Method com/jme/math/ApproxMath.abs:(F)F
    3151: invokestatic  #32                 // Method java/lang/Float.valueOf:(F)Ljava/lang/Float;
    3154: invokeinterface #33,  4           // InterfaceMethod enerj/rt/PrecisionRuntime.storeLocal:(Lenerj/rt/Reference;ZLjava/lang/Object;)Ljava/lang/Object;
    3159: pop           
    3160: getstatic     #2                  // Field enerj/rt/PrecisionRuntimeRoot.impl:Lenerj/rt/PrecisionRuntime;
    3163: aload         51
    3165: iconst_0      
    3166: iconst_0      
    3167: invokestatic  #54                 // Method java/lang/Short.valueOf:(S)Ljava/lang/Short;
    3170: invokeinterface #33,  4           // InterfaceMethod enerj/rt/PrecisionRuntime.storeLocal:(Lenerj/rt/Reference;ZLjava/lang/Object;)Ljava/lang/Object;
    3175: pop           
    3176: getstatic     #2                  // Field enerj/rt/PrecisionRuntimeRoot.impl:Lenerj/rt/PrecisionRuntime;
    3179: aload         65
    3181: iconst_1      
    3182: getstatic     #2                  // Field enerj/rt/PrecisionRuntimeRoot.impl:Lenerj/rt/PrecisionRuntime;
    3185: aload         37
    3187: iconst_1      
    3188: invokeinterface #28,  3           // InterfaceMethod enerj/rt/PrecisionRuntime.loadLocal:(Lenerj/rt/Reference;Z)Ljava/lang/Object;
    3193: checkcast     #9                  // class com/jme/math/Vector3f
    3196: getfield      #55                 // Field com/jme/math/Vector3f.y:F
    3199: invokestatic  #41                 // Method com/jme/math/ApproxMath.abs:(F)F
    3202: invokestatic  #32                 // Method java/lang/Float.valueOf:(F)Ljava/lang/Float;
    3205: invokeinterface #33,  4           // InterfaceMethod enerj/rt/PrecisionRuntime.storeLocal:(Lenerj/rt/Reference;ZLjava/lang/Object;)Ljava/lang/Object;
    3210: pop           
    3211: getstatic     #2                  // Field enerj/rt/PrecisionRuntimeRoot.impl:Lenerj/rt/PrecisionRuntime;
    3214: aload         67
    3216: iconst_1      
    3217: getstatic     #2                  // Field enerj/rt/PrecisionRuntimeRoot.impl:Lenerj/rt/PrecisionRuntime;
    3220: aload         37
    3222: iconst_1      
    3223: invokeinterface #28,  3           // InterfaceMethod enerj/rt/PrecisionRuntime.loadLocal:(Lenerj/rt/Reference;Z)Ljava/lang/Object;
    3228: checkcast     #9                  // class com/jme/math/Vector3f
    3231: getfield      #56                 // Field com/jme/math/Vector3f.z:F
    3234: invokestatic  #41                 // Method com/jme/math/ApproxMath.abs:(F)F
    3237: invokestatic  #32                 // Method java/lang/Float.valueOf:(F)Ljava/lang/Float;
    3240: invokeinterface #33,  4           // InterfaceMethod enerj/rt/PrecisionRuntime.storeLocal:(Lenerj/rt/Reference;ZLjava/lang/Object;)Ljava/lang/Object;
    3245: pop           
    3246: getstatic     #2                  // Field enerj/rt/PrecisionRuntimeRoot.impl:Lenerj/rt/PrecisionRuntime;
    3249: aload         65
    3251: iconst_0      
    3252: getstatic     #2                  // Field enerj/rt/PrecisionRuntimeRoot.impl:Lenerj/rt/PrecisionRuntime;
    3255: aload         65
    3257: iconst_1      
    3258: invokeinterface #28,  3           // InterfaceMethod enerj/rt/PrecisionRuntime.loadLocal:(Lenerj/rt/Reference;Z)Ljava/lang/Object;
    3263: checkcast     #34                 // class java/lang/Float
    3266: invokevirtual #35                 // Method java/lang/Float.floatValue:()F
    3269: invokestatic  #40                 // Method accept:(F)F
    3272: invokestatic  #32                 // Method java/lang/Float.valueOf:(F)Ljava/lang/Float;
    3275: invokeinterface #33,  4           // InterfaceMethod enerj/rt/PrecisionRuntime.storeLocal:(Lenerj/rt/Reference;ZLjava/lang/Object;)Ljava/lang/Object;
    3280: pop           
    3281: getstatic     #2                  // Field enerj/rt/PrecisionRuntimeRoot.impl:Lenerj/rt/PrecisionRuntime;
    3284: aload         67
    3286: iconst_0      
    3287: getstatic     #2                  // Field enerj/rt/PrecisionRuntimeRoot.impl:Lenerj/rt/PrecisionRuntime;
    3290: aload         67
    3292: iconst_1      
    3293: invokeinterface #28,  3           // InterfaceMethod enerj/rt/PrecisionRuntime.loadLocal:(Lenerj/rt/Reference;Z)Ljava/lang/Object;
    3298: checkcast     #34                 // class java/lang/Float
    3301: invokevirtual #35                 // Method java/lang/Float.floatValue:()F
    3304: invokestatic  #40                 // Method accept:(F)F
    3307: invokestatic  #32                 // Method java/lang/Float.valueOf:(F)Ljava/lang/Float;
    3310: invokeinterface #33,  4           // InterfaceMethod enerj/rt/PrecisionRuntime.storeLocal:(Lenerj/rt/Reference;ZLjava/lang/Object;)Ljava/lang/Object;
    3315: pop           
    3316: getstatic     #2                  // Field enerj/rt/PrecisionRuntimeRoot.impl:Lenerj/rt/PrecisionRuntime;
    3319: aload         69
    3321: iconst_0      
    3322: getstatic     #2                  // Field enerj/rt/PrecisionRuntimeRoot.impl:Lenerj/rt/PrecisionRuntime;
    3325: aload         69
    3327: iconst_1      
    3328: invokeinterface #28,  3           // InterfaceMethod enerj/rt/PrecisionRuntime.loadLocal:(Lenerj/rt/Reference;Z)Ljava/lang/Object;
    3333: checkcast     #34                 // class java/lang/Float
    3336: invokevirtual #35                 // Method java/lang/Float.floatValue:()F
    3339: invokestatic  #40                 // Method accept:(F)F
    3342: invokestatic  #32                 // Method java/lang/Float.valueOf:(F)Ljava/lang/Float;
    3345: invokeinterface #33,  4           // InterfaceMethod enerj/rt/PrecisionRuntime.storeLocal:(Lenerj/rt/Reference;ZLjava/lang/Object;)Ljava/lang/Object;
    3350: pop           
    3351: getstatic     #2                  // Field enerj/rt/PrecisionRuntimeRoot.impl:Lenerj/rt/PrecisionRuntime;
    3354: getstatic     #2                  // Field enerj/rt/PrecisionRuntimeRoot.impl:Lenerj/rt/PrecisionRuntime;
    3357: aload         65
    3359: iconst_1      
    3360: invokeinterface #28,  3           // InterfaceMethod enerj/rt/PrecisionRuntime.loadLocal:(Lenerj/rt/Reference;Z)Ljava/lang/Object;
    3365: checkcast     #34                 // class java/lang/Float
    3368: invokevirtual #35                 // Method java/lang/Float.floatValue:()F
    3371: getstatic     #2                  // Field enerj/rt/PrecisionRuntimeRoot.impl:Lenerj/rt/PrecisionRuntime;
    3374: aload         69
    3376: iconst_1      
    3377: invokeinterface #28,  3           // InterfaceMethod enerj/rt/PrecisionRuntime.loadLocal:(Lenerj/rt/Reference;Z)Ljava/lang/Object;
    3382: checkcast     #34                 // class java/lang/Float
    3385: invokevirtual #35                 // Method java/lang/Float.floatValue:()F
    3388: fcmpl         
    3389: ifle          3396
    3392: iconst_1      
    3393: goto          3397
    3396: iconst_0      
    3397: invokestatic  #45                 // Method java/lang/Boolean.valueOf:(Z)Ljava/lang/Boolean;
    3400: invokeinterface #46,  2           // InterfaceMethod enerj/rt/PrecisionRuntime.countLogicalOp:(Ljava/lang/Object;)Ljava/lang/Object;
    3405: checkcast     #47                 // class java/lang/Boolean
    3408: invokevirtual #48                 // Method java/lang/Boolean.booleanValue:()Z
    3411: ifeq          3462
    3414: getstatic     #2                  // Field enerj/rt/PrecisionRuntimeRoot.impl:Lenerj/rt/PrecisionRuntime;
    3417: aload         69
    3419: iconst_0      
    3420: getstatic     #2                  // Field enerj/rt/PrecisionRuntimeRoot.impl:Lenerj/rt/PrecisionRuntime;
    3423: aload         65
    3425: iconst_1      
    3426: invokeinterface #28,  3           // InterfaceMethod enerj/rt/PrecisionRuntime.loadLocal:(Lenerj/rt/Reference;Z)Ljava/lang/Object;
    3431: checkcast     #34                 // class java/lang/Float
    3434: invokevirtual #35                 // Method java/lang/Float.floatValue:()F
    3437: invokestatic  #32                 // Method java/lang/Float.valueOf:(F)Ljava/lang/Float;
    3440: invokeinterface #33,  4           // InterfaceMethod enerj/rt/PrecisionRuntime.storeLocal:(Lenerj/rt/Reference;ZLjava/lang/Object;)Ljava/lang/Object;
    3445: pop           
    3446: getstatic     #2                  // Field enerj/rt/PrecisionRuntimeRoot.impl:Lenerj/rt/PrecisionRuntime;
    3449: aload         51
    3451: iconst_0      
    3452: iconst_1      
    3453: invokestatic  #54                 // Method java/lang/Short.valueOf:(S)Ljava/lang/Short;
    3456: invokeinterface #33,  4           // InterfaceMethod enerj/rt/PrecisionRuntime.storeLocal:(Lenerj/rt/Reference;ZLjava/lang/Object;)Ljava/lang/Object;
    3461: pop           
    3462: getstatic     #2                  // Field enerj/rt/PrecisionRuntimeRoot.impl:Lenerj/rt/PrecisionRuntime;
    3465: getstatic     #2                  // Field enerj/rt/PrecisionRuntimeRoot.impl:Lenerj/rt/PrecisionRuntime;
    3468: aload         67
    3470: iconst_1      
    3471: invokeinterface #28,  3           // InterfaceMethod enerj/rt/PrecisionRuntime.loadLocal:(Lenerj/rt/Reference;Z)Ljava/lang/Object;
    3476: checkcast     #34                 // class java/lang/Float
    3479: invokevirtual #35                 // Method java/lang/Float.floatValue:()F
    3482: getstatic     #2                  // Field enerj/rt/PrecisionRuntimeRoot.impl:Lenerj/rt/PrecisionRuntime;
    3485: aload         69
    3487: iconst_1      
    3488: invokeinterface #28,  3           // InterfaceMethod enerj/rt/PrecisionRuntime.loadLocal:(Lenerj/rt/Reference;Z)Ljava/lang/Object;
    3493: checkcast     #34                 // class java/lang/Float
    3496: invokevirtual #35                 // Method java/lang/Float.floatValue:()F
    3499: fcmpl         
    3500: ifle          3507
    3503: iconst_1      
    3504: goto          3508
    3507: iconst_0      
    3508: invokestatic  #45                 // Method java/lang/Boolean.valueOf:(Z)Ljava/lang/Boolean;
    3511: invokeinterface #46,  2           // InterfaceMethod enerj/rt/PrecisionRuntime.countLogicalOp:(Ljava/lang/Object;)Ljava/lang/Object;
    3516: checkcast     #47                 // class java/lang/Boolean
    3519: invokevirtual #48                 // Method java/lang/Boolean.booleanValue:()Z
    3522: ifeq          3752
    3525: getstatic     #2                  // Field enerj/rt/PrecisionRuntimeRoot.impl:Lenerj/rt/PrecisionRuntime;
    3528: aload         69
    3530: iconst_1      
    3531: getstatic     #2                  // Field enerj/rt/PrecisionRuntimeRoot.impl:Lenerj/rt/PrecisionRuntime;
    3534: aload         67
    3536: iconst_1      
    3537: invokeinterface #28,  3           // InterfaceMethod enerj/rt/PrecisionRuntime.loadLocal:(Lenerj/rt/Reference;Z)Ljava/lang/Object;
    3542: checkcast     #34                 // class java/lang/Float
    3545: invokevirtual #35                 // Method java/lang/Float.floatValue:()F
    3548: invokestatic  #32                 // Method java/lang/Float.valueOf:(F)Ljava/lang/Float;
    3551: invokeinterface #33,  4           // InterfaceMethod enerj/rt/PrecisionRuntime.storeLocal:(Lenerj/rt/Reference;ZLjava/lang/Object;)Ljava/lang/Object;
    3556: pop           
    3557: getstatic     #2                  // Field enerj/rt/PrecisionRuntimeRoot.impl:Lenerj/rt/PrecisionRuntime;
    3560: aload         53
    3562: iconst_1      
    3563: getstatic     #2                  // Field enerj/rt/PrecisionRuntimeRoot.impl:Lenerj/rt/PrecisionRuntime;
    3566: aload         11
    3568: iconst_1      
    3569: invokeinterface #28,  3           // InterfaceMethod enerj/rt/PrecisionRuntime.loadLocal:(Lenerj/rt/Reference;Z)Ljava/lang/Object;
    3574: checkcast     #9                  // class com/jme/math/Vector3f
    3577: getfield      #56                 // Field com/jme/math/Vector3f.z:F
    3580: invokestatic  #32                 // Method java/lang/Float.valueOf:(F)Ljava/lang/Float;
    3583: invokeinterface #33,  4           // InterfaceMethod enerj/rt/PrecisionRuntime.storeLocal:(Lenerj/rt/Reference;ZLjava/lang/Object;)Ljava/lang/Object;
    3588: pop           
    3589: getstatic     #2                  // Field enerj/rt/PrecisionRuntimeRoot.impl:Lenerj/rt/PrecisionRuntime;
    3592: aload         55
    3594: iconst_1      
    3595: getstatic     #2                  // Field enerj/rt/PrecisionRuntimeRoot.impl:Lenerj/rt/PrecisionRuntime;
    3598: aload         10
    3600: iconst_1      
    3601: invokeinterface #28,  3           // InterfaceMethod enerj/rt/PrecisionRuntime.loadLocal:(Lenerj/rt/Reference;Z)Ljava/lang/Object;
    3606: checkcast     #9                  // class com/jme/math/Vector3f
    3609: getfield      #56                 // Field com/jme/math/Vector3f.z:F
    3612: invokestatic  #32                 // Method java/lang/Float.valueOf:(F)Ljava/lang/Float;
    3615: invokeinterface #33,  4           // InterfaceMethod enerj/rt/PrecisionRuntime.storeLocal:(Lenerj/rt/Reference;ZLjava/lang/Object;)Ljava/lang/Object;
    3620: pop           
    3621: getstatic     #2                  // Field enerj/rt/PrecisionRuntimeRoot.impl:Lenerj/rt/PrecisionRuntime;
    3624: aload         57
    3626: iconst_1      
    3627: getstatic     #2                  // Field enerj/rt/PrecisionRuntimeRoot.impl:Lenerj/rt/PrecisionRuntime;
    3630: aload         9
    3632: iconst_1      
    3633: invokeinterface #28,  3           // InterfaceMethod enerj/rt/PrecisionRuntime.loadLocal:(Lenerj/rt/Reference;Z)Ljava/lang/Object;
    3638: checkcast     #9                  // class com/jme/math/Vector3f
    3641: getfield      #56                 // Field com/jme/math/Vector3f.z:F
    3644: invokestatic  #32                 // Method java/lang/Float.valueOf:(F)Ljava/lang/Float;
    3647: invokeinterface #33,  4           // InterfaceMethod enerj/rt/PrecisionRuntime.storeLocal:(Lenerj/rt/Reference;ZLjava/lang/Object;)Ljava/lang/Object;
    3652: pop           
    3653: getstatic     #2                  // Field enerj/rt/PrecisionRuntimeRoot.impl:Lenerj/rt/PrecisionRuntime;
    3656: aload         59
    3658: iconst_1      
    3659: getstatic     #2                  // Field enerj/rt/PrecisionRuntimeRoot.impl:Lenerj/rt/PrecisionRuntime;
    3662: aload         8
    3664: iconst_1      
    3665: invokeinterface #28,  3           // InterfaceMethod enerj/rt/PrecisionRuntime.loadLocal:(Lenerj/rt/Reference;Z)Ljava/lang/Object;
    3670: checkcast     #9                  // class com/jme/math/Vector3f
    3673: getfield      #56                 // Field com/jme/math/Vector3f.z:F
    3676: invokestatic  #32                 // Method java/lang/Float.valueOf:(F)Ljava/lang/Float;
    3679: invokeinterface #33,  4           // InterfaceMethod enerj/rt/PrecisionRuntime.storeLocal:(Lenerj/rt/Reference;ZLjava/lang/Object;)Ljava/lang/Object;
    3684: pop           
    3685: getstatic     #2                  // Field enerj/rt/PrecisionRuntimeRoot.impl:Lenerj/rt/PrecisionRuntime;
    3688: aload         61
    3690: iconst_1      
    3691: getstatic     #2                  // Field enerj/rt/PrecisionRuntimeRoot.impl:Lenerj/rt/PrecisionRuntime;
    3694: aload         7
    3696: iconst_1      
    3697: invokeinterface #28,  3           // InterfaceMethod enerj/rt/PrecisionRuntime.loadLocal:(Lenerj/rt/Reference;Z)Ljava/lang/Object;
    3702: checkcast     #9                  // class com/jme/math/Vector3f
    3705: getfield      #56                 // Field com/jme/math/Vector3f.z:F
    3708: invokestatic  #32                 // Method java/lang/Float.valueOf:(F)Ljava/lang/Float;
    3711: invokeinterface #33,  4           // InterfaceMethod enerj/rt/PrecisionRuntime.storeLocal:(Lenerj/rt/Reference;ZLjava/lang/Object;)Ljava/lang/Object;
    3716: pop           
    3717: getstatic     #2                  // Field enerj/rt/PrecisionRuntimeRoot.impl:Lenerj/rt/PrecisionRuntime;
    3720: aload         63
    3722: iconst_1      
    3723: getstatic     #2                  // Field enerj/rt/PrecisionRuntimeRoot.impl:Lenerj/rt/PrecisionRuntime;
    3726: aload         6
    3728: iconst_1      
    3729: invokeinterface #28,  3           // InterfaceMethod enerj/rt/PrecisionRuntime.loadLocal:(Lenerj/rt/Reference;Z)Ljava/lang/Object;
    3734: checkcast     #9                  // class com/jme/math/Vector3f
    3737: getfield      #56                 // Field com/jme/math/Vector3f.z:F
    3740: invokestatic  #32                 // Method java/lang/Float.valueOf:(F)Ljava/lang/Float;
    3743: invokeinterface #33,  4           // InterfaceMethod enerj/rt/PrecisionRuntime.storeLocal:(Lenerj/rt/Reference;ZLjava/lang/Object;)Ljava/lang/Object;
    3748: pop           
    3749: goto          4185
    3752: getstatic     #2                  // Field enerj/rt/PrecisionRuntimeRoot.impl:Lenerj/rt/PrecisionRuntime;
    3755: getstatic     #2                  // Field enerj/rt/PrecisionRuntimeRoot.impl:Lenerj/rt/PrecisionRuntime;
    3758: aload         51
    3760: iconst_0      
    3761: invokeinterface #28,  3           // InterfaceMethod enerj/rt/PrecisionRuntime.loadLocal:(Lenerj/rt/Reference;Z)Ljava/lang/Object;
    3766: checkcast     #57                 // class java/lang/Short
    3769: invokevirtual #58                 // Method java/lang/Short.shortValue:()S
    3772: iconst_1      
    3773: if_icmpne     3780
    3776: iconst_1      
    3777: goto          3781
    3780: iconst_0      
    3781: invokestatic  #45                 // Method java/lang/Boolean.valueOf:(Z)Ljava/lang/Boolean;
    3784: invokeinterface #46,  2           // InterfaceMethod enerj/rt/PrecisionRuntime.countLogicalOp:(Ljava/lang/Object;)Ljava/lang/Object;
    3789: checkcast     #47                 // class java/lang/Boolean
    3792: invokevirtual #48                 // Method java/lang/Boolean.booleanValue:()Z
    3795: ifeq          3993
    3798: getstatic     #2                  // Field enerj/rt/PrecisionRuntimeRoot.impl:Lenerj/rt/PrecisionRuntime;
    3801: aload         53
    3803: iconst_1      
    3804: getstatic     #2                  // Field enerj/rt/PrecisionRuntimeRoot.impl:Lenerj/rt/PrecisionRuntime;
    3807: aload         11
    3809: iconst_1      
    3810: invokeinterface #28,  3           // InterfaceMethod enerj/rt/PrecisionRuntime.loadLocal:(Lenerj/rt/Reference;Z)Ljava/lang/Object;
    3815: checkcast     #9                  // class com/jme/math/Vector3f
    3818: getfield      #55                 // Field com/jme/math/Vector3f.y:F
    3821: invokestatic  #32                 // Method java/lang/Float.valueOf:(F)Ljava/lang/Float;
    3824: invokeinterface #33,  4           // InterfaceMethod enerj/rt/PrecisionRuntime.storeLocal:(Lenerj/rt/Reference;ZLjava/lang/Object;)Ljava/lang/Object;
    3829: pop           
    3830: getstatic     #2                  // Field enerj/rt/PrecisionRuntimeRoot.impl:Lenerj/rt/PrecisionRuntime;
    3833: aload         55
    3835: iconst_1      
    3836: getstatic     #2                  // Field enerj/rt/PrecisionRuntimeRoot.impl:Lenerj/rt/PrecisionRuntime;
    3839: aload         10
    3841: iconst_1      
    3842: invokeinterface #28,  3           // InterfaceMethod enerj/rt/PrecisionRuntime.loadLocal:(Lenerj/rt/Reference;Z)Ljava/lang/Object;
    3847: checkcast     #9                  // class com/jme/math/Vector3f
    3850: getfield      #55                 // Field com/jme/math/Vector3f.y:F
    3853: invokestatic  #32                 // Method java/lang/Float.valueOf:(F)Ljava/lang/Float;
    3856: invokeinterface #33,  4           // InterfaceMethod enerj/rt/PrecisionRuntime.storeLocal:(Lenerj/rt/Reference;ZLjava/lang/Object;)Ljava/lang/Object;
    3861: pop           
    3862: getstatic     #2                  // Field enerj/rt/PrecisionRuntimeRoot.impl:Lenerj/rt/PrecisionRuntime;
    3865: aload         57
    3867: iconst_1      
    3868: getstatic     #2                  // Field enerj/rt/PrecisionRuntimeRoot.impl:Lenerj/rt/PrecisionRuntime;
    3871: aload         9
    3873: iconst_1      
    3874: invokeinterface #28,  3           // InterfaceMethod enerj/rt/PrecisionRuntime.loadLocal:(Lenerj/rt/Reference;Z)Ljava/lang/Object;
    3879: checkcast     #9                  // class com/jme/math/Vector3f
    3882: getfield      #55                 // Field com/jme/math/Vector3f.y:F
    3885: invokestatic  #32                 // Method java/lang/Float.valueOf:(F)Ljava/lang/Float;
    3888: invokeinterface #33,  4           // InterfaceMethod enerj/rt/PrecisionRuntime.storeLocal:(Lenerj/rt/Reference;ZLjava/lang/Object;)Ljava/lang/Object;
    3893: pop           
    3894: getstatic     #2                  // Field enerj/rt/PrecisionRuntimeRoot.impl:Lenerj/rt/PrecisionRuntime;
    3897: aload         59
    3899: iconst_1      
    3900: getstatic     #2                  // Field enerj/rt/PrecisionRuntimeRoot.impl:Lenerj/rt/PrecisionRuntime;
    3903: aload         8
    3905: iconst_1      
    3906: invokeinterface #28,  3           // InterfaceMethod enerj/rt/PrecisionRuntime.loadLocal:(Lenerj/rt/Reference;Z)Ljava/lang/Object;
    3911: checkcast     #9                  // class com/jme/math/Vector3f
    3914: getfield      #55                 // Field com/jme/math/Vector3f.y:F
    3917: invokestatic  #32                 // Method java/lang/Float.valueOf:(F)Ljava/lang/Float;
    3920: invokeinterface #33,  4           // InterfaceMethod enerj/rt/PrecisionRuntime.storeLocal:(Lenerj/rt/Reference;ZLjava/lang/Object;)Ljava/lang/Object;
    3925: pop           
    3926: getstatic     #2                  // Field enerj/rt/PrecisionRuntimeRoot.impl:Lenerj/rt/PrecisionRuntime;
    3929: aload         61
    3931: iconst_1      
    3932: getstatic     #2                  // Field enerj/rt/PrecisionRuntimeRoot.impl:Lenerj/rt/PrecisionRuntime;
    3935: aload         7
    3937: iconst_1      
    3938: invokeinterface #28,  3           // InterfaceMethod enerj/rt/PrecisionRuntime.loadLocal:(Lenerj/rt/Reference;Z)Ljava/lang/Object;
    3943: checkcast     #9                  // class com/jme/math/Vector3f
    3946: getfield      #55                 // Field com/jme/math/Vector3f.y:F
    3949: invokestatic  #32                 // Method java/lang/Float.valueOf:(F)Ljava/lang/Float;
    3952: invokeinterface #33,  4           // InterfaceMethod enerj/rt/PrecisionRuntime.storeLocal:(Lenerj/rt/Reference;ZLjava/lang/Object;)Ljava/lang/Object;
    3957: pop           
    3958: getstatic     #2                  // Field enerj/rt/PrecisionRuntimeRoot.impl:Lenerj/rt/PrecisionRuntime;
    3961: aload         63
    3963: iconst_1      
    3964: getstatic     #2                  // Field enerj/rt/PrecisionRuntimeRoot.impl:Lenerj/rt/PrecisionRuntime;
    3967: aload         6
    3969: iconst_1      
    3970: invokeinterface #28,  3           // InterfaceMethod enerj/rt/PrecisionRuntime.loadLocal:(Lenerj/rt/Reference;Z)Ljava/lang/Object;
    3975: checkcast     #9                  // class com/jme/math/Vector3f
    3978: getfield      #55                 // Field com/jme/math/Vector3f.y:F
    3981: invokestatic  #32                 // Method java/lang/Float.valueOf:(F)Ljava/lang/Float;
    3984: invokeinterface #33,  4           // InterfaceMethod enerj/rt/PrecisionRuntime.storeLocal:(Lenerj/rt/Reference;ZLjava/lang/Object;)Ljava/lang/Object;
    3989: pop           
    3990: goto          4185
    3993: getstatic     #2                  // Field enerj/rt/PrecisionRuntimeRoot.impl:Lenerj/rt/PrecisionRuntime;
    3996: aload         53
    3998: iconst_1      
    3999: getstatic     #2                  // Field enerj/rt/PrecisionRuntimeRoot.impl:Lenerj/rt/PrecisionRuntime;
    4002: aload         11
    4004: iconst_1      
    4005: invokeinterface #28,  3           // InterfaceMethod enerj/rt/PrecisionRuntime.loadLocal:(Lenerj/rt/Reference;Z)Ljava/lang/Object;
    4010: checkcast     #9                  // class com/jme/math/Vector3f
    4013: getfield      #53                 // Field com/jme/math/Vector3f.x:F
    4016: invokestatic  #32                 // Method java/lang/Float.valueOf:(F)Ljava/lang/Float;
    4019: invokeinterface #33,  4           // InterfaceMethod enerj/rt/PrecisionRuntime.storeLocal:(Lenerj/rt/Reference;ZLjava/lang/Object;)Ljava/lang/Object;
    4024: pop           
    4025: getstatic     #2                  // Field enerj/rt/PrecisionRuntimeRoot.impl:Lenerj/rt/PrecisionRuntime;
    4028: aload         55
    4030: iconst_1      
    4031: getstatic     #2                  // Field enerj/rt/PrecisionRuntimeRoot.impl:Lenerj/rt/PrecisionRuntime;
    4034: aload         10
    4036: iconst_1      
    4037: invokeinterface #28,  3           // InterfaceMethod enerj/rt/PrecisionRuntime.loadLocal:(Lenerj/rt/Reference;Z)Ljava/lang/Object;
    4042: checkcast     #9                  // class com/jme/math/Vector3f
    4045: getfield      #53                 // Field com/jme/math/Vector3f.x:F
    4048: invokestatic  #32                 // Method java/lang/Float.valueOf:(F)Ljava/lang/Float;
    4051: invokeinterface #33,  4           // InterfaceMethod enerj/rt/PrecisionRuntime.storeLocal:(Lenerj/rt/Reference;ZLjava/lang/Object;)Ljava/lang/Object;
    4056: pop           
    4057: getstatic     #2                  // Field enerj/rt/PrecisionRuntimeRoot.impl:Lenerj/rt/PrecisionRuntime;
    4060: aload         57
    4062: iconst_1      
    4063: getstatic     #2                  // Field enerj/rt/PrecisionRuntimeRoot.impl:Lenerj/rt/PrecisionRuntime;
    4066: aload         9
    4068: iconst_1      
    4069: invokeinterface #28,  3           // InterfaceMethod enerj/rt/PrecisionRuntime.loadLocal:(Lenerj/rt/Reference;Z)Ljava/lang/Object;
    4074: checkcast     #9                  // class com/jme/math/Vector3f
    4077: getfield      #53                 // Field com/jme/math/Vector3f.x:F
    4080: invokestatic  #32                 // Method java/lang/Float.valueOf:(F)Ljava/lang/Float;
    4083: invokeinterface #33,  4           // InterfaceMethod enerj/rt/PrecisionRuntime.storeLocal:(Lenerj/rt/Reference;ZLjava/lang/Object;)Ljava/lang/Object;
    4088: pop           
    4089: getstatic     #2                  // Field enerj/rt/PrecisionRuntimeRoot.impl:Lenerj/rt/PrecisionRuntime;
    4092: aload         59
    4094: iconst_1      
    4095: getstatic     #2                  // Field enerj/rt/PrecisionRuntimeRoot.impl:Lenerj/rt/PrecisionRuntime;
    4098: aload         8
    4100: iconst_1      
    4101: invokeinterface #28,  3           // InterfaceMethod enerj/rt/PrecisionRuntime.loadLocal:(Lenerj/rt/Reference;Z)Ljava/lang/Object;
    4106: checkcast     #9                  // class com/jme/math/Vector3f
    4109: getfield      #53                 // Field com/jme/math/Vector3f.x:F
    4112: invokestatic  #32                 // Method java/lang/Float.valueOf:(F)Ljava/lang/Float;
    4115: invokeinterface #33,  4           // InterfaceMethod enerj/rt/PrecisionRuntime.storeLocal:(Lenerj/rt/Reference;ZLjava/lang/Object;)Ljava/lang/Object;
    4120: pop           
    4121: getstatic     #2                  // Field enerj/rt/PrecisionRuntimeRoot.impl:Lenerj/rt/PrecisionRuntime;
    4124: aload         61
    4126: iconst_1      
    4127: getstatic     #2                  // Field enerj/rt/PrecisionRuntimeRoot.impl:Lenerj/rt/PrecisionRuntime;
    4130: aload         7
    4132: iconst_1      
    4133: invokeinterface #28,  3           // InterfaceMethod enerj/rt/PrecisionRuntime.loadLocal:(Lenerj/rt/Reference;Z)Ljava/lang/Object;
    4138: checkcast     #9                  // class com/jme/math/Vector3f
    4141: getfield      #53                 // Field com/jme/math/Vector3f.x:F
    4144: invokestatic  #32                 // Method java/lang/Float.valueOf:(F)Ljava/lang/Float;
    4147: invokeinterface #33,  4           // InterfaceMethod enerj/rt/PrecisionRuntime.storeLocal:(Lenerj/rt/Reference;ZLjava/lang/Object;)Ljava/lang/Object;
    4152: pop           
    4153: getstatic     #2                  // Field enerj/rt/PrecisionRuntimeRoot.impl:Lenerj/rt/PrecisionRuntime;
    4156: aload         63
    4158: iconst_1      
    4159: getstatic     #2                  // Field enerj/rt/PrecisionRuntimeRoot.impl:Lenerj/rt/PrecisionRuntime;
    4162: aload         6
    4164: iconst_1      
    4165: invokeinterface #28,  3           // InterfaceMethod enerj/rt/PrecisionRuntime.loadLocal:(Lenerj/rt/Reference;Z)Ljava/lang/Object;
    4170: checkcast     #9                  // class com/jme/math/Vector3f
    4173: getfield      #53                 // Field com/jme/math/Vector3f.x:F
    4176: invokestatic  #32                 // Method java/lang/Float.valueOf:(F)Ljava/lang/Float;
    4179: invokeinterface #33,  4           // InterfaceMethod enerj/rt/PrecisionRuntime.storeLocal:(Lenerj/rt/Reference;ZLjava/lang/Object;)Ljava/lang/Object;
    4184: pop           
    4185: getstatic     #2                  // Field enerj/rt/PrecisionRuntimeRoot.impl:Lenerj/rt/PrecisionRuntime;
    4188: getstatic     #2                  // Field enerj/rt/PrecisionRuntimeRoot.impl:Lenerj/rt/PrecisionRuntime;
    4191: ldc_w         #5                  // class com/jme/intersection/Intersection
    4194: ldc           #23                 // String tempVa
    4196: iconst_1      
    4197: invokeinterface #24,  4           // InterfaceMethod enerj/rt/PrecisionRuntime.loadField:(Ljava/lang/Object;Ljava/lang/String;Z)Ljava/lang/Object;
    4202: iconst_0      
    4203: getstatic     #25                 // Field enerj/rt/PrecisionRuntime$MemKind.VARIABLE:Lenerj/rt/PrecisionRuntime$MemKind;
    4206: invokeinterface #26,  4           // InterfaceMethod enerj/rt/PrecisionRuntime.storeValue:(Ljava/lang/Object;ZLenerj/rt/PrecisionRuntime$MemKind;)Ljava/lang/Object;
    4211: checkcast     #9                  // class com/jme/math/Vector3f
    4214: astore        78
    4216: new           #21                 // class enerj/rt/Reference
    4219: dup           
    4220: aload         78
    4222: iconst_0      
    4223: iconst_0      
    4224: invokespecial #22                 // Method enerj/rt/Reference."<init>":(Ljava/lang/Object;ZZ)V
    4227: astore        79
    4229: getstatic     #2                  // Field enerj/rt/PrecisionRuntimeRoot.impl:Lenerj/rt/PrecisionRuntime;
    4232: getstatic     #2                  // Field enerj/rt/PrecisionRuntimeRoot.impl:Lenerj/rt/PrecisionRuntime;
    4235: ldc_w         #5                  // class com/jme/intersection/Intersection
    4238: ldc           #59                 // String tempV2a
    4240: iconst_1      
    4241: invokeinterface #24,  4           // InterfaceMethod enerj/rt/PrecisionRuntime.loadField:(Ljava/lang/Object;Ljava/lang/String;Z)Ljava/lang/Object;
    4246: iconst_0      
    4247: getstatic     #25                 // Field enerj/rt/PrecisionRuntime$MemKind.VARIABLE:Lenerj/rt/PrecisionRuntime$MemKind;
    4250: invokeinterface #26,  4           // InterfaceMethod enerj/rt/PrecisionRuntime.storeValue:(Ljava/lang/Object;ZLenerj/rt/PrecisionRuntime$MemKind;)Ljava/lang/Object;
    4255: checkcast     #60                 // class com/jme/math/Vector2f
    4258: astore        80
    4260: new           #21                 // class enerj/rt/Reference
    4263: dup           
    4264: aload         80
    4266: iconst_0      
    4267: iconst_0      
    4268: invokespecial #22                 // Method enerj/rt/Reference."<init>":(Ljava/lang/Object;ZZ)V
    4271: astore        81
    4273: getstatic     #2                  // Field enerj/rt/PrecisionRuntimeRoot.impl:Lenerj/rt/PrecisionRuntime;
    4276: aload         53
    4278: iconst_1      
    4279: invokeinterface #28,  3           // InterfaceMethod enerj/rt/PrecisionRuntime.loadLocal:(Lenerj/rt/Reference;Z)Ljava/lang/Object;
    4284: checkcast     #34                 // class java/lang/Float
    4287: invokevirtual #35                 // Method java/lang/Float.floatValue:()F
    4290: getstatic     #2                  // Field enerj/rt/PrecisionRuntimeRoot.impl:Lenerj/rt/PrecisionRuntime;
    4293: aload         55
    4295: iconst_1      
    4296: invokeinterface #28,  3           // InterfaceMethod enerj/rt/PrecisionRuntime.loadLocal:(Lenerj/rt/Reference;Z)Ljava/lang/Object;
    4301: checkcast     #34                 // class java/lang/Float
    4304: invokevirtual #35                 // Method java/lang/Float.floatValue:()F
    4307: getstatic     #2                  // Field enerj/rt/PrecisionRuntimeRoot.impl:Lenerj/rt/PrecisionRuntime;
    4310: aload         57
    4312: iconst_1      
    4313: invokeinterface #28,  3           // InterfaceMethod enerj/rt/PrecisionRuntime.loadLocal:(Lenerj/rt/Reference;Z)Ljava/lang/Object;
    4318: checkcast     #34                 // class java/lang/Float
    4321: invokevirtual #35                 // Method java/lang/Float.floatValue:()F
    4324: getstatic     #2                  // Field enerj/rt/PrecisionRuntimeRoot.impl:Lenerj/rt/PrecisionRuntime;
    4327: aload         31
    4329: iconst_1      
    4330: invokeinterface #28,  3           // InterfaceMethod enerj/rt/PrecisionRuntime.loadLocal:(Lenerj/rt/Reference;Z)Ljava/lang/Object;
    4335: checkcast     #34                 // class java/lang/Float
    4338: invokevirtual #35                 // Method java/lang/Float.floatValue:()F
    4341: getstatic     #2                  // Field enerj/rt/PrecisionRuntimeRoot.impl:Lenerj/rt/PrecisionRuntime;
    4344: aload         33
    4346: iconst_1      
    4347: invokeinterface #28,  3           // InterfaceMethod enerj/rt/PrecisionRuntime.loadLocal:(Lenerj/rt/Reference;Z)Ljava/lang/Object;
    4352: checkcast     #34                 // class java/lang/Float
    4355: invokevirtual #35                 // Method java/lang/Float.floatValue:()F
    4358: getstatic     #2                  // Field enerj/rt/PrecisionRuntimeRoot.impl:Lenerj/rt/PrecisionRuntime;
    4361: aload         35
    4363: iconst_1      
    4364: invokeinterface #28,  3           // InterfaceMethod enerj/rt/PrecisionRuntime.loadLocal:(Lenerj/rt/Reference;Z)Ljava/lang/Object;
    4369: checkcast     #34                 // class java/lang/Float
    4372: invokevirtual #35                 // Method java/lang/Float.floatValue:()F
    4375: getstatic     #2                  // Field enerj/rt/PrecisionRuntimeRoot.impl:Lenerj/rt/PrecisionRuntime;
    4378: aload         47
    4380: iconst_1      
    4381: invokeinterface #28,  3           // InterfaceMethod enerj/rt/PrecisionRuntime.loadLocal:(Lenerj/rt/Reference;Z)Ljava/lang/Object;
    4386: checkcast     #34                 // class java/lang/Float
    4389: invokevirtual #35                 // Method java/lang/Float.floatValue:()F
    4392: getstatic     #2                  // Field enerj/rt/PrecisionRuntimeRoot.impl:Lenerj/rt/PrecisionRuntime;
    4395: aload         49
    4397: iconst_1      
    4398: invokeinterface #28,  3           // InterfaceMethod enerj/rt/PrecisionRuntime.loadLocal:(Lenerj/rt/Reference;Z)Ljava/lang/Object;
    4403: checkcast     #34                 // class java/lang/Float
    4406: invokevirtual #35                 // Method java/lang/Float.floatValue:()F
    4409: getstatic     #2                  // Field enerj/rt/PrecisionRuntimeRoot.impl:Lenerj/rt/PrecisionRuntime;
    4412: aload         79
    4414: iconst_1      
    4415: invokeinterface #28,  3           // InterfaceMethod enerj/rt/PrecisionRuntime.loadLocal:(Lenerj/rt/Reference;Z)Ljava/lang/Object;
    4420: checkcast     #9                  // class com/jme/math/Vector3f
    4423: getstatic     #2                  // Field enerj/rt/PrecisionRuntimeRoot.impl:Lenerj/rt/PrecisionRuntime;
    4426: aload         81
    4428: iconst_1      
    4429: invokeinterface #28,  3           // InterfaceMethod enerj/rt/PrecisionRuntime.loadLocal:(Lenerj/rt/Reference;Z)Ljava/lang/Object;
    4434: checkcast     #60                 // class com/jme/math/Vector2f
    4437: invokestatic  #61                 // Method newComputeIntervals:(FFFFFFFFLcom/jme/math/Vector3f;Lcom/jme/math/Vector2f;)Z
    4440: ifeq          4545
    4443: getstatic     #2                  // Field enerj/rt/PrecisionRuntimeRoot.impl:Lenerj/rt/PrecisionRuntime;
    4446: aload         17
    4448: iconst_1      
    4449: invokeinterface #28,  3           // InterfaceMethod enerj/rt/PrecisionRuntime.loadLocal:(Lenerj/rt/Reference;Z)Ljava/lang/Object;
    4454: checkcast     #9                  // class com/jme/math/Vector3f
    4457: getstatic     #2                  // Field enerj/rt/PrecisionRuntimeRoot.impl:Lenerj/rt/PrecisionRuntime;
    4460: aload         11
    4462: iconst_1      
    4463: invokeinterface #28,  3           // InterfaceMethod enerj/rt/PrecisionRuntime.loadLocal:(Lenerj/rt/Reference;Z)Ljava/lang/Object;
    4468: checkcast     #9                  // class com/jme/math/Vector3f
    4471: getstatic     #2                  // Field enerj/rt/PrecisionRuntimeRoot.impl:Lenerj/rt/PrecisionRuntime;
    4474: aload         10
    4476: iconst_1      
    4477: invokeinterface #28,  3           // InterfaceMethod enerj/rt/PrecisionRuntime.loadLocal:(Lenerj/rt/Reference;Z)Ljava/lang/Object;
    4482: checkcast     #9                  // class com/jme/math/Vector3f
    4485: getstatic     #2                  // Field enerj/rt/PrecisionRuntimeRoot.impl:Lenerj/rt/PrecisionRuntime;
    4488: aload         9
    4490: iconst_1      
    4491: invokeinterface #28,  3           // InterfaceMethod enerj/rt/PrecisionRuntime.loadLocal:(Lenerj/rt/Reference;Z)Ljava/lang/Object;
    4496: checkcast     #9                  // class com/jme/math/Vector3f
    4499: getstatic     #2                  // Field enerj/rt/PrecisionRuntimeRoot.impl:Lenerj/rt/PrecisionRuntime;
    4502: aload         8
    4504: iconst_1      
    4505: invokeinterface #28,  3           // InterfaceMethod enerj/rt/PrecisionRuntime.loadLocal:(Lenerj/rt/Reference;Z)Ljava/lang/Object;
    4510: checkcast     #9                  // class com/jme/math/Vector3f
    4513: getstatic     #2                  // Field enerj/rt/PrecisionRuntimeRoot.impl:Lenerj/rt/PrecisionRuntime;
    4516: aload         7
    4518: iconst_1      
    4519: invokeinterface #28,  3           // InterfaceMethod enerj/rt/PrecisionRuntime.loadLocal:(Lenerj/rt/Reference;Z)Ljava/lang/Object;
    4524: checkcast     #9                  // class com/jme/math/Vector3f
    4527: getstatic     #2                  // Field enerj/rt/PrecisionRuntimeRoot.impl:Lenerj/rt/PrecisionRuntime;
    4530: aload         6
    4532: iconst_1      
    4533: invokeinterface #28,  3           // InterfaceMethod enerj/rt/PrecisionRuntime.loadLocal:(Lenerj/rt/Reference;Z)Ljava/lang/Object;
    4538: checkcast     #9                  // class com/jme/math/Vector3f
    4541: invokestatic  #62                 // Method coplanarTriTri:(Lcom/jme/math/Vector3f;Lcom/jme/math/Vector3f;Lcom/jme/math/Vector3f;Lcom/jme/math/Vector3f;Lcom/jme/math/Vector3f;Lcom/jme/math/Vector3f;Lcom/jme/math/Vector3f;)Z
    4544: ireturn       
    4545: getstatic     #2                  // Field enerj/rt/PrecisionRuntimeRoot.impl:Lenerj/rt/PrecisionRuntime;
    4548: getstatic     #2                  // Field enerj/rt/PrecisionRuntimeRoot.impl:Lenerj/rt/PrecisionRuntime;
    4551: ldc_w         #5                  // class com/jme/intersection/Intersection
    4554: ldc           #27                 // String tempVb
    4556: iconst_1      
    4557: invokeinterface #24,  4           // InterfaceMethod enerj/rt/PrecisionRuntime.loadField:(Ljava/lang/Object;Ljava/lang/String;Z)Ljava/lang/Object;
    4562: iconst_0      
    4563: getstatic     #25                 // Field enerj/rt/PrecisionRuntime$MemKind.VARIABLE:Lenerj/rt/PrecisionRuntime$MemKind;
    4566: invokeinterface #26,  4           // InterfaceMethod enerj/rt/PrecisionRuntime.storeValue:(Ljava/lang/Object;ZLenerj/rt/PrecisionRuntime$MemKind;)Ljava/lang/Object;
    4571: checkcast     #9                  // class com/jme/math/Vector3f
    4574: astore        82
    4576: new           #21                 // class enerj/rt/Reference
    4579: dup           
    4580: aload         82
    4582: iconst_0      
    4583: iconst_0      
    4584: invokespecial #22                 // Method enerj/rt/Reference."<init>":(Ljava/lang/Object;ZZ)V
    4587: astore        83
    4589: getstatic     #2                  // Field enerj/rt/PrecisionRuntimeRoot.impl:Lenerj/rt/PrecisionRuntime;
    4592: getstatic     #2                  // Field enerj/rt/PrecisionRuntimeRoot.impl:Lenerj/rt/PrecisionRuntime;
    4595: ldc_w         #5                  // class com/jme/intersection/Intersection
    4598: ldc           #63                 // String tempV2b
    4600: iconst_1      
    4601: invokeinterface #24,  4           // InterfaceMethod enerj/rt/PrecisionRuntime.loadField:(Ljava/lang/Object;Ljava/lang/String;Z)Ljava/lang/Object;
    4606: iconst_0      
    4607: getstatic     #25                 // Field enerj/rt/PrecisionRuntime$MemKind.VARIABLE:Lenerj/rt/PrecisionRuntime$MemKind;
    4610: invokeinterface #26,  4           // InterfaceMethod enerj/rt/PrecisionRuntime.storeValue:(Ljava/lang/Object;ZLenerj/rt/PrecisionRuntime$MemKind;)Ljava/lang/Object;
    4615: checkcast     #60                 // class com/jme/math/Vector2f
    4618: astore        84
    4620: new           #21                 // class enerj/rt/Reference
    4623: dup           
    4624: aload         84
    4626: iconst_0      
    4627: iconst_0      
    4628: invokespecial #22                 // Method enerj/rt/Reference."<init>":(Ljava/lang/Object;ZZ)V
    4631: astore        85
    4633: getstatic     #2                  // Field enerj/rt/PrecisionRuntimeRoot.impl:Lenerj/rt/PrecisionRuntime;
    4636: aload         59
    4638: iconst_1      
    4639: invokeinterface #28,  3           // InterfaceMethod enerj/rt/PrecisionRuntime.loadLocal:(Lenerj/rt/Reference;Z)Ljava/lang/Object;
    4644: checkcast     #34                 // class java/lang/Float
    4647: invokevirtual #35                 // Method java/lang/Float.floatValue:()F
    4650: getstatic     #2                  // Field enerj/rt/PrecisionRuntimeRoot.impl:Lenerj/rt/PrecisionRuntime;
    4653: aload         61
    4655: iconst_1      
    4656: invokeinterface #28,  3           // InterfaceMethod enerj/rt/PrecisionRuntime.loadLocal:(Lenerj/rt/Reference;Z)Ljava/lang/Object;
    4661: checkcast     #34                 // class java/lang/Float
    4664: invokevirtual #35                 // Method java/lang/Float.floatValue:()F
    4667: getstatic     #2                  // Field enerj/rt/PrecisionRuntimeRoot.impl:Lenerj/rt/PrecisionRuntime;
    4670: aload         63
    4672: iconst_1      
    4673: invokeinterface #28,  3           // InterfaceMethod enerj/rt/PrecisionRuntime.loadLocal:(Lenerj/rt/Reference;Z)Ljava/lang/Object;
    4678: checkcast     #34                 // class java/lang/Float
    4681: invokevirtual #35                 // Method java/lang/Float.floatValue:()F
    4684: getstatic     #2                  // Field enerj/rt/PrecisionRuntimeRoot.impl:Lenerj/rt/PrecisionRuntime;
    4687: aload         25
    4689: iconst_1      
    4690: invokeinterface #28,  3           // InterfaceMethod enerj/rt/PrecisionRuntime.loadLocal:(Lenerj/rt/Reference;Z)Ljava/lang/Object;
    4695: checkcast     #34                 // class java/lang/Float
    4698: invokevirtual #35                 // Method java/lang/Float.floatValue:()F
    4701: getstatic     #2                  // Field enerj/rt/PrecisionRuntimeRoot.impl:Lenerj/rt/PrecisionRuntime;
    4704: aload         27
    4706: iconst_1      
    4707: invokeinterface #28,  3           // InterfaceMethod enerj/rt/PrecisionRuntime.loadLocal:(Lenerj/rt/Reference;Z)Ljava/lang/Object;
    4712: checkcast     #34                 // class java/lang/Float
    4715: invokevirtual #35                 // Method java/lang/Float.floatValue:()F
    4718: getstatic     #2                  // Field enerj/rt/PrecisionRuntimeRoot.impl:Lenerj/rt/PrecisionRuntime;
    4721: aload         29
    4723: iconst_1      
    4724: invokeinterface #28,  3           // InterfaceMethod enerj/rt/PrecisionRuntime.loadLocal:(Lenerj/rt/Reference;Z)Ljava/lang/Object;
    4729: checkcast     #34                 // class java/lang/Float
    4732: invokevirtual #35                 // Method java/lang/Float.floatValue:()F
    4735: getstatic     #2                  // Field enerj/rt/PrecisionRuntimeRoot.impl:Lenerj/rt/PrecisionRuntime;
    4738: aload         43
    4740: iconst_1      
    4741: invokeinterface #28,  3           // InterfaceMethod enerj/rt/PrecisionRuntime.loadLocal:(Lenerj/rt/Reference;Z)Ljava/lang/Object;
    4746: checkcast     #34                 // class java/lang/Float
    4749: invokevirtual #35                 // Method java/lang/Float.floatValue:()F
    4752: getstatic     #2                  // Field enerj/rt/PrecisionRuntimeRoot.impl:Lenerj/rt/PrecisionRuntime;
    4755: aload         45
    4757: iconst_1      
    4758: invokeinterface #28,  3           // InterfaceMethod enerj/rt/PrecisionRuntime.loadLocal:(Lenerj/rt/Reference;Z)Ljava/lang/Object;
    4763: checkcast     #34                 // class java/lang/Float
    4766: invokevirtual #35                 // Method java/lang/Float.floatValue:()F
    4769: getstatic     #2                  // Field enerj/rt/PrecisionRuntimeRoot.impl:Lenerj/rt/PrecisionRuntime;
    4772: aload         83
    4774: iconst_1      
    4775: invokeinterface #28,  3           // InterfaceMethod enerj/rt/PrecisionRuntime.loadLocal:(Lenerj/rt/Reference;Z)Ljava/lang/Object;
    4780: checkcast     #9                  // class com/jme/math/Vector3f
    4783: getstatic     #2                  // Field enerj/rt/PrecisionRuntimeRoot.impl:Lenerj/rt/PrecisionRuntime;
    4786: aload         85
    4788: iconst_1      
    4789: invokeinterface #28,  3           // InterfaceMethod enerj/rt/PrecisionRuntime.loadLocal:(Lenerj/rt/Reference;Z)Ljava/lang/Object;
    4794: checkcast     #60                 // class com/jme/math/Vector2f
    4797: invokestatic  #61                 // Method newComputeIntervals:(FFFFFFFFLcom/jme/math/Vector3f;Lcom/jme/math/Vector2f;)Z
    4800: ifeq          4905
    4803: getstatic     #2                  // Field enerj/rt/PrecisionRuntimeRoot.impl:Lenerj/rt/PrecisionRuntime;
    4806: aload         17
    4808: iconst_1      
    4809: invokeinterface #28,  3           // InterfaceMethod enerj/rt/PrecisionRuntime.loadLocal:(Lenerj/rt/Reference;Z)Ljava/lang/Object;
    4814: checkcast     #9                  // class com/jme/math/Vector3f
    4817: getstatic     #2                  // Field enerj/rt/PrecisionRuntimeRoot.impl:Lenerj/rt/PrecisionRuntime;
    4820: aload         11
    4822: iconst_1      
    4823: invokeinterface #28,  3           // InterfaceMethod enerj/rt/PrecisionRuntime.loadLocal:(Lenerj/rt/Reference;Z)Ljava/lang/Object;
    4828: checkcast     #9                  // class com/jme/math/Vector3f
    4831: getstatic     #2                  // Field enerj/rt/PrecisionRuntimeRoot.impl:Lenerj/rt/PrecisionRuntime;
    4834: aload         10
    4836: iconst_1      
    4837: invokeinterface #28,  3           // InterfaceMethod enerj/rt/PrecisionRuntime.loadLocal:(Lenerj/rt/Reference;Z)Ljava/lang/Object;
    4842: checkcast     #9                  // class com/jme/math/Vector3f
    4845: getstatic     #2                  // Field enerj/rt/PrecisionRuntimeRoot.impl:Lenerj/rt/PrecisionRuntime;
    4848: aload         9
    4850: iconst_1      
    4851: invokeinterface #28,  3           // InterfaceMethod enerj/rt/PrecisionRuntime.loadLocal:(Lenerj/rt/Reference;Z)Ljava/lang/Object;
    4856: checkcast     #9                  // class com/jme/math/Vector3f
    4859: getstatic     #2                  // Field enerj/rt/PrecisionRuntimeRoot.impl:Lenerj/rt/PrecisionRuntime;
    4862: aload         8
    4864: iconst_1      
    4865: invokeinterface #28,  3           // InterfaceMethod enerj/rt/PrecisionRuntime.loadLocal:(Lenerj/rt/Reference;Z)Ljava/lang/Object;
    4870: checkcast     #9                  // class com/jme/math/Vector3f
    4873: getstatic     #2                  // Field enerj/rt/PrecisionRuntimeRoot.impl:Lenerj/rt/PrecisionRuntime;
    4876: aload         7
    4878: iconst_1      
    4879: invokeinterface #28,  3           // InterfaceMethod enerj/rt/PrecisionRuntime.loadLocal:(Lenerj/rt/Reference;Z)Ljava/lang/Object;
    4884: checkcast     #9                  // class com/jme/math/Vector3f
    4887: getstatic     #2                  // Field enerj/rt/PrecisionRuntimeRoot.impl:Lenerj/rt/PrecisionRuntime;
    4890: aload         6
    4892: iconst_1      
    4893: invokeinterface #28,  3           // InterfaceMethod enerj/rt/PrecisionRuntime.loadLocal:(Lenerj/rt/Reference;Z)Ljava/lang/Object;
    4898: checkcast     #9                  // class com/jme/math/Vector3f
    4901: invokestatic  #62                 // Method coplanarTriTri:(Lcom/jme/math/Vector3f;Lcom/jme/math/Vector3f;Lcom/jme/math/Vector3f;Lcom/jme/math/Vector3f;Lcom/jme/math/Vector3f;Lcom/jme/math/Vector3f;Lcom/jme/math/Vector3f;)Z
    4904: ireturn       
    4905: getstatic     #2                  // Field enerj/rt/PrecisionRuntimeRoot.impl:Lenerj/rt/PrecisionRuntime;
    4908: aload         71
    4910: iconst_1      
    4911: getstatic     #2                  // Field enerj/rt/PrecisionRuntimeRoot.impl:Lenerj/rt/PrecisionRuntime;
    4914: getstatic     #2                  // Field enerj/rt/PrecisionRuntimeRoot.impl:Lenerj/rt/PrecisionRuntime;
    4917: aload         81
    4919: iconst_1      
    4920: invokeinterface #28,  3           // InterfaceMethod enerj/rt/PrecisionRuntime.loadLocal:(Lenerj/rt/Reference;Z)Ljava/lang/Object;
    4925: checkcast     #60                 // class com/jme/math/Vector2f
    4928: getfield      #64                 // Field com/jme/math/Vector2f.x:F
    4931: invokestatic  #32                 // Method java/lang/Float.valueOf:(F)Ljava/lang/Float;
    4934: getstatic     #2                  // Field enerj/rt/PrecisionRuntimeRoot.impl:Lenerj/rt/PrecisionRuntime;
    4937: aload         81
    4939: iconst_1      
    4940: invokeinterface #28,  3           // InterfaceMethod enerj/rt/PrecisionRuntime.loadLocal:(Lenerj/rt/Reference;Z)Ljava/lang/Object;
    4945: checkcast     #60                 // class com/jme/math/Vector2f
    4948: getfield      #65                 // Field com/jme/math/Vector2f.y:F
    4951: invokestatic  #32                 // Method java/lang/Float.valueOf:(F)Ljava/lang/Float;
    4954: getstatic     #49                 // Field enerj/rt/PrecisionRuntime$ArithOperator.MULTIPLY:Lenerj/rt/PrecisionRuntime$ArithOperator;
    4957: getstatic     #37                 // Field enerj/rt/PrecisionRuntime$NumberKind.FLOAT:Lenerj/rt/PrecisionRuntime$NumberKind;
    4960: iconst_1      
    4961: invokeinterface #38,  6           // InterfaceMethod enerj/rt/PrecisionRuntime.binaryOp:(Ljava/lang/Number;Ljava/lang/Number;Lenerj/rt/PrecisionRuntime$ArithOperator;Lenerj/rt/PrecisionRuntime$NumberKind;Z)Ljava/lang/Number;
    4966: invokevirtual #39                 // Method java/lang/Number.floatValue:()F
    4969: invokestatic  #32                 // Method java/lang/Float.valueOf:(F)Ljava/lang/Float;
    4972: invokeinterface #33,  4           // InterfaceMethod enerj/rt/PrecisionRuntime.storeLocal:(Lenerj/rt/Reference;ZLjava/lang/Object;)Ljava/lang/Object;
    4977: pop           
    4978: getstatic     #2                  // Field enerj/rt/PrecisionRuntimeRoot.impl:Lenerj/rt/PrecisionRuntime;
    4981: aload         73
    4983: iconst_1      
    4984: getstatic     #2                  // Field enerj/rt/PrecisionRuntimeRoot.impl:Lenerj/rt/PrecisionRuntime;
    4987: getstatic     #2                  // Field enerj/rt/PrecisionRuntimeRoot.impl:Lenerj/rt/PrecisionRuntime;
    4990: aload         85
    4992: iconst_1      
    4993: invokeinterface #28,  3           // InterfaceMethod enerj/rt/PrecisionRuntime.loadLocal:(Lenerj/rt/Reference;Z)Ljava/lang/Object;
    4998: checkcast     #60                 // class com/jme/math/Vector2f
    5001: getfield      #64                 // Field com/jme/math/Vector2f.x:F
    5004: invokestatic  #32                 // Method java/lang/Float.valueOf:(F)Ljava/lang/Float;
    5007: getstatic     #2                  // Field enerj/rt/PrecisionRuntimeRoot.impl:Lenerj/rt/PrecisionRuntime;
    5010: aload         85
    5012: iconst_1      
    5013: invokeinterface #28,  3           // InterfaceMethod enerj/rt/PrecisionRuntime.loadLocal:(Lenerj/rt/Reference;Z)Ljava/lang/Object;
    5018: checkcast     #60                 // class com/jme/math/Vector2f
    5021: getfield      #65                 // Field com/jme/math/Vector2f.y:F
    5024: invokestatic  #32                 // Method java/lang/Float.valueOf:(F)Ljava/lang/Float;
    5027: getstatic     #49                 // Field enerj/rt/PrecisionRuntime$ArithOperator.MULTIPLY:Lenerj/rt/PrecisionRuntime$ArithOperator;
    5030: getstatic     #37                 // Field enerj/rt/PrecisionRuntime$NumberKind.FLOAT:Lenerj/rt/PrecisionRuntime$NumberKind;
    5033: iconst_1      
    5034: invokeinterface #38,  6           // InterfaceMethod enerj/rt/PrecisionRuntime.binaryOp:(Ljava/lang/Number;Ljava/lang/Number;Lenerj/rt/PrecisionRuntime$ArithOperator;Lenerj/rt/PrecisionRuntime$NumberKind;Z)Ljava/lang/Number;
    5039: invokevirtual #39                 // Method java/lang/Number.floatValue:()F
    5042: invokestatic  #32                 // Method java/lang/Float.valueOf:(F)Ljava/lang/Float;
    5045: invokeinterface #33,  4           // InterfaceMethod enerj/rt/PrecisionRuntime.storeLocal:(Lenerj/rt/Reference;ZLjava/lang/Object;)Ljava/lang/Object;
    5050: pop           
    5051: getstatic     #2                  // Field enerj/rt/PrecisionRuntimeRoot.impl:Lenerj/rt/PrecisionRuntime;
    5054: aload         75
    5056: iconst_1      
    5057: getstatic     #2                  // Field enerj/rt/PrecisionRuntimeRoot.impl:Lenerj/rt/PrecisionRuntime;
    5060: getstatic     #2                  // Field enerj/rt/PrecisionRuntimeRoot.impl:Lenerj/rt/PrecisionRuntime;
    5063: aload         71
    5065: iconst_1      
    5066: invokeinterface #28,  3           // InterfaceMethod enerj/rt/PrecisionRuntime.loadLocal:(Lenerj/rt/Reference;Z)Ljava/lang/Object;
    5071: checkcast     #34                 // class java/lang/Float
    5074: invokevirtual #35                 // Method java/lang/Float.floatValue:()F
    5077: invokestatic  #32                 // Method java/lang/Float.valueOf:(F)Ljava/lang/Float;
    5080: getstatic     #2                  // Field enerj/rt/PrecisionRuntimeRoot.impl:Lenerj/rt/PrecisionRuntime;
    5083: aload         73
    5085: iconst_1      
    5086: invokeinterface #28,  3           // InterfaceMethod enerj/rt/PrecisionRuntime.loadLocal:(Lenerj/rt/Reference;Z)Ljava/lang/Object;
    5091: checkcast     #34                 // class java/lang/Float
    5094: invokevirtual #35                 // Method java/lang/Float.floatValue:()F
    5097: invokestatic  #32                 // Method java/lang/Float.valueOf:(F)Ljava/lang/Float;
    5100: getstatic     #49                 // Field enerj/rt/PrecisionRuntime$ArithOperator.MULTIPLY:Lenerj/rt/PrecisionRuntime$ArithOperator;
    5103: getstatic     #37                 // Field enerj/rt/PrecisionRuntime$NumberKind.FLOAT:Lenerj/rt/PrecisionRuntime$NumberKind;
    5106: iconst_1      
    5107: invokeinterface #38,  6           // InterfaceMethod enerj/rt/PrecisionRuntime.binaryOp:(Ljava/lang/Number;Ljava/lang/Number;Lenerj/rt/PrecisionRuntime$ArithOperator;Lenerj/rt/PrecisionRuntime$NumberKind;Z)Ljava/lang/Number;
    5112: invokevirtual #39                 // Method java/lang/Number.floatValue:()F
    5115: invokestatic  #32                 // Method java/lang/Float.valueOf:(F)Ljava/lang/Float;
    5118: invokeinterface #33,  4           // InterfaceMethod enerj/rt/PrecisionRuntime.storeLocal:(Lenerj/rt/Reference;ZLjava/lang/Object;)Ljava/lang/Object;
    5123: pop           
    5124: getstatic     #2                  // Field enerj/rt/PrecisionRuntimeRoot.impl:Lenerj/rt/PrecisionRuntime;
    5127: aload         77
    5129: iconst_1      
    5130: getstatic     #2                  // Field enerj/rt/PrecisionRuntimeRoot.impl:Lenerj/rt/PrecisionRuntime;
    5133: getstatic     #2                  // Field enerj/rt/PrecisionRuntimeRoot.impl:Lenerj/rt/PrecisionRuntime;
    5136: aload         79
    5138: iconst_1      
    5139: invokeinterface #28,  3           // InterfaceMethod enerj/rt/PrecisionRuntime.loadLocal:(Lenerj/rt/Reference;Z)Ljava/lang/Object;
    5144: checkcast     #9                  // class com/jme/math/Vector3f
    5147: getfield      #53                 // Field com/jme/math/Vector3f.x:F
    5150: invokestatic  #32                 // Method java/lang/Float.valueOf:(F)Ljava/lang/Float;
    5153: getstatic     #2                  // Field enerj/rt/PrecisionRuntimeRoot.impl:Lenerj/rt/PrecisionRuntime;
    5156: aload         75
    5158: iconst_1      
    5159: invokeinterface #28,  3           // InterfaceMethod enerj/rt/PrecisionRuntime.loadLocal:(Lenerj/rt/Reference;Z)Ljava/lang/Object;
    5164: checkcast     #34                 // class java/lang/Float
    5167: invokevirtual #35                 // Method java/lang/Float.floatValue:()F
    5170: invokestatic  #32                 // Method java/lang/Float.valueOf:(F)Ljava/lang/Float;
    5173: getstatic     #49                 // Field enerj/rt/PrecisionRuntime$ArithOperator.MULTIPLY:Lenerj/rt/PrecisionRuntime$ArithOperator;
    5176: getstatic     #37                 // Field enerj/rt/PrecisionRuntime$NumberKind.FLOAT:Lenerj/rt/PrecisionRuntime$NumberKind;
    5179: iconst_1      
    5180: invokeinterface #38,  6           // InterfaceMethod enerj/rt/PrecisionRuntime.binaryOp:(Ljava/lang/Number;Ljava/lang/Number;Lenerj/rt/PrecisionRuntime$ArithOperator;Lenerj/rt/PrecisionRuntime$NumberKind;Z)Ljava/lang/Number;
    5185: invokevirtual #39                 // Method java/lang/Number.floatValue:()F
    5188: invokestatic  #32                 // Method java/lang/Float.valueOf:(F)Ljava/lang/Float;
    5191: invokeinterface #33,  4           // InterfaceMethod enerj/rt/PrecisionRuntime.storeLocal:(Lenerj/rt/Reference;ZLjava/lang/Object;)Ljava/lang/Object;
    5196: pop           
    5197: getstatic     #2                  // Field enerj/rt/PrecisionRuntimeRoot.impl:Lenerj/rt/PrecisionRuntime;
    5200: getstatic     #2                  // Field enerj/rt/PrecisionRuntimeRoot.impl:Lenerj/rt/PrecisionRuntime;
    5203: aload         39
    5205: iconst_0      
    5206: invokeinterface #28,  3           // InterfaceMethod enerj/rt/PrecisionRuntime.loadLocal:(Lenerj/rt/Reference;Z)Ljava/lang/Object;
    5211: iconst_0      
    5212: iconst_1      
    5213: getstatic     #2                  // Field enerj/rt/PrecisionRuntimeRoot.impl:Lenerj/rt/PrecisionRuntime;
    5216: getstatic     #2                  // Field enerj/rt/PrecisionRuntimeRoot.impl:Lenerj/rt/PrecisionRuntime;
    5219: aload         77
    5221: iconst_1      
    5222: invokeinterface #28,  3           // InterfaceMethod enerj/rt/PrecisionRuntime.loadLocal:(Lenerj/rt/Reference;Z)Ljava/lang/Object;
    5227: checkcast     #34                 // class java/lang/Float
    5230: invokevirtual #35                 // Method java/lang/Float.floatValue:()F
    5233: invokestatic  #32                 // Method java/lang/Float.valueOf:(F)Ljava/lang/Float;
    5236: getstatic     #2                  // Field enerj/rt/PrecisionRuntimeRoot.impl:Lenerj/rt/PrecisionRuntime;
    5239: getstatic     #2                  // Field enerj/rt/PrecisionRuntimeRoot.impl:Lenerj/rt/PrecisionRuntime;
    5242: getstatic     #2                  // Field enerj/rt/PrecisionRuntimeRoot.impl:Lenerj/rt/PrecisionRuntime;
    5245: aload         79
    5247: iconst_1      
    5248: invokeinterface #28,  3           // InterfaceMethod enerj/rt/PrecisionRuntime.loadLocal:(Lenerj/rt/Reference;Z)Ljava/lang/Object;
    5253: checkcast     #9                  // class com/jme/math/Vector3f
    5256: getfield      #55                 // Field com/jme/math/Vector3f.y:F
    5259: invokestatic  #32                 // Method java/lang/Float.valueOf:(F)Ljava/lang/Float;
    5262: getstatic     #2                  // Field enerj/rt/PrecisionRuntimeRoot.impl:Lenerj/rt/PrecisionRuntime;
    5265: aload         81
    5267: iconst_1      
    5268: invokeinterface #28,  3           // InterfaceMethod enerj/rt/PrecisionRuntime.loadLocal:(Lenerj/rt/Reference;Z)Ljava/lang/Object;
    5273: checkcast     #60                 // class com/jme/math/Vector2f
    5276: getfield      #65                 // Field com/jme/math/Vector2f.y:F
    5279: invokestatic  #32                 // Method java/lang/Float.valueOf:(F)Ljava/lang/Float;
    5282: getstatic     #49                 // Field enerj/rt/PrecisionRuntime$ArithOperator.MULTIPLY:Lenerj/rt/PrecisionRuntime$ArithOperator;
    5285: getstatic     #37                 // Field enerj/rt/PrecisionRuntime$NumberKind.FLOAT:Lenerj/rt/PrecisionRuntime$NumberKind;
    5288: iconst_1      
    5289: invokeinterface #38,  6           // InterfaceMethod enerj/rt/PrecisionRuntime.binaryOp:(Ljava/lang/Number;Ljava/lang/Number;Lenerj/rt/PrecisionRuntime$ArithOperator;Lenerj/rt/PrecisionRuntime$NumberKind;Z)Ljava/lang/Number;
    5294: invokevirtual #39                 // Method java/lang/Number.floatValue:()F
    5297: invokestatic  #32                 // Method java/lang/Float.valueOf:(F)Ljava/lang/Float;
    5300: getstatic     #2                  // Field enerj/rt/PrecisionRuntimeRoot.impl:Lenerj/rt/PrecisionRuntime;
    5303: aload         73
    5305: iconst_1      
    5306: invokeinterface #28,  3           // InterfaceMethod enerj/rt/PrecisionRuntime.loadLocal:(Lenerj/rt/Reference;Z)Ljava/lang/Object;
    5311: checkcast     #34                 // class java/lang/Float
    5314: invokevirtual #35                 // Method java/lang/Float.floatValue:()F
    5317: invokestatic  #32                 // Method java/lang/Float.valueOf:(F)Ljava/lang/Float;
    5320: getstatic     #49                 // Field enerj/rt/PrecisionRuntime$ArithOperator.MULTIPLY:Lenerj/rt/PrecisionRuntime$ArithOperator;
    5323: getstatic     #37                 // Field enerj/rt/PrecisionRuntime$NumberKind.FLOAT:Lenerj/rt/PrecisionRuntime$NumberKind;
    5326: iconst_1      
    5327: invokeinterface #38,  6           // InterfaceMethod enerj/rt/PrecisionRuntime.binaryOp:(Ljava/lang/Number;Ljava/lang/Number;Lenerj/rt/PrecisionRuntime$ArithOperator;Lenerj/rt/PrecisionRuntime$NumberKind;Z)Ljava/lang/Number;
    5332: invokevirtual #39                 // Method java/lang/Number.floatValue:()F
    5335: invokestatic  #32                 // Method java/lang/Float.valueOf:(F)Ljava/lang/Float;
    5338: getstatic     #36                 // Field enerj/rt/PrecisionRuntime$ArithOperator.PLUS:Lenerj/rt/PrecisionRuntime$ArithOperator;
    5341: getstatic     #37                 // Field enerj/rt/PrecisionRuntime$NumberKind.FLOAT:Lenerj/rt/PrecisionRuntime$NumberKind;
    5344: iconst_1      
    5345: invokeinterface #38,  6           // InterfaceMethod enerj/rt/PrecisionRuntime.binaryOp:(Ljava/lang/Number;Ljava/lang/Number;Lenerj/rt/PrecisionRuntime$ArithOperator;Lenerj/rt/PrecisionRuntime$NumberKind;Z)Ljava/lang/Number;
    5350: invokevirtual #39                 // Method java/lang/Number.floatValue:()F
    5353: invokestatic  #32                 // Method java/lang/Float.valueOf:(F)Ljava/lang/Float;
    5356: invokeinterface #66,  5           // InterfaceMethod enerj/rt/PrecisionRuntime.storeArray:(Ljava/lang/Object;IZLjava/lang/Object;)Ljava/lang/Object;
    5361: checkcast     #34                 // class java/lang/Float
    5364: invokevirtual #35                 // Method java/lang/Float.floatValue:()F
    5367: pop           
    5368: getstatic     #2                  // Field enerj/rt/PrecisionRuntimeRoot.impl:Lenerj/rt/PrecisionRuntime;
    5371: getstatic     #2                  // Field enerj/rt/PrecisionRuntimeRoot.impl:Lenerj/rt/PrecisionRuntime;
    5374: aload         39
    5376: iconst_0      
    5377: invokeinterface #28,  3           // InterfaceMethod enerj/rt/PrecisionRuntime.loadLocal:(Lenerj/rt/Reference;Z)Ljava/lang/Object;
    5382: iconst_1      
    5383: iconst_1      
    5384: getstatic     #2                  // Field enerj/rt/PrecisionRuntimeRoot.impl:Lenerj/rt/PrecisionRuntime;
    5387: getstatic     #2                  // Field enerj/rt/PrecisionRuntimeRoot.impl:Lenerj/rt/PrecisionRuntime;
    5390: aload         77
    5392: iconst_1      
    5393: invokeinterface #28,  3           // InterfaceMethod enerj/rt/PrecisionRuntime.loadLocal:(Lenerj/rt/Reference;Z)Ljava/lang/Object;
    5398: checkcast     #34                 // class java/lang/Float
    5401: invokevirtual #35                 // Method java/lang/Float.floatValue:()F
    5404: invokestatic  #32                 // Method java/lang/Float.valueOf:(F)Ljava/lang/Float;
    5407: getstatic     #2                  // Field enerj/rt/PrecisionRuntimeRoot.impl:Lenerj/rt/PrecisionRuntime;
    5410: getstatic     #2                  // Field enerj/rt/PrecisionRuntimeRoot.impl:Lenerj/rt/PrecisionRuntime;
    5413: getstatic     #2                  // Field enerj/rt/PrecisionRuntimeRoot.impl:Lenerj/rt/PrecisionRuntime;
    5416: aload         79
    5418: iconst_1      
    5419: invokeinterface #28,  3           // InterfaceMethod enerj/rt/PrecisionRuntime.loadLocal:(Lenerj/rt/Reference;Z)Ljava/lang/Object;
    5424: checkcast     #9                  // class com/jme/math/Vector3f
    5427: getfield      #56                 // Field com/jme/math/Vector3f.z:F
    5430: invokestatic  #32                 // Method java/lang/Float.valueOf:(F)Ljava/lang/Float;
    5433: getstatic     #2                  // Field enerj/rt/PrecisionRuntimeRoot.impl:Lenerj/rt/PrecisionRuntime;
    5436: aload         81
    5438: iconst_1      
    5439: invokeinterface #28,  3           // InterfaceMethod enerj/rt/PrecisionRuntime.loadLocal:(Lenerj/rt/Reference;Z)Ljava/lang/Object;
    5444: checkcast     #60                 // class com/jme/math/Vector2f
    5447: getfield      #64                 // Field com/jme/math/Vector2f.x:F
    5450: invokestatic  #32                 // Method java/lang/Float.valueOf:(F)Ljava/lang/Float;
    5453: getstatic     #49                 // Field enerj/rt/PrecisionRuntime$ArithOperator.MULTIPLY:Lenerj/rt/PrecisionRuntime$ArithOperator;
    5456: getstatic     #37                 // Field enerj/rt/PrecisionRuntime$NumberKind.FLOAT:Lenerj/rt/PrecisionRuntime$NumberKind;
    5459: iconst_1      
    5460: invokeinterface #38,  6           // InterfaceMethod enerj/rt/PrecisionRuntime.binaryOp:(Ljava/lang/Number;Ljava/lang/Number;Lenerj/rt/PrecisionRuntime$ArithOperator;Lenerj/rt/PrecisionRuntime$NumberKind;Z)Ljava/lang/Number;
    5465: invokevirtual #39                 // Method java/lang/Number.floatValue:()F
    5468: invokestatic  #32                 // Method java/lang/Float.valueOf:(F)Ljava/lang/Float;
    5471: getstatic     #2                  // Field enerj/rt/PrecisionRuntimeRoot.impl:Lenerj/rt/PrecisionRuntime;
    5474: aload         73
    5476: iconst_1      
    5477: invokeinterface #28,  3           // InterfaceMethod enerj/rt/PrecisionRuntime.loadLocal:(Lenerj/rt/Reference;Z)Ljava/lang/Object;
    5482: checkcast     #34                 // class java/lang/Float
    5485: invokevirtual #35                 // Method java/lang/Float.floatValue:()F
    5488: invokestatic  #32                 // Method java/lang/Float.valueOf:(F)Ljava/lang/Float;
    5491: getstatic     #49                 // Field enerj/rt/PrecisionRuntime$ArithOperator.MULTIPLY:Lenerj/rt/PrecisionRuntime$ArithOperator;
    5494: getstatic     #37                 // Field enerj/rt/PrecisionRuntime$NumberKind.FLOAT:Lenerj/rt/PrecisionRuntime$NumberKind;
    5497: iconst_1      
    5498: invokeinterface #38,  6           // InterfaceMethod enerj/rt/PrecisionRuntime.binaryOp:(Ljava/lang/Number;Ljava/lang/Number;Lenerj/rt/PrecisionRuntime$ArithOperator;Lenerj/rt/PrecisionRuntime$NumberKind;Z)Ljava/lang/Number;
    5503: invokevirtual #39                 // Method java/lang/Number.floatValue:()F
    5506: invokestatic  #32                 // Method java/lang/Float.valueOf:(F)Ljava/lang/Float;
    5509: getstatic     #36                 // Field enerj/rt/PrecisionRuntime$ArithOperator.PLUS:Lenerj/rt/PrecisionRuntime$ArithOperator;
    5512: getstatic     #37                 // Field enerj/rt/PrecisionRuntime$NumberKind.FLOAT:Lenerj/rt/PrecisionRuntime$NumberKind;
    5515: iconst_1      
    5516: invokeinterface #38,  6           // InterfaceMethod enerj/rt/PrecisionRuntime.binaryOp:(Ljava/lang/Number;Ljava/lang/Number;Lenerj/rt/PrecisionRuntime$ArithOperator;Lenerj/rt/PrecisionRuntime$NumberKind;Z)Ljava/lang/Number;
    5521: invokevirtual #39                 // Method java/lang/Number.floatValue:()F
    5524: invokestatic  #32                 // Method java/lang/Float.valueOf:(F)Ljava/lang/Float;
    5527: invokeinterface #66,  5           // InterfaceMethod enerj/rt/PrecisionRuntime.storeArray:(Ljava/lang/Object;IZLjava/lang/Object;)Ljava/lang/Object;
    5532: checkcast     #34                 // class java/lang/Float
    5535: invokevirtual #35                 // Method java/lang/Float.floatValue:()F
    5538: pop           
    5539: getstatic     #2                  // Field enerj/rt/PrecisionRuntimeRoot.impl:Lenerj/rt/PrecisionRuntime;
    5542: aload         77
    5544: iconst_1      
    5545: getstatic     #2                  // Field enerj/rt/PrecisionRuntimeRoot.impl:Lenerj/rt/PrecisionRuntime;
    5548: getstatic     #2                  // Field enerj/rt/PrecisionRuntimeRoot.impl:Lenerj/rt/PrecisionRuntime;
    5551: aload         83
    5553: iconst_1      
    5554: invokeinterface #28,  3           // InterfaceMethod enerj/rt/PrecisionRuntime.loadLocal:(Lenerj/rt/Reference;Z)Ljava/lang/Object;
    5559: checkcast     #9                  // class com/jme/math/Vector3f
    5562: getfield      #53                 // Field com/jme/math/Vector3f.x:F
    5565: invokestatic  #32                 // Method java/lang/Float.valueOf:(F)Ljava/lang/Float;
    5568: getstatic     #2                  // Field enerj/rt/PrecisionRuntimeRoot.impl:Lenerj/rt/PrecisionRuntime;
    5571: aload         75
    5573: iconst_1      
    5574: invokeinterface #28,  3           // InterfaceMethod enerj/rt/PrecisionRuntime.loadLocal:(Lenerj/rt/Reference;Z)Ljava/lang/Object;
    5579: checkcast     #34                 // class java/lang/Float
    5582: invokevirtual #35                 // Method java/lang/Float.floatValue:()F
    5585: invokestatic  #32                 // Method java/lang/Float.valueOf:(F)Ljava/lang/Float;
    5588: getstatic     #49                 // Field enerj/rt/PrecisionRuntime$ArithOperator.MULTIPLY:Lenerj/rt/PrecisionRuntime$ArithOperator;
    5591: getstatic     #37                 // Field enerj/rt/PrecisionRuntime$NumberKind.FLOAT:Lenerj/rt/PrecisionRuntime$NumberKind;
    5594: iconst_1      
    5595: invokeinterface #38,  6           // InterfaceMethod enerj/rt/PrecisionRuntime.binaryOp:(Ljava/lang/Number;Ljava/lang/Number;Lenerj/rt/PrecisionRuntime$ArithOperator;Lenerj/rt/PrecisionRuntime$NumberKind;Z)Ljava/lang/Number;
    5600: invokevirtual #39                 // Method java/lang/Number.floatValue:()F
    5603: invokestatic  #32                 // Method java/lang/Float.valueOf:(F)Ljava/lang/Float;
    5606: invokeinterface #33,  4           // InterfaceMethod enerj/rt/PrecisionRuntime.storeLocal:(Lenerj/rt/Reference;ZLjava/lang/Object;)Ljava/lang/Object;
    5611: pop           
    5612: getstatic     #2                  // Field enerj/rt/PrecisionRuntimeRoot.impl:Lenerj/rt/PrecisionRuntime;
    5615: getstatic     #2                  // Field enerj/rt/PrecisionRuntimeRoot.impl:Lenerj/rt/PrecisionRuntime;
    5618: aload         41
    5620: iconst_0      
    5621: invokeinterface #28,  3           // InterfaceMethod enerj/rt/PrecisionRuntime.loadLocal:(Lenerj/rt/Reference;Z)Ljava/lang/Object;
    5626: iconst_0      
    5627: iconst_1      
    5628: getstatic     #2                  // Field enerj/rt/PrecisionRuntimeRoot.impl:Lenerj/rt/PrecisionRuntime;
    5631: getstatic     #2                  // Field enerj/rt/PrecisionRuntimeRoot.impl:Lenerj/rt/PrecisionRuntime;
    5634: aload         77
    5636: iconst_1      
    5637: invokeinterface #28,  3           // InterfaceMethod enerj/rt/PrecisionRuntime.loadLocal:(Lenerj/rt/Reference;Z)Ljava/lang/Object;
    5642: checkcast     #34                 // class java/lang/Float
    5645: invokevirtual #35                 // Method java/lang/Float.floatValue:()F
    5648: invokestatic  #32                 // Method java/lang/Float.valueOf:(F)Ljava/lang/Float;
    5651: getstatic     #2                  // Field enerj/rt/PrecisionRuntimeRoot.impl:Lenerj/rt/PrecisionRuntime;
    5654: getstatic     #2                  // Field enerj/rt/PrecisionRuntimeRoot.impl:Lenerj/rt/PrecisionRuntime;
    5657: getstatic     #2                  // Field enerj/rt/PrecisionRuntimeRoot.impl:Lenerj/rt/PrecisionRuntime;
    5660: aload         83
    5662: iconst_1      
    5663: invokeinterface #28,  3           // InterfaceMethod enerj/rt/PrecisionRuntime.loadLocal:(Lenerj/rt/Reference;Z)Ljava/lang/Object;
    5668: checkcast     #9                  // class com/jme/math/Vector3f
    5671: getfield      #55                 // Field com/jme/math/Vector3f.y:F
    5674: invokestatic  #32                 // Method java/lang/Float.valueOf:(F)Ljava/lang/Float;
    5677: getstatic     #2                  // Field enerj/rt/PrecisionRuntimeRoot.impl:Lenerj/rt/PrecisionRuntime;
    5680: aload         71
    5682: iconst_1      
    5683: invokeinterface #28,  3           // InterfaceMethod enerj/rt/PrecisionRuntime.loadLocal:(Lenerj/rt/Reference;Z)Ljava/lang/Object;
    5688: checkcast     #34                 // class java/lang/Float
    5691: invokevirtual #35                 // Method java/lang/Float.floatValue:()F
    5694: invokestatic  #32                 // Method java/lang/Float.valueOf:(F)Ljava/lang/Float;
    5697: getstatic     #49                 // Field enerj/rt/PrecisionRuntime$ArithOperator.MULTIPLY:Lenerj/rt/PrecisionRuntime$ArithOperator;
    5700: getstatic     #37                 // Field enerj/rt/PrecisionRuntime$NumberKind.FLOAT:Lenerj/rt/PrecisionRuntime$NumberKind;
    5703: iconst_1      
    5704: invokeinterface #38,  6           // InterfaceMethod enerj/rt/PrecisionRuntime.binaryOp:(Ljava/lang/Number;Ljava/lang/Number;Lenerj/rt/PrecisionRuntime$ArithOperator;Lenerj/rt/PrecisionRuntime$NumberKind;Z)Ljava/lang/Number;
    5709: invokevirtual #39                 // Method java/lang/Number.floatValue:()F
    5712: invokestatic  #32                 // Method java/lang/Float.valueOf:(F)Ljava/lang/Float;
    5715: getstatic     #2                  // Field enerj/rt/PrecisionRuntimeRoot.impl:Lenerj/rt/PrecisionRuntime;
    5718: aload         85
    5720: iconst_1      
    5721: invokeinterface #28,  3           // InterfaceMethod enerj/rt/PrecisionRuntime.loadLocal:(Lenerj/rt/Reference;Z)Ljava/lang/Object;
    5726: checkcast     #60                 // class com/jme/math/Vector2f
    5729: getfield      #65                 // Field com/jme/math/Vector2f.y:F
    5732: invokestatic  #32                 // Method java/lang/Float.valueOf:(F)Ljava/lang/Float;
    5735: getstatic     #49                 // Field enerj/rt/PrecisionRuntime$ArithOperator.MULTIPLY:Lenerj/rt/PrecisionRuntime$ArithOperator;
    5738: getstatic     #37                 // Field enerj/rt/PrecisionRuntime$NumberKind.FLOAT:Lenerj/rt/PrecisionRuntime$NumberKind;
    5741: iconst_1      
    5742: invokeinterface #38,  6           // InterfaceMethod enerj/rt/PrecisionRuntime.binaryOp:(Ljava/lang/Number;Ljava/lang/Number;Lenerj/rt/PrecisionRuntime$ArithOperator;Lenerj/rt/PrecisionRuntime$NumberKind;Z)Ljava/lang/Number;
    5747: invokevirtual #39                 // Method java/lang/Number.floatValue:()F
    5750: invokestatic  #32                 // Method java/lang/Float.valueOf:(F)Ljava/lang/Float;
    5753: getstatic     #36                 // Field enerj/rt/PrecisionRuntime$ArithOperator.PLUS:Lenerj/rt/PrecisionRuntime$ArithOperator;
    5756: getstatic     #37                 // Field enerj/rt/PrecisionRuntime$NumberKind.FLOAT:Lenerj/rt/PrecisionRuntime$NumberKind;
    5759: iconst_1      
    5760: invokeinterface #38,  6           // InterfaceMethod enerj/rt/PrecisionRuntime.binaryOp:(Ljava/lang/Number;Ljava/lang/Number;Lenerj/rt/PrecisionRuntime$ArithOperator;Lenerj/rt/PrecisionRuntime$NumberKind;Z)Ljava/lang/Number;
    5765: invokevirtual #39                 // Method java/lang/Number.floatValue:()F
    5768: invokestatic  #32                 // Method java/lang/Float.valueOf:(F)Ljava/lang/Float;
    5771: invokeinterface #66,  5           // InterfaceMethod enerj/rt/PrecisionRuntime.storeArray:(Ljava/lang/Object;IZLjava/lang/Object;)Ljava/lang/Object;
    5776: checkcast     #34                 // class java/lang/Float
    5779: invokevirtual #35                 // Method java/lang/Float.floatValue:()F
    5782: pop           
    5783: getstatic     #2                  // Field enerj/rt/PrecisionRuntimeRoot.impl:Lenerj/rt/PrecisionRuntime;
    5786: getstatic     #2                  // Field enerj/rt/PrecisionRuntimeRoot.impl:Lenerj/rt/PrecisionRuntime;
    5789: aload         41
    5791: iconst_0      
    5792: invokeinterface #28,  3           // InterfaceMethod enerj/rt/PrecisionRuntime.loadLocal:(Lenerj/rt/Reference;Z)Ljava/lang/Object;
    5797: iconst_1      
    5798: iconst_1      
    5799: getstatic     #2                  // Field enerj/rt/PrecisionRuntimeRoot.impl:Lenerj/rt/PrecisionRuntime;
    5802: getstatic     #2                  // Field enerj/rt/PrecisionRuntimeRoot.impl:Lenerj/rt/PrecisionRuntime;
    5805: aload         77
    5807: iconst_1      
    5808: invokeinterface #28,  3           // InterfaceMethod enerj/rt/PrecisionRuntime.loadLocal:(Lenerj/rt/Reference;Z)Ljava/lang/Object;
    5813: checkcast     #34                 // class java/lang/Float
    5816: invokevirtual #35                 // Method java/lang/Float.floatValue:()F
    5819: invokestatic  #32                 // Method java/lang/Float.valueOf:(F)Ljava/lang/Float;
    5822: getstatic     #2                  // Field enerj/rt/PrecisionRuntimeRoot.impl:Lenerj/rt/PrecisionRuntime;
    5825: getstatic     #2                  // Field enerj/rt/PrecisionRuntimeRoot.impl:Lenerj/rt/PrecisionRuntime;
    5828: getstatic     #2                  // Field enerj/rt/PrecisionRuntimeRoot.impl:Lenerj/rt/PrecisionRuntime;
    5831: aload         83
    5833: iconst_1      
    5834: invokeinterface #28,  3           // InterfaceMethod enerj/rt/PrecisionRuntime.loadLocal:(Lenerj/rt/Reference;Z)Ljava/lang/Object;
    5839: checkcast     #9                  // class com/jme/math/Vector3f
    5842: getfield      #56                 // Field com/jme/math/Vector3f.z:F
    5845: invokestatic  #32                 // Method java/lang/Float.valueOf:(F)Ljava/lang/Float;
    5848: getstatic     #2                  // Field enerj/rt/PrecisionRuntimeRoot.impl:Lenerj/rt/PrecisionRuntime;
    5851: aload         71
    5853: iconst_1      
    5854: invokeinterface #28,  3           // InterfaceMethod enerj/rt/PrecisionRuntime.loadLocal:(Lenerj/rt/Reference;Z)Ljava/lang/Object;
    5859: checkcast     #34                 // class java/lang/Float
    5862: invokevirtual #35                 // Method java/lang/Float.floatValue:()F
    5865: invokestatic  #32                 // Method java/lang/Float.valueOf:(F)Ljava/lang/Float;
    5868: getstatic     #49                 // Field enerj/rt/PrecisionRuntime$ArithOperator.MULTIPLY:Lenerj/rt/PrecisionRuntime$ArithOperator;
    5871: getstatic     #37                 // Field enerj/rt/PrecisionRuntime$NumberKind.FLOAT:Lenerj/rt/PrecisionRuntime$NumberKind;
    5874: iconst_1      
    5875: invokeinterface #38,  6           // InterfaceMethod enerj/rt/PrecisionRuntime.binaryOp:(Ljava/lang/Number;Ljava/lang/Number;Lenerj/rt/PrecisionRuntime$ArithOperator;Lenerj/rt/PrecisionRuntime$NumberKind;Z)Ljava/lang/Number;
    5880: invokevirtual #39                 // Method java/lang/Number.floatValue:()F
    5883: invokestatic  #32                 // Method java/lang/Float.valueOf:(F)Ljava/lang/Float;
    5886: getstatic     #2                  // Field enerj/rt/PrecisionRuntimeRoot.impl:Lenerj/rt/PrecisionRuntime;
    5889: aload         85
    5891: iconst_1      
    5892: invokeinterface #28,  3           // InterfaceMethod enerj/rt/PrecisionRuntime.loadLocal:(Lenerj/rt/Reference;Z)Ljava/lang/Object;
    5897: checkcast     #60                 // class com/jme/math/Vector2f
    5900: getfield      #64                 // Field com/jme/math/Vector2f.x:F
    5903: invokestatic  #32                 // Method java/lang/Float.valueOf:(F)Ljava/lang/Float;
    5906: getstatic     #49                 // Field enerj/rt/PrecisionRuntime$ArithOperator.MULTIPLY:Lenerj/rt/PrecisionRuntime$ArithOperator;
    5909: getstatic     #37                 // Field enerj/rt/PrecisionRuntime$NumberKind.FLOAT:Lenerj/rt/PrecisionRuntime$NumberKind;
    5912: iconst_1      
    5913: invokeinterface #38,  6           // InterfaceMethod enerj/rt/PrecisionRuntime.binaryOp:(Ljava/lang/Number;Ljava/lang/Number;Lenerj/rt/PrecisionRuntime$ArithOperator;Lenerj/rt/PrecisionRuntime$NumberKind;Z)Ljava/lang/Number;
    5918: invokevirtual #39                 // Method java/lang/Number.floatValue:()F
    5921: invokestatic  #32                 // Method java/lang/Float.valueOf:(F)Ljava/lang/Float;
    5924: getstatic     #36                 // Field enerj/rt/PrecisionRuntime$ArithOperator.PLUS:Lenerj/rt/PrecisionRuntime$ArithOperator;
    5927: getstatic     #37                 // Field enerj/rt/PrecisionRuntime$NumberKind.FLOAT:Lenerj/rt/PrecisionRuntime$NumberKind;
    5930: iconst_1      
    5931: invokeinterface #38,  6           // InterfaceMethod enerj/rt/PrecisionRuntime.binaryOp:(Ljava/lang/Number;Ljava/lang/Number;Lenerj/rt/PrecisionRuntime$ArithOperator;Lenerj/rt/PrecisionRuntime$NumberKind;Z)Ljava/lang/Number;
    5936: invokevirtual #39                 // Method java/lang/Number.floatValue:()F
    5939: invokestatic  #32                 // Method java/lang/Float.valueOf:(F)Ljava/lang/Float;
    5942: invokeinterface #66,  5           // InterfaceMethod enerj/rt/PrecisionRuntime.storeArray:(Ljava/lang/Object;IZLjava/lang/Object;)Ljava/lang/Object;
    5947: checkcast     #34                 // class java/lang/Float
    5950: invokevirtual #35                 // Method java/lang/Float.floatValue:()F
    5953: pop           
    5954: getstatic     #2                  // Field enerj/rt/PrecisionRuntimeRoot.impl:Lenerj/rt/PrecisionRuntime;
    5957: aload         39
    5959: iconst_0      
    5960: invokeinterface #28,  3           // InterfaceMethod enerj/rt/PrecisionRuntime.loadLocal:(Lenerj/rt/Reference;Z)Ljava/lang/Object;
    5965: checkcast     #19                 // class "[F"
    5968: invokestatic  #67                 // Method sort:([F)V
    5971: getstatic     #2                  // Field enerj/rt/PrecisionRuntimeRoot.impl:Lenerj/rt/PrecisionRuntime;
    5974: aload         41
    5976: iconst_0      
    5977: invokeinterface #28,  3           // InterfaceMethod enerj/rt/PrecisionRuntime.loadLocal:(Lenerj/rt/Reference;Z)Ljava/lang/Object;
    5982: checkcast     #19                 // class "[F"
    5985: invokestatic  #67                 // Method sort:([F)V
    5988: getstatic     #2                  // Field enerj/rt/PrecisionRuntimeRoot.impl:Lenerj/rt/PrecisionRuntime;
    5991: getstatic     #2                  // Field enerj/rt/PrecisionRuntimeRoot.impl:Lenerj/rt/PrecisionRuntime;
    5994: getstatic     #2                  // Field enerj/rt/PrecisionRuntimeRoot.impl:Lenerj/rt/PrecisionRuntime;
    5997: getstatic     #2                  // Field enerj/rt/PrecisionRuntimeRoot.impl:Lenerj/rt/PrecisionRuntime;
    6000: aload         39
    6002: iconst_0      
    6003: invokeinterface #28,  3           // InterfaceMethod enerj/rt/PrecisionRuntime.loadLocal:(Lenerj/rt/Reference;Z)Ljava/lang/Object;
    6008: iconst_1      
    6009: iconst_0      
    6010: invokeinterface #68,  4           // InterfaceMethod enerj/rt/PrecisionRuntime.loadArray:(Ljava/lang/Object;IZ)Ljava/lang/Object;
    6015: checkcast     #34                 // class java/lang/Float
    6018: invokevirtual #35                 // Method java/lang/Float.floatValue:()F
    6021: getstatic     #2                  // Field enerj/rt/PrecisionRuntimeRoot.impl:Lenerj/rt/PrecisionRuntime;
    6024: getstatic     #2                  // Field enerj/rt/PrecisionRuntimeRoot.impl:Lenerj/rt/PrecisionRuntime;
    6027: aload         41
    6029: iconst_0      
    6030: invokeinterface #28,  3           // InterfaceMethod enerj/rt/PrecisionRuntime.loadLocal:(Lenerj/rt/Reference;Z)Ljava/lang/Object;
    6035: iconst_0      
    6036: iconst_0      
    6037: invokeinterface #68,  4           // InterfaceMethod enerj/rt/PrecisionRuntime.loadArray:(Ljava/lang/Object;IZ)Ljava/lang/Object;
    6042: checkcast     #34                 // class java/lang/Float
    6045: invokevirtual #35                 // Method java/lang/Float.floatValue:()F
    6048: fcmpg         
    6049: ifge          6056
    6052: iconst_1      
    6053: goto          6057
    6056: iconst_0      
    6057: invokestatic  #45                 // Method java/lang/Boolean.valueOf:(Z)Ljava/lang/Boolean;
    6060: invokeinterface #46,  2           // InterfaceMethod enerj/rt/PrecisionRuntime.countLogicalOp:(Ljava/lang/Object;)Ljava/lang/Object;
    6065: checkcast     #47                 // class java/lang/Boolean
    6068: invokevirtual #48                 // Method java/lang/Boolean.booleanValue:()Z
    6071: ifne          6157
    6074: getstatic     #2                  // Field enerj/rt/PrecisionRuntimeRoot.impl:Lenerj/rt/PrecisionRuntime;
    6077: getstatic     #2                  // Field enerj/rt/PrecisionRuntimeRoot.impl:Lenerj/rt/PrecisionRuntime;
    6080: getstatic     #2                  // Field enerj/rt/PrecisionRuntimeRoot.impl:Lenerj/rt/PrecisionRuntime;
    6083: aload         41
    6085: iconst_0      
    6086: invokeinterface #28,  3           // InterfaceMethod enerj/rt/PrecisionRuntime.loadLocal:(Lenerj/rt/Reference;Z)Ljava/lang/Object;
    6091: iconst_1      
    6092: iconst_0      
    6093: invokeinterface #68,  4           // InterfaceMethod enerj/rt/PrecisionRuntime.loadArray:(Ljava/lang/Object;IZ)Ljava/lang/Object;
    6098: checkcast     #34                 // class java/lang/Float
    6101: invokevirtual #35                 // Method java/lang/Float.floatValue:()F
    6104: getstatic     #2                  // Field enerj/rt/PrecisionRuntimeRoot.impl:Lenerj/rt/PrecisionRuntime;
    6107: getstatic     #2                  // Field enerj/rt/PrecisionRuntimeRoot.impl:Lenerj/rt/PrecisionRuntime;
    6110: aload         39
    6112: iconst_0      
    6113: invokeinterface #28,  3           // InterfaceMethod enerj/rt/PrecisionRuntime.loadLocal:(Lenerj/rt/Reference;Z)Ljava/lang/Object;
    6118: iconst_0      
    6119: iconst_0      
    6120: invokeinterface #68,  4           // InterfaceMethod enerj/rt/PrecisionRuntime.loadArray:(Ljava/lang/Object;IZ)Ljava/lang/Object;
    6125: checkcast     #34                 // class java/lang/Float
    6128: invokevirtual #35                 // Method java/lang/Float.floatValue:()F
    6131: fcmpg         
    6132: ifge          6139
    6135: iconst_1      
    6136: goto          6140
    6139: iconst_0      
    6140: invokestatic  #45                 // Method java/lang/Boolean.valueOf:(Z)Ljava/lang/Boolean;
    6143: invokeinterface #46,  2           // InterfaceMethod enerj/rt/PrecisionRuntime.countLogicalOp:(Ljava/lang/Object;)Ljava/lang/Object;
    6148: checkcast     #47                 // class java/lang/Boolean
    6151: invokevirtual #48                 // Method java/lang/Boolean.booleanValue:()Z
    6154: ifeq          6161
    6157: iconst_1      
    6158: goto          6162
    6161: iconst_0      
    6162: invokestatic  #45                 // Method java/lang/Boolean.valueOf:(Z)Ljava/lang/Boolean;
    6165: invokeinterface #46,  2           // InterfaceMethod enerj/rt/PrecisionRuntime.countLogicalOp:(Ljava/lang/Object;)Ljava/lang/Object;
    6170: checkcast     #47                 // class java/lang/Boolean
    6173: invokevirtual #48                 // Method java/lang/Boolean.booleanValue:()Z
    6176: ifeq          6181
    6179: iconst_0      
    6180: ireturn       
    6181: iconst_1      
    6182: ireturn       

  public static void alloc_TAG1();
    Code:
       0: return        

  public static void alloc_TAG2();
    Code:
       0: return        

  public static void alloc_TAG3();
    Code:
       0: return        

  public static void alloc_TAG4();
    Code:
       0: return        

  public static boolean accept(boolean);
    Code:
       0: new           #21                 // class enerj/rt/Reference
       3: dup           
       4: iload_0       
       5: invokestatic  #45                 // Method java/lang/Boolean.valueOf:(Z)Ljava/lang/Boolean;
       8: iconst_0      
       9: iconst_1      
      10: invokespecial #22                 // Method enerj/rt/Reference."<init>":(Ljava/lang/Object;ZZ)V
      13: astore_1      
      14: getstatic     #2                  // Field enerj/rt/PrecisionRuntimeRoot.impl:Lenerj/rt/PrecisionRuntime;
      17: aload_1       
      18: iconst_0      
      19: invokeinterface #28,  3           // InterfaceMethod enerj/rt/PrecisionRuntime.loadLocal:(Lenerj/rt/Reference;Z)Ljava/lang/Object;
      24: checkcast     #47                 // class java/lang/Boolean
      27: invokevirtual #48                 // Method java/lang/Boolean.booleanValue:()Z
      30: ireturn       

  public static float accept(float);
    Code:
       0: new           #21                 // class enerj/rt/Reference
       3: dup           
       4: fload_0       
       5: invokestatic  #32                 // Method java/lang/Float.valueOf:(F)Ljava/lang/Float;
       8: iconst_0      
       9: iconst_1      
      10: invokespecial #22                 // Method enerj/rt/Reference."<init>":(Ljava/lang/Object;ZZ)V
      13: astore_1      
      14: getstatic     #2                  // Field enerj/rt/PrecisionRuntimeRoot.impl:Lenerj/rt/PrecisionRuntime;
      17: aload_1       
      18: iconst_0      
      19: invokeinterface #28,  3           // InterfaceMethod enerj/rt/PrecisionRuntime.loadLocal:(Lenerj/rt/Reference;Z)Ljava/lang/Object;
      24: checkcast     #34                 // class java/lang/Float
      27: invokevirtual #35                 // Method java/lang/Float.floatValue:()F
      30: freturn       

  public static com.jme.math.Vector3f accept_all_FIELD1_TAG1(com.jme.math.Vector3f);
    Code:
       0: new           #21                 // class enerj/rt/Reference
       3: dup           
       4: aload_0       
       5: iconst_0      
       6: iconst_0      
       7: invokespecial #22                 // Method enerj/rt/Reference."<init>":(Ljava/lang/Object;ZZ)V
      10: astore_1      
      11: getstatic     #2                  // Field enerj/rt/PrecisionRuntimeRoot.impl:Lenerj/rt/PrecisionRuntime;
      14: aload_1       
      15: iconst_1      
      16: invokeinterface #28,  3           // InterfaceMethod enerj/rt/PrecisionRuntime.loadLocal:(Lenerj/rt/Reference;Z)Ljava/lang/Object;
      21: checkcast     #9                  // class com/jme/math/Vector3f
      24: areturn       

  public static com.jme.math.Vector3f accept_all_FIELD2_TAG1(com.jme.math.Vector3f);
    Code:
       0: new           #21                 // class enerj/rt/Reference
       3: dup           
       4: aload_0       
       5: iconst_0      
       6: iconst_0      
       7: invokespecial #22                 // Method enerj/rt/Reference."<init>":(Ljava/lang/Object;ZZ)V
      10: astore_1      
      11: getstatic     #2                  // Field enerj/rt/PrecisionRuntimeRoot.impl:Lenerj/rt/PrecisionRuntime;
      14: aload_1       
      15: iconst_1      
      16: invokeinterface #28,  3           // InterfaceMethod enerj/rt/PrecisionRuntime.loadLocal:(Lenerj/rt/Reference;Z)Ljava/lang/Object;
      21: checkcast     #9                  // class com/jme/math/Vector3f
      24: areturn       

  public static com.jme.math.Vector3f accept_all_FIELD3_TAG1(com.jme.math.Vector3f);
    Code:
       0: new           #21                 // class enerj/rt/Reference
       3: dup           
       4: aload_0       
       5: iconst_0      
       6: iconst_0      
       7: invokespecial #22                 // Method enerj/rt/Reference."<init>":(Ljava/lang/Object;ZZ)V
      10: astore_1      
      11: getstatic     #2                  // Field enerj/rt/PrecisionRuntimeRoot.impl:Lenerj/rt/PrecisionRuntime;
      14: aload_1       
      15: iconst_1      
      16: invokeinterface #28,  3           // InterfaceMethod enerj/rt/PrecisionRuntime.loadLocal:(Lenerj/rt/Reference;Z)Ljava/lang/Object;
      21: checkcast     #9                  // class com/jme/math/Vector3f
      24: areturn       

  public static com.jme.math.Vector3f accept_all_FIELD1_TAG3(com.jme.math.Vector3f);
    Code:
       0: new           #21                 // class enerj/rt/Reference
       3: dup           
       4: aload_0       
       5: iconst_0      
       6: iconst_0      
       7: invokespecial #22                 // Method enerj/rt/Reference."<init>":(Ljava/lang/Object;ZZ)V
      10: astore_1      
      11: getstatic     #2                  // Field enerj/rt/PrecisionRuntimeRoot.impl:Lenerj/rt/PrecisionRuntime;
      14: aload_1       
      15: iconst_1      
      16: invokeinterface #28,  3           // InterfaceMethod enerj/rt/PrecisionRuntime.loadLocal:(Lenerj/rt/Reference;Z)Ljava/lang/Object;
      21: checkcast     #9                  // class com/jme/math/Vector3f
      24: areturn       

  public static com.jme.math.Vector3f accept_all_FIELD2_TAG3(com.jme.math.Vector3f);
    Code:
       0: new           #21                 // class enerj/rt/Reference
       3: dup           
       4: aload_0       
       5: iconst_0      
       6: iconst_0      
       7: invokespecial #22                 // Method enerj/rt/Reference."<init>":(Ljava/lang/Object;ZZ)V
      10: astore_1      
      11: getstatic     #2                  // Field enerj/rt/PrecisionRuntimeRoot.impl:Lenerj/rt/PrecisionRuntime;
      14: aload_1       
      15: iconst_1      
      16: invokeinterface #28,  3           // InterfaceMethod enerj/rt/PrecisionRuntime.loadLocal:(Lenerj/rt/Reference;Z)Ljava/lang/Object;
      21: checkcast     #9                  // class com/jme/math/Vector3f
      24: areturn       

  public static com.jme.math.Vector3f accept_all_FIELD3_TAG3(com.jme.math.Vector3f);
    Code:
       0: new           #21                 // class enerj/rt/Reference
       3: dup           
       4: aload_0       
       5: iconst_0      
       6: iconst_0      
       7: invokespecial #22                 // Method enerj/rt/Reference."<init>":(Ljava/lang/Object;ZZ)V
      10: astore_1      
      11: getstatic     #2                  // Field enerj/rt/PrecisionRuntimeRoot.impl:Lenerj/rt/PrecisionRuntime;
      14: aload_1       
      15: iconst_1      
      16: invokeinterface #28,  3           // InterfaceMethod enerj/rt/PrecisionRuntime.loadLocal:(Lenerj/rt/Reference;Z)Ljava/lang/Object;
      21: checkcast     #9                  // class com/jme/math/Vector3f
      24: areturn       

  public static com.jme.math.Vector3f accept_all_FIELD1_TAG4(com.jme.math.Vector3f);
    Code:
       0: new           #21                 // class enerj/rt/Reference
       3: dup           
       4: aload_0       
       5: iconst_0      
       6: iconst_0      
       7: invokespecial #22                 // Method enerj/rt/Reference."<init>":(Ljava/lang/Object;ZZ)V
      10: astore_1      
      11: getstatic     #2                  // Field enerj/rt/PrecisionRuntimeRoot.impl:Lenerj/rt/PrecisionRuntime;
      14: aload_1       
      15: iconst_1      
      16: invokeinterface #28,  3           // InterfaceMethod enerj/rt/PrecisionRuntime.loadLocal:(Lenerj/rt/Reference;Z)Ljava/lang/Object;
      21: checkcast     #9                  // class com/jme/math/Vector3f
      24: areturn       

  public static com.jme.math.Vector3f accept_all_FIELD2_TAG4(com.jme.math.Vector3f);
    Code:
       0: new           #21                 // class enerj/rt/Reference
       3: dup           
       4: aload_0       
       5: iconst_0      
       6: iconst_0      
       7: invokespecial #22                 // Method enerj/rt/Reference."<init>":(Ljava/lang/Object;ZZ)V
      10: astore_1      
      11: getstatic     #2                  // Field enerj/rt/PrecisionRuntimeRoot.impl:Lenerj/rt/PrecisionRuntime;
      14: aload_1       
      15: iconst_1      
      16: invokeinterface #28,  3           // InterfaceMethod enerj/rt/PrecisionRuntime.loadLocal:(Lenerj/rt/Reference;Z)Ljava/lang/Object;
      21: checkcast     #9                  // class com/jme/math/Vector3f
      24: areturn       

  public static com.jme.math.Vector3f accept_all_FIELD3_TAG4(com.jme.math.Vector3f);
    Code:
       0: new           #21                 // class enerj/rt/Reference
       3: dup           
       4: aload_0       
       5: iconst_0      
       6: iconst_0      
       7: invokespecial #22                 // Method enerj/rt/Reference."<init>":(Ljava/lang/Object;ZZ)V
      10: astore_1      
      11: getstatic     #2                  // Field enerj/rt/PrecisionRuntimeRoot.impl:Lenerj/rt/PrecisionRuntime;
      14: aload_1       
      15: iconst_1      
      16: invokeinterface #28,  3           // InterfaceMethod enerj/rt/PrecisionRuntime.loadLocal:(Lenerj/rt/Reference;Z)Ljava/lang/Object;
      21: checkcast     #9                  // class com/jme/math/Vector3f
      24: areturn       

  public static float[] accept_all_FIELD4_TAG2(float[]);
    Code:
       0: new           #21                 // class enerj/rt/Reference
       3: dup           
       4: aload_0       
       5: iconst_0      
       6: iconst_0      
       7: invokespecial #22                 // Method enerj/rt/Reference."<init>":(Ljava/lang/Object;ZZ)V
      10: astore_1      
      11: getstatic     #2                  // Field enerj/rt/PrecisionRuntimeRoot.impl:Lenerj/rt/PrecisionRuntime;
      14: aload_1       
      15: iconst_0      
      16: invokeinterface #28,  3           // InterfaceMethod enerj/rt/PrecisionRuntime.loadLocal:(Lenerj/rt/Reference;Z)Ljava/lang/Object;
      21: checkcast     #19                 // class "[F"
      24: areturn       

  public static void __htt_staticInitializerMethod();
    Code:
       0: invokestatic  #4                  // Method alloc_TAG3:()V
       3: getstatic     #2                  // Field enerj/rt/PrecisionRuntimeRoot.impl:Lenerj/rt/PrecisionRuntime;
       6: ldc_w         #5                  // class com/jme/intersection/Intersection
       9: ldc           #6                  // String tempVc
      11: iconst_0      
      12: getstatic     #2                  // Field enerj/rt/PrecisionRuntimeRoot.impl:Lenerj/rt/PrecisionRuntime;
      15: getstatic     #2                  // Field enerj/rt/PrecisionRuntimeRoot.impl:Lenerj/rt/PrecisionRuntime;
      18: invokestatic  #7                  // Method java/lang/Thread.currentThread:()Ljava/lang/Thread;
      21: iconst_1      
      22: bipush        76
      24: iconst_0      
      25: invokeinterface #8,  5            // InterfaceMethod enerj/rt/PrecisionRuntime.beforeCreation:(Ljava/lang/Object;ZII)Z
      30: new           #9                  // class com/jme/math/Vector3f
      33: dup           
      34: invokespecial #10                 // Method com/jme/math/Vector3f."<init>":()V
      37: invokestatic  #7                  // Method java/lang/Thread.currentThread:()Ljava/lang/Thread;
      40: invokeinterface #11,  4           // InterfaceMethod enerj/rt/PrecisionRuntime.wrappedNew:(ZLjava/lang/Object;Ljava/lang/Object;)Ljava/lang/Object;
      45: checkcast     #9                  // class com/jme/math/Vector3f
      48: invokeinterface #12,  5           // InterfaceMethod enerj/rt/PrecisionRuntime.storeField:(Ljava/lang/Object;Ljava/lang/String;ZLjava/lang/Object;)Ljava/lang/Object;
      53: pop           
      54: invokestatic  #4                  // Method alloc_TAG3:()V
      57: getstatic     #2                  // Field enerj/rt/PrecisionRuntimeRoot.impl:Lenerj/rt/PrecisionRuntime;
      60: ldc_w         #5                  // class com/jme/intersection/Intersection
      63: ldc           #13                 // String tempVd
      65: iconst_0      
      66: getstatic     #2                  // Field enerj/rt/PrecisionRuntimeRoot.impl:Lenerj/rt/PrecisionRuntime;
      69: getstatic     #2                  // Field enerj/rt/PrecisionRuntimeRoot.impl:Lenerj/rt/PrecisionRuntime;
      72: invokestatic  #7                  // Method java/lang/Thread.currentThread:()Ljava/lang/Thread;
      75: iconst_1      
      76: bipush        76
      78: iconst_0      
      79: invokeinterface #8,  5            // InterfaceMethod enerj/rt/PrecisionRuntime.beforeCreation:(Ljava/lang/Object;ZII)Z
      84: new           #9                  // class com/jme/math/Vector3f
      87: dup           
      88: invokespecial #10                 // Method com/jme/math/Vector3f."<init>":()V
      91: invokestatic  #7                  // Method java/lang/Thread.currentThread:()Ljava/lang/Thread;
      94: invokeinterface #11,  4           // InterfaceMethod enerj/rt/PrecisionRuntime.wrappedNew:(ZLjava/lang/Object;Ljava/lang/Object;)Ljava/lang/Object;
      99: checkcast     #9                  // class com/jme/math/Vector3f
     102: invokeinterface #12,  5           // InterfaceMethod enerj/rt/PrecisionRuntime.storeField:(Ljava/lang/Object;Ljava/lang/String;ZLjava/lang/Object;)Ljava/lang/Object;
     107: pop           
     108: invokestatic  #14                 // Method alloc_TAG1:()V
     111: getstatic     #2                  // Field enerj/rt/PrecisionRuntimeRoot.impl:Lenerj/rt/PrecisionRuntime;
     114: ldc_w         #5                  // class com/jme/intersection/Intersection
     117: ldc           #15                 // String tempVe
     119: iconst_0      
     120: getstatic     #2                  // Field enerj/rt/PrecisionRuntimeRoot.impl:Lenerj/rt/PrecisionRuntime;
     123: getstatic     #2                  // Field enerj/rt/PrecisionRuntimeRoot.impl:Lenerj/rt/PrecisionRuntime;
     126: invokestatic  #7                  // Method java/lang/Thread.currentThread:()Ljava/lang/Thread;
     129: iconst_1      
     130: bipush        76
     132: iconst_0      
     133: invokeinterface #8,  5            // InterfaceMethod enerj/rt/PrecisionRuntime.beforeCreation:(Ljava/lang/Object;ZII)Z
     138: new           #9                  // class com/jme/math/Vector3f
     141: dup           
     142: invokespecial #10                 // Method com/jme/math/Vector3f."<init>":()V
     145: invokestatic  #7                  // Method java/lang/Thread.currentThread:()Ljava/lang/Thread;
     148: invokeinterface #11,  4           // InterfaceMethod enerj/rt/PrecisionRuntime.wrappedNew:(ZLjava/lang/Object;Ljava/lang/Object;)Ljava/lang/Object;
     153: checkcast     #9                  // class com/jme/math/Vector3f
     156: invokeinterface #12,  5           // InterfaceMethod enerj/rt/PrecisionRuntime.storeField:(Ljava/lang/Object;Ljava/lang/String;ZLjava/lang/Object;)Ljava/lang/Object;
     161: pop           
     162: invokestatic  #16                 // Method alloc_TAG2:()V
     165: getstatic     #2                  // Field enerj/rt/PrecisionRuntimeRoot.impl:Lenerj/rt/PrecisionRuntime;
     168: ldc_w         #5                  // class com/jme/intersection/Intersection
     171: ldc           #17                 // String tempFa
     173: iconst_0      
     174: getstatic     #2                  // Field enerj/rt/PrecisionRuntimeRoot.impl:Lenerj/rt/PrecisionRuntime;
     177: iconst_2      
     178: newarray       float
     180: iconst_1      
     181: iconst_1      
     182: iconst_4      
     183: iconst_0      
     184: invokeinterface #18,  6           // InterfaceMethod enerj/rt/PrecisionRuntime.newArray:(Ljava/lang/Object;IZII)Ljava/lang/Object;
     189: checkcast     #19                 // class "[F"
     192: checkcast     #19                 // class "[F"
     195: invokeinterface #12,  5           // InterfaceMethod enerj/rt/PrecisionRuntime.storeField:(Ljava/lang/Object;Ljava/lang/String;ZLjava/lang/Object;)Ljava/lang/Object;
     200: pop           
     201: invokestatic  #16                 // Method alloc_TAG2:()V
     204: getstatic     #2                  // Field enerj/rt/PrecisionRuntimeRoot.impl:Lenerj/rt/PrecisionRuntime;
     207: ldc_w         #5                  // class com/jme/intersection/Intersection
     210: ldc           #20                 // String tempFb
     212: iconst_0      
     213: getstatic     #2                  // Field enerj/rt/PrecisionRuntimeRoot.impl:Lenerj/rt/PrecisionRuntime;
     216: iconst_2      
     217: newarray       float
     219: iconst_1      
     220: iconst_1      
     221: iconst_4      
     222: iconst_0      
     223: invokeinterface #18,  6           // InterfaceMethod enerj/rt/PrecisionRuntime.newArray:(Ljava/lang/Object;IZII)Ljava/lang/Object;
     228: checkcast     #19                 // class "[F"
     231: checkcast     #19                 // class "[F"
     234: invokeinterface #12,  5           // InterfaceMethod enerj/rt/PrecisionRuntime.storeField:(Ljava/lang/Object;Ljava/lang/String;ZLjava/lang/Object;)Ljava/lang/Object;
     239: pop           
     240: return        

  static {};
    Code:
       0: getstatic     #2                  // Field enerj/rt/PrecisionRuntimeRoot.impl:Lenerj/rt/PrecisionRuntime;
       3: ldc2_w        #88                 // double 1.0E-12d
       6: invokestatic  #90                 // Method java/lang/Double.valueOf:(D)Ljava/lang/Double;
       9: iconst_0      
      10: getstatic     #91                 // Field enerj/rt/PrecisionRuntime$MemKind.FIELD:Lenerj/rt/PrecisionRuntime$MemKind;
      13: invokeinterface #26,  4           // InterfaceMethod enerj/rt/PrecisionRuntime.storeValue:(Ljava/lang/Object;ZLenerj/rt/PrecisionRuntime$MemKind;)Ljava/lang/Object;
      18: checkcast     #43                 // class java/lang/Double
      21: invokevirtual #44                 // Method java/lang/Double.doubleValue:()D
      24: putstatic     #92                 // Field EPSILON:D
      27: getstatic     #2                  // Field enerj/rt/PrecisionRuntimeRoot.impl:Lenerj/rt/PrecisionRuntime;
      30: getstatic     #2                  // Field enerj/rt/PrecisionRuntimeRoot.impl:Lenerj/rt/PrecisionRuntime;
      33: getstatic     #2                  // Field enerj/rt/PrecisionRuntimeRoot.impl:Lenerj/rt/PrecisionRuntime;
      36: invokestatic  #7                  // Method java/lang/Thread.currentThread:()Ljava/lang/Thread;
      39: iconst_0      
      40: bipush        76
      42: iconst_0      
      43: invokeinterface #8,  5            // InterfaceMethod enerj/rt/PrecisionRuntime.beforeCreation:(Ljava/lang/Object;ZII)Z
      48: new           #9                  // class com/jme/math/Vector3f
      51: dup           
      52: invokespecial #10                 // Method com/jme/math/Vector3f."<init>":()V
      55: invokestatic  #7                  // Method java/lang/Thread.currentThread:()Ljava/lang/Thread;
      58: invokeinterface #11,  4           // InterfaceMethod enerj/rt/PrecisionRuntime.wrappedNew:(ZLjava/lang/Object;Ljava/lang/Object;)Ljava/lang/Object;
      63: iconst_0      
      64: getstatic     #91                 // Field enerj/rt/PrecisionRuntime$MemKind.FIELD:Lenerj/rt/PrecisionRuntime$MemKind;
      67: invokeinterface #26,  4           // InterfaceMethod enerj/rt/PrecisionRuntime.storeValue:(Ljava/lang/Object;ZLenerj/rt/PrecisionRuntime$MemKind;)Ljava/lang/Object;
      72: checkcast     #9                  // class com/jme/math/Vector3f
      75: putstatic     #93                 // Field tempVa:Lcom/jme/math/Vector3f;
      78: getstatic     #2                  // Field enerj/rt/PrecisionRuntimeRoot.impl:Lenerj/rt/PrecisionRuntime;
      81: getstatic     #2                  // Field enerj/rt/PrecisionRuntimeRoot.impl:Lenerj/rt/PrecisionRuntime;
      84: getstatic     #2                  // Field enerj/rt/PrecisionRuntimeRoot.impl:Lenerj/rt/PrecisionRuntime;
      87: invokestatic  #7                  // Method java/lang/Thread.currentThread:()Ljava/lang/Thread;
      90: iconst_0      
      91: bipush        76
      93: iconst_0      
      94: invokeinterface #8,  5            // InterfaceMethod enerj/rt/PrecisionRuntime.beforeCreation:(Ljava/lang/Object;ZII)Z
      99: new           #9                  // class com/jme/math/Vector3f
     102: dup           
     103: invokespecial #10                 // Method com/jme/math/Vector3f."<init>":()V
     106: invokestatic  #7                  // Method java/lang/Thread.currentThread:()Ljava/lang/Thread;
     109: invokeinterface #11,  4           // InterfaceMethod enerj/rt/PrecisionRuntime.wrappedNew:(ZLjava/lang/Object;Ljava/lang/Object;)Ljava/lang/Object;
     114: iconst_0      
     115: getstatic     #91                 // Field enerj/rt/PrecisionRuntime$MemKind.FIELD:Lenerj/rt/PrecisionRuntime$MemKind;
     118: invokeinterface #26,  4           // InterfaceMethod enerj/rt/PrecisionRuntime.storeValue:(Ljava/lang/Object;ZLenerj/rt/PrecisionRuntime$MemKind;)Ljava/lang/Object;
     123: checkcast     #9                  // class com/jme/math/Vector3f
     126: putstatic     #94                 // Field tempVb:Lcom/jme/math/Vector3f;
     129: getstatic     #2                  // Field enerj/rt/PrecisionRuntimeRoot.impl:Lenerj/rt/PrecisionRuntime;
     132: getstatic     #2                  // Field enerj/rt/PrecisionRuntimeRoot.impl:Lenerj/rt/PrecisionRuntime;
     135: getstatic     #2                  // Field enerj/rt/PrecisionRuntimeRoot.impl:Lenerj/rt/PrecisionRuntime;
     138: invokestatic  #7                  // Method java/lang/Thread.currentThread:()Ljava/lang/Thread;
     141: iconst_0      
     142: bipush        32
     144: iconst_0      
     145: invokeinterface #8,  5            // InterfaceMethod enerj/rt/PrecisionRuntime.beforeCreation:(Ljava/lang/Object;ZII)Z
     150: new           #60                 // class com/jme/math/Vector2f
     153: dup           
     154: invokespecial #95                 // Method com/jme/math/Vector2f."<init>":()V
     157: invokestatic  #7                  // Method java/lang/Thread.currentThread:()Ljava/lang/Thread;
     160: invokeinterface #11,  4           // InterfaceMethod enerj/rt/PrecisionRuntime.wrappedNew:(ZLjava/lang/Object;Ljava/lang/Object;)Ljava/lang/Object;
     165: iconst_0      
     166: getstatic     #91                 // Field enerj/rt/PrecisionRuntime$MemKind.FIELD:Lenerj/rt/PrecisionRuntime$MemKind;
     169: invokeinterface #26,  4           // InterfaceMethod enerj/rt/PrecisionRuntime.storeValue:(Ljava/lang/Object;ZLenerj/rt/PrecisionRuntime$MemKind;)Ljava/lang/Object;
     174: checkcast     #60                 // class com/jme/math/Vector2f
     177: putstatic     #96                 // Field tempV2a:Lcom/jme/math/Vector2f;
     180: getstatic     #2                  // Field enerj/rt/PrecisionRuntimeRoot.impl:Lenerj/rt/PrecisionRuntime;
     183: getstatic     #2                  // Field enerj/rt/PrecisionRuntimeRoot.impl:Lenerj/rt/PrecisionRuntime;
     186: getstatic     #2                  // Field enerj/rt/PrecisionRuntimeRoot.impl:Lenerj/rt/PrecisionRuntime;
     189: invokestatic  #7                  // Method java/lang/Thread.currentThread:()Ljava/lang/Thread;
     192: iconst_0      
     193: bipush        32
     195: iconst_0      
     196: invokeinterface #8,  5            // InterfaceMethod enerj/rt/PrecisionRuntime.beforeCreation:(Ljava/lang/Object;ZII)Z
     201: new           #60                 // class com/jme/math/Vector2f
     204: dup           
     205: invokespecial #95                 // Method com/jme/math/Vector2f."<init>":()V
     208: invokestatic  #7                  // Method java/lang/Thread.currentThread:()Ljava/lang/Thread;
     211: invokeinterface #11,  4           // InterfaceMethod enerj/rt/PrecisionRuntime.wrappedNew:(ZLjava/lang/Object;Ljava/lang/Object;)Ljava/lang/Object;
     216: iconst_0      
     217: getstatic     #91                 // Field enerj/rt/PrecisionRuntime$MemKind.FIELD:Lenerj/rt/PrecisionRuntime$MemKind;
     220: invokeinterface #26,  4           // InterfaceMethod enerj/rt/PrecisionRuntime.storeValue:(Ljava/lang/Object;ZLenerj/rt/PrecisionRuntime$MemKind;)Ljava/lang/Object;
     225: checkcast     #60                 // class com/jme/math/Vector2f
     228: putstatic     #97                 // Field tempV2b:Lcom/jme/math/Vector2f;
     231: invokestatic  #98                 // Method __htt_staticInitializerMethod:()V
     234: return        
}
