Compiled from "RgbImage.java"
public class Sobel.RgbImage {
  public int width;

  public int height;

  public int[][][] image;

  public Sobel.RgbImage();
    Code:
       0: aload_0       
       1: invokespecial #1                  // Method java/lang/Object."<init>":()V
       4: getstatic     #2                  // Field enerj/rt/PrecisionRuntimeRoot.impl:Lenerj/rt/PrecisionRuntime;
       7: aload_0       
       8: invokeinterface #3,  2            // InterfaceMethod enerj/rt/PrecisionRuntime.enterConstructor:(Ljava/lang/Object;)Z
      13: pop           
      14: return        

  public void load(java.lang.String) throws java.io.IOException;
    Code:
       0: new           #4                  // class enerj/rt/Reference
       3: dup           
       4: aload_1       
       5: iconst_0      
       6: iconst_0      
       7: invokespecial #5                  // Method enerj/rt/Reference."<init>":(Ljava/lang/Object;ZZ)V
      10: astore_2      
      11: getstatic     #2                  // Field enerj/rt/PrecisionRuntimeRoot.impl:Lenerj/rt/PrecisionRuntime;
      14: getstatic     #2                  // Field enerj/rt/PrecisionRuntimeRoot.impl:Lenerj/rt/PrecisionRuntime;
      17: getstatic     #2                  // Field enerj/rt/PrecisionRuntimeRoot.impl:Lenerj/rt/PrecisionRuntime;
      20: invokestatic  #6                  // Method java/lang/Thread.currentThread:()Ljava/lang/Thread;
      23: iconst_0      
      24: bipush        57
      26: iconst_0      
      27: invokeinterface #7,  5            // InterfaceMethod enerj/rt/PrecisionRuntime.beforeCreation:(Ljava/lang/Object;ZII)Z
      32: new           #8                  // class Sobel/TextFile
      35: dup           
      36: getstatic     #2                  // Field enerj/rt/PrecisionRuntimeRoot.impl:Lenerj/rt/PrecisionRuntime;
      39: aload_2       
      40: iconst_0      
      41: invokeinterface #9,  3            // InterfaceMethod enerj/rt/PrecisionRuntime.loadLocal:(Lenerj/rt/Reference;Z)Ljava/lang/Object;
      46: checkcast     #10                 // class java/lang/String
      49: getstatic     #2                  // Field enerj/rt/PrecisionRuntimeRoot.impl:Lenerj/rt/PrecisionRuntime;
      52: ldc_w         #11                 // class Sobel/TextFile$Mode
      55: ldc           #12                 // String READ
      57: iconst_0      
      58: invokeinterface #13,  4           // InterfaceMethod enerj/rt/PrecisionRuntime.loadField:(Ljava/lang/Object;Ljava/lang/String;Z)Ljava/lang/Object;
      63: checkcast     #11                 // class Sobel/TextFile$Mode
      66: invokespecial #14                 // Method Sobel/TextFile."<init>":(Ljava/lang/String;LSobel/TextFile$Mode;)V
      69: invokestatic  #6                  // Method java/lang/Thread.currentThread:()Ljava/lang/Thread;
      72: invokeinterface #15,  4           // InterfaceMethod enerj/rt/PrecisionRuntime.wrappedNew:(ZLjava/lang/Object;Ljava/lang/Object;)Ljava/lang/Object;
      77: iconst_0      
      78: getstatic     #16                 // Field enerj/rt/PrecisionRuntime$MemKind.VARIABLE:Lenerj/rt/PrecisionRuntime$MemKind;
      81: invokeinterface #17,  4           // InterfaceMethod enerj/rt/PrecisionRuntime.storeValue:(Ljava/lang/Object;ZLenerj/rt/PrecisionRuntime$MemKind;)Ljava/lang/Object;
      86: checkcast     #8                  // class Sobel/TextFile
      89: astore_3      
      90: new           #4                  // class enerj/rt/Reference
      93: dup           
      94: aload_3       
      95: iconst_0      
      96: iconst_0      
      97: invokespecial #5                  // Method enerj/rt/Reference."<init>":(Ljava/lang/Object;ZZ)V
     100: astore        4
     102: getstatic     #2                  // Field enerj/rt/PrecisionRuntimeRoot.impl:Lenerj/rt/PrecisionRuntime;
     105: aload_0       
     106: ldc           #18                 // String width
     108: iconst_0      
     109: getstatic     #2                  // Field enerj/rt/PrecisionRuntimeRoot.impl:Lenerj/rt/PrecisionRuntime;
     112: aload         4
     114: iconst_0      
     115: invokeinterface #9,  3            // InterfaceMethod enerj/rt/PrecisionRuntime.loadLocal:(Lenerj/rt/Reference;Z)Ljava/lang/Object;
     120: checkcast     #8                  // class Sobel/TextFile
     123: invokevirtual #19                 // Method Sobel/TextFile.loadInt:()I
     126: invokestatic  #20                 // Method java/lang/Integer.valueOf:(I)Ljava/lang/Integer;
     129: invokeinterface #21,  5           // InterfaceMethod enerj/rt/PrecisionRuntime.storeField:(Ljava/lang/Object;Ljava/lang/String;ZLjava/lang/Object;)Ljava/lang/Object;
     134: checkcast     #22                 // class java/lang/Integer
     137: invokevirtual #23                 // Method java/lang/Integer.intValue:()I
     140: pop           
     141: getstatic     #2                  // Field enerj/rt/PrecisionRuntimeRoot.impl:Lenerj/rt/PrecisionRuntime;
     144: aload         4
     146: iconst_0      
     147: invokeinterface #9,  3            // InterfaceMethod enerj/rt/PrecisionRuntime.loadLocal:(Lenerj/rt/Reference;Z)Ljava/lang/Object;
     152: checkcast     #8                  // class Sobel/TextFile
     155: invokevirtual #24                 // Method Sobel/TextFile.loadChar:()C
     158: pop           
     159: getstatic     #2                  // Field enerj/rt/PrecisionRuntimeRoot.impl:Lenerj/rt/PrecisionRuntime;
     162: aload_0       
     163: ldc           #25                 // String height
     165: iconst_0      
     166: getstatic     #2                  // Field enerj/rt/PrecisionRuntimeRoot.impl:Lenerj/rt/PrecisionRuntime;
     169: aload         4
     171: iconst_0      
     172: invokeinterface #9,  3            // InterfaceMethod enerj/rt/PrecisionRuntime.loadLocal:(Lenerj/rt/Reference;Z)Ljava/lang/Object;
     177: checkcast     #8                  // class Sobel/TextFile
     180: invokevirtual #19                 // Method Sobel/TextFile.loadInt:()I
     183: invokestatic  #20                 // Method java/lang/Integer.valueOf:(I)Ljava/lang/Integer;
     186: invokeinterface #21,  5           // InterfaceMethod enerj/rt/PrecisionRuntime.storeField:(Ljava/lang/Object;Ljava/lang/String;ZLjava/lang/Object;)Ljava/lang/Object;
     191: checkcast     #22                 // class java/lang/Integer
     194: invokevirtual #23                 // Method java/lang/Integer.intValue:()I
     197: pop           
     198: getstatic     #2                  // Field enerj/rt/PrecisionRuntimeRoot.impl:Lenerj/rt/PrecisionRuntime;
     201: aload_0       
     202: ldc           #26                 // String image
     204: iconst_0      
     205: getstatic     #2                  // Field enerj/rt/PrecisionRuntimeRoot.impl:Lenerj/rt/PrecisionRuntime;
     208: getstatic     #2                  // Field enerj/rt/PrecisionRuntimeRoot.impl:Lenerj/rt/PrecisionRuntime;
     211: aload_0       
     212: ldc           #25                 // String height
     214: iconst_0      
     215: invokeinterface #13,  4           // InterfaceMethod enerj/rt/PrecisionRuntime.loadField:(Ljava/lang/Object;Ljava/lang/String;Z)Ljava/lang/Object;
     220: checkcast     #22                 // class java/lang/Integer
     223: invokevirtual #23                 // Method java/lang/Integer.intValue:()I
     226: anewarray     #27                 // class "[[I"
     229: iconst_1      
     230: iconst_0      
     231: iconst_0      
     232: iconst_0      
     233: invokeinterface #28,  6           // InterfaceMethod enerj/rt/PrecisionRuntime.newArray:(Ljava/lang/Object;IZII)Ljava/lang/Object;
     238: checkcast     #29                 // class "[[[I"
     241: checkcast     #29                 // class "[[[I"
     244: invokeinterface #21,  5           // InterfaceMethod enerj/rt/PrecisionRuntime.storeField:(Ljava/lang/Object;Ljava/lang/String;ZLjava/lang/Object;)Ljava/lang/Object;
     249: pop           
     250: getstatic     #2                  // Field enerj/rt/PrecisionRuntimeRoot.impl:Lenerj/rt/PrecisionRuntime;
     253: iconst_0      
     254: invokestatic  #20                 // Method java/lang/Integer.valueOf:(I)Ljava/lang/Integer;
     257: iconst_0      
     258: getstatic     #16                 // Field enerj/rt/PrecisionRuntime$MemKind.VARIABLE:Lenerj/rt/PrecisionRuntime$MemKind;
     261: invokeinterface #17,  4           // InterfaceMethod enerj/rt/PrecisionRuntime.storeValue:(Ljava/lang/Object;ZLenerj/rt/PrecisionRuntime$MemKind;)Ljava/lang/Object;
     266: checkcast     #22                 // class java/lang/Integer
     269: invokevirtual #23                 // Method java/lang/Integer.intValue:()I
     272: istore        5
     274: new           #4                  // class enerj/rt/Reference
     277: dup           
     278: iload         5
     280: invokestatic  #20                 // Method java/lang/Integer.valueOf:(I)Ljava/lang/Integer;
     283: iconst_0      
     284: iconst_1      
     285: invokespecial #5                  // Method enerj/rt/Reference."<init>":(Ljava/lang/Object;ZZ)V
     288: astore        6
     290: getstatic     #2                  // Field enerj/rt/PrecisionRuntimeRoot.impl:Lenerj/rt/PrecisionRuntime;
     293: getstatic     #2                  // Field enerj/rt/PrecisionRuntimeRoot.impl:Lenerj/rt/PrecisionRuntime;
     296: aload         6
     298: iconst_0      
     299: invokeinterface #9,  3            // InterfaceMethod enerj/rt/PrecisionRuntime.loadLocal:(Lenerj/rt/Reference;Z)Ljava/lang/Object;
     304: checkcast     #22                 // class java/lang/Integer
     307: invokevirtual #23                 // Method java/lang/Integer.intValue:()I
     310: getstatic     #2                  // Field enerj/rt/PrecisionRuntimeRoot.impl:Lenerj/rt/PrecisionRuntime;
     313: aload_0       
     314: ldc           #25                 // String height
     316: iconst_0      
     317: invokeinterface #13,  4           // InterfaceMethod enerj/rt/PrecisionRuntime.loadField:(Ljava/lang/Object;Ljava/lang/String;Z)Ljava/lang/Object;
     322: checkcast     #22                 // class java/lang/Integer
     325: invokevirtual #23                 // Method java/lang/Integer.intValue:()I
     328: if_icmpge     335
     331: iconst_1      
     332: goto          336
     335: iconst_0      
     336: invokestatic  #30                 // Method java/lang/Boolean.valueOf:(Z)Ljava/lang/Boolean;
     339: invokeinterface #31,  2           // InterfaceMethod enerj/rt/PrecisionRuntime.countLogicalOp:(Ljava/lang/Object;)Ljava/lang/Object;
     344: checkcast     #32                 // class java/lang/Boolean
     347: invokevirtual #33                 // Method java/lang/Boolean.booleanValue:()Z
     350: ifeq          672
     353: getstatic     #2                  // Field enerj/rt/PrecisionRuntimeRoot.impl:Lenerj/rt/PrecisionRuntime;
     356: getstatic     #2                  // Field enerj/rt/PrecisionRuntimeRoot.impl:Lenerj/rt/PrecisionRuntime;
     359: aload_0       
     360: ldc           #26                 // String image
     362: iconst_0      
     363: invokeinterface #13,  4           // InterfaceMethod enerj/rt/PrecisionRuntime.loadField:(Ljava/lang/Object;Ljava/lang/String;Z)Ljava/lang/Object;
     368: getstatic     #2                  // Field enerj/rt/PrecisionRuntimeRoot.impl:Lenerj/rt/PrecisionRuntime;
     371: aload         6
     373: iconst_0      
     374: invokeinterface #9,  3            // InterfaceMethod enerj/rt/PrecisionRuntime.loadLocal:(Lenerj/rt/Reference;Z)Ljava/lang/Object;
     379: checkcast     #22                 // class java/lang/Integer
     382: invokevirtual #23                 // Method java/lang/Integer.intValue:()I
     385: iconst_0      
     386: getstatic     #2                  // Field enerj/rt/PrecisionRuntimeRoot.impl:Lenerj/rt/PrecisionRuntime;
     389: getstatic     #2                  // Field enerj/rt/PrecisionRuntimeRoot.impl:Lenerj/rt/PrecisionRuntime;
     392: aload_0       
     393: ldc           #18                 // String width
     395: iconst_0      
     396: invokeinterface #13,  4           // InterfaceMethod enerj/rt/PrecisionRuntime.loadField:(Ljava/lang/Object;Ljava/lang/String;Z)Ljava/lang/Object;
     401: checkcast     #22                 // class java/lang/Integer
     404: invokevirtual #23                 // Method java/lang/Integer.intValue:()I
     407: anewarray     #34                 // class "[I"
     410: iconst_1      
     411: iconst_0      
     412: iconst_0      
     413: iconst_0      
     414: invokeinterface #28,  6           // InterfaceMethod enerj/rt/PrecisionRuntime.newArray:(Ljava/lang/Object;IZII)Ljava/lang/Object;
     419: checkcast     #27                 // class "[[I"
     422: checkcast     #27                 // class "[[I"
     425: invokeinterface #35,  5           // InterfaceMethod enerj/rt/PrecisionRuntime.storeArray:(Ljava/lang/Object;IZLjava/lang/Object;)Ljava/lang/Object;
     430: pop           
     431: getstatic     #2                  // Field enerj/rt/PrecisionRuntimeRoot.impl:Lenerj/rt/PrecisionRuntime;
     434: iconst_0      
     435: invokestatic  #20                 // Method java/lang/Integer.valueOf:(I)Ljava/lang/Integer;
     438: iconst_0      
     439: getstatic     #16                 // Field enerj/rt/PrecisionRuntime$MemKind.VARIABLE:Lenerj/rt/PrecisionRuntime$MemKind;
     442: invokeinterface #17,  4           // InterfaceMethod enerj/rt/PrecisionRuntime.storeValue:(Ljava/lang/Object;ZLenerj/rt/PrecisionRuntime$MemKind;)Ljava/lang/Object;
     447: checkcast     #22                 // class java/lang/Integer
     450: invokevirtual #23                 // Method java/lang/Integer.intValue:()I
     453: istore        7
     455: new           #4                  // class enerj/rt/Reference
     458: dup           
     459: iload         7
     461: invokestatic  #20                 // Method java/lang/Integer.valueOf:(I)Ljava/lang/Integer;
     464: iconst_0      
     465: iconst_1      
     466: invokespecial #5                  // Method enerj/rt/Reference."<init>":(Ljava/lang/Object;ZZ)V
     469: astore        8
     471: getstatic     #2                  // Field enerj/rt/PrecisionRuntimeRoot.impl:Lenerj/rt/PrecisionRuntime;
     474: getstatic     #2                  // Field enerj/rt/PrecisionRuntimeRoot.impl:Lenerj/rt/PrecisionRuntime;
     477: aload         8
     479: iconst_0      
     480: invokeinterface #9,  3            // InterfaceMethod enerj/rt/PrecisionRuntime.loadLocal:(Lenerj/rt/Reference;Z)Ljava/lang/Object;
     485: checkcast     #22                 // class java/lang/Integer
     488: invokevirtual #23                 // Method java/lang/Integer.intValue:()I
     491: getstatic     #2                  // Field enerj/rt/PrecisionRuntimeRoot.impl:Lenerj/rt/PrecisionRuntime;
     494: aload_0       
     495: ldc           #18                 // String width
     497: iconst_0      
     498: invokeinterface #13,  4           // InterfaceMethod enerj/rt/PrecisionRuntime.loadField:(Ljava/lang/Object;Ljava/lang/String;Z)Ljava/lang/Object;
     503: checkcast     #22                 // class java/lang/Integer
     506: invokevirtual #23                 // Method java/lang/Integer.intValue:()I
     509: if_icmpge     516
     512: iconst_1      
     513: goto          517
     516: iconst_0      
     517: invokestatic  #30                 // Method java/lang/Boolean.valueOf:(Z)Ljava/lang/Boolean;
     520: invokeinterface #31,  2           // InterfaceMethod enerj/rt/PrecisionRuntime.countLogicalOp:(Ljava/lang/Object;)Ljava/lang/Object;
     525: checkcast     #32                 // class java/lang/Boolean
     528: invokevirtual #33                 // Method java/lang/Boolean.booleanValue:()Z
     531: ifeq          646
     534: getstatic     #2                  // Field enerj/rt/PrecisionRuntimeRoot.impl:Lenerj/rt/PrecisionRuntime;
     537: getstatic     #2                  // Field enerj/rt/PrecisionRuntimeRoot.impl:Lenerj/rt/PrecisionRuntime;
     540: getstatic     #2                  // Field enerj/rt/PrecisionRuntimeRoot.impl:Lenerj/rt/PrecisionRuntime;
     543: aload_0       
     544: ldc           #26                 // String image
     546: iconst_0      
     547: invokeinterface #13,  4           // InterfaceMethod enerj/rt/PrecisionRuntime.loadField:(Ljava/lang/Object;Ljava/lang/String;Z)Ljava/lang/Object;
     552: getstatic     #2                  // Field enerj/rt/PrecisionRuntimeRoot.impl:Lenerj/rt/PrecisionRuntime;
     555: aload         6
     557: iconst_0      
     558: invokeinterface #9,  3            // InterfaceMethod enerj/rt/PrecisionRuntime.loadLocal:(Lenerj/rt/Reference;Z)Ljava/lang/Object;
     563: checkcast     #22                 // class java/lang/Integer
     566: invokevirtual #23                 // Method java/lang/Integer.intValue:()I
     569: iconst_0      
     570: invokeinterface #36,  4           // InterfaceMethod enerj/rt/PrecisionRuntime.loadArray:(Ljava/lang/Object;IZ)Ljava/lang/Object;
     575: getstatic     #2                  // Field enerj/rt/PrecisionRuntimeRoot.impl:Lenerj/rt/PrecisionRuntime;
     578: aload         8
     580: iconst_0      
     581: invokeinterface #9,  3            // InterfaceMethod enerj/rt/PrecisionRuntime.loadLocal:(Lenerj/rt/Reference;Z)Ljava/lang/Object;
     586: checkcast     #22                 // class java/lang/Integer
     589: invokevirtual #23                 // Method java/lang/Integer.intValue:()I
     592: iconst_0      
     593: getstatic     #2                  // Field enerj/rt/PrecisionRuntimeRoot.impl:Lenerj/rt/PrecisionRuntime;
     596: iconst_3      
     597: newarray       int
     599: iconst_1      
     600: iconst_0      
     601: iconst_4      
     602: iconst_0      
     603: invokeinterface #28,  6           // InterfaceMethod enerj/rt/PrecisionRuntime.newArray:(Ljava/lang/Object;IZII)Ljava/lang/Object;
     608: checkcast     #34                 // class "[I"
     611: checkcast     #34                 // class "[I"
     614: invokeinterface #35,  5           // InterfaceMethod enerj/rt/PrecisionRuntime.storeArray:(Ljava/lang/Object;IZLjava/lang/Object;)Ljava/lang/Object;
     619: pop           
     620: getstatic     #2                  // Field enerj/rt/PrecisionRuntimeRoot.impl:Lenerj/rt/PrecisionRuntime;
     623: aload         8
     625: getstatic     #37                 // Field enerj/rt/PrecisionRuntime$ArithOperator.PLUS:Lenerj/rt/PrecisionRuntime$ArithOperator;
     628: iconst_1      
     629: invokestatic  #20                 // Method java/lang/Integer.valueOf:(I)Ljava/lang/Integer;
     632: iconst_1      
     633: getstatic     #38                 // Field enerj/rt/PrecisionRuntime$NumberKind.INT:Lenerj/rt/PrecisionRuntime$NumberKind;
     636: iconst_0      
     637: invokeinterface #39,  7           // InterfaceMethod enerj/rt/PrecisionRuntime.assignopLocal:(Lenerj/rt/Reference;Lenerj/rt/PrecisionRuntime$ArithOperator;Ljava/lang/Number;ZLenerj/rt/PrecisionRuntime$NumberKind;Z)Ljava/lang/Number;
     642: pop           
     643: goto          471
     646: getstatic     #2                  // Field enerj/rt/PrecisionRuntimeRoot.impl:Lenerj/rt/PrecisionRuntime;
     649: aload         6
     651: getstatic     #37                 // Field enerj/rt/PrecisionRuntime$ArithOperator.PLUS:Lenerj/rt/PrecisionRuntime$ArithOperator;
     654: iconst_1      
     655: invokestatic  #20                 // Method java/lang/Integer.valueOf:(I)Ljava/lang/Integer;
     658: iconst_1      
     659: getstatic     #38                 // Field enerj/rt/PrecisionRuntime$NumberKind.INT:Lenerj/rt/PrecisionRuntime$NumberKind;
     662: iconst_0      
     663: invokeinterface #39,  7           // InterfaceMethod enerj/rt/PrecisionRuntime.assignopLocal:(Lenerj/rt/Reference;Lenerj/rt/PrecisionRuntime$ArithOperator;Ljava/lang/Number;ZLenerj/rt/PrecisionRuntime$NumberKind;Z)Ljava/lang/Number;
     668: pop           
     669: goto          290
     672: getstatic     #2                  // Field enerj/rt/PrecisionRuntimeRoot.impl:Lenerj/rt/PrecisionRuntime;
     675: iconst_0      
     676: invokestatic  #20                 // Method java/lang/Integer.valueOf:(I)Ljava/lang/Integer;
     679: iconst_0      
     680: getstatic     #16                 // Field enerj/rt/PrecisionRuntime$MemKind.VARIABLE:Lenerj/rt/PrecisionRuntime$MemKind;
     683: invokeinterface #17,  4           // InterfaceMethod enerj/rt/PrecisionRuntime.storeValue:(Ljava/lang/Object;ZLenerj/rt/PrecisionRuntime$MemKind;)Ljava/lang/Object;
     688: checkcast     #22                 // class java/lang/Integer
     691: invokevirtual #23                 // Method java/lang/Integer.intValue:()I
     694: istore        5
     696: new           #4                  // class enerj/rt/Reference
     699: dup           
     700: iload         5
     702: invokestatic  #20                 // Method java/lang/Integer.valueOf:(I)Ljava/lang/Integer;
     705: iconst_0      
     706: iconst_1      
     707: invokespecial #5                  // Method enerj/rt/Reference."<init>":(Ljava/lang/Object;ZZ)V
     710: astore        6
     712: getstatic     #2                  // Field enerj/rt/PrecisionRuntimeRoot.impl:Lenerj/rt/PrecisionRuntime;
     715: getstatic     #2                  // Field enerj/rt/PrecisionRuntimeRoot.impl:Lenerj/rt/PrecisionRuntime;
     718: aload         6
     720: iconst_0      
     721: invokeinterface #9,  3            // InterfaceMethod enerj/rt/PrecisionRuntime.loadLocal:(Lenerj/rt/Reference;Z)Ljava/lang/Object;
     726: checkcast     #22                 // class java/lang/Integer
     729: invokevirtual #23                 // Method java/lang/Integer.intValue:()I
     732: getstatic     #2                  // Field enerj/rt/PrecisionRuntimeRoot.impl:Lenerj/rt/PrecisionRuntime;
     735: aload_0       
     736: ldc           #25                 // String height
     738: iconst_0      
     739: invokeinterface #13,  4           // InterfaceMethod enerj/rt/PrecisionRuntime.loadField:(Ljava/lang/Object;Ljava/lang/String;Z)Ljava/lang/Object;
     744: checkcast     #22                 // class java/lang/Integer
     747: invokevirtual #23                 // Method java/lang/Integer.intValue:()I
     750: if_icmpge     757
     753: iconst_1      
     754: goto          758
     757: iconst_0      
     758: invokestatic  #30                 // Method java/lang/Boolean.valueOf:(Z)Ljava/lang/Boolean;
     761: invokeinterface #31,  2           // InterfaceMethod enerj/rt/PrecisionRuntime.countLogicalOp:(Ljava/lang/Object;)Ljava/lang/Object;
     766: checkcast     #32                 // class java/lang/Boolean
     769: invokevirtual #33                 // Method java/lang/Boolean.booleanValue:()Z
     772: ifeq          1375
     775: getstatic     #2                  // Field enerj/rt/PrecisionRuntimeRoot.impl:Lenerj/rt/PrecisionRuntime;
     778: iconst_0      
     779: invokestatic  #20                 // Method java/lang/Integer.valueOf:(I)Ljava/lang/Integer;
     782: iconst_0      
     783: getstatic     #16                 // Field enerj/rt/PrecisionRuntime$MemKind.VARIABLE:Lenerj/rt/PrecisionRuntime$MemKind;
     786: invokeinterface #17,  4           // InterfaceMethod enerj/rt/PrecisionRuntime.storeValue:(Ljava/lang/Object;ZLenerj/rt/PrecisionRuntime$MemKind;)Ljava/lang/Object;
     791: checkcast     #22                 // class java/lang/Integer
     794: invokevirtual #23                 // Method java/lang/Integer.intValue:()I
     797: istore        7
     799: new           #4                  // class enerj/rt/Reference
     802: dup           
     803: iload         7
     805: invokestatic  #20                 // Method java/lang/Integer.valueOf:(I)Ljava/lang/Integer;
     808: iconst_0      
     809: iconst_1      
     810: invokespecial #5                  // Method enerj/rt/Reference."<init>":(Ljava/lang/Object;ZZ)V
     813: astore        8
     815: getstatic     #2                  // Field enerj/rt/PrecisionRuntimeRoot.impl:Lenerj/rt/PrecisionRuntime;
     818: getstatic     #2                  // Field enerj/rt/PrecisionRuntimeRoot.impl:Lenerj/rt/PrecisionRuntime;
     821: aload         8
     823: iconst_0      
     824: invokeinterface #9,  3            // InterfaceMethod enerj/rt/PrecisionRuntime.loadLocal:(Lenerj/rt/Reference;Z)Ljava/lang/Object;
     829: checkcast     #22                 // class java/lang/Integer
     832: invokevirtual #23                 // Method java/lang/Integer.intValue:()I
     835: getstatic     #2                  // Field enerj/rt/PrecisionRuntimeRoot.impl:Lenerj/rt/PrecisionRuntime;
     838: aload_0       
     839: ldc           #18                 // String width
     841: iconst_0      
     842: invokeinterface #13,  4           // InterfaceMethod enerj/rt/PrecisionRuntime.loadField:(Ljava/lang/Object;Ljava/lang/String;Z)Ljava/lang/Object;
     847: checkcast     #22                 // class java/lang/Integer
     850: invokevirtual #23                 // Method java/lang/Integer.intValue:()I
     853: if_icmpge     860
     856: iconst_1      
     857: goto          861
     860: iconst_0      
     861: invokestatic  #30                 // Method java/lang/Boolean.valueOf:(Z)Ljava/lang/Boolean;
     864: invokeinterface #31,  2           // InterfaceMethod enerj/rt/PrecisionRuntime.countLogicalOp:(Ljava/lang/Object;)Ljava/lang/Object;
     869: checkcast     #32                 // class java/lang/Boolean
     872: invokevirtual #33                 // Method java/lang/Boolean.booleanValue:()Z
     875: ifeq          1349
     878: getstatic     #2                  // Field enerj/rt/PrecisionRuntimeRoot.impl:Lenerj/rt/PrecisionRuntime;
     881: getstatic     #2                  // Field enerj/rt/PrecisionRuntimeRoot.impl:Lenerj/rt/PrecisionRuntime;
     884: getstatic     #2                  // Field enerj/rt/PrecisionRuntimeRoot.impl:Lenerj/rt/PrecisionRuntime;
     887: getstatic     #2                  // Field enerj/rt/PrecisionRuntimeRoot.impl:Lenerj/rt/PrecisionRuntime;
     890: aload_0       
     891: ldc           #26                 // String image
     893: iconst_0      
     894: invokeinterface #13,  4           // InterfaceMethod enerj/rt/PrecisionRuntime.loadField:(Ljava/lang/Object;Ljava/lang/String;Z)Ljava/lang/Object;
     899: getstatic     #2                  // Field enerj/rt/PrecisionRuntimeRoot.impl:Lenerj/rt/PrecisionRuntime;
     902: aload         6
     904: iconst_0      
     905: invokeinterface #9,  3            // InterfaceMethod enerj/rt/PrecisionRuntime.loadLocal:(Lenerj/rt/Reference;Z)Ljava/lang/Object;
     910: checkcast     #22                 // class java/lang/Integer
     913: invokevirtual #23                 // Method java/lang/Integer.intValue:()I
     916: iconst_0      
     917: invokeinterface #36,  4           // InterfaceMethod enerj/rt/PrecisionRuntime.loadArray:(Ljava/lang/Object;IZ)Ljava/lang/Object;
     922: getstatic     #2                  // Field enerj/rt/PrecisionRuntimeRoot.impl:Lenerj/rt/PrecisionRuntime;
     925: aload         8
     927: iconst_0      
     928: invokeinterface #9,  3            // InterfaceMethod enerj/rt/PrecisionRuntime.loadLocal:(Lenerj/rt/Reference;Z)Ljava/lang/Object;
     933: checkcast     #22                 // class java/lang/Integer
     936: invokevirtual #23                 // Method java/lang/Integer.intValue:()I
     939: iconst_0      
     940: invokeinterface #36,  4           // InterfaceMethod enerj/rt/PrecisionRuntime.loadArray:(Ljava/lang/Object;IZ)Ljava/lang/Object;
     945: iconst_0      
     946: iconst_1      
     947: getstatic     #2                  // Field enerj/rt/PrecisionRuntimeRoot.impl:Lenerj/rt/PrecisionRuntime;
     950: aload         4
     952: iconst_0      
     953: invokeinterface #9,  3            // InterfaceMethod enerj/rt/PrecisionRuntime.loadLocal:(Lenerj/rt/Reference;Z)Ljava/lang/Object;
     958: checkcast     #8                  // class Sobel/TextFile
     961: invokevirtual #19                 // Method Sobel/TextFile.loadInt:()I
     964: invokestatic  #20                 // Method java/lang/Integer.valueOf:(I)Ljava/lang/Integer;
     967: invokeinterface #35,  5           // InterfaceMethod enerj/rt/PrecisionRuntime.storeArray:(Ljava/lang/Object;IZLjava/lang/Object;)Ljava/lang/Object;
     972: checkcast     #22                 // class java/lang/Integer
     975: invokevirtual #23                 // Method java/lang/Integer.intValue:()I
     978: pop           
     979: getstatic     #2                  // Field enerj/rt/PrecisionRuntimeRoot.impl:Lenerj/rt/PrecisionRuntime;
     982: aload         4
     984: iconst_0      
     985: invokeinterface #9,  3            // InterfaceMethod enerj/rt/PrecisionRuntime.loadLocal:(Lenerj/rt/Reference;Z)Ljava/lang/Object;
     990: checkcast     #8                  // class Sobel/TextFile
     993: invokevirtual #24                 // Method Sobel/TextFile.loadChar:()C
     996: pop           
     997: getstatic     #2                  // Field enerj/rt/PrecisionRuntimeRoot.impl:Lenerj/rt/PrecisionRuntime;
    1000: getstatic     #2                  // Field enerj/rt/PrecisionRuntimeRoot.impl:Lenerj/rt/PrecisionRuntime;
    1003: getstatic     #2                  // Field enerj/rt/PrecisionRuntimeRoot.impl:Lenerj/rt/PrecisionRuntime;
    1006: getstatic     #2                  // Field enerj/rt/PrecisionRuntimeRoot.impl:Lenerj/rt/PrecisionRuntime;
    1009: aload_0       
    1010: ldc           #26                 // String image
    1012: iconst_0      
    1013: invokeinterface #13,  4           // InterfaceMethod enerj/rt/PrecisionRuntime.loadField:(Ljava/lang/Object;Ljava/lang/String;Z)Ljava/lang/Object;
    1018: getstatic     #2                  // Field enerj/rt/PrecisionRuntimeRoot.impl:Lenerj/rt/PrecisionRuntime;
    1021: aload         6
    1023: iconst_0      
    1024: invokeinterface #9,  3            // InterfaceMethod enerj/rt/PrecisionRuntime.loadLocal:(Lenerj/rt/Reference;Z)Ljava/lang/Object;
    1029: checkcast     #22                 // class java/lang/Integer
    1032: invokevirtual #23                 // Method java/lang/Integer.intValue:()I
    1035: iconst_0      
    1036: invokeinterface #36,  4           // InterfaceMethod enerj/rt/PrecisionRuntime.loadArray:(Ljava/lang/Object;IZ)Ljava/lang/Object;
    1041: getstatic     #2                  // Field enerj/rt/PrecisionRuntimeRoot.impl:Lenerj/rt/PrecisionRuntime;
    1044: aload         8
    1046: iconst_0      
    1047: invokeinterface #9,  3            // InterfaceMethod enerj/rt/PrecisionRuntime.loadLocal:(Lenerj/rt/Reference;Z)Ljava/lang/Object;
    1052: checkcast     #22                 // class java/lang/Integer
    1055: invokevirtual #23                 // Method java/lang/Integer.intValue:()I
    1058: iconst_0      
    1059: invokeinterface #36,  4           // InterfaceMethod enerj/rt/PrecisionRuntime.loadArray:(Ljava/lang/Object;IZ)Ljava/lang/Object;
    1064: iconst_1      
    1065: iconst_1      
    1066: getstatic     #2                  // Field enerj/rt/PrecisionRuntimeRoot.impl:Lenerj/rt/PrecisionRuntime;
    1069: aload         4
    1071: iconst_0      
    1072: invokeinterface #9,  3            // InterfaceMethod enerj/rt/PrecisionRuntime.loadLocal:(Lenerj/rt/Reference;Z)Ljava/lang/Object;
    1077: checkcast     #8                  // class Sobel/TextFile
    1080: invokevirtual #19                 // Method Sobel/TextFile.loadInt:()I
    1083: invokestatic  #20                 // Method java/lang/Integer.valueOf:(I)Ljava/lang/Integer;
    1086: invokeinterface #35,  5           // InterfaceMethod enerj/rt/PrecisionRuntime.storeArray:(Ljava/lang/Object;IZLjava/lang/Object;)Ljava/lang/Object;
    1091: checkcast     #22                 // class java/lang/Integer
    1094: invokevirtual #23                 // Method java/lang/Integer.intValue:()I
    1097: pop           
    1098: getstatic     #2                  // Field enerj/rt/PrecisionRuntimeRoot.impl:Lenerj/rt/PrecisionRuntime;
    1101: aload         4
    1103: iconst_0      
    1104: invokeinterface #9,  3            // InterfaceMethod enerj/rt/PrecisionRuntime.loadLocal:(Lenerj/rt/Reference;Z)Ljava/lang/Object;
    1109: checkcast     #8                  // class Sobel/TextFile
    1112: invokevirtual #24                 // Method Sobel/TextFile.loadChar:()C
    1115: pop           
    1116: getstatic     #2                  // Field enerj/rt/PrecisionRuntimeRoot.impl:Lenerj/rt/PrecisionRuntime;
    1119: getstatic     #2                  // Field enerj/rt/PrecisionRuntimeRoot.impl:Lenerj/rt/PrecisionRuntime;
    1122: getstatic     #2                  // Field enerj/rt/PrecisionRuntimeRoot.impl:Lenerj/rt/PrecisionRuntime;
    1125: getstatic     #2                  // Field enerj/rt/PrecisionRuntimeRoot.impl:Lenerj/rt/PrecisionRuntime;
    1128: aload_0       
    1129: ldc           #26                 // String image
    1131: iconst_0      
    1132: invokeinterface #13,  4           // InterfaceMethod enerj/rt/PrecisionRuntime.loadField:(Ljava/lang/Object;Ljava/lang/String;Z)Ljava/lang/Object;
    1137: getstatic     #2                  // Field enerj/rt/PrecisionRuntimeRoot.impl:Lenerj/rt/PrecisionRuntime;
    1140: aload         6
    1142: iconst_0      
    1143: invokeinterface #9,  3            // InterfaceMethod enerj/rt/PrecisionRuntime.loadLocal:(Lenerj/rt/Reference;Z)Ljava/lang/Object;
    1148: checkcast     #22                 // class java/lang/Integer
    1151: invokevirtual #23                 // Method java/lang/Integer.intValue:()I
    1154: iconst_0      
    1155: invokeinterface #36,  4           // InterfaceMethod enerj/rt/PrecisionRuntime.loadArray:(Ljava/lang/Object;IZ)Ljava/lang/Object;
    1160: getstatic     #2                  // Field enerj/rt/PrecisionRuntimeRoot.impl:Lenerj/rt/PrecisionRuntime;
    1163: aload         8
    1165: iconst_0      
    1166: invokeinterface #9,  3            // InterfaceMethod enerj/rt/PrecisionRuntime.loadLocal:(Lenerj/rt/Reference;Z)Ljava/lang/Object;
    1171: checkcast     #22                 // class java/lang/Integer
    1174: invokevirtual #23                 // Method java/lang/Integer.intValue:()I
    1177: iconst_0      
    1178: invokeinterface #36,  4           // InterfaceMethod enerj/rt/PrecisionRuntime.loadArray:(Ljava/lang/Object;IZ)Ljava/lang/Object;
    1183: iconst_2      
    1184: iconst_1      
    1185: getstatic     #2                  // Field enerj/rt/PrecisionRuntimeRoot.impl:Lenerj/rt/PrecisionRuntime;
    1188: aload         4
    1190: iconst_0      
    1191: invokeinterface #9,  3            // InterfaceMethod enerj/rt/PrecisionRuntime.loadLocal:(Lenerj/rt/Reference;Z)Ljava/lang/Object;
    1196: checkcast     #8                  // class Sobel/TextFile
    1199: invokevirtual #19                 // Method Sobel/TextFile.loadInt:()I
    1202: invokestatic  #20                 // Method java/lang/Integer.valueOf:(I)Ljava/lang/Integer;
    1205: invokeinterface #35,  5           // InterfaceMethod enerj/rt/PrecisionRuntime.storeArray:(Ljava/lang/Object;IZLjava/lang/Object;)Ljava/lang/Object;
    1210: checkcast     #22                 // class java/lang/Integer
    1213: invokevirtual #23                 // Method java/lang/Integer.intValue:()I
    1216: pop           
    1217: getstatic     #2                  // Field enerj/rt/PrecisionRuntimeRoot.impl:Lenerj/rt/PrecisionRuntime;
    1220: getstatic     #2                  // Field enerj/rt/PrecisionRuntimeRoot.impl:Lenerj/rt/PrecisionRuntime;
    1223: aload         8
    1225: iconst_0      
    1226: invokeinterface #9,  3            // InterfaceMethod enerj/rt/PrecisionRuntime.loadLocal:(Lenerj/rt/Reference;Z)Ljava/lang/Object;
    1231: checkcast     #22                 // class java/lang/Integer
    1234: invokevirtual #23                 // Method java/lang/Integer.intValue:()I
    1237: getstatic     #2                  // Field enerj/rt/PrecisionRuntimeRoot.impl:Lenerj/rt/PrecisionRuntime;
    1240: getstatic     #2                  // Field enerj/rt/PrecisionRuntimeRoot.impl:Lenerj/rt/PrecisionRuntime;
    1243: aload_0       
    1244: ldc           #18                 // String width
    1246: iconst_0      
    1247: invokeinterface #13,  4           // InterfaceMethod enerj/rt/PrecisionRuntime.loadField:(Ljava/lang/Object;Ljava/lang/String;Z)Ljava/lang/Object;
    1252: checkcast     #22                 // class java/lang/Integer
    1255: invokevirtual #23                 // Method java/lang/Integer.intValue:()I
    1258: invokestatic  #20                 // Method java/lang/Integer.valueOf:(I)Ljava/lang/Integer;
    1261: iconst_1      
    1262: invokestatic  #20                 // Method java/lang/Integer.valueOf:(I)Ljava/lang/Integer;
    1265: getstatic     #40                 // Field enerj/rt/PrecisionRuntime$ArithOperator.MINUS:Lenerj/rt/PrecisionRuntime$ArithOperator;
    1268: getstatic     #38                 // Field enerj/rt/PrecisionRuntime$NumberKind.INT:Lenerj/rt/PrecisionRuntime$NumberKind;
    1271: iconst_0      
    1272: invokeinterface #41,  6           // InterfaceMethod enerj/rt/PrecisionRuntime.binaryOp:(Ljava/lang/Number;Ljava/lang/Number;Lenerj/rt/PrecisionRuntime$ArithOperator;Lenerj/rt/PrecisionRuntime$NumberKind;Z)Ljava/lang/Number;
    1277: invokevirtual #42                 // Method java/lang/Number.intValue:()I
    1280: if_icmpge     1287
    1283: iconst_1      
    1284: goto          1288
    1287: iconst_0      
    1288: invokestatic  #30                 // Method java/lang/Boolean.valueOf:(Z)Ljava/lang/Boolean;
    1291: invokeinterface #31,  2           // InterfaceMethod enerj/rt/PrecisionRuntime.countLogicalOp:(Ljava/lang/Object;)Ljava/lang/Object;
    1296: checkcast     #32                 // class java/lang/Boolean
    1299: invokevirtual #33                 // Method java/lang/Boolean.booleanValue:()Z
    1302: ifeq          1323
    1305: getstatic     #2                  // Field enerj/rt/PrecisionRuntimeRoot.impl:Lenerj/rt/PrecisionRuntime;
    1308: aload         4
    1310: iconst_0      
    1311: invokeinterface #9,  3            // InterfaceMethod enerj/rt/PrecisionRuntime.loadLocal:(Lenerj/rt/Reference;Z)Ljava/lang/Object;
    1316: checkcast     #8                  // class Sobel/TextFile
    1319: invokevirtual #24                 // Method Sobel/TextFile.loadChar:()C
    1322: pop           
    1323: getstatic     #2                  // Field enerj/rt/PrecisionRuntimeRoot.impl:Lenerj/rt/PrecisionRuntime;
    1326: aload         8
    1328: getstatic     #37                 // Field enerj/rt/PrecisionRuntime$ArithOperator.PLUS:Lenerj/rt/PrecisionRuntime$ArithOperator;
    1331: iconst_1      
    1332: invokestatic  #20                 // Method java/lang/Integer.valueOf:(I)Ljava/lang/Integer;
    1335: iconst_1      
    1336: getstatic     #38                 // Field enerj/rt/PrecisionRuntime$NumberKind.INT:Lenerj/rt/PrecisionRuntime$NumberKind;
    1339: iconst_0      
    1340: invokeinterface #39,  7           // InterfaceMethod enerj/rt/PrecisionRuntime.assignopLocal:(Lenerj/rt/Reference;Lenerj/rt/PrecisionRuntime$ArithOperator;Ljava/lang/Number;ZLenerj/rt/PrecisionRuntime$NumberKind;Z)Ljava/lang/Number;
    1345: pop           
    1346: goto          815
    1349: getstatic     #2                  // Field enerj/rt/PrecisionRuntimeRoot.impl:Lenerj/rt/PrecisionRuntime;
    1352: aload         6
    1354: getstatic     #37                 // Field enerj/rt/PrecisionRuntime$ArithOperator.PLUS:Lenerj/rt/PrecisionRuntime$ArithOperator;
    1357: iconst_1      
    1358: invokestatic  #20                 // Method java/lang/Integer.valueOf:(I)Ljava/lang/Integer;
    1361: iconst_0      
    1362: getstatic     #38                 // Field enerj/rt/PrecisionRuntime$NumberKind.INT:Lenerj/rt/PrecisionRuntime$NumberKind;
    1365: iconst_0      
    1366: invokeinterface #39,  7           // InterfaceMethod enerj/rt/PrecisionRuntime.assignopLocal:(Lenerj/rt/Reference;Lenerj/rt/PrecisionRuntime$ArithOperator;Ljava/lang/Number;ZLenerj/rt/PrecisionRuntime$NumberKind;Z)Ljava/lang/Number;
    1371: pop           
    1372: goto          712
    1375: return        

  public void slideWindow(int, int, int[][][]);
    Code:
       0: new           #4                  // class enerj/rt/Reference
       3: dup           
       4: aload_3       
       5: iconst_0      
       6: iconst_0      
       7: invokespecial #5                  // Method enerj/rt/Reference."<init>":(Ljava/lang/Object;ZZ)V
      10: astore        4
      12: new           #4                  // class enerj/rt/Reference
      15: dup           
      16: iload_2       
      17: invokestatic  #20                 // Method java/lang/Integer.valueOf:(I)Ljava/lang/Integer;
      20: iconst_0      
      21: iconst_1      
      22: invokespecial #5                  // Method enerj/rt/Reference."<init>":(Ljava/lang/Object;ZZ)V
      25: astore        5
      27: new           #4                  // class enerj/rt/Reference
      30: dup           
      31: iload_1       
      32: invokestatic  #20                 // Method java/lang/Integer.valueOf:(I)Ljava/lang/Integer;
      35: iconst_0      
      36: iconst_1      
      37: invokespecial #5                  // Method enerj/rt/Reference."<init>":(Ljava/lang/Object;ZZ)V
      40: astore        6
      42: getstatic     #2                  // Field enerj/rt/PrecisionRuntimeRoot.impl:Lenerj/rt/PrecisionRuntime;
      45: getstatic     #2                  // Field enerj/rt/PrecisionRuntimeRoot.impl:Lenerj/rt/PrecisionRuntime;
      48: aload         4
      50: iconst_0      
      51: invokeinterface #9,  3            // InterfaceMethod enerj/rt/PrecisionRuntime.loadLocal:(Lenerj/rt/Reference;Z)Ljava/lang/Object;
      56: checkcast     #29                 // class "[[[I"
      59: arraylength   
      60: invokestatic  #20                 // Method java/lang/Integer.valueOf:(I)Ljava/lang/Integer;
      63: iconst_0      
      64: getstatic     #16                 // Field enerj/rt/PrecisionRuntime$MemKind.VARIABLE:Lenerj/rt/PrecisionRuntime$MemKind;
      67: invokeinterface #17,  4           // InterfaceMethod enerj/rt/PrecisionRuntime.storeValue:(Ljava/lang/Object;ZLenerj/rt/PrecisionRuntime$MemKind;)Ljava/lang/Object;
      72: checkcast     #22                 // class java/lang/Integer
      75: invokevirtual #23                 // Method java/lang/Integer.intValue:()I
      78: istore        7
      80: new           #4                  // class enerj/rt/Reference
      83: dup           
      84: iload         7
      86: invokestatic  #20                 // Method java/lang/Integer.valueOf:(I)Ljava/lang/Integer;
      89: iconst_0      
      90: iconst_1      
      91: invokespecial #5                  // Method enerj/rt/Reference."<init>":(Ljava/lang/Object;ZZ)V
      94: astore        8
      96: getstatic     #2                  // Field enerj/rt/PrecisionRuntimeRoot.impl:Lenerj/rt/PrecisionRuntime;
      99: getstatic     #2                  // Field enerj/rt/PrecisionRuntimeRoot.impl:Lenerj/rt/PrecisionRuntime;
     102: getstatic     #2                  // Field enerj/rt/PrecisionRuntimeRoot.impl:Lenerj/rt/PrecisionRuntime;
     105: aload         4
     107: iconst_0      
     108: invokeinterface #9,  3            // InterfaceMethod enerj/rt/PrecisionRuntime.loadLocal:(Lenerj/rt/Reference;Z)Ljava/lang/Object;
     113: iconst_0      
     114: iconst_0      
     115: invokeinterface #36,  4           // InterfaceMethod enerj/rt/PrecisionRuntime.loadArray:(Ljava/lang/Object;IZ)Ljava/lang/Object;
     120: checkcast     #27                 // class "[[I"
     123: arraylength   
     124: invokestatic  #20                 // Method java/lang/Integer.valueOf:(I)Ljava/lang/Integer;
     127: iconst_0      
     128: getstatic     #16                 // Field enerj/rt/PrecisionRuntime$MemKind.VARIABLE:Lenerj/rt/PrecisionRuntime$MemKind;
     131: invokeinterface #17,  4           // InterfaceMethod enerj/rt/PrecisionRuntime.storeValue:(Ljava/lang/Object;ZLenerj/rt/PrecisionRuntime$MemKind;)Ljava/lang/Object;
     136: checkcast     #22                 // class java/lang/Integer
     139: invokevirtual #23                 // Method java/lang/Integer.intValue:()I
     142: istore        9
     144: new           #4                  // class enerj/rt/Reference
     147: dup           
     148: iload         9
     150: invokestatic  #20                 // Method java/lang/Integer.valueOf:(I)Ljava/lang/Integer;
     153: iconst_0      
     154: iconst_1      
     155: invokespecial #5                  // Method enerj/rt/Reference."<init>":(Ljava/lang/Object;ZZ)V
     158: astore        10
     160: getstatic     #2                  // Field enerj/rt/PrecisionRuntimeRoot.impl:Lenerj/rt/PrecisionRuntime;
     163: getstatic     #2                  // Field enerj/rt/PrecisionRuntimeRoot.impl:Lenerj/rt/PrecisionRuntime;
     166: getstatic     #2                  // Field enerj/rt/PrecisionRuntimeRoot.impl:Lenerj/rt/PrecisionRuntime;
     169: aload         6
     171: iconst_0      
     172: invokeinterface #9,  3            // InterfaceMethod enerj/rt/PrecisionRuntime.loadLocal:(Lenerj/rt/Reference;Z)Ljava/lang/Object;
     177: checkcast     #22                 // class java/lang/Integer
     180: invokevirtual #23                 // Method java/lang/Integer.intValue:()I
     183: invokestatic  #20                 // Method java/lang/Integer.valueOf:(I)Ljava/lang/Integer;
     186: getstatic     #2                  // Field enerj/rt/PrecisionRuntimeRoot.impl:Lenerj/rt/PrecisionRuntime;
     189: getstatic     #2                  // Field enerj/rt/PrecisionRuntimeRoot.impl:Lenerj/rt/PrecisionRuntime;
     192: aload         10
     194: iconst_0      
     195: invokeinterface #9,  3            // InterfaceMethod enerj/rt/PrecisionRuntime.loadLocal:(Lenerj/rt/Reference;Z)Ljava/lang/Object;
     200: checkcast     #22                 // class java/lang/Integer
     203: invokevirtual #23                 // Method java/lang/Integer.intValue:()I
     206: i2f           
     207: invokestatic  #43                 // Method java/lang/Float.valueOf:(F)Ljava/lang/Float;
     210: ldc2_w        #44                 // double 2.0d
     213: invokestatic  #46                 // Method java/lang/Double.valueOf:(D)Ljava/lang/Double;
     216: getstatic     #47                 // Field enerj/rt/PrecisionRuntime$ArithOperator.DIVIDE:Lenerj/rt/PrecisionRuntime$ArithOperator;
     219: getstatic     #48                 // Field enerj/rt/PrecisionRuntime$NumberKind.DOUBLE:Lenerj/rt/PrecisionRuntime$NumberKind;
     222: iconst_0      
     223: invokeinterface #41,  6           // InterfaceMethod enerj/rt/PrecisionRuntime.binaryOp:(Ljava/lang/Number;Ljava/lang/Number;Lenerj/rt/PrecisionRuntime$ArithOperator;Lenerj/rt/PrecisionRuntime$NumberKind;Z)Ljava/lang/Number;
     228: invokevirtual #49                 // Method java/lang/Number.doubleValue:()D
     231: d2i           
     232: invokestatic  #20                 // Method java/lang/Integer.valueOf:(I)Ljava/lang/Integer;
     235: getstatic     #40                 // Field enerj/rt/PrecisionRuntime$ArithOperator.MINUS:Lenerj/rt/PrecisionRuntime$ArithOperator;
     238: getstatic     #38                 // Field enerj/rt/PrecisionRuntime$NumberKind.INT:Lenerj/rt/PrecisionRuntime$NumberKind;
     241: iconst_0      
     242: invokeinterface #41,  6           // InterfaceMethod enerj/rt/PrecisionRuntime.binaryOp:(Ljava/lang/Number;Ljava/lang/Number;Lenerj/rt/PrecisionRuntime$ArithOperator;Lenerj/rt/PrecisionRuntime$NumberKind;Z)Ljava/lang/Number;
     247: invokevirtual #42                 // Method java/lang/Number.intValue:()I
     250: invokestatic  #20                 // Method java/lang/Integer.valueOf:(I)Ljava/lang/Integer;
     253: iconst_0      
     254: getstatic     #16                 // Field enerj/rt/PrecisionRuntime$MemKind.VARIABLE:Lenerj/rt/PrecisionRuntime$MemKind;
     257: invokeinterface #17,  4           // InterfaceMethod enerj/rt/PrecisionRuntime.storeValue:(Ljava/lang/Object;ZLenerj/rt/PrecisionRuntime$MemKind;)Ljava/lang/Object;
     262: checkcast     #22                 // class java/lang/Integer
     265: invokevirtual #23                 // Method java/lang/Integer.intValue:()I
     268: istore        11
     270: new           #4                  // class enerj/rt/Reference
     273: dup           
     274: iload         11
     276: invokestatic  #20                 // Method java/lang/Integer.valueOf:(I)Ljava/lang/Integer;
     279: iconst_0      
     280: iconst_1      
     281: invokespecial #5                  // Method enerj/rt/Reference."<init>":(Ljava/lang/Object;ZZ)V
     284: astore        12
     286: getstatic     #2                  // Field enerj/rt/PrecisionRuntimeRoot.impl:Lenerj/rt/PrecisionRuntime;
     289: getstatic     #2                  // Field enerj/rt/PrecisionRuntimeRoot.impl:Lenerj/rt/PrecisionRuntime;
     292: getstatic     #2                  // Field enerj/rt/PrecisionRuntimeRoot.impl:Lenerj/rt/PrecisionRuntime;
     295: aload         6
     297: iconst_0      
     298: invokeinterface #9,  3            // InterfaceMethod enerj/rt/PrecisionRuntime.loadLocal:(Lenerj/rt/Reference;Z)Ljava/lang/Object;
     303: checkcast     #22                 // class java/lang/Integer
     306: invokevirtual #23                 // Method java/lang/Integer.intValue:()I
     309: invokestatic  #20                 // Method java/lang/Integer.valueOf:(I)Ljava/lang/Integer;
     312: getstatic     #2                  // Field enerj/rt/PrecisionRuntimeRoot.impl:Lenerj/rt/PrecisionRuntime;
     315: getstatic     #2                  // Field enerj/rt/PrecisionRuntimeRoot.impl:Lenerj/rt/PrecisionRuntime;
     318: aload         10
     320: iconst_0      
     321: invokeinterface #9,  3            // InterfaceMethod enerj/rt/PrecisionRuntime.loadLocal:(Lenerj/rt/Reference;Z)Ljava/lang/Object;
     326: checkcast     #22                 // class java/lang/Integer
     329: invokevirtual #23                 // Method java/lang/Integer.intValue:()I
     332: i2f           
     333: invokestatic  #43                 // Method java/lang/Float.valueOf:(F)Ljava/lang/Float;
     336: ldc2_w        #44                 // double 2.0d
     339: invokestatic  #46                 // Method java/lang/Double.valueOf:(D)Ljava/lang/Double;
     342: getstatic     #47                 // Field enerj/rt/PrecisionRuntime$ArithOperator.DIVIDE:Lenerj/rt/PrecisionRuntime$ArithOperator;
     345: getstatic     #48                 // Field enerj/rt/PrecisionRuntime$NumberKind.DOUBLE:Lenerj/rt/PrecisionRuntime$NumberKind;
     348: iconst_0      
     349: invokeinterface #41,  6           // InterfaceMethod enerj/rt/PrecisionRuntime.binaryOp:(Ljava/lang/Number;Ljava/lang/Number;Lenerj/rt/PrecisionRuntime$ArithOperator;Lenerj/rt/PrecisionRuntime$NumberKind;Z)Ljava/lang/Number;
     354: invokevirtual #49                 // Method java/lang/Number.doubleValue:()D
     357: d2i           
     358: invokestatic  #20                 // Method java/lang/Integer.valueOf:(I)Ljava/lang/Integer;
     361: getstatic     #37                 // Field enerj/rt/PrecisionRuntime$ArithOperator.PLUS:Lenerj/rt/PrecisionRuntime$ArithOperator;
     364: getstatic     #38                 // Field enerj/rt/PrecisionRuntime$NumberKind.INT:Lenerj/rt/PrecisionRuntime$NumberKind;
     367: iconst_0      
     368: invokeinterface #41,  6           // InterfaceMethod enerj/rt/PrecisionRuntime.binaryOp:(Ljava/lang/Number;Ljava/lang/Number;Lenerj/rt/PrecisionRuntime$ArithOperator;Lenerj/rt/PrecisionRuntime$NumberKind;Z)Ljava/lang/Number;
     373: invokevirtual #42                 // Method java/lang/Number.intValue:()I
     376: invokestatic  #20                 // Method java/lang/Integer.valueOf:(I)Ljava/lang/Integer;
     379: iconst_0      
     380: getstatic     #16                 // Field enerj/rt/PrecisionRuntime$MemKind.VARIABLE:Lenerj/rt/PrecisionRuntime$MemKind;
     383: invokeinterface #17,  4           // InterfaceMethod enerj/rt/PrecisionRuntime.storeValue:(Ljava/lang/Object;ZLenerj/rt/PrecisionRuntime$MemKind;)Ljava/lang/Object;
     388: checkcast     #22                 // class java/lang/Integer
     391: invokevirtual #23                 // Method java/lang/Integer.intValue:()I
     394: istore        13
     396: new           #4                  // class enerj/rt/Reference
     399: dup           
     400: iload         13
     402: invokestatic  #20                 // Method java/lang/Integer.valueOf:(I)Ljava/lang/Integer;
     405: iconst_0      
     406: iconst_1      
     407: invokespecial #5                  // Method enerj/rt/Reference."<init>":(Ljava/lang/Object;ZZ)V
     410: astore        14
     412: getstatic     #2                  // Field enerj/rt/PrecisionRuntimeRoot.impl:Lenerj/rt/PrecisionRuntime;
     415: getstatic     #2                  // Field enerj/rt/PrecisionRuntimeRoot.impl:Lenerj/rt/PrecisionRuntime;
     418: getstatic     #2                  // Field enerj/rt/PrecisionRuntimeRoot.impl:Lenerj/rt/PrecisionRuntime;
     421: aload         5
     423: iconst_0      
     424: invokeinterface #9,  3            // InterfaceMethod enerj/rt/PrecisionRuntime.loadLocal:(Lenerj/rt/Reference;Z)Ljava/lang/Object;
     429: checkcast     #22                 // class java/lang/Integer
     432: invokevirtual #23                 // Method java/lang/Integer.intValue:()I
     435: invokestatic  #20                 // Method java/lang/Integer.valueOf:(I)Ljava/lang/Integer;
     438: getstatic     #2                  // Field enerj/rt/PrecisionRuntimeRoot.impl:Lenerj/rt/PrecisionRuntime;
     441: getstatic     #2                  // Field enerj/rt/PrecisionRuntimeRoot.impl:Lenerj/rt/PrecisionRuntime;
     444: aload         8
     446: iconst_0      
     447: invokeinterface #9,  3            // InterfaceMethod enerj/rt/PrecisionRuntime.loadLocal:(Lenerj/rt/Reference;Z)Ljava/lang/Object;
     452: checkcast     #22                 // class java/lang/Integer
     455: invokevirtual #23                 // Method java/lang/Integer.intValue:()I
     458: i2f           
     459: invokestatic  #43                 // Method java/lang/Float.valueOf:(F)Ljava/lang/Float;
     462: ldc2_w        #44                 // double 2.0d
     465: invokestatic  #46                 // Method java/lang/Double.valueOf:(D)Ljava/lang/Double;
     468: getstatic     #47                 // Field enerj/rt/PrecisionRuntime$ArithOperator.DIVIDE:Lenerj/rt/PrecisionRuntime$ArithOperator;
     471: getstatic     #48                 // Field enerj/rt/PrecisionRuntime$NumberKind.DOUBLE:Lenerj/rt/PrecisionRuntime$NumberKind;
     474: iconst_0      
     475: invokeinterface #41,  6           // InterfaceMethod enerj/rt/PrecisionRuntime.binaryOp:(Ljava/lang/Number;Ljava/lang/Number;Lenerj/rt/PrecisionRuntime$ArithOperator;Lenerj/rt/PrecisionRuntime$NumberKind;Z)Ljava/lang/Number;
     480: invokevirtual #49                 // Method java/lang/Number.doubleValue:()D
     483: d2i           
     484: invokestatic  #20                 // Method java/lang/Integer.valueOf:(I)Ljava/lang/Integer;
     487: getstatic     #40                 // Field enerj/rt/PrecisionRuntime$ArithOperator.MINUS:Lenerj/rt/PrecisionRuntime$ArithOperator;
     490: getstatic     #38                 // Field enerj/rt/PrecisionRuntime$NumberKind.INT:Lenerj/rt/PrecisionRuntime$NumberKind;
     493: iconst_0      
     494: invokeinterface #41,  6           // InterfaceMethod enerj/rt/PrecisionRuntime.binaryOp:(Ljava/lang/Number;Ljava/lang/Number;Lenerj/rt/PrecisionRuntime$ArithOperator;Lenerj/rt/PrecisionRuntime$NumberKind;Z)Ljava/lang/Number;
     499: invokevirtual #42                 // Method java/lang/Number.intValue:()I
     502: invokestatic  #20                 // Method java/lang/Integer.valueOf:(I)Ljava/lang/Integer;
     505: iconst_0      
     506: getstatic     #16                 // Field enerj/rt/PrecisionRuntime$MemKind.VARIABLE:Lenerj/rt/PrecisionRuntime$MemKind;
     509: invokeinterface #17,  4           // InterfaceMethod enerj/rt/PrecisionRuntime.storeValue:(Ljava/lang/Object;ZLenerj/rt/PrecisionRuntime$MemKind;)Ljava/lang/Object;
     514: checkcast     #22                 // class java/lang/Integer
     517: invokevirtual #23                 // Method java/lang/Integer.intValue:()I
     520: istore        15
     522: new           #4                  // class enerj/rt/Reference
     525: dup           
     526: iload         15
     528: invokestatic  #20                 // Method java/lang/Integer.valueOf:(I)Ljava/lang/Integer;
     531: iconst_0      
     532: iconst_1      
     533: invokespecial #5                  // Method enerj/rt/Reference."<init>":(Ljava/lang/Object;ZZ)V
     536: astore        16
     538: getstatic     #2                  // Field enerj/rt/PrecisionRuntimeRoot.impl:Lenerj/rt/PrecisionRuntime;
     541: getstatic     #2                  // Field enerj/rt/PrecisionRuntimeRoot.impl:Lenerj/rt/PrecisionRuntime;
     544: getstatic     #2                  // Field enerj/rt/PrecisionRuntimeRoot.impl:Lenerj/rt/PrecisionRuntime;
     547: aload         5
     549: iconst_0      
     550: invokeinterface #9,  3            // InterfaceMethod enerj/rt/PrecisionRuntime.loadLocal:(Lenerj/rt/Reference;Z)Ljava/lang/Object;
     555: checkcast     #22                 // class java/lang/Integer
     558: invokevirtual #23                 // Method java/lang/Integer.intValue:()I
     561: invokestatic  #20                 // Method java/lang/Integer.valueOf:(I)Ljava/lang/Integer;
     564: getstatic     #2                  // Field enerj/rt/PrecisionRuntimeRoot.impl:Lenerj/rt/PrecisionRuntime;
     567: getstatic     #2                  // Field enerj/rt/PrecisionRuntimeRoot.impl:Lenerj/rt/PrecisionRuntime;
     570: aload         8
     572: iconst_0      
     573: invokeinterface #9,  3            // InterfaceMethod enerj/rt/PrecisionRuntime.loadLocal:(Lenerj/rt/Reference;Z)Ljava/lang/Object;
     578: checkcast     #22                 // class java/lang/Integer
     581: invokevirtual #23                 // Method java/lang/Integer.intValue:()I
     584: i2f           
     585: invokestatic  #43                 // Method java/lang/Float.valueOf:(F)Ljava/lang/Float;
     588: ldc2_w        #44                 // double 2.0d
     591: invokestatic  #46                 // Method java/lang/Double.valueOf:(D)Ljava/lang/Double;
     594: getstatic     #47                 // Field enerj/rt/PrecisionRuntime$ArithOperator.DIVIDE:Lenerj/rt/PrecisionRuntime$ArithOperator;
     597: getstatic     #48                 // Field enerj/rt/PrecisionRuntime$NumberKind.DOUBLE:Lenerj/rt/PrecisionRuntime$NumberKind;
     600: iconst_0      
     601: invokeinterface #41,  6           // InterfaceMethod enerj/rt/PrecisionRuntime.binaryOp:(Ljava/lang/Number;Ljava/lang/Number;Lenerj/rt/PrecisionRuntime$ArithOperator;Lenerj/rt/PrecisionRuntime$NumberKind;Z)Ljava/lang/Number;
     606: invokevirtual #49                 // Method java/lang/Number.doubleValue:()D
     609: d2i           
     610: invokestatic  #20                 // Method java/lang/Integer.valueOf:(I)Ljava/lang/Integer;
     613: getstatic     #37                 // Field enerj/rt/PrecisionRuntime$ArithOperator.PLUS:Lenerj/rt/PrecisionRuntime$ArithOperator;
     616: getstatic     #38                 // Field enerj/rt/PrecisionRuntime$NumberKind.INT:Lenerj/rt/PrecisionRuntime$NumberKind;
     619: iconst_0      
     620: invokeinterface #41,  6           // InterfaceMethod enerj/rt/PrecisionRuntime.binaryOp:(Ljava/lang/Number;Ljava/lang/Number;Lenerj/rt/PrecisionRuntime$ArithOperator;Lenerj/rt/PrecisionRuntime$NumberKind;Z)Ljava/lang/Number;
     625: invokevirtual #42                 // Method java/lang/Number.intValue:()I
     628: invokestatic  #20                 // Method java/lang/Integer.valueOf:(I)Ljava/lang/Integer;
     631: iconst_0      
     632: getstatic     #16                 // Field enerj/rt/PrecisionRuntime$MemKind.VARIABLE:Lenerj/rt/PrecisionRuntime$MemKind;
     635: invokeinterface #17,  4           // InterfaceMethod enerj/rt/PrecisionRuntime.storeValue:(Ljava/lang/Object;ZLenerj/rt/PrecisionRuntime$MemKind;)Ljava/lang/Object;
     640: checkcast     #22                 // class java/lang/Integer
     643: invokevirtual #23                 // Method java/lang/Integer.intValue:()I
     646: istore        17
     648: new           #4                  // class enerj/rt/Reference
     651: dup           
     652: iload         17
     654: invokestatic  #20                 // Method java/lang/Integer.valueOf:(I)Ljava/lang/Integer;
     657: iconst_0      
     658: iconst_1      
     659: invokespecial #5                  // Method enerj/rt/Reference."<init>":(Ljava/lang/Object;ZZ)V
     662: astore        18
     664: getstatic     #2                  // Field enerj/rt/PrecisionRuntimeRoot.impl:Lenerj/rt/PrecisionRuntime;
     667: iconst_0      
     668: invokestatic  #20                 // Method java/lang/Integer.valueOf:(I)Ljava/lang/Integer;
     671: iconst_0      
     672: getstatic     #16                 // Field enerj/rt/PrecisionRuntime$MemKind.VARIABLE:Lenerj/rt/PrecisionRuntime$MemKind;
     675: invokeinterface #17,  4           // InterfaceMethod enerj/rt/PrecisionRuntime.storeValue:(Ljava/lang/Object;ZLenerj/rt/PrecisionRuntime$MemKind;)Ljava/lang/Object;
     680: checkcast     #22                 // class java/lang/Integer
     683: invokevirtual #23                 // Method java/lang/Integer.intValue:()I
     686: istore        19
     688: new           #4                  // class enerj/rt/Reference
     691: dup           
     692: iload         19
     694: invokestatic  #20                 // Method java/lang/Integer.valueOf:(I)Ljava/lang/Integer;
     697: iconst_0      
     698: iconst_1      
     699: invokespecial #5                  // Method enerj/rt/Reference."<init>":(Ljava/lang/Object;ZZ)V
     702: astore        20
     704: getstatic     #2                  // Field enerj/rt/PrecisionRuntimeRoot.impl:Lenerj/rt/PrecisionRuntime;
     707: getstatic     #2                  // Field enerj/rt/PrecisionRuntimeRoot.impl:Lenerj/rt/PrecisionRuntime;
     710: aload         16
     712: iconst_0      
     713: invokeinterface #9,  3            // InterfaceMethod enerj/rt/PrecisionRuntime.loadLocal:(Lenerj/rt/Reference;Z)Ljava/lang/Object;
     718: checkcast     #22                 // class java/lang/Integer
     721: invokevirtual #23                 // Method java/lang/Integer.intValue:()I
     724: invokestatic  #20                 // Method java/lang/Integer.valueOf:(I)Ljava/lang/Integer;
     727: iconst_0      
     728: getstatic     #16                 // Field enerj/rt/PrecisionRuntime$MemKind.VARIABLE:Lenerj/rt/PrecisionRuntime$MemKind;
     731: invokeinterface #17,  4           // InterfaceMethod enerj/rt/PrecisionRuntime.storeValue:(Ljava/lang/Object;ZLenerj/rt/PrecisionRuntime$MemKind;)Ljava/lang/Object;
     736: checkcast     #22                 // class java/lang/Integer
     739: invokevirtual #23                 // Method java/lang/Integer.intValue:()I
     742: istore        21
     744: new           #4                  // class enerj/rt/Reference
     747: dup           
     748: iload         21
     750: invokestatic  #20                 // Method java/lang/Integer.valueOf:(I)Ljava/lang/Integer;
     753: iconst_0      
     754: iconst_1      
     755: invokespecial #5                  // Method enerj/rt/Reference."<init>":(Ljava/lang/Object;ZZ)V
     758: astore        22
     760: getstatic     #2                  // Field enerj/rt/PrecisionRuntimeRoot.impl:Lenerj/rt/PrecisionRuntime;
     763: getstatic     #2                  // Field enerj/rt/PrecisionRuntimeRoot.impl:Lenerj/rt/PrecisionRuntime;
     766: aload         22
     768: iconst_0      
     769: invokeinterface #9,  3            // InterfaceMethod enerj/rt/PrecisionRuntime.loadLocal:(Lenerj/rt/Reference;Z)Ljava/lang/Object;
     774: checkcast     #22                 // class java/lang/Integer
     777: invokevirtual #23                 // Method java/lang/Integer.intValue:()I
     780: getstatic     #2                  // Field enerj/rt/PrecisionRuntimeRoot.impl:Lenerj/rt/PrecisionRuntime;
     783: aload         18
     785: iconst_0      
     786: invokeinterface #9,  3            // InterfaceMethod enerj/rt/PrecisionRuntime.loadLocal:(Lenerj/rt/Reference;Z)Ljava/lang/Object;
     791: checkcast     #22                 // class java/lang/Integer
     794: invokevirtual #23                 // Method java/lang/Integer.intValue:()I
     797: if_icmpgt     804
     800: iconst_1      
     801: goto          805
     804: iconst_0      
     805: invokestatic  #30                 // Method java/lang/Boolean.valueOf:(Z)Ljava/lang/Boolean;
     808: invokeinterface #31,  2           // InterfaceMethod enerj/rt/PrecisionRuntime.countLogicalOp:(Ljava/lang/Object;)Ljava/lang/Object;
     813: checkcast     #32                 // class java/lang/Boolean
     816: invokevirtual #33                 // Method java/lang/Boolean.booleanValue:()Z
     819: ifeq          2793
     822: getstatic     #2                  // Field enerj/rt/PrecisionRuntimeRoot.impl:Lenerj/rt/PrecisionRuntime;
     825: getstatic     #2                  // Field enerj/rt/PrecisionRuntimeRoot.impl:Lenerj/rt/PrecisionRuntime;
     828: getstatic     #2                  // Field enerj/rt/PrecisionRuntimeRoot.impl:Lenerj/rt/PrecisionRuntime;
     831: aload         22
     833: iconst_0      
     834: invokeinterface #9,  3            // InterfaceMethod enerj/rt/PrecisionRuntime.loadLocal:(Lenerj/rt/Reference;Z)Ljava/lang/Object;
     839: checkcast     #22                 // class java/lang/Integer
     842: invokevirtual #23                 // Method java/lang/Integer.intValue:()I
     845: ifge          852
     848: iconst_1      
     849: goto          853
     852: iconst_0      
     853: invokestatic  #30                 // Method java/lang/Boolean.valueOf:(Z)Ljava/lang/Boolean;
     856: invokeinterface #31,  2           // InterfaceMethod enerj/rt/PrecisionRuntime.countLogicalOp:(Ljava/lang/Object;)Ljava/lang/Object;
     861: checkcast     #32                 // class java/lang/Boolean
     864: invokevirtual #33                 // Method java/lang/Boolean.booleanValue:()Z
     867: ifne          933
     870: getstatic     #2                  // Field enerj/rt/PrecisionRuntimeRoot.impl:Lenerj/rt/PrecisionRuntime;
     873: getstatic     #2                  // Field enerj/rt/PrecisionRuntimeRoot.impl:Lenerj/rt/PrecisionRuntime;
     876: aload         22
     878: iconst_0      
     879: invokeinterface #9,  3            // InterfaceMethod enerj/rt/PrecisionRuntime.loadLocal:(Lenerj/rt/Reference;Z)Ljava/lang/Object;
     884: checkcast     #22                 // class java/lang/Integer
     887: invokevirtual #23                 // Method java/lang/Integer.intValue:()I
     890: getstatic     #2                  // Field enerj/rt/PrecisionRuntimeRoot.impl:Lenerj/rt/PrecisionRuntime;
     893: aload_0       
     894: ldc           #25                 // String height
     896: iconst_0      
     897: invokeinterface #13,  4           // InterfaceMethod enerj/rt/PrecisionRuntime.loadField:(Ljava/lang/Object;Ljava/lang/String;Z)Ljava/lang/Object;
     902: checkcast     #22                 // class java/lang/Integer
     905: invokevirtual #23                 // Method java/lang/Integer.intValue:()I
     908: if_icmplt     915
     911: iconst_1      
     912: goto          916
     915: iconst_0      
     916: invokestatic  #30                 // Method java/lang/Boolean.valueOf:(Z)Ljava/lang/Boolean;
     919: invokeinterface #31,  2           // InterfaceMethod enerj/rt/PrecisionRuntime.countLogicalOp:(Ljava/lang/Object;)Ljava/lang/Object;
     924: checkcast     #32                 // class java/lang/Boolean
     927: invokevirtual #33                 // Method java/lang/Boolean.booleanValue:()Z
     930: ifeq          937
     933: iconst_1      
     934: goto          938
     937: iconst_0      
     938: invokestatic  #30                 // Method java/lang/Boolean.valueOf:(Z)Ljava/lang/Boolean;
     941: invokeinterface #31,  2           // InterfaceMethod enerj/rt/PrecisionRuntime.countLogicalOp:(Ljava/lang/Object;)Ljava/lang/Object;
     946: checkcast     #32                 // class java/lang/Boolean
     949: invokevirtual #33                 // Method java/lang/Boolean.booleanValue:()Z
     952: ifeq          1477
     955: getstatic     #2                  // Field enerj/rt/PrecisionRuntimeRoot.impl:Lenerj/rt/PrecisionRuntime;
     958: getstatic     #2                  // Field enerj/rt/PrecisionRuntimeRoot.impl:Lenerj/rt/PrecisionRuntime;
     961: aload         12
     963: iconst_0      
     964: invokeinterface #9,  3            // InterfaceMethod enerj/rt/PrecisionRuntime.loadLocal:(Lenerj/rt/Reference;Z)Ljava/lang/Object;
     969: checkcast     #22                 // class java/lang/Integer
     972: invokevirtual #23                 // Method java/lang/Integer.intValue:()I
     975: invokestatic  #20                 // Method java/lang/Integer.valueOf:(I)Ljava/lang/Integer;
     978: iconst_0      
     979: getstatic     #16                 // Field enerj/rt/PrecisionRuntime$MemKind.VARIABLE:Lenerj/rt/PrecisionRuntime$MemKind;
     982: invokeinterface #17,  4           // InterfaceMethod enerj/rt/PrecisionRuntime.storeValue:(Ljava/lang/Object;ZLenerj/rt/PrecisionRuntime$MemKind;)Ljava/lang/Object;
     987: checkcast     #22                 // class java/lang/Integer
     990: invokevirtual #23                 // Method java/lang/Integer.intValue:()I
     993: istore        23
     995: new           #4                  // class enerj/rt/Reference
     998: dup           
     999: iload         23
    1001: invokestatic  #20                 // Method java/lang/Integer.valueOf:(I)Ljava/lang/Integer;
    1004: iconst_0      
    1005: iconst_1      
    1006: invokespecial #5                  // Method enerj/rt/Reference."<init>":(Ljava/lang/Object;ZZ)V
    1009: astore        24
    1011: getstatic     #2                  // Field enerj/rt/PrecisionRuntimeRoot.impl:Lenerj/rt/PrecisionRuntime;
    1014: getstatic     #2                  // Field enerj/rt/PrecisionRuntimeRoot.impl:Lenerj/rt/PrecisionRuntime;
    1017: aload         24
    1019: iconst_0      
    1020: invokeinterface #9,  3            // InterfaceMethod enerj/rt/PrecisionRuntime.loadLocal:(Lenerj/rt/Reference;Z)Ljava/lang/Object;
    1025: checkcast     #22                 // class java/lang/Integer
    1028: invokevirtual #23                 // Method java/lang/Integer.intValue:()I
    1031: getstatic     #2                  // Field enerj/rt/PrecisionRuntimeRoot.impl:Lenerj/rt/PrecisionRuntime;
    1034: aload         14
    1036: iconst_0      
    1037: invokeinterface #9,  3            // InterfaceMethod enerj/rt/PrecisionRuntime.loadLocal:(Lenerj/rt/Reference;Z)Ljava/lang/Object;
    1042: checkcast     #22                 // class java/lang/Integer
    1045: invokevirtual #23                 // Method java/lang/Integer.intValue:()I
    1048: if_icmpgt     1055
    1051: iconst_1      
    1052: goto          1056
    1055: iconst_0      
    1056: invokestatic  #30                 // Method java/lang/Boolean.valueOf:(Z)Ljava/lang/Boolean;
    1059: invokeinterface #31,  2           // InterfaceMethod enerj/rt/PrecisionRuntime.countLogicalOp:(Ljava/lang/Object;)Ljava/lang/Object;
    1064: checkcast     #32                 // class java/lang/Boolean
    1067: invokevirtual #33                 // Method java/lang/Boolean.booleanValue:()Z
    1070: ifeq          1474
    1073: getstatic     #2                  // Field enerj/rt/PrecisionRuntimeRoot.impl:Lenerj/rt/PrecisionRuntime;
    1076: getstatic     #2                  // Field enerj/rt/PrecisionRuntimeRoot.impl:Lenerj/rt/PrecisionRuntime;
    1079: getstatic     #2                  // Field enerj/rt/PrecisionRuntimeRoot.impl:Lenerj/rt/PrecisionRuntime;
    1082: getstatic     #2                  // Field enerj/rt/PrecisionRuntimeRoot.impl:Lenerj/rt/PrecisionRuntime;
    1085: aload         4
    1087: iconst_0      
    1088: invokeinterface #9,  3            // InterfaceMethod enerj/rt/PrecisionRuntime.loadLocal:(Lenerj/rt/Reference;Z)Ljava/lang/Object;
    1093: getstatic     #2                  // Field enerj/rt/PrecisionRuntimeRoot.impl:Lenerj/rt/PrecisionRuntime;
    1096: aload         20
    1098: iconst_0      
    1099: invokeinterface #9,  3            // InterfaceMethod enerj/rt/PrecisionRuntime.loadLocal:(Lenerj/rt/Reference;Z)Ljava/lang/Object;
    1104: checkcast     #22                 // class java/lang/Integer
    1107: invokevirtual #23                 // Method java/lang/Integer.intValue:()I
    1110: iconst_0      
    1111: invokeinterface #36,  4           // InterfaceMethod enerj/rt/PrecisionRuntime.loadArray:(Ljava/lang/Object;IZ)Ljava/lang/Object;
    1116: getstatic     #2                  // Field enerj/rt/PrecisionRuntimeRoot.impl:Lenerj/rt/PrecisionRuntime;
    1119: getstatic     #2                  // Field enerj/rt/PrecisionRuntimeRoot.impl:Lenerj/rt/PrecisionRuntime;
    1122: aload         24
    1124: iconst_0      
    1125: invokeinterface #9,  3            // InterfaceMethod enerj/rt/PrecisionRuntime.loadLocal:(Lenerj/rt/Reference;Z)Ljava/lang/Object;
    1130: checkcast     #22                 // class java/lang/Integer
    1133: invokevirtual #23                 // Method java/lang/Integer.intValue:()I
    1136: invokestatic  #20                 // Method java/lang/Integer.valueOf:(I)Ljava/lang/Integer;
    1139: getstatic     #2                  // Field enerj/rt/PrecisionRuntimeRoot.impl:Lenerj/rt/PrecisionRuntime;
    1142: aload         12
    1144: iconst_0      
    1145: invokeinterface #9,  3            // InterfaceMethod enerj/rt/PrecisionRuntime.loadLocal:(Lenerj/rt/Reference;Z)Ljava/lang/Object;
    1150: checkcast     #22                 // class java/lang/Integer
    1153: invokevirtual #23                 // Method java/lang/Integer.intValue:()I
    1156: invokestatic  #20                 // Method java/lang/Integer.valueOf:(I)Ljava/lang/Integer;
    1159: getstatic     #40                 // Field enerj/rt/PrecisionRuntime$ArithOperator.MINUS:Lenerj/rt/PrecisionRuntime$ArithOperator;
    1162: getstatic     #38                 // Field enerj/rt/PrecisionRuntime$NumberKind.INT:Lenerj/rt/PrecisionRuntime$NumberKind;
    1165: iconst_0      
    1166: invokeinterface #41,  6           // InterfaceMethod enerj/rt/PrecisionRuntime.binaryOp:(Ljava/lang/Number;Ljava/lang/Number;Lenerj/rt/PrecisionRuntime$ArithOperator;Lenerj/rt/PrecisionRuntime$NumberKind;Z)Ljava/lang/Number;
    1171: invokevirtual #42                 // Method java/lang/Number.intValue:()I
    1174: iconst_0      
    1175: invokeinterface #36,  4           // InterfaceMethod enerj/rt/PrecisionRuntime.loadArray:(Ljava/lang/Object;IZ)Ljava/lang/Object;
    1180: iconst_0      
    1181: iconst_1      
    1182: iconst_0      
    1183: invokestatic  #20                 // Method java/lang/Integer.valueOf:(I)Ljava/lang/Integer;
    1186: invokeinterface #35,  5           // InterfaceMethod enerj/rt/PrecisionRuntime.storeArray:(Ljava/lang/Object;IZLjava/lang/Object;)Ljava/lang/Object;
    1191: checkcast     #22                 // class java/lang/Integer
    1194: invokevirtual #23                 // Method java/lang/Integer.intValue:()I
    1197: pop           
    1198: getstatic     #2                  // Field enerj/rt/PrecisionRuntimeRoot.impl:Lenerj/rt/PrecisionRuntime;
    1201: getstatic     #2                  // Field enerj/rt/PrecisionRuntimeRoot.impl:Lenerj/rt/PrecisionRuntime;
    1204: getstatic     #2                  // Field enerj/rt/PrecisionRuntimeRoot.impl:Lenerj/rt/PrecisionRuntime;
    1207: getstatic     #2                  // Field enerj/rt/PrecisionRuntimeRoot.impl:Lenerj/rt/PrecisionRuntime;
    1210: aload         4
    1212: iconst_0      
    1213: invokeinterface #9,  3            // InterfaceMethod enerj/rt/PrecisionRuntime.loadLocal:(Lenerj/rt/Reference;Z)Ljava/lang/Object;
    1218: getstatic     #2                  // Field enerj/rt/PrecisionRuntimeRoot.impl:Lenerj/rt/PrecisionRuntime;
    1221: aload         20
    1223: iconst_0      
    1224: invokeinterface #9,  3            // InterfaceMethod enerj/rt/PrecisionRuntime.loadLocal:(Lenerj/rt/Reference;Z)Ljava/lang/Object;
    1229: checkcast     #22                 // class java/lang/Integer
    1232: invokevirtual #23                 // Method java/lang/Integer.intValue:()I
    1235: iconst_0      
    1236: invokeinterface #36,  4           // InterfaceMethod enerj/rt/PrecisionRuntime.loadArray:(Ljava/lang/Object;IZ)Ljava/lang/Object;
    1241: getstatic     #2                  // Field enerj/rt/PrecisionRuntimeRoot.impl:Lenerj/rt/PrecisionRuntime;
    1244: getstatic     #2                  // Field enerj/rt/PrecisionRuntimeRoot.impl:Lenerj/rt/PrecisionRuntime;
    1247: aload         24
    1249: iconst_0      
    1250: invokeinterface #9,  3            // InterfaceMethod enerj/rt/PrecisionRuntime.loadLocal:(Lenerj/rt/Reference;Z)Ljava/lang/Object;
    1255: checkcast     #22                 // class java/lang/Integer
    1258: invokevirtual #23                 // Method java/lang/Integer.intValue:()I
    1261: invokestatic  #20                 // Method java/lang/Integer.valueOf:(I)Ljava/lang/Integer;
    1264: getstatic     #2                  // Field enerj/rt/PrecisionRuntimeRoot.impl:Lenerj/rt/PrecisionRuntime;
    1267: aload         12
    1269: iconst_0      
    1270: invokeinterface #9,  3            // InterfaceMethod enerj/rt/PrecisionRuntime.loadLocal:(Lenerj/rt/Reference;Z)Ljava/lang/Object;
    1275: checkcast     #22                 // class java/lang/Integer
    1278: invokevirtual #23                 // Method java/lang/Integer.intValue:()I
    1281: invokestatic  #20                 // Method java/lang/Integer.valueOf:(I)Ljava/lang/Integer;
    1284: getstatic     #40                 // Field enerj/rt/PrecisionRuntime$ArithOperator.MINUS:Lenerj/rt/PrecisionRuntime$ArithOperator;
    1287: getstatic     #38                 // Field enerj/rt/PrecisionRuntime$NumberKind.INT:Lenerj/rt/PrecisionRuntime$NumberKind;
    1290: iconst_0      
    1291: invokeinterface #41,  6           // InterfaceMethod enerj/rt/PrecisionRuntime.binaryOp:(Ljava/lang/Number;Ljava/lang/Number;Lenerj/rt/PrecisionRuntime$ArithOperator;Lenerj/rt/PrecisionRuntime$NumberKind;Z)Ljava/lang/Number;
    1296: invokevirtual #42                 // Method java/lang/Number.intValue:()I
    1299: iconst_0      
    1300: invokeinterface #36,  4           // InterfaceMethod enerj/rt/PrecisionRuntime.loadArray:(Ljava/lang/Object;IZ)Ljava/lang/Object;
    1305: iconst_1      
    1306: iconst_1      
    1307: iconst_0      
    1308: invokestatic  #20                 // Method java/lang/Integer.valueOf:(I)Ljava/lang/Integer;
    1311: invokeinterface #35,  5           // InterfaceMethod enerj/rt/PrecisionRuntime.storeArray:(Ljava/lang/Object;IZLjava/lang/Object;)Ljava/lang/Object;
    1316: checkcast     #22                 // class java/lang/Integer
    1319: invokevirtual #23                 // Method java/lang/Integer.intValue:()I
    1322: pop           
    1323: getstatic     #2                  // Field enerj/rt/PrecisionRuntimeRoot.impl:Lenerj/rt/PrecisionRuntime;
    1326: getstatic     #2                  // Field enerj/rt/PrecisionRuntimeRoot.impl:Lenerj/rt/PrecisionRuntime;
    1329: getstatic     #2                  // Field enerj/rt/PrecisionRuntimeRoot.impl:Lenerj/rt/PrecisionRuntime;
    1332: getstatic     #2                  // Field enerj/rt/PrecisionRuntimeRoot.impl:Lenerj/rt/PrecisionRuntime;
    1335: aload         4
    1337: iconst_0      
    1338: invokeinterface #9,  3            // InterfaceMethod enerj/rt/PrecisionRuntime.loadLocal:(Lenerj/rt/Reference;Z)Ljava/lang/Object;
    1343: getstatic     #2                  // Field enerj/rt/PrecisionRuntimeRoot.impl:Lenerj/rt/PrecisionRuntime;
    1346: aload         20
    1348: iconst_0      
    1349: invokeinterface #9,  3            // InterfaceMethod enerj/rt/PrecisionRuntime.loadLocal:(Lenerj/rt/Reference;Z)Ljava/lang/Object;
    1354: checkcast     #22                 // class java/lang/Integer
    1357: invokevirtual #23                 // Method java/lang/Integer.intValue:()I
    1360: iconst_0      
    1361: invokeinterface #36,  4           // InterfaceMethod enerj/rt/PrecisionRuntime.loadArray:(Ljava/lang/Object;IZ)Ljava/lang/Object;
    1366: getstatic     #2                  // Field enerj/rt/PrecisionRuntimeRoot.impl:Lenerj/rt/PrecisionRuntime;
    1369: getstatic     #2                  // Field enerj/rt/PrecisionRuntimeRoot.impl:Lenerj/rt/PrecisionRuntime;
    1372: aload         24
    1374: iconst_0      
    1375: invokeinterface #9,  3            // InterfaceMethod enerj/rt/PrecisionRuntime.loadLocal:(Lenerj/rt/Reference;Z)Ljava/lang/Object;
    1380: checkcast     #22                 // class java/lang/Integer
    1383: invokevirtual #23                 // Method java/lang/Integer.intValue:()I
    1386: invokestatic  #20                 // Method java/lang/Integer.valueOf:(I)Ljava/lang/Integer;
    1389: getstatic     #2                  // Field enerj/rt/PrecisionRuntimeRoot.impl:Lenerj/rt/PrecisionRuntime;
    1392: aload         12
    1394: iconst_0      
    1395: invokeinterface #9,  3            // InterfaceMethod enerj/rt/PrecisionRuntime.loadLocal:(Lenerj/rt/Reference;Z)Ljava/lang/Object;
    1400: checkcast     #22                 // class java/lang/Integer
    1403: invokevirtual #23                 // Method java/lang/Integer.intValue:()I
    1406: invokestatic  #20                 // Method java/lang/Integer.valueOf:(I)Ljava/lang/Integer;
    1409: getstatic     #40                 // Field enerj/rt/PrecisionRuntime$ArithOperator.MINUS:Lenerj/rt/PrecisionRuntime$ArithOperator;
    1412: getstatic     #38                 // Field enerj/rt/PrecisionRuntime$NumberKind.INT:Lenerj/rt/PrecisionRuntime$NumberKind;
    1415: iconst_0      
    1416: invokeinterface #41,  6           // InterfaceMethod enerj/rt/PrecisionRuntime.binaryOp:(Ljava/lang/Number;Ljava/lang/Number;Lenerj/rt/PrecisionRuntime$ArithOperator;Lenerj/rt/PrecisionRuntime$NumberKind;Z)Ljava/lang/Number;
    1421: invokevirtual #42                 // Method java/lang/Number.intValue:()I
    1424: iconst_0      
    1425: invokeinterface #36,  4           // InterfaceMethod enerj/rt/PrecisionRuntime.loadArray:(Ljava/lang/Object;IZ)Ljava/lang/Object;
    1430: iconst_2      
    1431: iconst_1      
    1432: iconst_0      
    1433: invokestatic  #20                 // Method java/lang/Integer.valueOf:(I)Ljava/lang/Integer;
    1436: invokeinterface #35,  5           // InterfaceMethod enerj/rt/PrecisionRuntime.storeArray:(Ljava/lang/Object;IZLjava/lang/Object;)Ljava/lang/Object;
    1441: checkcast     #22                 // class java/lang/Integer
    1444: invokevirtual #23                 // Method java/lang/Integer.intValue:()I
    1447: pop           
    1448: getstatic     #2                  // Field enerj/rt/PrecisionRuntimeRoot.impl:Lenerj/rt/PrecisionRuntime;
    1451: aload         24
    1453: getstatic     #37                 // Field enerj/rt/PrecisionRuntime$ArithOperator.PLUS:Lenerj/rt/PrecisionRuntime$ArithOperator;
    1456: iconst_1      
    1457: invokestatic  #20                 // Method java/lang/Integer.valueOf:(I)Ljava/lang/Integer;
    1460: iconst_0      
    1461: getstatic     #38                 // Field enerj/rt/PrecisionRuntime$NumberKind.INT:Lenerj/rt/PrecisionRuntime$NumberKind;
    1464: iconst_0      
    1465: invokeinterface #39,  7           // InterfaceMethod enerj/rt/PrecisionRuntime.assignopLocal:(Lenerj/rt/Reference;Lenerj/rt/PrecisionRuntime$ArithOperator;Ljava/lang/Number;ZLenerj/rt/PrecisionRuntime$NumberKind;Z)Ljava/lang/Number;
    1470: pop           
    1471: goto          1011
    1474: goto          2744
    1477: getstatic     #2                  // Field enerj/rt/PrecisionRuntimeRoot.impl:Lenerj/rt/PrecisionRuntime;
    1480: getstatic     #2                  // Field enerj/rt/PrecisionRuntimeRoot.impl:Lenerj/rt/PrecisionRuntime;
    1483: aload         12
    1485: iconst_0      
    1486: invokeinterface #9,  3            // InterfaceMethod enerj/rt/PrecisionRuntime.loadLocal:(Lenerj/rt/Reference;Z)Ljava/lang/Object;
    1491: checkcast     #22                 // class java/lang/Integer
    1494: invokevirtual #23                 // Method java/lang/Integer.intValue:()I
    1497: invokestatic  #20                 // Method java/lang/Integer.valueOf:(I)Ljava/lang/Integer;
    1500: iconst_0      
    1501: getstatic     #16                 // Field enerj/rt/PrecisionRuntime$MemKind.VARIABLE:Lenerj/rt/PrecisionRuntime$MemKind;
    1504: invokeinterface #17,  4           // InterfaceMethod enerj/rt/PrecisionRuntime.storeValue:(Ljava/lang/Object;ZLenerj/rt/PrecisionRuntime$MemKind;)Ljava/lang/Object;
    1509: checkcast     #22                 // class java/lang/Integer
    1512: invokevirtual #23                 // Method java/lang/Integer.intValue:()I
    1515: istore        23
    1517: new           #4                  // class enerj/rt/Reference
    1520: dup           
    1521: iload         23
    1523: invokestatic  #20                 // Method java/lang/Integer.valueOf:(I)Ljava/lang/Integer;
    1526: iconst_0      
    1527: iconst_1      
    1528: invokespecial #5                  // Method enerj/rt/Reference."<init>":(Ljava/lang/Object;ZZ)V
    1531: astore        24
    1533: getstatic     #2                  // Field enerj/rt/PrecisionRuntimeRoot.impl:Lenerj/rt/PrecisionRuntime;
    1536: getstatic     #2                  // Field enerj/rt/PrecisionRuntimeRoot.impl:Lenerj/rt/PrecisionRuntime;
    1539: aload         24
    1541: iconst_0      
    1542: invokeinterface #9,  3            // InterfaceMethod enerj/rt/PrecisionRuntime.loadLocal:(Lenerj/rt/Reference;Z)Ljava/lang/Object;
    1547: checkcast     #22                 // class java/lang/Integer
    1550: invokevirtual #23                 // Method java/lang/Integer.intValue:()I
    1553: getstatic     #2                  // Field enerj/rt/PrecisionRuntimeRoot.impl:Lenerj/rt/PrecisionRuntime;
    1556: aload         14
    1558: iconst_0      
    1559: invokeinterface #9,  3            // InterfaceMethod enerj/rt/PrecisionRuntime.loadLocal:(Lenerj/rt/Reference;Z)Ljava/lang/Object;
    1564: checkcast     #22                 // class java/lang/Integer
    1567: invokevirtual #23                 // Method java/lang/Integer.intValue:()I
    1570: if_icmpgt     1577
    1573: iconst_1      
    1574: goto          1578
    1577: iconst_0      
    1578: invokestatic  #30                 // Method java/lang/Boolean.valueOf:(Z)Ljava/lang/Boolean;
    1581: invokeinterface #31,  2           // InterfaceMethod enerj/rt/PrecisionRuntime.countLogicalOp:(Ljava/lang/Object;)Ljava/lang/Object;
    1586: checkcast     #32                 // class java/lang/Boolean
    1589: invokevirtual #33                 // Method java/lang/Boolean.booleanValue:()Z
    1592: ifeq          2744
    1595: getstatic     #2                  // Field enerj/rt/PrecisionRuntimeRoot.impl:Lenerj/rt/PrecisionRuntime;
    1598: getstatic     #2                  // Field enerj/rt/PrecisionRuntimeRoot.impl:Lenerj/rt/PrecisionRuntime;
    1601: getstatic     #2                  // Field enerj/rt/PrecisionRuntimeRoot.impl:Lenerj/rt/PrecisionRuntime;
    1604: aload         24
    1606: iconst_0      
    1607: invokeinterface #9,  3            // InterfaceMethod enerj/rt/PrecisionRuntime.loadLocal:(Lenerj/rt/Reference;Z)Ljava/lang/Object;
    1612: checkcast     #22                 // class java/lang/Integer
    1615: invokevirtual #23                 // Method java/lang/Integer.intValue:()I
    1618: ifge          1625
    1621: iconst_1      
    1622: goto          1626
    1625: iconst_0      
    1626: invokestatic  #30                 // Method java/lang/Boolean.valueOf:(Z)Ljava/lang/Boolean;
    1629: invokeinterface #31,  2           // InterfaceMethod enerj/rt/PrecisionRuntime.countLogicalOp:(Ljava/lang/Object;)Ljava/lang/Object;
    1634: checkcast     #32                 // class java/lang/Boolean
    1637: invokevirtual #33                 // Method java/lang/Boolean.booleanValue:()Z
    1640: ifne          1706
    1643: getstatic     #2                  // Field enerj/rt/PrecisionRuntimeRoot.impl:Lenerj/rt/PrecisionRuntime;
    1646: getstatic     #2                  // Field enerj/rt/PrecisionRuntimeRoot.impl:Lenerj/rt/PrecisionRuntime;
    1649: aload         24
    1651: iconst_0      
    1652: invokeinterface #9,  3            // InterfaceMethod enerj/rt/PrecisionRuntime.loadLocal:(Lenerj/rt/Reference;Z)Ljava/lang/Object;
    1657: checkcast     #22                 // class java/lang/Integer
    1660: invokevirtual #23                 // Method java/lang/Integer.intValue:()I
    1663: getstatic     #2                  // Field enerj/rt/PrecisionRuntimeRoot.impl:Lenerj/rt/PrecisionRuntime;
    1666: aload_0       
    1667: ldc           #18                 // String width
    1669: iconst_0      
    1670: invokeinterface #13,  4           // InterfaceMethod enerj/rt/PrecisionRuntime.loadField:(Ljava/lang/Object;Ljava/lang/String;Z)Ljava/lang/Object;
    1675: checkcast     #22                 // class java/lang/Integer
    1678: invokevirtual #23                 // Method java/lang/Integer.intValue:()I
    1681: if_icmplt     1688
    1684: iconst_1      
    1685: goto          1689
    1688: iconst_0      
    1689: invokestatic  #30                 // Method java/lang/Boolean.valueOf:(Z)Ljava/lang/Boolean;
    1692: invokeinterface #31,  2           // InterfaceMethod enerj/rt/PrecisionRuntime.countLogicalOp:(Ljava/lang/Object;)Ljava/lang/Object;
    1697: checkcast     #32                 // class java/lang/Boolean
    1700: invokevirtual #33                 // Method java/lang/Boolean.booleanValue:()Z
    1703: ifeq          1710
    1706: iconst_1      
    1707: goto          1711
    1710: iconst_0      
    1711: invokestatic  #30                 // Method java/lang/Boolean.valueOf:(Z)Ljava/lang/Boolean;
    1714: invokeinterface #31,  2           // InterfaceMethod enerj/rt/PrecisionRuntime.countLogicalOp:(Ljava/lang/Object;)Ljava/lang/Object;
    1719: checkcast     #32                 // class java/lang/Boolean
    1722: invokevirtual #33                 // Method java/lang/Boolean.booleanValue:()Z
    1725: ifeq          2106
    1728: getstatic     #2                  // Field enerj/rt/PrecisionRuntimeRoot.impl:Lenerj/rt/PrecisionRuntime;
    1731: getstatic     #2                  // Field enerj/rt/PrecisionRuntimeRoot.impl:Lenerj/rt/PrecisionRuntime;
    1734: getstatic     #2                  // Field enerj/rt/PrecisionRuntimeRoot.impl:Lenerj/rt/PrecisionRuntime;
    1737: getstatic     #2                  // Field enerj/rt/PrecisionRuntimeRoot.impl:Lenerj/rt/PrecisionRuntime;
    1740: aload         4
    1742: iconst_0      
    1743: invokeinterface #9,  3            // InterfaceMethod enerj/rt/PrecisionRuntime.loadLocal:(Lenerj/rt/Reference;Z)Ljava/lang/Object;
    1748: getstatic     #2                  // Field enerj/rt/PrecisionRuntimeRoot.impl:Lenerj/rt/PrecisionRuntime;
    1751: aload         20
    1753: iconst_0      
    1754: invokeinterface #9,  3            // InterfaceMethod enerj/rt/PrecisionRuntime.loadLocal:(Lenerj/rt/Reference;Z)Ljava/lang/Object;
    1759: checkcast     #22                 // class java/lang/Integer
    1762: invokevirtual #23                 // Method java/lang/Integer.intValue:()I
    1765: iconst_0      
    1766: invokeinterface #36,  4           // InterfaceMethod enerj/rt/PrecisionRuntime.loadArray:(Ljava/lang/Object;IZ)Ljava/lang/Object;
    1771: getstatic     #2                  // Field enerj/rt/PrecisionRuntimeRoot.impl:Lenerj/rt/PrecisionRuntime;
    1774: getstatic     #2                  // Field enerj/rt/PrecisionRuntimeRoot.impl:Lenerj/rt/PrecisionRuntime;
    1777: aload         24
    1779: iconst_0      
    1780: invokeinterface #9,  3            // InterfaceMethod enerj/rt/PrecisionRuntime.loadLocal:(Lenerj/rt/Reference;Z)Ljava/lang/Object;
    1785: checkcast     #22                 // class java/lang/Integer
    1788: invokevirtual #23                 // Method java/lang/Integer.intValue:()I
    1791: invokestatic  #20                 // Method java/lang/Integer.valueOf:(I)Ljava/lang/Integer;
    1794: getstatic     #2                  // Field enerj/rt/PrecisionRuntimeRoot.impl:Lenerj/rt/PrecisionRuntime;
    1797: aload         12
    1799: iconst_0      
    1800: invokeinterface #9,  3            // InterfaceMethod enerj/rt/PrecisionRuntime.loadLocal:(Lenerj/rt/Reference;Z)Ljava/lang/Object;
    1805: checkcast     #22                 // class java/lang/Integer
    1808: invokevirtual #23                 // Method java/lang/Integer.intValue:()I
    1811: invokestatic  #20                 // Method java/lang/Integer.valueOf:(I)Ljava/lang/Integer;
    1814: getstatic     #40                 // Field enerj/rt/PrecisionRuntime$ArithOperator.MINUS:Lenerj/rt/PrecisionRuntime$ArithOperator;
    1817: getstatic     #38                 // Field enerj/rt/PrecisionRuntime$NumberKind.INT:Lenerj/rt/PrecisionRuntime$NumberKind;
    1820: iconst_0      
    1821: invokeinterface #41,  6           // InterfaceMethod enerj/rt/PrecisionRuntime.binaryOp:(Ljava/lang/Number;Ljava/lang/Number;Lenerj/rt/PrecisionRuntime$ArithOperator;Lenerj/rt/PrecisionRuntime$NumberKind;Z)Ljava/lang/Number;
    1826: invokevirtual #42                 // Method java/lang/Number.intValue:()I
    1829: iconst_0      
    1830: invokeinterface #36,  4           // InterfaceMethod enerj/rt/PrecisionRuntime.loadArray:(Ljava/lang/Object;IZ)Ljava/lang/Object;
    1835: iconst_0      
    1836: iconst_1      
    1837: iconst_0      
    1838: invokestatic  #20                 // Method java/lang/Integer.valueOf:(I)Ljava/lang/Integer;
    1841: invokeinterface #35,  5           // InterfaceMethod enerj/rt/PrecisionRuntime.storeArray:(Ljava/lang/Object;IZLjava/lang/Object;)Ljava/lang/Object;
    1846: checkcast     #22                 // class java/lang/Integer
    1849: invokevirtual #23                 // Method java/lang/Integer.intValue:()I
    1852: pop           
    1853: getstatic     #2                  // Field enerj/rt/PrecisionRuntimeRoot.impl:Lenerj/rt/PrecisionRuntime;
    1856: getstatic     #2                  // Field enerj/rt/PrecisionRuntimeRoot.impl:Lenerj/rt/PrecisionRuntime;
    1859: getstatic     #2                  // Field enerj/rt/PrecisionRuntimeRoot.impl:Lenerj/rt/PrecisionRuntime;
    1862: getstatic     #2                  // Field enerj/rt/PrecisionRuntimeRoot.impl:Lenerj/rt/PrecisionRuntime;
    1865: aload         4
    1867: iconst_0      
    1868: invokeinterface #9,  3            // InterfaceMethod enerj/rt/PrecisionRuntime.loadLocal:(Lenerj/rt/Reference;Z)Ljava/lang/Object;
    1873: getstatic     #2                  // Field enerj/rt/PrecisionRuntimeRoot.impl:Lenerj/rt/PrecisionRuntime;
    1876: aload         20
    1878: iconst_0      
    1879: invokeinterface #9,  3            // InterfaceMethod enerj/rt/PrecisionRuntime.loadLocal:(Lenerj/rt/Reference;Z)Ljava/lang/Object;
    1884: checkcast     #22                 // class java/lang/Integer
    1887: invokevirtual #23                 // Method java/lang/Integer.intValue:()I
    1890: iconst_0      
    1891: invokeinterface #36,  4           // InterfaceMethod enerj/rt/PrecisionRuntime.loadArray:(Ljava/lang/Object;IZ)Ljava/lang/Object;
    1896: getstatic     #2                  // Field enerj/rt/PrecisionRuntimeRoot.impl:Lenerj/rt/PrecisionRuntime;
    1899: getstatic     #2                  // Field enerj/rt/PrecisionRuntimeRoot.impl:Lenerj/rt/PrecisionRuntime;
    1902: aload         24
    1904: iconst_0      
    1905: invokeinterface #9,  3            // InterfaceMethod enerj/rt/PrecisionRuntime.loadLocal:(Lenerj/rt/Reference;Z)Ljava/lang/Object;
    1910: checkcast     #22                 // class java/lang/Integer
    1913: invokevirtual #23                 // Method java/lang/Integer.intValue:()I
    1916: invokestatic  #20                 // Method java/lang/Integer.valueOf:(I)Ljava/lang/Integer;
    1919: getstatic     #2                  // Field enerj/rt/PrecisionRuntimeRoot.impl:Lenerj/rt/PrecisionRuntime;
    1922: aload         12
    1924: iconst_0      
    1925: invokeinterface #9,  3            // InterfaceMethod enerj/rt/PrecisionRuntime.loadLocal:(Lenerj/rt/Reference;Z)Ljava/lang/Object;
    1930: checkcast     #22                 // class java/lang/Integer
    1933: invokevirtual #23                 // Method java/lang/Integer.intValue:()I
    1936: invokestatic  #20                 // Method java/lang/Integer.valueOf:(I)Ljava/lang/Integer;
    1939: getstatic     #40                 // Field enerj/rt/PrecisionRuntime$ArithOperator.MINUS:Lenerj/rt/PrecisionRuntime$ArithOperator;
    1942: getstatic     #38                 // Field enerj/rt/PrecisionRuntime$NumberKind.INT:Lenerj/rt/PrecisionRuntime$NumberKind;
    1945: iconst_0      
    1946: invokeinterface #41,  6           // InterfaceMethod enerj/rt/PrecisionRuntime.binaryOp:(Ljava/lang/Number;Ljava/lang/Number;Lenerj/rt/PrecisionRuntime$ArithOperator;Lenerj/rt/PrecisionRuntime$NumberKind;Z)Ljava/lang/Number;
    1951: invokevirtual #42                 // Method java/lang/Number.intValue:()I
    1954: iconst_0      
    1955: invokeinterface #36,  4           // InterfaceMethod enerj/rt/PrecisionRuntime.loadArray:(Ljava/lang/Object;IZ)Ljava/lang/Object;
    1960: iconst_1      
    1961: iconst_1      
    1962: iconst_0      
    1963: invokestatic  #20                 // Method java/lang/Integer.valueOf:(I)Ljava/lang/Integer;
    1966: invokeinterface #35,  5           // InterfaceMethod enerj/rt/PrecisionRuntime.storeArray:(Ljava/lang/Object;IZLjava/lang/Object;)Ljava/lang/Object;
    1971: checkcast     #22                 // class java/lang/Integer
    1974: invokevirtual #23                 // Method java/lang/Integer.intValue:()I
    1977: pop           
    1978: getstatic     #2                  // Field enerj/rt/PrecisionRuntimeRoot.impl:Lenerj/rt/PrecisionRuntime;
    1981: getstatic     #2                  // Field enerj/rt/PrecisionRuntimeRoot.impl:Lenerj/rt/PrecisionRuntime;
    1984: getstatic     #2                  // Field enerj/rt/PrecisionRuntimeRoot.impl:Lenerj/rt/PrecisionRuntime;
    1987: getstatic     #2                  // Field enerj/rt/PrecisionRuntimeRoot.impl:Lenerj/rt/PrecisionRuntime;
    1990: aload         4
    1992: iconst_0      
    1993: invokeinterface #9,  3            // InterfaceMethod enerj/rt/PrecisionRuntime.loadLocal:(Lenerj/rt/Reference;Z)Ljava/lang/Object;
    1998: getstatic     #2                  // Field enerj/rt/PrecisionRuntimeRoot.impl:Lenerj/rt/PrecisionRuntime;
    2001: aload         20
    2003: iconst_0      
    2004: invokeinterface #9,  3            // InterfaceMethod enerj/rt/PrecisionRuntime.loadLocal:(Lenerj/rt/Reference;Z)Ljava/lang/Object;
    2009: checkcast     #22                 // class java/lang/Integer
    2012: invokevirtual #23                 // Method java/lang/Integer.intValue:()I
    2015: iconst_0      
    2016: invokeinterface #36,  4           // InterfaceMethod enerj/rt/PrecisionRuntime.loadArray:(Ljava/lang/Object;IZ)Ljava/lang/Object;
    2021: getstatic     #2                  // Field enerj/rt/PrecisionRuntimeRoot.impl:Lenerj/rt/PrecisionRuntime;
    2024: getstatic     #2                  // Field enerj/rt/PrecisionRuntimeRoot.impl:Lenerj/rt/PrecisionRuntime;
    2027: aload         24
    2029: iconst_0      
    2030: invokeinterface #9,  3            // InterfaceMethod enerj/rt/PrecisionRuntime.loadLocal:(Lenerj/rt/Reference;Z)Ljava/lang/Object;
    2035: checkcast     #22                 // class java/lang/Integer
    2038: invokevirtual #23                 // Method java/lang/Integer.intValue:()I
    2041: invokestatic  #20                 // Method java/lang/Integer.valueOf:(I)Ljava/lang/Integer;
    2044: getstatic     #2                  // Field enerj/rt/PrecisionRuntimeRoot.impl:Lenerj/rt/PrecisionRuntime;
    2047: aload         12
    2049: iconst_0      
    2050: invokeinterface #9,  3            // InterfaceMethod enerj/rt/PrecisionRuntime.loadLocal:(Lenerj/rt/Reference;Z)Ljava/lang/Object;
    2055: checkcast     #22                 // class java/lang/Integer
    2058: invokevirtual #23                 // Method java/lang/Integer.intValue:()I
    2061: invokestatic  #20                 // Method java/lang/Integer.valueOf:(I)Ljava/lang/Integer;
    2064: getstatic     #40                 // Field enerj/rt/PrecisionRuntime$ArithOperator.MINUS:Lenerj/rt/PrecisionRuntime$ArithOperator;
    2067: getstatic     #38                 // Field enerj/rt/PrecisionRuntime$NumberKind.INT:Lenerj/rt/PrecisionRuntime$NumberKind;
    2070: iconst_0      
    2071: invokeinterface #41,  6           // InterfaceMethod enerj/rt/PrecisionRuntime.binaryOp:(Ljava/lang/Number;Ljava/lang/Number;Lenerj/rt/PrecisionRuntime$ArithOperator;Lenerj/rt/PrecisionRuntime$NumberKind;Z)Ljava/lang/Number;
    2076: invokevirtual #42                 // Method java/lang/Number.intValue:()I
    2079: iconst_0      
    2080: invokeinterface #36,  4           // InterfaceMethod enerj/rt/PrecisionRuntime.loadArray:(Ljava/lang/Object;IZ)Ljava/lang/Object;
    2085: iconst_2      
    2086: iconst_1      
    2087: iconst_0      
    2088: invokestatic  #20                 // Method java/lang/Integer.valueOf:(I)Ljava/lang/Integer;
    2091: invokeinterface #35,  5           // InterfaceMethod enerj/rt/PrecisionRuntime.storeArray:(Ljava/lang/Object;IZLjava/lang/Object;)Ljava/lang/Object;
    2096: checkcast     #22                 // class java/lang/Integer
    2099: invokevirtual #23                 // Method java/lang/Integer.intValue:()I
    2102: pop           
    2103: goto          2718
    2106: getstatic     #2                  // Field enerj/rt/PrecisionRuntimeRoot.impl:Lenerj/rt/PrecisionRuntime;
    2109: getstatic     #2                  // Field enerj/rt/PrecisionRuntimeRoot.impl:Lenerj/rt/PrecisionRuntime;
    2112: getstatic     #2                  // Field enerj/rt/PrecisionRuntimeRoot.impl:Lenerj/rt/PrecisionRuntime;
    2115: getstatic     #2                  // Field enerj/rt/PrecisionRuntimeRoot.impl:Lenerj/rt/PrecisionRuntime;
    2118: aload         4
    2120: iconst_0      
    2121: invokeinterface #9,  3            // InterfaceMethod enerj/rt/PrecisionRuntime.loadLocal:(Lenerj/rt/Reference;Z)Ljava/lang/Object;
    2126: getstatic     #2                  // Field enerj/rt/PrecisionRuntimeRoot.impl:Lenerj/rt/PrecisionRuntime;
    2129: aload         20
    2131: iconst_0      
    2132: invokeinterface #9,  3            // InterfaceMethod enerj/rt/PrecisionRuntime.loadLocal:(Lenerj/rt/Reference;Z)Ljava/lang/Object;
    2137: checkcast     #22                 // class java/lang/Integer
    2140: invokevirtual #23                 // Method java/lang/Integer.intValue:()I
    2143: iconst_0      
    2144: invokeinterface #36,  4           // InterfaceMethod enerj/rt/PrecisionRuntime.loadArray:(Ljava/lang/Object;IZ)Ljava/lang/Object;
    2149: getstatic     #2                  // Field enerj/rt/PrecisionRuntimeRoot.impl:Lenerj/rt/PrecisionRuntime;
    2152: getstatic     #2                  // Field enerj/rt/PrecisionRuntimeRoot.impl:Lenerj/rt/PrecisionRuntime;
    2155: aload         24
    2157: iconst_0      
    2158: invokeinterface #9,  3            // InterfaceMethod enerj/rt/PrecisionRuntime.loadLocal:(Lenerj/rt/Reference;Z)Ljava/lang/Object;
    2163: checkcast     #22                 // class java/lang/Integer
    2166: invokevirtual #23                 // Method java/lang/Integer.intValue:()I
    2169: invokestatic  #20                 // Method java/lang/Integer.valueOf:(I)Ljava/lang/Integer;
    2172: getstatic     #2                  // Field enerj/rt/PrecisionRuntimeRoot.impl:Lenerj/rt/PrecisionRuntime;
    2175: aload         12
    2177: iconst_0      
    2178: invokeinterface #9,  3            // InterfaceMethod enerj/rt/PrecisionRuntime.loadLocal:(Lenerj/rt/Reference;Z)Ljava/lang/Object;
    2183: checkcast     #22                 // class java/lang/Integer
    2186: invokevirtual #23                 // Method java/lang/Integer.intValue:()I
    2189: invokestatic  #20                 // Method java/lang/Integer.valueOf:(I)Ljava/lang/Integer;
    2192: getstatic     #40                 // Field enerj/rt/PrecisionRuntime$ArithOperator.MINUS:Lenerj/rt/PrecisionRuntime$ArithOperator;
    2195: getstatic     #38                 // Field enerj/rt/PrecisionRuntime$NumberKind.INT:Lenerj/rt/PrecisionRuntime$NumberKind;
    2198: iconst_0      
    2199: invokeinterface #41,  6           // InterfaceMethod enerj/rt/PrecisionRuntime.binaryOp:(Ljava/lang/Number;Ljava/lang/Number;Lenerj/rt/PrecisionRuntime$ArithOperator;Lenerj/rt/PrecisionRuntime$NumberKind;Z)Ljava/lang/Number;
    2204: invokevirtual #42                 // Method java/lang/Number.intValue:()I
    2207: iconst_0      
    2208: invokeinterface #36,  4           // InterfaceMethod enerj/rt/PrecisionRuntime.loadArray:(Ljava/lang/Object;IZ)Ljava/lang/Object;
    2213: iconst_0      
    2214: iconst_1      
    2215: getstatic     #2                  // Field enerj/rt/PrecisionRuntimeRoot.impl:Lenerj/rt/PrecisionRuntime;
    2218: getstatic     #2                  // Field enerj/rt/PrecisionRuntimeRoot.impl:Lenerj/rt/PrecisionRuntime;
    2221: getstatic     #2                  // Field enerj/rt/PrecisionRuntimeRoot.impl:Lenerj/rt/PrecisionRuntime;
    2224: getstatic     #2                  // Field enerj/rt/PrecisionRuntimeRoot.impl:Lenerj/rt/PrecisionRuntime;
    2227: aload_0       
    2228: ldc           #26                 // String image
    2230: iconst_0      
    2231: invokeinterface #13,  4           // InterfaceMethod enerj/rt/PrecisionRuntime.loadField:(Ljava/lang/Object;Ljava/lang/String;Z)Ljava/lang/Object;
    2236: getstatic     #2                  // Field enerj/rt/PrecisionRuntimeRoot.impl:Lenerj/rt/PrecisionRuntime;
    2239: aload         22
    2241: iconst_0      
    2242: invokeinterface #9,  3            // InterfaceMethod enerj/rt/PrecisionRuntime.loadLocal:(Lenerj/rt/Reference;Z)Ljava/lang/Object;
    2247: checkcast     #22                 // class java/lang/Integer
    2250: invokevirtual #23                 // Method java/lang/Integer.intValue:()I
    2253: iconst_0      
    2254: invokeinterface #36,  4           // InterfaceMethod enerj/rt/PrecisionRuntime.loadArray:(Ljava/lang/Object;IZ)Ljava/lang/Object;
    2259: getstatic     #2                  // Field enerj/rt/PrecisionRuntimeRoot.impl:Lenerj/rt/PrecisionRuntime;
    2262: aload         24
    2264: iconst_0      
    2265: invokeinterface #9,  3            // InterfaceMethod enerj/rt/PrecisionRuntime.loadLocal:(Lenerj/rt/Reference;Z)Ljava/lang/Object;
    2270: checkcast     #22                 // class java/lang/Integer
    2273: invokevirtual #23                 // Method java/lang/Integer.intValue:()I
    2276: iconst_0      
    2277: invokeinterface #36,  4           // InterfaceMethod enerj/rt/PrecisionRuntime.loadArray:(Ljava/lang/Object;IZ)Ljava/lang/Object;
    2282: iconst_0      
    2283: iconst_0      
    2284: invokeinterface #36,  4           // InterfaceMethod enerj/rt/PrecisionRuntime.loadArray:(Ljava/lang/Object;IZ)Ljava/lang/Object;
    2289: checkcast     #22                 // class java/lang/Integer
    2292: invokevirtual #23                 // Method java/lang/Integer.intValue:()I
    2295: invokestatic  #20                 // Method java/lang/Integer.valueOf:(I)Ljava/lang/Integer;
    2298: invokeinterface #35,  5           // InterfaceMethod enerj/rt/PrecisionRuntime.storeArray:(Ljava/lang/Object;IZLjava/lang/Object;)Ljava/lang/Object;
    2303: checkcast     #22                 // class java/lang/Integer
    2306: invokevirtual #23                 // Method java/lang/Integer.intValue:()I
    2309: pop           
    2310: getstatic     #2                  // Field enerj/rt/PrecisionRuntimeRoot.impl:Lenerj/rt/PrecisionRuntime;
    2313: getstatic     #2                  // Field enerj/rt/PrecisionRuntimeRoot.impl:Lenerj/rt/PrecisionRuntime;
    2316: getstatic     #2                  // Field enerj/rt/PrecisionRuntimeRoot.impl:Lenerj/rt/PrecisionRuntime;
    2319: getstatic     #2                  // Field enerj/rt/PrecisionRuntimeRoot.impl:Lenerj/rt/PrecisionRuntime;
    2322: aload         4
    2324: iconst_0      
    2325: invokeinterface #9,  3            // InterfaceMethod enerj/rt/PrecisionRuntime.loadLocal:(Lenerj/rt/Reference;Z)Ljava/lang/Object;
    2330: getstatic     #2                  // Field enerj/rt/PrecisionRuntimeRoot.impl:Lenerj/rt/PrecisionRuntime;
    2333: aload         20
    2335: iconst_0      
    2336: invokeinterface #9,  3            // InterfaceMethod enerj/rt/PrecisionRuntime.loadLocal:(Lenerj/rt/Reference;Z)Ljava/lang/Object;
    2341: checkcast     #22                 // class java/lang/Integer
    2344: invokevirtual #23                 // Method java/lang/Integer.intValue:()I
    2347: iconst_0      
    2348: invokeinterface #36,  4           // InterfaceMethod enerj/rt/PrecisionRuntime.loadArray:(Ljava/lang/Object;IZ)Ljava/lang/Object;
    2353: getstatic     #2                  // Field enerj/rt/PrecisionRuntimeRoot.impl:Lenerj/rt/PrecisionRuntime;
    2356: getstatic     #2                  // Field enerj/rt/PrecisionRuntimeRoot.impl:Lenerj/rt/PrecisionRuntime;
    2359: aload         24
    2361: iconst_0      
    2362: invokeinterface #9,  3            // InterfaceMethod enerj/rt/PrecisionRuntime.loadLocal:(Lenerj/rt/Reference;Z)Ljava/lang/Object;
    2367: checkcast     #22                 // class java/lang/Integer
    2370: invokevirtual #23                 // Method java/lang/Integer.intValue:()I
    2373: invokestatic  #20                 // Method java/lang/Integer.valueOf:(I)Ljava/lang/Integer;
    2376: getstatic     #2                  // Field enerj/rt/PrecisionRuntimeRoot.impl:Lenerj/rt/PrecisionRuntime;
    2379: aload         12
    2381: iconst_0      
    2382: invokeinterface #9,  3            // InterfaceMethod enerj/rt/PrecisionRuntime.loadLocal:(Lenerj/rt/Reference;Z)Ljava/lang/Object;
    2387: checkcast     #22                 // class java/lang/Integer
    2390: invokevirtual #23                 // Method java/lang/Integer.intValue:()I
    2393: invokestatic  #20                 // Method java/lang/Integer.valueOf:(I)Ljava/lang/Integer;
    2396: getstatic     #40                 // Field enerj/rt/PrecisionRuntime$ArithOperator.MINUS:Lenerj/rt/PrecisionRuntime$ArithOperator;
    2399: getstatic     #38                 // Field enerj/rt/PrecisionRuntime$NumberKind.INT:Lenerj/rt/PrecisionRuntime$NumberKind;
    2402: iconst_0      
    2403: invokeinterface #41,  6           // InterfaceMethod enerj/rt/PrecisionRuntime.binaryOp:(Ljava/lang/Number;Ljava/lang/Number;Lenerj/rt/PrecisionRuntime$ArithOperator;Lenerj/rt/PrecisionRuntime$NumberKind;Z)Ljava/lang/Number;
    2408: invokevirtual #42                 // Method java/lang/Number.intValue:()I
    2411: iconst_0      
    2412: invokeinterface #36,  4           // InterfaceMethod enerj/rt/PrecisionRuntime.loadArray:(Ljava/lang/Object;IZ)Ljava/lang/Object;
    2417: iconst_1      
    2418: iconst_1      
    2419: getstatic     #2                  // Field enerj/rt/PrecisionRuntimeRoot.impl:Lenerj/rt/PrecisionRuntime;
    2422: getstatic     #2                  // Field enerj/rt/PrecisionRuntimeRoot.impl:Lenerj/rt/PrecisionRuntime;
    2425: getstatic     #2                  // Field enerj/rt/PrecisionRuntimeRoot.impl:Lenerj/rt/PrecisionRuntime;
    2428: getstatic     #2                  // Field enerj/rt/PrecisionRuntimeRoot.impl:Lenerj/rt/PrecisionRuntime;
    2431: aload_0       
    2432: ldc           #26                 // String image
    2434: iconst_0      
    2435: invokeinterface #13,  4           // InterfaceMethod enerj/rt/PrecisionRuntime.loadField:(Ljava/lang/Object;Ljava/lang/String;Z)Ljava/lang/Object;
    2440: getstatic     #2                  // Field enerj/rt/PrecisionRuntimeRoot.impl:Lenerj/rt/PrecisionRuntime;
    2443: aload         22
    2445: iconst_0      
    2446: invokeinterface #9,  3            // InterfaceMethod enerj/rt/PrecisionRuntime.loadLocal:(Lenerj/rt/Reference;Z)Ljava/lang/Object;
    2451: checkcast     #22                 // class java/lang/Integer
    2454: invokevirtual #23                 // Method java/lang/Integer.intValue:()I
    2457: iconst_0      
    2458: invokeinterface #36,  4           // InterfaceMethod enerj/rt/PrecisionRuntime.loadArray:(Ljava/lang/Object;IZ)Ljava/lang/Object;
    2463: getstatic     #2                  // Field enerj/rt/PrecisionRuntimeRoot.impl:Lenerj/rt/PrecisionRuntime;
    2466: aload         24
    2468: iconst_0      
    2469: invokeinterface #9,  3            // InterfaceMethod enerj/rt/PrecisionRuntime.loadLocal:(Lenerj/rt/Reference;Z)Ljava/lang/Object;
    2474: checkcast     #22                 // class java/lang/Integer
    2477: invokevirtual #23                 // Method java/lang/Integer.intValue:()I
    2480: iconst_0      
    2481: invokeinterface #36,  4           // InterfaceMethod enerj/rt/PrecisionRuntime.loadArray:(Ljava/lang/Object;IZ)Ljava/lang/Object;
    2486: iconst_1      
    2487: iconst_0      
    2488: invokeinterface #36,  4           // InterfaceMethod enerj/rt/PrecisionRuntime.loadArray:(Ljava/lang/Object;IZ)Ljava/lang/Object;
    2493: checkcast     #22                 // class java/lang/Integer
    2496: invokevirtual #23                 // Method java/lang/Integer.intValue:()I
    2499: invokestatic  #20                 // Method java/lang/Integer.valueOf:(I)Ljava/lang/Integer;
    2502: invokeinterface #35,  5           // InterfaceMethod enerj/rt/PrecisionRuntime.storeArray:(Ljava/lang/Object;IZLjava/lang/Object;)Ljava/lang/Object;
    2507: checkcast     #22                 // class java/lang/Integer
    2510: invokevirtual #23                 // Method java/lang/Integer.intValue:()I
    2513: pop           
    2514: getstatic     #2                  // Field enerj/rt/PrecisionRuntimeRoot.impl:Lenerj/rt/PrecisionRuntime;
    2517: getstatic     #2                  // Field enerj/rt/PrecisionRuntimeRoot.impl:Lenerj/rt/PrecisionRuntime;
    2520: getstatic     #2                  // Field enerj/rt/PrecisionRuntimeRoot.impl:Lenerj/rt/PrecisionRuntime;
    2523: getstatic     #2                  // Field enerj/rt/PrecisionRuntimeRoot.impl:Lenerj/rt/PrecisionRuntime;
    2526: aload         4
    2528: iconst_0      
    2529: invokeinterface #9,  3            // InterfaceMethod enerj/rt/PrecisionRuntime.loadLocal:(Lenerj/rt/Reference;Z)Ljava/lang/Object;
    2534: getstatic     #2                  // Field enerj/rt/PrecisionRuntimeRoot.impl:Lenerj/rt/PrecisionRuntime;
    2537: aload         20
    2539: iconst_0      
    2540: invokeinterface #9,  3            // InterfaceMethod enerj/rt/PrecisionRuntime.loadLocal:(Lenerj/rt/Reference;Z)Ljava/lang/Object;
    2545: checkcast     #22                 // class java/lang/Integer
    2548: invokevirtual #23                 // Method java/lang/Integer.intValue:()I
    2551: iconst_0      
    2552: invokeinterface #36,  4           // InterfaceMethod enerj/rt/PrecisionRuntime.loadArray:(Ljava/lang/Object;IZ)Ljava/lang/Object;
    2557: getstatic     #2                  // Field enerj/rt/PrecisionRuntimeRoot.impl:Lenerj/rt/PrecisionRuntime;
    2560: getstatic     #2                  // Field enerj/rt/PrecisionRuntimeRoot.impl:Lenerj/rt/PrecisionRuntime;
    2563: aload         24
    2565: iconst_0      
    2566: invokeinterface #9,  3            // InterfaceMethod enerj/rt/PrecisionRuntime.loadLocal:(Lenerj/rt/Reference;Z)Ljava/lang/Object;
    2571: checkcast     #22                 // class java/lang/Integer
    2574: invokevirtual #23                 // Method java/lang/Integer.intValue:()I
    2577: invokestatic  #20                 // Method java/lang/Integer.valueOf:(I)Ljava/lang/Integer;
    2580: getstatic     #2                  // Field enerj/rt/PrecisionRuntimeRoot.impl:Lenerj/rt/PrecisionRuntime;
    2583: aload         12
    2585: iconst_0      
    2586: invokeinterface #9,  3            // InterfaceMethod enerj/rt/PrecisionRuntime.loadLocal:(Lenerj/rt/Reference;Z)Ljava/lang/Object;
    2591: checkcast     #22                 // class java/lang/Integer
    2594: invokevirtual #23                 // Method java/lang/Integer.intValue:()I
    2597: invokestatic  #20                 // Method java/lang/Integer.valueOf:(I)Ljava/lang/Integer;
    2600: getstatic     #40                 // Field enerj/rt/PrecisionRuntime$ArithOperator.MINUS:Lenerj/rt/PrecisionRuntime$ArithOperator;
    2603: getstatic     #38                 // Field enerj/rt/PrecisionRuntime$NumberKind.INT:Lenerj/rt/PrecisionRuntime$NumberKind;
    2606: iconst_0      
    2607: invokeinterface #41,  6           // InterfaceMethod enerj/rt/PrecisionRuntime.binaryOp:(Ljava/lang/Number;Ljava/lang/Number;Lenerj/rt/PrecisionRuntime$ArithOperator;Lenerj/rt/PrecisionRuntime$NumberKind;Z)Ljava/lang/Number;
    2612: invokevirtual #42                 // Method java/lang/Number.intValue:()I
    2615: iconst_0      
    2616: invokeinterface #36,  4           // InterfaceMethod enerj/rt/PrecisionRuntime.loadArray:(Ljava/lang/Object;IZ)Ljava/lang/Object;
    2621: iconst_2      
    2622: iconst_1      
    2623: getstatic     #2                  // Field enerj/rt/PrecisionRuntimeRoot.impl:Lenerj/rt/PrecisionRuntime;
    2626: getstatic     #2                  // Field enerj/rt/PrecisionRuntimeRoot.impl:Lenerj/rt/PrecisionRuntime;
    2629: getstatic     #2                  // Field enerj/rt/PrecisionRuntimeRoot.impl:Lenerj/rt/PrecisionRuntime;
    2632: getstatic     #2                  // Field enerj/rt/PrecisionRuntimeRoot.impl:Lenerj/rt/PrecisionRuntime;
    2635: aload_0       
    2636: ldc           #26                 // String image
    2638: iconst_0      
    2639: invokeinterface #13,  4           // InterfaceMethod enerj/rt/PrecisionRuntime.loadField:(Ljava/lang/Object;Ljava/lang/String;Z)Ljava/lang/Object;
    2644: getstatic     #2                  // Field enerj/rt/PrecisionRuntimeRoot.impl:Lenerj/rt/PrecisionRuntime;
    2647: aload         22
    2649: iconst_0      
    2650: invokeinterface #9,  3            // InterfaceMethod enerj/rt/PrecisionRuntime.loadLocal:(Lenerj/rt/Reference;Z)Ljava/lang/Object;
    2655: checkcast     #22                 // class java/lang/Integer
    2658: invokevirtual #23                 // Method java/lang/Integer.intValue:()I
    2661: iconst_0      
    2662: invokeinterface #36,  4           // InterfaceMethod enerj/rt/PrecisionRuntime.loadArray:(Ljava/lang/Object;IZ)Ljava/lang/Object;
    2667: getstatic     #2                  // Field enerj/rt/PrecisionRuntimeRoot.impl:Lenerj/rt/PrecisionRuntime;
    2670: aload         24
    2672: iconst_0      
    2673: invokeinterface #9,  3            // InterfaceMethod enerj/rt/PrecisionRuntime.loadLocal:(Lenerj/rt/Reference;Z)Ljava/lang/Object;
    2678: checkcast     #22                 // class java/lang/Integer
    2681: invokevirtual #23                 // Method java/lang/Integer.intValue:()I
    2684: iconst_0      
    2685: invokeinterface #36,  4           // InterfaceMethod enerj/rt/PrecisionRuntime.loadArray:(Ljava/lang/Object;IZ)Ljava/lang/Object;
    2690: iconst_2      
    2691: iconst_0      
    2692: invokeinterface #36,  4           // InterfaceMethod enerj/rt/PrecisionRuntime.loadArray:(Ljava/lang/Object;IZ)Ljava/lang/Object;
    2697: checkcast     #22                 // class java/lang/Integer
    2700: invokevirtual #23                 // Method java/lang/Integer.intValue:()I
    2703: invokestatic  #20                 // Method java/lang/Integer.valueOf:(I)Ljava/lang/Integer;
    2706: invokeinterface #35,  5           // InterfaceMethod enerj/rt/PrecisionRuntime.storeArray:(Ljava/lang/Object;IZLjava/lang/Object;)Ljava/lang/Object;
    2711: checkcast     #22                 // class java/lang/Integer
    2714: invokevirtual #23                 // Method java/lang/Integer.intValue:()I
    2717: pop           
    2718: getstatic     #2                  // Field enerj/rt/PrecisionRuntimeRoot.impl:Lenerj/rt/PrecisionRuntime;
    2721: aload         24
    2723: getstatic     #37                 // Field enerj/rt/PrecisionRuntime$ArithOperator.PLUS:Lenerj/rt/PrecisionRuntime$ArithOperator;
    2726: iconst_1      
    2727: invokestatic  #20                 // Method java/lang/Integer.valueOf:(I)Ljava/lang/Integer;
    2730: iconst_0      
    2731: getstatic     #38                 // Field enerj/rt/PrecisionRuntime$NumberKind.INT:Lenerj/rt/PrecisionRuntime$NumberKind;
    2734: iconst_0      
    2735: invokeinterface #39,  7           // InterfaceMethod enerj/rt/PrecisionRuntime.assignopLocal:(Lenerj/rt/Reference;Lenerj/rt/PrecisionRuntime$ArithOperator;Ljava/lang/Number;ZLenerj/rt/PrecisionRuntime$NumberKind;Z)Ljava/lang/Number;
    2740: pop           
    2741: goto          1533
    2744: getstatic     #2                  // Field enerj/rt/PrecisionRuntimeRoot.impl:Lenerj/rt/PrecisionRuntime;
    2747: aload         20
    2749: getstatic     #37                 // Field enerj/rt/PrecisionRuntime$ArithOperator.PLUS:Lenerj/rt/PrecisionRuntime$ArithOperator;
    2752: iconst_1      
    2753: invokestatic  #20                 // Method java/lang/Integer.valueOf:(I)Ljava/lang/Integer;
    2756: iconst_1      
    2757: getstatic     #38                 // Field enerj/rt/PrecisionRuntime$NumberKind.INT:Lenerj/rt/PrecisionRuntime$NumberKind;
    2760: iconst_0      
    2761: invokeinterface #39,  7           // InterfaceMethod enerj/rt/PrecisionRuntime.assignopLocal:(Lenerj/rt/Reference;Lenerj/rt/PrecisionRuntime$ArithOperator;Ljava/lang/Number;ZLenerj/rt/PrecisionRuntime$NumberKind;Z)Ljava/lang/Number;
    2766: pop           
    2767: getstatic     #2                  // Field enerj/rt/PrecisionRuntimeRoot.impl:Lenerj/rt/PrecisionRuntime;
    2770: aload         22
    2772: getstatic     #37                 // Field enerj/rt/PrecisionRuntime$ArithOperator.PLUS:Lenerj/rt/PrecisionRuntime$ArithOperator;
    2775: iconst_1      
    2776: invokestatic  #20                 // Method java/lang/Integer.valueOf:(I)Ljava/lang/Integer;
    2779: iconst_0      
    2780: getstatic     #38                 // Field enerj/rt/PrecisionRuntime$NumberKind.INT:Lenerj/rt/PrecisionRuntime$NumberKind;
    2783: iconst_0      
    2784: invokeinterface #39,  7           // InterfaceMethod enerj/rt/PrecisionRuntime.assignopLocal:(Lenerj/rt/Reference;Lenerj/rt/PrecisionRuntime$ArithOperator;Ljava/lang/Number;ZLenerj/rt/PrecisionRuntime$NumberKind;Z)Ljava/lang/Number;
    2789: pop           
    2790: goto          760
    2793: return        

  public static double sqrt(double);
    Code:
       0: new           #4                  // class enerj/rt/Reference
       3: dup           
       4: dload_0       
       5: invokestatic  #46                 // Method java/lang/Double.valueOf:(D)Ljava/lang/Double;
       8: iconst_1      
       9: iconst_1      
      10: invokespecial #5                  // Method enerj/rt/Reference."<init>":(Ljava/lang/Object;ZZ)V
      13: astore_2      
      14: getstatic     #2                  // Field enerj/rt/PrecisionRuntimeRoot.impl:Lenerj/rt/PrecisionRuntime;
      17: aload_2       
      18: iconst_1      
      19: invokeinterface #9,  3            // InterfaceMethod enerj/rt/PrecisionRuntime.loadLocal:(Lenerj/rt/Reference;Z)Ljava/lang/Object;
      24: checkcast     #50                 // class java/lang/Double
      27: invokevirtual #51                 // Method java/lang/Double.doubleValue:()D
      30: invokestatic  #52                 // Method enerj/lang/Endorsements.endorse:(D)D
      33: invokestatic  #53                 // Method java/lang/Math.sqrt:(D)D
      36: dreturn       

  public double sobel(int[][][]);
    Code:
       0: new           #4                  // class enerj/rt/Reference
       3: dup           
       4: aload_1       
       5: iconst_0      
       6: iconst_0      
       7: invokespecial #5                  // Method enerj/rt/Reference."<init>":(Ljava/lang/Object;ZZ)V
      10: astore_2      
      11: getstatic     #2                  // Field enerj/rt/PrecisionRuntimeRoot.impl:Lenerj/rt/PrecisionRuntime;
      14: aload_0       
      15: getstatic     #2                  // Field enerj/rt/PrecisionRuntimeRoot.impl:Lenerj/rt/PrecisionRuntime;
      18: getstatic     #2                  // Field enerj/rt/PrecisionRuntimeRoot.impl:Lenerj/rt/PrecisionRuntime;
      21: getstatic     #2                  // Field enerj/rt/PrecisionRuntimeRoot.impl:Lenerj/rt/PrecisionRuntime;
      24: aload_2       
      25: iconst_0      
      26: invokeinterface #9,  3            // InterfaceMethod enerj/rt/PrecisionRuntime.loadLocal:(Lenerj/rt/Reference;Z)Ljava/lang/Object;
      31: iconst_0      
      32: iconst_0      
      33: invokeinterface #36,  4           // InterfaceMethod enerj/rt/PrecisionRuntime.loadArray:(Ljava/lang/Object;IZ)Ljava/lang/Object;
      38: iconst_0      
      39: iconst_0      
      40: invokeinterface #36,  4           // InterfaceMethod enerj/rt/PrecisionRuntime.loadArray:(Ljava/lang/Object;IZ)Ljava/lang/Object;
      45: checkcast     #34                 // class "[I"
      48: invokevirtual #54                 // Method luminance:([I)I
      51: i2d           
      52: invokestatic  #46                 // Method java/lang/Double.valueOf:(D)Ljava/lang/Double;
      55: iconst_1      
      56: getstatic     #16                 // Field enerj/rt/PrecisionRuntime$MemKind.VARIABLE:Lenerj/rt/PrecisionRuntime$MemKind;
      59: invokeinterface #17,  4           // InterfaceMethod enerj/rt/PrecisionRuntime.storeValue:(Ljava/lang/Object;ZLenerj/rt/PrecisionRuntime$MemKind;)Ljava/lang/Object;
      64: checkcast     #50                 // class java/lang/Double
      67: invokevirtual #51                 // Method java/lang/Double.doubleValue:()D
      70: dstore_3      
      71: new           #4                  // class enerj/rt/Reference
      74: dup           
      75: dload_3       
      76: invokestatic  #46                 // Method java/lang/Double.valueOf:(D)Ljava/lang/Double;
      79: iconst_1      
      80: iconst_1      
      81: invokespecial #5                  // Method enerj/rt/Reference."<init>":(Ljava/lang/Object;ZZ)V
      84: astore        5
      86: getstatic     #2                  // Field enerj/rt/PrecisionRuntimeRoot.impl:Lenerj/rt/PrecisionRuntime;
      89: aload_0       
      90: getstatic     #2                  // Field enerj/rt/PrecisionRuntimeRoot.impl:Lenerj/rt/PrecisionRuntime;
      93: getstatic     #2                  // Field enerj/rt/PrecisionRuntimeRoot.impl:Lenerj/rt/PrecisionRuntime;
      96: getstatic     #2                  // Field enerj/rt/PrecisionRuntimeRoot.impl:Lenerj/rt/PrecisionRuntime;
      99: aload_2       
     100: iconst_0      
     101: invokeinterface #9,  3            // InterfaceMethod enerj/rt/PrecisionRuntime.loadLocal:(Lenerj/rt/Reference;Z)Ljava/lang/Object;
     106: iconst_0      
     107: iconst_0      
     108: invokeinterface #36,  4           // InterfaceMethod enerj/rt/PrecisionRuntime.loadArray:(Ljava/lang/Object;IZ)Ljava/lang/Object;
     113: iconst_1      
     114: iconst_0      
     115: invokeinterface #36,  4           // InterfaceMethod enerj/rt/PrecisionRuntime.loadArray:(Ljava/lang/Object;IZ)Ljava/lang/Object;
     120: checkcast     #34                 // class "[I"
     123: invokevirtual #54                 // Method luminance:([I)I
     126: i2d           
     127: invokestatic  #46                 // Method java/lang/Double.valueOf:(D)Ljava/lang/Double;
     130: iconst_1      
     131: getstatic     #16                 // Field enerj/rt/PrecisionRuntime$MemKind.VARIABLE:Lenerj/rt/PrecisionRuntime$MemKind;
     134: invokeinterface #17,  4           // InterfaceMethod enerj/rt/PrecisionRuntime.storeValue:(Ljava/lang/Object;ZLenerj/rt/PrecisionRuntime$MemKind;)Ljava/lang/Object;
     139: checkcast     #50                 // class java/lang/Double
     142: invokevirtual #51                 // Method java/lang/Double.doubleValue:()D
     145: dstore        6
     147: new           #4                  // class enerj/rt/Reference
     150: dup           
     151: dload         6
     153: invokestatic  #46                 // Method java/lang/Double.valueOf:(D)Ljava/lang/Double;
     156: iconst_1      
     157: iconst_1      
     158: invokespecial #5                  // Method enerj/rt/Reference."<init>":(Ljava/lang/Object;ZZ)V
     161: astore        8
     163: getstatic     #2                  // Field enerj/rt/PrecisionRuntimeRoot.impl:Lenerj/rt/PrecisionRuntime;
     166: aload_0       
     167: getstatic     #2                  // Field enerj/rt/PrecisionRuntimeRoot.impl:Lenerj/rt/PrecisionRuntime;
     170: getstatic     #2                  // Field enerj/rt/PrecisionRuntimeRoot.impl:Lenerj/rt/PrecisionRuntime;
     173: getstatic     #2                  // Field enerj/rt/PrecisionRuntimeRoot.impl:Lenerj/rt/PrecisionRuntime;
     176: aload_2       
     177: iconst_0      
     178: invokeinterface #9,  3            // InterfaceMethod enerj/rt/PrecisionRuntime.loadLocal:(Lenerj/rt/Reference;Z)Ljava/lang/Object;
     183: iconst_0      
     184: iconst_0      
     185: invokeinterface #36,  4           // InterfaceMethod enerj/rt/PrecisionRuntime.loadArray:(Ljava/lang/Object;IZ)Ljava/lang/Object;
     190: iconst_2      
     191: iconst_0      
     192: invokeinterface #36,  4           // InterfaceMethod enerj/rt/PrecisionRuntime.loadArray:(Ljava/lang/Object;IZ)Ljava/lang/Object;
     197: checkcast     #34                 // class "[I"
     200: invokevirtual #54                 // Method luminance:([I)I
     203: i2d           
     204: invokestatic  #46                 // Method java/lang/Double.valueOf:(D)Ljava/lang/Double;
     207: iconst_1      
     208: getstatic     #16                 // Field enerj/rt/PrecisionRuntime$MemKind.VARIABLE:Lenerj/rt/PrecisionRuntime$MemKind;
     211: invokeinterface #17,  4           // InterfaceMethod enerj/rt/PrecisionRuntime.storeValue:(Ljava/lang/Object;ZLenerj/rt/PrecisionRuntime$MemKind;)Ljava/lang/Object;
     216: checkcast     #50                 // class java/lang/Double
     219: invokevirtual #51                 // Method java/lang/Double.doubleValue:()D
     222: dstore        9
     224: new           #4                  // class enerj/rt/Reference
     227: dup           
     228: dload         9
     230: invokestatic  #46                 // Method java/lang/Double.valueOf:(D)Ljava/lang/Double;
     233: iconst_1      
     234: iconst_1      
     235: invokespecial #5                  // Method enerj/rt/Reference."<init>":(Ljava/lang/Object;ZZ)V
     238: astore        11
     240: getstatic     #2                  // Field enerj/rt/PrecisionRuntimeRoot.impl:Lenerj/rt/PrecisionRuntime;
     243: aload_0       
     244: getstatic     #2                  // Field enerj/rt/PrecisionRuntimeRoot.impl:Lenerj/rt/PrecisionRuntime;
     247: getstatic     #2                  // Field enerj/rt/PrecisionRuntimeRoot.impl:Lenerj/rt/PrecisionRuntime;
     250: getstatic     #2                  // Field enerj/rt/PrecisionRuntimeRoot.impl:Lenerj/rt/PrecisionRuntime;
     253: aload_2       
     254: iconst_0      
     255: invokeinterface #9,  3            // InterfaceMethod enerj/rt/PrecisionRuntime.loadLocal:(Lenerj/rt/Reference;Z)Ljava/lang/Object;
     260: iconst_1      
     261: iconst_0      
     262: invokeinterface #36,  4           // InterfaceMethod enerj/rt/PrecisionRuntime.loadArray:(Ljava/lang/Object;IZ)Ljava/lang/Object;
     267: iconst_0      
     268: iconst_0      
     269: invokeinterface #36,  4           // InterfaceMethod enerj/rt/PrecisionRuntime.loadArray:(Ljava/lang/Object;IZ)Ljava/lang/Object;
     274: checkcast     #34                 // class "[I"
     277: invokevirtual #54                 // Method luminance:([I)I
     280: i2d           
     281: invokestatic  #46                 // Method java/lang/Double.valueOf:(D)Ljava/lang/Double;
     284: iconst_1      
     285: getstatic     #16                 // Field enerj/rt/PrecisionRuntime$MemKind.VARIABLE:Lenerj/rt/PrecisionRuntime$MemKind;
     288: invokeinterface #17,  4           // InterfaceMethod enerj/rt/PrecisionRuntime.storeValue:(Ljava/lang/Object;ZLenerj/rt/PrecisionRuntime$MemKind;)Ljava/lang/Object;
     293: checkcast     #50                 // class java/lang/Double
     296: invokevirtual #51                 // Method java/lang/Double.doubleValue:()D
     299: dstore        12
     301: new           #4                  // class enerj/rt/Reference
     304: dup           
     305: dload         12
     307: invokestatic  #46                 // Method java/lang/Double.valueOf:(D)Ljava/lang/Double;
     310: iconst_1      
     311: iconst_1      
     312: invokespecial #5                  // Method enerj/rt/Reference."<init>":(Ljava/lang/Object;ZZ)V
     315: astore        14
     317: getstatic     #2                  // Field enerj/rt/PrecisionRuntimeRoot.impl:Lenerj/rt/PrecisionRuntime;
     320: aload_0       
     321: getstatic     #2                  // Field enerj/rt/PrecisionRuntimeRoot.impl:Lenerj/rt/PrecisionRuntime;
     324: getstatic     #2                  // Field enerj/rt/PrecisionRuntimeRoot.impl:Lenerj/rt/PrecisionRuntime;
     327: getstatic     #2                  // Field enerj/rt/PrecisionRuntimeRoot.impl:Lenerj/rt/PrecisionRuntime;
     330: aload_2       
     331: iconst_0      
     332: invokeinterface #9,  3            // InterfaceMethod enerj/rt/PrecisionRuntime.loadLocal:(Lenerj/rt/Reference;Z)Ljava/lang/Object;
     337: iconst_1      
     338: iconst_0      
     339: invokeinterface #36,  4           // InterfaceMethod enerj/rt/PrecisionRuntime.loadArray:(Ljava/lang/Object;IZ)Ljava/lang/Object;
     344: iconst_1      
     345: iconst_0      
     346: invokeinterface #36,  4           // InterfaceMethod enerj/rt/PrecisionRuntime.loadArray:(Ljava/lang/Object;IZ)Ljava/lang/Object;
     351: checkcast     #34                 // class "[I"
     354: invokevirtual #54                 // Method luminance:([I)I
     357: i2d           
     358: invokestatic  #46                 // Method java/lang/Double.valueOf:(D)Ljava/lang/Double;
     361: iconst_1      
     362: getstatic     #16                 // Field enerj/rt/PrecisionRuntime$MemKind.VARIABLE:Lenerj/rt/PrecisionRuntime$MemKind;
     365: invokeinterface #17,  4           // InterfaceMethod enerj/rt/PrecisionRuntime.storeValue:(Ljava/lang/Object;ZLenerj/rt/PrecisionRuntime$MemKind;)Ljava/lang/Object;
     370: checkcast     #50                 // class java/lang/Double
     373: invokevirtual #51                 // Method java/lang/Double.doubleValue:()D
     376: dstore        15
     378: new           #4                  // class enerj/rt/Reference
     381: dup           
     382: dload         15
     384: invokestatic  #46                 // Method java/lang/Double.valueOf:(D)Ljava/lang/Double;
     387: iconst_1      
     388: iconst_1      
     389: invokespecial #5                  // Method enerj/rt/Reference."<init>":(Ljava/lang/Object;ZZ)V
     392: astore        17
     394: getstatic     #2                  // Field enerj/rt/PrecisionRuntimeRoot.impl:Lenerj/rt/PrecisionRuntime;
     397: aload_0       
     398: getstatic     #2                  // Field enerj/rt/PrecisionRuntimeRoot.impl:Lenerj/rt/PrecisionRuntime;
     401: getstatic     #2                  // Field enerj/rt/PrecisionRuntimeRoot.impl:Lenerj/rt/PrecisionRuntime;
     404: getstatic     #2                  // Field enerj/rt/PrecisionRuntimeRoot.impl:Lenerj/rt/PrecisionRuntime;
     407: aload_2       
     408: iconst_0      
     409: invokeinterface #9,  3            // InterfaceMethod enerj/rt/PrecisionRuntime.loadLocal:(Lenerj/rt/Reference;Z)Ljava/lang/Object;
     414: iconst_1      
     415: iconst_0      
     416: invokeinterface #36,  4           // InterfaceMethod enerj/rt/PrecisionRuntime.loadArray:(Ljava/lang/Object;IZ)Ljava/lang/Object;
     421: iconst_2      
     422: iconst_0      
     423: invokeinterface #36,  4           // InterfaceMethod enerj/rt/PrecisionRuntime.loadArray:(Ljava/lang/Object;IZ)Ljava/lang/Object;
     428: checkcast     #34                 // class "[I"
     431: invokevirtual #54                 // Method luminance:([I)I
     434: i2d           
     435: invokestatic  #46                 // Method java/lang/Double.valueOf:(D)Ljava/lang/Double;
     438: iconst_1      
     439: getstatic     #16                 // Field enerj/rt/PrecisionRuntime$MemKind.VARIABLE:Lenerj/rt/PrecisionRuntime$MemKind;
     442: invokeinterface #17,  4           // InterfaceMethod enerj/rt/PrecisionRuntime.storeValue:(Ljava/lang/Object;ZLenerj/rt/PrecisionRuntime$MemKind;)Ljava/lang/Object;
     447: checkcast     #50                 // class java/lang/Double
     450: invokevirtual #51                 // Method java/lang/Double.doubleValue:()D
     453: dstore        18
     455: new           #4                  // class enerj/rt/Reference
     458: dup           
     459: dload         18
     461: invokestatic  #46                 // Method java/lang/Double.valueOf:(D)Ljava/lang/Double;
     464: iconst_1      
     465: iconst_1      
     466: invokespecial #5                  // Method enerj/rt/Reference."<init>":(Ljava/lang/Object;ZZ)V
     469: astore        20
     471: getstatic     #2                  // Field enerj/rt/PrecisionRuntimeRoot.impl:Lenerj/rt/PrecisionRuntime;
     474: aload_0       
     475: getstatic     #2                  // Field enerj/rt/PrecisionRuntimeRoot.impl:Lenerj/rt/PrecisionRuntime;
     478: getstatic     #2                  // Field enerj/rt/PrecisionRuntimeRoot.impl:Lenerj/rt/PrecisionRuntime;
     481: getstatic     #2                  // Field enerj/rt/PrecisionRuntimeRoot.impl:Lenerj/rt/PrecisionRuntime;
     484: aload_2       
     485: iconst_0      
     486: invokeinterface #9,  3            // InterfaceMethod enerj/rt/PrecisionRuntime.loadLocal:(Lenerj/rt/Reference;Z)Ljava/lang/Object;
     491: iconst_2      
     492: iconst_0      
     493: invokeinterface #36,  4           // InterfaceMethod enerj/rt/PrecisionRuntime.loadArray:(Ljava/lang/Object;IZ)Ljava/lang/Object;
     498: iconst_0      
     499: iconst_0      
     500: invokeinterface #36,  4           // InterfaceMethod enerj/rt/PrecisionRuntime.loadArray:(Ljava/lang/Object;IZ)Ljava/lang/Object;
     505: checkcast     #34                 // class "[I"
     508: invokevirtual #54                 // Method luminance:([I)I
     511: i2d           
     512: invokestatic  #46                 // Method java/lang/Double.valueOf:(D)Ljava/lang/Double;
     515: iconst_1      
     516: getstatic     #16                 // Field enerj/rt/PrecisionRuntime$MemKind.VARIABLE:Lenerj/rt/PrecisionRuntime$MemKind;
     519: invokeinterface #17,  4           // InterfaceMethod enerj/rt/PrecisionRuntime.storeValue:(Ljava/lang/Object;ZLenerj/rt/PrecisionRuntime$MemKind;)Ljava/lang/Object;
     524: checkcast     #50                 // class java/lang/Double
     527: invokevirtual #51                 // Method java/lang/Double.doubleValue:()D
     530: dstore        21
     532: new           #4                  // class enerj/rt/Reference
     535: dup           
     536: dload         21
     538: invokestatic  #46                 // Method java/lang/Double.valueOf:(D)Ljava/lang/Double;
     541: iconst_1      
     542: iconst_1      
     543: invokespecial #5                  // Method enerj/rt/Reference."<init>":(Ljava/lang/Object;ZZ)V
     546: astore        23
     548: getstatic     #2                  // Field enerj/rt/PrecisionRuntimeRoot.impl:Lenerj/rt/PrecisionRuntime;
     551: aload_0       
     552: getstatic     #2                  // Field enerj/rt/PrecisionRuntimeRoot.impl:Lenerj/rt/PrecisionRuntime;
     555: getstatic     #2                  // Field enerj/rt/PrecisionRuntimeRoot.impl:Lenerj/rt/PrecisionRuntime;
     558: getstatic     #2                  // Field enerj/rt/PrecisionRuntimeRoot.impl:Lenerj/rt/PrecisionRuntime;
     561: aload_2       
     562: iconst_0      
     563: invokeinterface #9,  3            // InterfaceMethod enerj/rt/PrecisionRuntime.loadLocal:(Lenerj/rt/Reference;Z)Ljava/lang/Object;
     568: iconst_2      
     569: iconst_0      
     570: invokeinterface #36,  4           // InterfaceMethod enerj/rt/PrecisionRuntime.loadArray:(Ljava/lang/Object;IZ)Ljava/lang/Object;
     575: iconst_1      
     576: iconst_0      
     577: invokeinterface #36,  4           // InterfaceMethod enerj/rt/PrecisionRuntime.loadArray:(Ljava/lang/Object;IZ)Ljava/lang/Object;
     582: checkcast     #34                 // class "[I"
     585: invokevirtual #54                 // Method luminance:([I)I
     588: i2d           
     589: invokestatic  #46                 // Method java/lang/Double.valueOf:(D)Ljava/lang/Double;
     592: iconst_1      
     593: getstatic     #16                 // Field enerj/rt/PrecisionRuntime$MemKind.VARIABLE:Lenerj/rt/PrecisionRuntime$MemKind;
     596: invokeinterface #17,  4           // InterfaceMethod enerj/rt/PrecisionRuntime.storeValue:(Ljava/lang/Object;ZLenerj/rt/PrecisionRuntime$MemKind;)Ljava/lang/Object;
     601: checkcast     #50                 // class java/lang/Double
     604: invokevirtual #51                 // Method java/lang/Double.doubleValue:()D
     607: dstore        24
     609: new           #4                  // class enerj/rt/Reference
     612: dup           
     613: dload         24
     615: invokestatic  #46                 // Method java/lang/Double.valueOf:(D)Ljava/lang/Double;
     618: iconst_1      
     619: iconst_1      
     620: invokespecial #5                  // Method enerj/rt/Reference."<init>":(Ljava/lang/Object;ZZ)V
     623: astore        26
     625: getstatic     #2                  // Field enerj/rt/PrecisionRuntimeRoot.impl:Lenerj/rt/PrecisionRuntime;
     628: aload_0       
     629: getstatic     #2                  // Field enerj/rt/PrecisionRuntimeRoot.impl:Lenerj/rt/PrecisionRuntime;
     632: getstatic     #2                  // Field enerj/rt/PrecisionRuntimeRoot.impl:Lenerj/rt/PrecisionRuntime;
     635: getstatic     #2                  // Field enerj/rt/PrecisionRuntimeRoot.impl:Lenerj/rt/PrecisionRuntime;
     638: aload_2       
     639: iconst_0      
     640: invokeinterface #9,  3            // InterfaceMethod enerj/rt/PrecisionRuntime.loadLocal:(Lenerj/rt/Reference;Z)Ljava/lang/Object;
     645: iconst_2      
     646: iconst_0      
     647: invokeinterface #36,  4           // InterfaceMethod enerj/rt/PrecisionRuntime.loadArray:(Ljava/lang/Object;IZ)Ljava/lang/Object;
     652: iconst_2      
     653: iconst_0      
     654: invokeinterface #36,  4           // InterfaceMethod enerj/rt/PrecisionRuntime.loadArray:(Ljava/lang/Object;IZ)Ljava/lang/Object;
     659: checkcast     #34                 // class "[I"
     662: invokevirtual #54                 // Method luminance:([I)I
     665: i2d           
     666: invokestatic  #46                 // Method java/lang/Double.valueOf:(D)Ljava/lang/Double;
     669: iconst_1      
     670: getstatic     #16                 // Field enerj/rt/PrecisionRuntime$MemKind.VARIABLE:Lenerj/rt/PrecisionRuntime$MemKind;
     673: invokeinterface #17,  4           // InterfaceMethod enerj/rt/PrecisionRuntime.storeValue:(Ljava/lang/Object;ZLenerj/rt/PrecisionRuntime$MemKind;)Ljava/lang/Object;
     678: checkcast     #50                 // class java/lang/Double
     681: invokevirtual #51                 // Method java/lang/Double.doubleValue:()D
     684: dstore        27
     686: new           #4                  // class enerj/rt/Reference
     689: dup           
     690: dload         27
     692: invokestatic  #46                 // Method java/lang/Double.valueOf:(D)Ljava/lang/Double;
     695: iconst_1      
     696: iconst_1      
     697: invokespecial #5                  // Method enerj/rt/Reference."<init>":(Ljava/lang/Object;ZZ)V
     700: astore        29
     702: getstatic     #2                  // Field enerj/rt/PrecisionRuntimeRoot.impl:Lenerj/rt/PrecisionRuntime;
     705: getstatic     #2                  // Field enerj/rt/PrecisionRuntimeRoot.impl:Lenerj/rt/PrecisionRuntime;
     708: getstatic     #2                  // Field enerj/rt/PrecisionRuntimeRoot.impl:Lenerj/rt/PrecisionRuntime;
     711: getstatic     #2                  // Field enerj/rt/PrecisionRuntimeRoot.impl:Lenerj/rt/PrecisionRuntime;
     714: getstatic     #2                  // Field enerj/rt/PrecisionRuntimeRoot.impl:Lenerj/rt/PrecisionRuntime;
     717: getstatic     #2                  // Field enerj/rt/PrecisionRuntimeRoot.impl:Lenerj/rt/PrecisionRuntime;
     720: getstatic     #2                  // Field enerj/rt/PrecisionRuntimeRoot.impl:Lenerj/rt/PrecisionRuntime;
     723: aload         5
     725: iconst_1      
     726: invokeinterface #9,  3            // InterfaceMethod enerj/rt/PrecisionRuntime.loadLocal:(Lenerj/rt/Reference;Z)Ljava/lang/Object;
     731: checkcast     #50                 // class java/lang/Double
     734: invokevirtual #51                 // Method java/lang/Double.doubleValue:()D
     737: invokestatic  #46                 // Method java/lang/Double.valueOf:(D)Ljava/lang/Double;
     740: getstatic     #2                  // Field enerj/rt/PrecisionRuntimeRoot.impl:Lenerj/rt/PrecisionRuntime;
     743: getstatic     #2                  // Field enerj/rt/PrecisionRuntimeRoot.impl:Lenerj/rt/PrecisionRuntime;
     746: aload         8
     748: iconst_1      
     749: invokeinterface #9,  3            // InterfaceMethod enerj/rt/PrecisionRuntime.loadLocal:(Lenerj/rt/Reference;Z)Ljava/lang/Object;
     754: checkcast     #50                 // class java/lang/Double
     757: invokevirtual #51                 // Method java/lang/Double.doubleValue:()D
     760: invokestatic  #46                 // Method java/lang/Double.valueOf:(D)Ljava/lang/Double;
     763: getstatic     #2                  // Field enerj/rt/PrecisionRuntimeRoot.impl:Lenerj/rt/PrecisionRuntime;
     766: aload         8
     768: iconst_1      
     769: invokeinterface #9,  3            // InterfaceMethod enerj/rt/PrecisionRuntime.loadLocal:(Lenerj/rt/Reference;Z)Ljava/lang/Object;
     774: checkcast     #50                 // class java/lang/Double
     777: invokevirtual #51                 // Method java/lang/Double.doubleValue:()D
     780: invokestatic  #46                 // Method java/lang/Double.valueOf:(D)Ljava/lang/Double;
     783: getstatic     #37                 // Field enerj/rt/PrecisionRuntime$ArithOperator.PLUS:Lenerj/rt/PrecisionRuntime$ArithOperator;
     786: getstatic     #48                 // Field enerj/rt/PrecisionRuntime$NumberKind.DOUBLE:Lenerj/rt/PrecisionRuntime$NumberKind;
     789: iconst_1      
     790: invokeinterface #41,  6           // InterfaceMethod enerj/rt/PrecisionRuntime.binaryOp:(Ljava/lang/Number;Ljava/lang/Number;Lenerj/rt/PrecisionRuntime$ArithOperator;Lenerj/rt/PrecisionRuntime$NumberKind;Z)Ljava/lang/Number;
     795: invokevirtual #49                 // Method java/lang/Number.doubleValue:()D
     798: invokestatic  #46                 // Method java/lang/Double.valueOf:(D)Ljava/lang/Double;
     801: getstatic     #37                 // Field enerj/rt/PrecisionRuntime$ArithOperator.PLUS:Lenerj/rt/PrecisionRuntime$ArithOperator;
     804: getstatic     #48                 // Field enerj/rt/PrecisionRuntime$NumberKind.DOUBLE:Lenerj/rt/PrecisionRuntime$NumberKind;
     807: iconst_1      
     808: invokeinterface #41,  6           // InterfaceMethod enerj/rt/PrecisionRuntime.binaryOp:(Ljava/lang/Number;Ljava/lang/Number;Lenerj/rt/PrecisionRuntime$ArithOperator;Lenerj/rt/PrecisionRuntime$NumberKind;Z)Ljava/lang/Number;
     813: invokevirtual #49                 // Method java/lang/Number.doubleValue:()D
     816: invokestatic  #46                 // Method java/lang/Double.valueOf:(D)Ljava/lang/Double;
     819: getstatic     #2                  // Field enerj/rt/PrecisionRuntimeRoot.impl:Lenerj/rt/PrecisionRuntime;
     822: aload         11
     824: iconst_1      
     825: invokeinterface #9,  3            // InterfaceMethod enerj/rt/PrecisionRuntime.loadLocal:(Lenerj/rt/Reference;Z)Ljava/lang/Object;
     830: checkcast     #50                 // class java/lang/Double
     833: invokevirtual #51                 // Method java/lang/Double.doubleValue:()D
     836: invokestatic  #46                 // Method java/lang/Double.valueOf:(D)Ljava/lang/Double;
     839: getstatic     #37                 // Field enerj/rt/PrecisionRuntime$ArithOperator.PLUS:Lenerj/rt/PrecisionRuntime$ArithOperator;
     842: getstatic     #48                 // Field enerj/rt/PrecisionRuntime$NumberKind.DOUBLE:Lenerj/rt/PrecisionRuntime$NumberKind;
     845: iconst_1      
     846: invokeinterface #41,  6           // InterfaceMethod enerj/rt/PrecisionRuntime.binaryOp:(Ljava/lang/Number;Ljava/lang/Number;Lenerj/rt/PrecisionRuntime$ArithOperator;Lenerj/rt/PrecisionRuntime$NumberKind;Z)Ljava/lang/Number;
     851: invokevirtual #49                 // Method java/lang/Number.doubleValue:()D
     854: invokestatic  #46                 // Method java/lang/Double.valueOf:(D)Ljava/lang/Double;
     857: getstatic     #2                  // Field enerj/rt/PrecisionRuntimeRoot.impl:Lenerj/rt/PrecisionRuntime;
     860: aload         23
     862: iconst_1      
     863: invokeinterface #9,  3            // InterfaceMethod enerj/rt/PrecisionRuntime.loadLocal:(Lenerj/rt/Reference;Z)Ljava/lang/Object;
     868: checkcast     #50                 // class java/lang/Double
     871: invokevirtual #51                 // Method java/lang/Double.doubleValue:()D
     874: invokestatic  #46                 // Method java/lang/Double.valueOf:(D)Ljava/lang/Double;
     877: getstatic     #40                 // Field enerj/rt/PrecisionRuntime$ArithOperator.MINUS:Lenerj/rt/PrecisionRuntime$ArithOperator;
     880: getstatic     #48                 // Field enerj/rt/PrecisionRuntime$NumberKind.DOUBLE:Lenerj/rt/PrecisionRuntime$NumberKind;
     883: iconst_1      
     884: invokeinterface #41,  6           // InterfaceMethod enerj/rt/PrecisionRuntime.binaryOp:(Ljava/lang/Number;Ljava/lang/Number;Lenerj/rt/PrecisionRuntime$ArithOperator;Lenerj/rt/PrecisionRuntime$NumberKind;Z)Ljava/lang/Number;
     889: invokevirtual #49                 // Method java/lang/Number.doubleValue:()D
     892: invokestatic  #46                 // Method java/lang/Double.valueOf:(D)Ljava/lang/Double;
     895: getstatic     #2                  // Field enerj/rt/PrecisionRuntimeRoot.impl:Lenerj/rt/PrecisionRuntime;
     898: getstatic     #2                  // Field enerj/rt/PrecisionRuntimeRoot.impl:Lenerj/rt/PrecisionRuntime;
     901: aload         26
     903: iconst_1      
     904: invokeinterface #9,  3            // InterfaceMethod enerj/rt/PrecisionRuntime.loadLocal:(Lenerj/rt/Reference;Z)Ljava/lang/Object;
     909: checkcast     #50                 // class java/lang/Double
     912: invokevirtual #51                 // Method java/lang/Double.doubleValue:()D
     915: invokestatic  #46                 // Method java/lang/Double.valueOf:(D)Ljava/lang/Double;
     918: getstatic     #2                  // Field enerj/rt/PrecisionRuntimeRoot.impl:Lenerj/rt/PrecisionRuntime;
     921: aload         26
     923: iconst_1      
     924: invokeinterface #9,  3            // InterfaceMethod enerj/rt/PrecisionRuntime.loadLocal:(Lenerj/rt/Reference;Z)Ljava/lang/Object;
     929: checkcast     #50                 // class java/lang/Double
     932: invokevirtual #51                 // Method java/lang/Double.doubleValue:()D
     935: invokestatic  #46                 // Method java/lang/Double.valueOf:(D)Ljava/lang/Double;
     938: getstatic     #37                 // Field enerj/rt/PrecisionRuntime$ArithOperator.PLUS:Lenerj/rt/PrecisionRuntime$ArithOperator;
     941: getstatic     #48                 // Field enerj/rt/PrecisionRuntime$NumberKind.DOUBLE:Lenerj/rt/PrecisionRuntime$NumberKind;
     944: iconst_1      
     945: invokeinterface #41,  6           // InterfaceMethod enerj/rt/PrecisionRuntime.binaryOp:(Ljava/lang/Number;Ljava/lang/Number;Lenerj/rt/PrecisionRuntime$ArithOperator;Lenerj/rt/PrecisionRuntime$NumberKind;Z)Ljava/lang/Number;
     950: invokevirtual #49                 // Method java/lang/Number.doubleValue:()D
     953: invokestatic  #46                 // Method java/lang/Double.valueOf:(D)Ljava/lang/Double;
     956: getstatic     #40                 // Field enerj/rt/PrecisionRuntime$ArithOperator.MINUS:Lenerj/rt/PrecisionRuntime$ArithOperator;
     959: getstatic     #48                 // Field enerj/rt/PrecisionRuntime$NumberKind.DOUBLE:Lenerj/rt/PrecisionRuntime$NumberKind;
     962: iconst_1      
     963: invokeinterface #41,  6           // InterfaceMethod enerj/rt/PrecisionRuntime.binaryOp:(Ljava/lang/Number;Ljava/lang/Number;Lenerj/rt/PrecisionRuntime$ArithOperator;Lenerj/rt/PrecisionRuntime$NumberKind;Z)Ljava/lang/Number;
     968: invokevirtual #49                 // Method java/lang/Number.doubleValue:()D
     971: invokestatic  #46                 // Method java/lang/Double.valueOf:(D)Ljava/lang/Double;
     974: getstatic     #2                  // Field enerj/rt/PrecisionRuntimeRoot.impl:Lenerj/rt/PrecisionRuntime;
     977: aload         29
     979: iconst_1      
     980: invokeinterface #9,  3            // InterfaceMethod enerj/rt/PrecisionRuntime.loadLocal:(Lenerj/rt/Reference;Z)Ljava/lang/Object;
     985: checkcast     #50                 // class java/lang/Double
     988: invokevirtual #51                 // Method java/lang/Double.doubleValue:()D
     991: invokestatic  #46                 // Method java/lang/Double.valueOf:(D)Ljava/lang/Double;
     994: getstatic     #40                 // Field enerj/rt/PrecisionRuntime$ArithOperator.MINUS:Lenerj/rt/PrecisionRuntime$ArithOperator;
     997: getstatic     #48                 // Field enerj/rt/PrecisionRuntime$NumberKind.DOUBLE:Lenerj/rt/PrecisionRuntime$NumberKind;
    1000: iconst_1      
    1001: invokeinterface #41,  6           // InterfaceMethod enerj/rt/PrecisionRuntime.binaryOp:(Ljava/lang/Number;Ljava/lang/Number;Lenerj/rt/PrecisionRuntime$ArithOperator;Lenerj/rt/PrecisionRuntime$NumberKind;Z)Ljava/lang/Number;
    1006: invokevirtual #49                 // Method java/lang/Number.doubleValue:()D
    1009: invokestatic  #46                 // Method java/lang/Double.valueOf:(D)Ljava/lang/Double;
    1012: iconst_1      
    1013: getstatic     #16                 // Field enerj/rt/PrecisionRuntime$MemKind.VARIABLE:Lenerj/rt/PrecisionRuntime$MemKind;
    1016: invokeinterface #17,  4           // InterfaceMethod enerj/rt/PrecisionRuntime.storeValue:(Ljava/lang/Object;ZLenerj/rt/PrecisionRuntime$MemKind;)Ljava/lang/Object;
    1021: checkcast     #50                 // class java/lang/Double
    1024: invokevirtual #51                 // Method java/lang/Double.doubleValue:()D
    1027: dstore        30
    1029: new           #4                  // class enerj/rt/Reference
    1032: dup           
    1033: dload         30
    1035: invokestatic  #46                 // Method java/lang/Double.valueOf:(D)Ljava/lang/Double;
    1038: iconst_1      
    1039: iconst_1      
    1040: invokespecial #5                  // Method enerj/rt/Reference."<init>":(Ljava/lang/Object;ZZ)V
    1043: astore        32
    1045: getstatic     #2                  // Field enerj/rt/PrecisionRuntimeRoot.impl:Lenerj/rt/PrecisionRuntime;
    1048: getstatic     #2                  // Field enerj/rt/PrecisionRuntimeRoot.impl:Lenerj/rt/PrecisionRuntime;
    1051: getstatic     #2                  // Field enerj/rt/PrecisionRuntimeRoot.impl:Lenerj/rt/PrecisionRuntime;
    1054: getstatic     #2                  // Field enerj/rt/PrecisionRuntimeRoot.impl:Lenerj/rt/PrecisionRuntime;
    1057: getstatic     #2                  // Field enerj/rt/PrecisionRuntimeRoot.impl:Lenerj/rt/PrecisionRuntime;
    1060: getstatic     #2                  // Field enerj/rt/PrecisionRuntimeRoot.impl:Lenerj/rt/PrecisionRuntime;
    1063: getstatic     #2                  // Field enerj/rt/PrecisionRuntimeRoot.impl:Lenerj/rt/PrecisionRuntime;
    1066: aload         11
    1068: iconst_1      
    1069: invokeinterface #9,  3            // InterfaceMethod enerj/rt/PrecisionRuntime.loadLocal:(Lenerj/rt/Reference;Z)Ljava/lang/Object;
    1074: checkcast     #50                 // class java/lang/Double
    1077: invokevirtual #51                 // Method java/lang/Double.doubleValue:()D
    1080: invokestatic  #46                 // Method java/lang/Double.valueOf:(D)Ljava/lang/Double;
    1083: getstatic     #2                  // Field enerj/rt/PrecisionRuntimeRoot.impl:Lenerj/rt/PrecisionRuntime;
    1086: getstatic     #2                  // Field enerj/rt/PrecisionRuntimeRoot.impl:Lenerj/rt/PrecisionRuntime;
    1089: aload         20
    1091: iconst_1      
    1092: invokeinterface #9,  3            // InterfaceMethod enerj/rt/PrecisionRuntime.loadLocal:(Lenerj/rt/Reference;Z)Ljava/lang/Object;
    1097: checkcast     #50                 // class java/lang/Double
    1100: invokevirtual #51                 // Method java/lang/Double.doubleValue:()D
    1103: invokestatic  #46                 // Method java/lang/Double.valueOf:(D)Ljava/lang/Double;
    1106: getstatic     #2                  // Field enerj/rt/PrecisionRuntimeRoot.impl:Lenerj/rt/PrecisionRuntime;
    1109: aload         20
    1111: iconst_1      
    1112: invokeinterface #9,  3            // InterfaceMethod enerj/rt/PrecisionRuntime.loadLocal:(Lenerj/rt/Reference;Z)Ljava/lang/Object;
    1117: checkcast     #50                 // class java/lang/Double
    1120: invokevirtual #51                 // Method java/lang/Double.doubleValue:()D
    1123: invokestatic  #46                 // Method java/lang/Double.valueOf:(D)Ljava/lang/Double;
    1126: getstatic     #37                 // Field enerj/rt/PrecisionRuntime$ArithOperator.PLUS:Lenerj/rt/PrecisionRuntime$ArithOperator;
    1129: getstatic     #48                 // Field enerj/rt/PrecisionRuntime$NumberKind.DOUBLE:Lenerj/rt/PrecisionRuntime$NumberKind;
    1132: iconst_1      
    1133: invokeinterface #41,  6           // InterfaceMethod enerj/rt/PrecisionRuntime.binaryOp:(Ljava/lang/Number;Ljava/lang/Number;Lenerj/rt/PrecisionRuntime$ArithOperator;Lenerj/rt/PrecisionRuntime$NumberKind;Z)Ljava/lang/Number;
    1138: invokevirtual #49                 // Method java/lang/Number.doubleValue:()D
    1141: invokestatic  #46                 // Method java/lang/Double.valueOf:(D)Ljava/lang/Double;
    1144: getstatic     #37                 // Field enerj/rt/PrecisionRuntime$ArithOperator.PLUS:Lenerj/rt/PrecisionRuntime$ArithOperator;
    1147: getstatic     #48                 // Field enerj/rt/PrecisionRuntime$NumberKind.DOUBLE:Lenerj/rt/PrecisionRuntime$NumberKind;
    1150: iconst_1      
    1151: invokeinterface #41,  6           // InterfaceMethod enerj/rt/PrecisionRuntime.binaryOp:(Ljava/lang/Number;Ljava/lang/Number;Lenerj/rt/PrecisionRuntime$ArithOperator;Lenerj/rt/PrecisionRuntime$NumberKind;Z)Ljava/lang/Number;
    1156: invokevirtual #49                 // Method java/lang/Number.doubleValue:()D
    1159: invokestatic  #46                 // Method java/lang/Double.valueOf:(D)Ljava/lang/Double;
    1162: getstatic     #2                  // Field enerj/rt/PrecisionRuntimeRoot.impl:Lenerj/rt/PrecisionRuntime;
    1165: aload         29
    1167: iconst_1      
    1168: invokeinterface #9,  3            // InterfaceMethod enerj/rt/PrecisionRuntime.loadLocal:(Lenerj/rt/Reference;Z)Ljava/lang/Object;
    1173: checkcast     #50                 // class java/lang/Double
    1176: invokevirtual #51                 // Method java/lang/Double.doubleValue:()D
    1179: invokestatic  #46                 // Method java/lang/Double.valueOf:(D)Ljava/lang/Double;
    1182: getstatic     #37                 // Field enerj/rt/PrecisionRuntime$ArithOperator.PLUS:Lenerj/rt/PrecisionRuntime$ArithOperator;
    1185: getstatic     #48                 // Field enerj/rt/PrecisionRuntime$NumberKind.DOUBLE:Lenerj/rt/PrecisionRuntime$NumberKind;
    1188: iconst_1      
    1189: invokeinterface #41,  6           // InterfaceMethod enerj/rt/PrecisionRuntime.binaryOp:(Ljava/lang/Number;Ljava/lang/Number;Lenerj/rt/PrecisionRuntime$ArithOperator;Lenerj/rt/PrecisionRuntime$NumberKind;Z)Ljava/lang/Number;
    1194: invokevirtual #49                 // Method java/lang/Number.doubleValue:()D
    1197: invokestatic  #46                 // Method java/lang/Double.valueOf:(D)Ljava/lang/Double;
    1200: getstatic     #2                  // Field enerj/rt/PrecisionRuntimeRoot.impl:Lenerj/rt/PrecisionRuntime;
    1203: aload         5
    1205: iconst_1      
    1206: invokeinterface #9,  3            // InterfaceMethod enerj/rt/PrecisionRuntime.loadLocal:(Lenerj/rt/Reference;Z)Ljava/lang/Object;
    1211: checkcast     #50                 // class java/lang/Double
    1214: invokevirtual #51                 // Method java/lang/Double.doubleValue:()D
    1217: invokestatic  #46                 // Method java/lang/Double.valueOf:(D)Ljava/lang/Double;
    1220: getstatic     #40                 // Field enerj/rt/PrecisionRuntime$ArithOperator.MINUS:Lenerj/rt/PrecisionRuntime$ArithOperator;
    1223: getstatic     #48                 // Field enerj/rt/PrecisionRuntime$NumberKind.DOUBLE:Lenerj/rt/PrecisionRuntime$NumberKind;
    1226: iconst_1      
    1227: invokeinterface #41,  6           // InterfaceMethod enerj/rt/PrecisionRuntime.binaryOp:(Ljava/lang/Number;Ljava/lang/Number;Lenerj/rt/PrecisionRuntime$ArithOperator;Lenerj/rt/PrecisionRuntime$NumberKind;Z)Ljava/lang/Number;
    1232: invokevirtual #49                 // Method java/lang/Number.doubleValue:()D
    1235: invokestatic  #46                 // Method java/lang/Double.valueOf:(D)Ljava/lang/Double;
    1238: getstatic     #2                  // Field enerj/rt/PrecisionRuntimeRoot.impl:Lenerj/rt/PrecisionRuntime;
    1241: getstatic     #2                  // Field enerj/rt/PrecisionRuntimeRoot.impl:Lenerj/rt/PrecisionRuntime;
    1244: aload         14
    1246: iconst_1      
    1247: invokeinterface #9,  3            // InterfaceMethod enerj/rt/PrecisionRuntime.loadLocal:(Lenerj/rt/Reference;Z)Ljava/lang/Object;
    1252: checkcast     #50                 // class java/lang/Double
    1255: invokevirtual #51                 // Method java/lang/Double.doubleValue:()D
    1258: invokestatic  #46                 // Method java/lang/Double.valueOf:(D)Ljava/lang/Double;
    1261: getstatic     #2                  // Field enerj/rt/PrecisionRuntimeRoot.impl:Lenerj/rt/PrecisionRuntime;
    1264: aload         14
    1266: iconst_1      
    1267: invokeinterface #9,  3            // InterfaceMethod enerj/rt/PrecisionRuntime.loadLocal:(Lenerj/rt/Reference;Z)Ljava/lang/Object;
    1272: checkcast     #50                 // class java/lang/Double
    1275: invokevirtual #51                 // Method java/lang/Double.doubleValue:()D
    1278: invokestatic  #46                 // Method java/lang/Double.valueOf:(D)Ljava/lang/Double;
    1281: getstatic     #37                 // Field enerj/rt/PrecisionRuntime$ArithOperator.PLUS:Lenerj/rt/PrecisionRuntime$ArithOperator;
    1284: getstatic     #48                 // Field enerj/rt/PrecisionRuntime$NumberKind.DOUBLE:Lenerj/rt/PrecisionRuntime$NumberKind;
    1287: iconst_1      
    1288: invokeinterface #41,  6           // InterfaceMethod enerj/rt/PrecisionRuntime.binaryOp:(Ljava/lang/Number;Ljava/lang/Number;Lenerj/rt/PrecisionRuntime$ArithOperator;Lenerj/rt/PrecisionRuntime$NumberKind;Z)Ljava/lang/Number;
    1293: invokevirtual #49                 // Method java/lang/Number.doubleValue:()D
    1296: invokestatic  #46                 // Method java/lang/Double.valueOf:(D)Ljava/lang/Double;
    1299: getstatic     #40                 // Field enerj/rt/PrecisionRuntime$ArithOperator.MINUS:Lenerj/rt/PrecisionRuntime$ArithOperator;
    1302: getstatic     #48                 // Field enerj/rt/PrecisionRuntime$NumberKind.DOUBLE:Lenerj/rt/PrecisionRuntime$NumberKind;
    1305: iconst_1      
    1306: invokeinterface #41,  6           // InterfaceMethod enerj/rt/PrecisionRuntime.binaryOp:(Ljava/lang/Number;Ljava/lang/Number;Lenerj/rt/PrecisionRuntime$ArithOperator;Lenerj/rt/PrecisionRuntime$NumberKind;Z)Ljava/lang/Number;
    1311: invokevirtual #49                 // Method java/lang/Number.doubleValue:()D
    1314: invokestatic  #46                 // Method java/lang/Double.valueOf:(D)Ljava/lang/Double;
    1317: getstatic     #2                  // Field enerj/rt/PrecisionRuntimeRoot.impl:Lenerj/rt/PrecisionRuntime;
    1320: aload         23
    1322: iconst_1      
    1323: invokeinterface #9,  3            // InterfaceMethod enerj/rt/PrecisionRuntime.loadLocal:(Lenerj/rt/Reference;Z)Ljava/lang/Object;
    1328: checkcast     #50                 // class java/lang/Double
    1331: invokevirtual #51                 // Method java/lang/Double.doubleValue:()D
    1334: invokestatic  #46                 // Method java/lang/Double.valueOf:(D)Ljava/lang/Double;
    1337: getstatic     #40                 // Field enerj/rt/PrecisionRuntime$ArithOperator.MINUS:Lenerj/rt/PrecisionRuntime$ArithOperator;
    1340: getstatic     #48                 // Field enerj/rt/PrecisionRuntime$NumberKind.DOUBLE:Lenerj/rt/PrecisionRuntime$NumberKind;
    1343: iconst_1      
    1344: invokeinterface #41,  6           // InterfaceMethod enerj/rt/PrecisionRuntime.binaryOp:(Ljava/lang/Number;Ljava/lang/Number;Lenerj/rt/PrecisionRuntime$ArithOperator;Lenerj/rt/PrecisionRuntime$NumberKind;Z)Ljava/lang/Number;
    1349: invokevirtual #49                 // Method java/lang/Number.doubleValue:()D
    1352: invokestatic  #46                 // Method java/lang/Double.valueOf:(D)Ljava/lang/Double;
    1355: iconst_1      
    1356: getstatic     #16                 // Field enerj/rt/PrecisionRuntime$MemKind.VARIABLE:Lenerj/rt/PrecisionRuntime$MemKind;
    1359: invokeinterface #17,  4           // InterfaceMethod enerj/rt/PrecisionRuntime.storeValue:(Ljava/lang/Object;ZLenerj/rt/PrecisionRuntime$MemKind;)Ljava/lang/Object;
    1364: checkcast     #50                 // class java/lang/Double
    1367: invokevirtual #51                 // Method java/lang/Double.doubleValue:()D
    1370: dstore        33
    1372: new           #4                  // class enerj/rt/Reference
    1375: dup           
    1376: dload         33
    1378: invokestatic  #46                 // Method java/lang/Double.valueOf:(D)Ljava/lang/Double;
    1381: iconst_1      
    1382: iconst_1      
    1383: invokespecial #5                  // Method enerj/rt/Reference."<init>":(Ljava/lang/Object;ZZ)V
    1386: astore        35
    1388: getstatic     #2                  // Field enerj/rt/PrecisionRuntimeRoot.impl:Lenerj/rt/PrecisionRuntime;
    1391: getstatic     #2                  // Field enerj/rt/PrecisionRuntimeRoot.impl:Lenerj/rt/PrecisionRuntime;
    1394: getstatic     #2                  // Field enerj/rt/PrecisionRuntimeRoot.impl:Lenerj/rt/PrecisionRuntime;
    1397: getstatic     #2                  // Field enerj/rt/PrecisionRuntimeRoot.impl:Lenerj/rt/PrecisionRuntime;
    1400: aload         32
    1402: iconst_1      
    1403: invokeinterface #9,  3            // InterfaceMethod enerj/rt/PrecisionRuntime.loadLocal:(Lenerj/rt/Reference;Z)Ljava/lang/Object;
    1408: checkcast     #50                 // class java/lang/Double
    1411: invokevirtual #51                 // Method java/lang/Double.doubleValue:()D
    1414: invokestatic  #46                 // Method java/lang/Double.valueOf:(D)Ljava/lang/Double;
    1417: getstatic     #2                  // Field enerj/rt/PrecisionRuntimeRoot.impl:Lenerj/rt/PrecisionRuntime;
    1420: aload         32
    1422: iconst_1      
    1423: invokeinterface #9,  3            // InterfaceMethod enerj/rt/PrecisionRuntime.loadLocal:(Lenerj/rt/Reference;Z)Ljava/lang/Object;
    1428: checkcast     #50                 // class java/lang/Double
    1431: invokevirtual #51                 // Method java/lang/Double.doubleValue:()D
    1434: invokestatic  #46                 // Method java/lang/Double.valueOf:(D)Ljava/lang/Double;
    1437: getstatic     #55                 // Field enerj/rt/PrecisionRuntime$ArithOperator.MULTIPLY:Lenerj/rt/PrecisionRuntime$ArithOperator;
    1440: getstatic     #48                 // Field enerj/rt/PrecisionRuntime$NumberKind.DOUBLE:Lenerj/rt/PrecisionRuntime$NumberKind;
    1443: iconst_1      
    1444: invokeinterface #41,  6           // InterfaceMethod enerj/rt/PrecisionRuntime.binaryOp:(Ljava/lang/Number;Ljava/lang/Number;Lenerj/rt/PrecisionRuntime$ArithOperator;Lenerj/rt/PrecisionRuntime$NumberKind;Z)Ljava/lang/Number;
    1449: invokevirtual #49                 // Method java/lang/Number.doubleValue:()D
    1452: invokestatic  #46                 // Method java/lang/Double.valueOf:(D)Ljava/lang/Double;
    1455: getstatic     #2                  // Field enerj/rt/PrecisionRuntimeRoot.impl:Lenerj/rt/PrecisionRuntime;
    1458: getstatic     #2                  // Field enerj/rt/PrecisionRuntimeRoot.impl:Lenerj/rt/PrecisionRuntime;
    1461: aload         35
    1463: iconst_1      
    1464: invokeinterface #9,  3            // InterfaceMethod enerj/rt/PrecisionRuntime.loadLocal:(Lenerj/rt/Reference;Z)Ljava/lang/Object;
    1469: checkcast     #50                 // class java/lang/Double
    1472: invokevirtual #51                 // Method java/lang/Double.doubleValue:()D
    1475: invokestatic  #46                 // Method java/lang/Double.valueOf:(D)Ljava/lang/Double;
    1478: getstatic     #2                  // Field enerj/rt/PrecisionRuntimeRoot.impl:Lenerj/rt/PrecisionRuntime;
    1481: aload         35
    1483: iconst_1      
    1484: invokeinterface #9,  3            // InterfaceMethod enerj/rt/PrecisionRuntime.loadLocal:(Lenerj/rt/Reference;Z)Ljava/lang/Object;
    1489: checkcast     #50                 // class java/lang/Double
    1492: invokevirtual #51                 // Method java/lang/Double.doubleValue:()D
    1495: invokestatic  #46                 // Method java/lang/Double.valueOf:(D)Ljava/lang/Double;
    1498: getstatic     #55                 // Field enerj/rt/PrecisionRuntime$ArithOperator.MULTIPLY:Lenerj/rt/PrecisionRuntime$ArithOperator;
    1501: getstatic     #48                 // Field enerj/rt/PrecisionRuntime$NumberKind.DOUBLE:Lenerj/rt/PrecisionRuntime$NumberKind;
    1504: iconst_1      
    1505: invokeinterface #41,  6           // InterfaceMethod enerj/rt/PrecisionRuntime.binaryOp:(Ljava/lang/Number;Ljava/lang/Number;Lenerj/rt/PrecisionRuntime$ArithOperator;Lenerj/rt/PrecisionRuntime$NumberKind;Z)Ljava/lang/Number;
    1510: invokevirtual #49                 // Method java/lang/Number.doubleValue:()D
    1513: invokestatic  #46                 // Method java/lang/Double.valueOf:(D)Ljava/lang/Double;
    1516: getstatic     #37                 // Field enerj/rt/PrecisionRuntime$ArithOperator.PLUS:Lenerj/rt/PrecisionRuntime$ArithOperator;
    1519: getstatic     #48                 // Field enerj/rt/PrecisionRuntime$NumberKind.DOUBLE:Lenerj/rt/PrecisionRuntime$NumberKind;
    1522: iconst_1      
    1523: invokeinterface #41,  6           // InterfaceMethod enerj/rt/PrecisionRuntime.binaryOp:(Ljava/lang/Number;Ljava/lang/Number;Lenerj/rt/PrecisionRuntime$ArithOperator;Lenerj/rt/PrecisionRuntime$NumberKind;Z)Ljava/lang/Number;
    1528: invokevirtual #49                 // Method java/lang/Number.doubleValue:()D
    1531: invokestatic  #56                 // Method sqrt:(D)D
    1534: invokestatic  #46                 // Method java/lang/Double.valueOf:(D)Ljava/lang/Double;
    1537: iconst_1      
    1538: getstatic     #16                 // Field enerj/rt/PrecisionRuntime$MemKind.VARIABLE:Lenerj/rt/PrecisionRuntime$MemKind;
    1541: invokeinterface #17,  4           // InterfaceMethod enerj/rt/PrecisionRuntime.storeValue:(Ljava/lang/Object;ZLenerj/rt/PrecisionRuntime$MemKind;)Ljava/lang/Object;
    1546: checkcast     #50                 // class java/lang/Double
    1549: invokevirtual #51                 // Method java/lang/Double.doubleValue:()D
    1552: dstore        36
    1554: new           #4                  // class enerj/rt/Reference
    1557: dup           
    1558: dload         36
    1560: invokestatic  #46                 // Method java/lang/Double.valueOf:(D)Ljava/lang/Double;
    1563: iconst_1      
    1564: iconst_1      
    1565: invokespecial #5                  // Method enerj/rt/Reference."<init>":(Ljava/lang/Object;ZZ)V
    1568: astore        38
    1570: getstatic     #2                  // Field enerj/rt/PrecisionRuntimeRoot.impl:Lenerj/rt/PrecisionRuntime;
    1573: aload         38
    1575: iconst_1      
    1576: invokeinterface #9,  3            // InterfaceMethod enerj/rt/PrecisionRuntime.loadLocal:(Lenerj/rt/Reference;Z)Ljava/lang/Object;
    1581: checkcast     #50                 // class java/lang/Double
    1584: invokevirtual #51                 // Method java/lang/Double.doubleValue:()D
    1587: dreturn       

  public int luminance(int[]);
    Code:
       0: new           #4                  // class enerj/rt/Reference
       3: dup           
       4: aload_1       
       5: iconst_0      
       6: iconst_0      
       7: invokespecial #5                  // Method enerj/rt/Reference."<init>":(Ljava/lang/Object;ZZ)V
      10: astore_2      
      11: getstatic     #2                  // Field enerj/rt/PrecisionRuntimeRoot.impl:Lenerj/rt/PrecisionRuntime;
      14: ldc2_w        #57                 // double 0.3d
      17: invokestatic  #46                 // Method java/lang/Double.valueOf:(D)Ljava/lang/Double;
      20: iconst_1      
      21: getstatic     #16                 // Field enerj/rt/PrecisionRuntime$MemKind.VARIABLE:Lenerj/rt/PrecisionRuntime$MemKind;
      24: invokeinterface #17,  4           // InterfaceMethod enerj/rt/PrecisionRuntime.storeValue:(Ljava/lang/Object;ZLenerj/rt/PrecisionRuntime$MemKind;)Ljava/lang/Object;
      29: checkcast     #50                 // class java/lang/Double
      32: invokevirtual #51                 // Method java/lang/Double.doubleValue:()D
      35: dstore_3      
      36: new           #4                  // class enerj/rt/Reference
      39: dup           
      40: dload_3       
      41: invokestatic  #46                 // Method java/lang/Double.valueOf:(D)Ljava/lang/Double;
      44: iconst_1      
      45: iconst_1      
      46: invokespecial #5                  // Method enerj/rt/Reference."<init>":(Ljava/lang/Object;ZZ)V
      49: astore        5
      51: getstatic     #2                  // Field enerj/rt/PrecisionRuntimeRoot.impl:Lenerj/rt/PrecisionRuntime;
      54: ldc2_w        #59                 // double 0.59d
      57: invokestatic  #46                 // Method java/lang/Double.valueOf:(D)Ljava/lang/Double;
      60: iconst_1      
      61: getstatic     #16                 // Field enerj/rt/PrecisionRuntime$MemKind.VARIABLE:Lenerj/rt/PrecisionRuntime$MemKind;
      64: invokeinterface #17,  4           // InterfaceMethod enerj/rt/PrecisionRuntime.storeValue:(Ljava/lang/Object;ZLenerj/rt/PrecisionRuntime$MemKind;)Ljava/lang/Object;
      69: checkcast     #50                 // class java/lang/Double
      72: invokevirtual #51                 // Method java/lang/Double.doubleValue:()D
      75: dstore        6
      77: new           #4                  // class enerj/rt/Reference
      80: dup           
      81: dload         6
      83: invokestatic  #46                 // Method java/lang/Double.valueOf:(D)Ljava/lang/Double;
      86: iconst_1      
      87: iconst_1      
      88: invokespecial #5                  // Method enerj/rt/Reference."<init>":(Ljava/lang/Object;ZZ)V
      91: astore        8
      93: getstatic     #2                  // Field enerj/rt/PrecisionRuntimeRoot.impl:Lenerj/rt/PrecisionRuntime;
      96: ldc2_w        #61                 // double 0.11d
      99: invokestatic  #46                 // Method java/lang/Double.valueOf:(D)Ljava/lang/Double;
     102: iconst_1      
     103: getstatic     #16                 // Field enerj/rt/PrecisionRuntime$MemKind.VARIABLE:Lenerj/rt/PrecisionRuntime$MemKind;
     106: invokeinterface #17,  4           // InterfaceMethod enerj/rt/PrecisionRuntime.storeValue:(Ljava/lang/Object;ZLenerj/rt/PrecisionRuntime$MemKind;)Ljava/lang/Object;
     111: checkcast     #50                 // class java/lang/Double
     114: invokevirtual #51                 // Method java/lang/Double.doubleValue:()D
     117: dstore        9
     119: new           #4                  // class enerj/rt/Reference
     122: dup           
     123: dload         9
     125: invokestatic  #46                 // Method java/lang/Double.valueOf:(D)Ljava/lang/Double;
     128: iconst_1      
     129: iconst_1      
     130: invokespecial #5                  // Method enerj/rt/Reference."<init>":(Ljava/lang/Object;ZZ)V
     133: astore        11
     135: getstatic     #2                  // Field enerj/rt/PrecisionRuntimeRoot.impl:Lenerj/rt/PrecisionRuntime;
     138: getstatic     #2                  // Field enerj/rt/PrecisionRuntimeRoot.impl:Lenerj/rt/PrecisionRuntime;
     141: getstatic     #2                  // Field enerj/rt/PrecisionRuntimeRoot.impl:Lenerj/rt/PrecisionRuntime;
     144: getstatic     #2                  // Field enerj/rt/PrecisionRuntimeRoot.impl:Lenerj/rt/PrecisionRuntime;
     147: getstatic     #2                  // Field enerj/rt/PrecisionRuntimeRoot.impl:Lenerj/rt/PrecisionRuntime;
     150: aload         5
     152: iconst_1      
     153: invokeinterface #9,  3            // InterfaceMethod enerj/rt/PrecisionRuntime.loadLocal:(Lenerj/rt/Reference;Z)Ljava/lang/Object;
     158: checkcast     #50                 // class java/lang/Double
     161: invokevirtual #51                 // Method java/lang/Double.doubleValue:()D
     164: invokestatic  #46                 // Method java/lang/Double.valueOf:(D)Ljava/lang/Double;
     167: getstatic     #2                  // Field enerj/rt/PrecisionRuntimeRoot.impl:Lenerj/rt/PrecisionRuntime;
     170: getstatic     #2                  // Field enerj/rt/PrecisionRuntimeRoot.impl:Lenerj/rt/PrecisionRuntime;
     173: aload_2       
     174: iconst_0      
     175: invokeinterface #9,  3            // InterfaceMethod enerj/rt/PrecisionRuntime.loadLocal:(Lenerj/rt/Reference;Z)Ljava/lang/Object;
     180: iconst_0      
     181: iconst_1      
     182: invokeinterface #36,  4           // InterfaceMethod enerj/rt/PrecisionRuntime.loadArray:(Ljava/lang/Object;IZ)Ljava/lang/Object;
     187: checkcast     #22                 // class java/lang/Integer
     190: invokevirtual #23                 // Method java/lang/Integer.intValue:()I
     193: invokestatic  #20                 // Method java/lang/Integer.valueOf:(I)Ljava/lang/Integer;
     196: getstatic     #55                 // Field enerj/rt/PrecisionRuntime$ArithOperator.MULTIPLY:Lenerj/rt/PrecisionRuntime$ArithOperator;
     199: getstatic     #48                 // Field enerj/rt/PrecisionRuntime$NumberKind.DOUBLE:Lenerj/rt/PrecisionRuntime$NumberKind;
     202: iconst_1      
     203: invokeinterface #41,  6           // InterfaceMethod enerj/rt/PrecisionRuntime.binaryOp:(Ljava/lang/Number;Ljava/lang/Number;Lenerj/rt/PrecisionRuntime$ArithOperator;Lenerj/rt/PrecisionRuntime$NumberKind;Z)Ljava/lang/Number;
     208: invokevirtual #49                 // Method java/lang/Number.doubleValue:()D
     211: invokestatic  #46                 // Method java/lang/Double.valueOf:(D)Ljava/lang/Double;
     214: getstatic     #2                  // Field enerj/rt/PrecisionRuntimeRoot.impl:Lenerj/rt/PrecisionRuntime;
     217: getstatic     #2                  // Field enerj/rt/PrecisionRuntimeRoot.impl:Lenerj/rt/PrecisionRuntime;
     220: aload         8
     222: iconst_1      
     223: invokeinterface #9,  3            // InterfaceMethod enerj/rt/PrecisionRuntime.loadLocal:(Lenerj/rt/Reference;Z)Ljava/lang/Object;
     228: checkcast     #50                 // class java/lang/Double
     231: invokevirtual #51                 // Method java/lang/Double.doubleValue:()D
     234: invokestatic  #46                 // Method java/lang/Double.valueOf:(D)Ljava/lang/Double;
     237: getstatic     #2                  // Field enerj/rt/PrecisionRuntimeRoot.impl:Lenerj/rt/PrecisionRuntime;
     240: getstatic     #2                  // Field enerj/rt/PrecisionRuntimeRoot.impl:Lenerj/rt/PrecisionRuntime;
     243: aload_2       
     244: iconst_0      
     245: invokeinterface #9,  3            // InterfaceMethod enerj/rt/PrecisionRuntime.loadLocal:(Lenerj/rt/Reference;Z)Ljava/lang/Object;
     250: iconst_1      
     251: iconst_1      
     252: invokeinterface #36,  4           // InterfaceMethod enerj/rt/PrecisionRuntime.loadArray:(Ljava/lang/Object;IZ)Ljava/lang/Object;
     257: checkcast     #22                 // class java/lang/Integer
     260: invokevirtual #23                 // Method java/lang/Integer.intValue:()I
     263: invokestatic  #20                 // Method java/lang/Integer.valueOf:(I)Ljava/lang/Integer;
     266: getstatic     #55                 // Field enerj/rt/PrecisionRuntime$ArithOperator.MULTIPLY:Lenerj/rt/PrecisionRuntime$ArithOperator;
     269: getstatic     #48                 // Field enerj/rt/PrecisionRuntime$NumberKind.DOUBLE:Lenerj/rt/PrecisionRuntime$NumberKind;
     272: iconst_1      
     273: invokeinterface #41,  6           // InterfaceMethod enerj/rt/PrecisionRuntime.binaryOp:(Ljava/lang/Number;Ljava/lang/Number;Lenerj/rt/PrecisionRuntime$ArithOperator;Lenerj/rt/PrecisionRuntime$NumberKind;Z)Ljava/lang/Number;
     278: invokevirtual #49                 // Method java/lang/Number.doubleValue:()D
     281: invokestatic  #46                 // Method java/lang/Double.valueOf:(D)Ljava/lang/Double;
     284: getstatic     #37                 // Field enerj/rt/PrecisionRuntime$ArithOperator.PLUS:Lenerj/rt/PrecisionRuntime$ArithOperator;
     287: getstatic     #48                 // Field enerj/rt/PrecisionRuntime$NumberKind.DOUBLE:Lenerj/rt/PrecisionRuntime$NumberKind;
     290: iconst_1      
     291: invokeinterface #41,  6           // InterfaceMethod enerj/rt/PrecisionRuntime.binaryOp:(Ljava/lang/Number;Ljava/lang/Number;Lenerj/rt/PrecisionRuntime$ArithOperator;Lenerj/rt/PrecisionRuntime$NumberKind;Z)Ljava/lang/Number;
     296: invokevirtual #49                 // Method java/lang/Number.doubleValue:()D
     299: invokestatic  #46                 // Method java/lang/Double.valueOf:(D)Ljava/lang/Double;
     302: getstatic     #2                  // Field enerj/rt/PrecisionRuntimeRoot.impl:Lenerj/rt/PrecisionRuntime;
     305: getstatic     #2                  // Field enerj/rt/PrecisionRuntimeRoot.impl:Lenerj/rt/PrecisionRuntime;
     308: aload         11
     310: iconst_1      
     311: invokeinterface #9,  3            // InterfaceMethod enerj/rt/PrecisionRuntime.loadLocal:(Lenerj/rt/Reference;Z)Ljava/lang/Object;
     316: checkcast     #50                 // class java/lang/Double
     319: invokevirtual #51                 // Method java/lang/Double.doubleValue:()D
     322: invokestatic  #46                 // Method java/lang/Double.valueOf:(D)Ljava/lang/Double;
     325: getstatic     #2                  // Field enerj/rt/PrecisionRuntimeRoot.impl:Lenerj/rt/PrecisionRuntime;
     328: getstatic     #2                  // Field enerj/rt/PrecisionRuntimeRoot.impl:Lenerj/rt/PrecisionRuntime;
     331: aload_2       
     332: iconst_0      
     333: invokeinterface #9,  3            // InterfaceMethod enerj/rt/PrecisionRuntime.loadLocal:(Lenerj/rt/Reference;Z)Ljava/lang/Object;
     338: iconst_2      
     339: iconst_1      
     340: invokeinterface #36,  4           // InterfaceMethod enerj/rt/PrecisionRuntime.loadArray:(Ljava/lang/Object;IZ)Ljava/lang/Object;
     345: checkcast     #22                 // class java/lang/Integer
     348: invokevirtual #23                 // Method java/lang/Integer.intValue:()I
     351: invokestatic  #20                 // Method java/lang/Integer.valueOf:(I)Ljava/lang/Integer;
     354: getstatic     #55                 // Field enerj/rt/PrecisionRuntime$ArithOperator.MULTIPLY:Lenerj/rt/PrecisionRuntime$ArithOperator;
     357: getstatic     #48                 // Field enerj/rt/PrecisionRuntime$NumberKind.DOUBLE:Lenerj/rt/PrecisionRuntime$NumberKind;
     360: iconst_1      
     361: invokeinterface #41,  6           // InterfaceMethod enerj/rt/PrecisionRuntime.binaryOp:(Ljava/lang/Number;Ljava/lang/Number;Lenerj/rt/PrecisionRuntime$ArithOperator;Lenerj/rt/PrecisionRuntime$NumberKind;Z)Ljava/lang/Number;
     366: invokevirtual #49                 // Method java/lang/Number.doubleValue:()D
     369: invokestatic  #46                 // Method java/lang/Double.valueOf:(D)Ljava/lang/Double;
     372: getstatic     #37                 // Field enerj/rt/PrecisionRuntime$ArithOperator.PLUS:Lenerj/rt/PrecisionRuntime$ArithOperator;
     375: getstatic     #48                 // Field enerj/rt/PrecisionRuntime$NumberKind.DOUBLE:Lenerj/rt/PrecisionRuntime$NumberKind;
     378: iconst_1      
     379: invokeinterface #41,  6           // InterfaceMethod enerj/rt/PrecisionRuntime.binaryOp:(Ljava/lang/Number;Ljava/lang/Number;Lenerj/rt/PrecisionRuntime$ArithOperator;Lenerj/rt/PrecisionRuntime$NumberKind;Z)Ljava/lang/Number;
     384: invokevirtual #49                 // Method java/lang/Number.doubleValue:()D
     387: invokestatic  #46                 // Method java/lang/Double.valueOf:(D)Ljava/lang/Double;
     390: ldc2_w        #63                 // double 0.5d
     393: invokestatic  #46                 // Method java/lang/Double.valueOf:(D)Ljava/lang/Double;
     396: getstatic     #37                 // Field enerj/rt/PrecisionRuntime$ArithOperator.PLUS:Lenerj/rt/PrecisionRuntime$ArithOperator;
     399: getstatic     #48                 // Field enerj/rt/PrecisionRuntime$NumberKind.DOUBLE:Lenerj/rt/PrecisionRuntime$NumberKind;
     402: iconst_1      
     403: invokeinterface #41,  6           // InterfaceMethod enerj/rt/PrecisionRuntime.binaryOp:(Ljava/lang/Number;Ljava/lang/Number;Lenerj/rt/PrecisionRuntime$ArithOperator;Lenerj/rt/PrecisionRuntime$NumberKind;Z)Ljava/lang/Number;
     408: invokevirtual #49                 // Method java/lang/Number.doubleValue:()D
     411: d2i           
     412: sipush        256
     415: irem          
     416: ireturn       

  public void makeGrayscale();
    Code:
       0: new           #4                  // class enerj/rt/Reference
       3: dup           
       4: aconst_null   
       5: iconst_0      
       6: iconst_1      
       7: invokespecial #5                  // Method enerj/rt/Reference."<init>":(Ljava/lang/Object;ZZ)V
      10: astore_2      
      11: new           #4                  // class enerj/rt/Reference
      14: dup           
      15: aconst_null   
      16: iconst_0      
      17: iconst_1      
      18: invokespecial #5                  // Method enerj/rt/Reference."<init>":(Ljava/lang/Object;ZZ)V
      21: astore        4
      23: new           #4                  // class enerj/rt/Reference
      26: dup           
      27: aconst_null   
      28: iconst_1      
      29: iconst_1      
      30: invokespecial #5                  // Method enerj/rt/Reference."<init>":(Ljava/lang/Object;ZZ)V
      33: astore        7
      35: getstatic     #2                  // Field enerj/rt/PrecisionRuntimeRoot.impl:Lenerj/rt/PrecisionRuntime;
      38: ldc2_w        #65                 // double 0.001171875d
      41: invokestatic  #46                 // Method java/lang/Double.valueOf:(D)Ljava/lang/Double;
      44: iconst_1      
      45: getstatic     #16                 // Field enerj/rt/PrecisionRuntime$MemKind.VARIABLE:Lenerj/rt/PrecisionRuntime$MemKind;
      48: invokeinterface #17,  4           // InterfaceMethod enerj/rt/PrecisionRuntime.storeValue:(Ljava/lang/Object;ZLenerj/rt/PrecisionRuntime$MemKind;)Ljava/lang/Object;
      53: checkcast     #50                 // class java/lang/Double
      56: invokevirtual #51                 // Method java/lang/Double.doubleValue:()D
      59: dstore        8
      61: new           #4                  // class enerj/rt/Reference
      64: dup           
      65: dload         8
      67: invokestatic  #46                 // Method java/lang/Double.valueOf:(D)Ljava/lang/Double;
      70: iconst_1      
      71: iconst_1      
      72: invokespecial #5                  // Method enerj/rt/Reference."<init>":(Ljava/lang/Object;ZZ)V
      75: astore        10
      77: getstatic     #2                  // Field enerj/rt/PrecisionRuntimeRoot.impl:Lenerj/rt/PrecisionRuntime;
      80: ldc2_w        #67                 // double 0.0023046875d
      83: invokestatic  #46                 // Method java/lang/Double.valueOf:(D)Ljava/lang/Double;
      86: iconst_1      
      87: getstatic     #16                 // Field enerj/rt/PrecisionRuntime$MemKind.VARIABLE:Lenerj/rt/PrecisionRuntime$MemKind;
      90: invokeinterface #17,  4           // InterfaceMethod enerj/rt/PrecisionRuntime.storeValue:(Ljava/lang/Object;ZLenerj/rt/PrecisionRuntime$MemKind;)Ljava/lang/Object;
      95: checkcast     #50                 // class java/lang/Double
      98: invokevirtual #51                 // Method java/lang/Double.doubleValue:()D
     101: dstore        11
     103: new           #4                  // class enerj/rt/Reference
     106: dup           
     107: dload         11
     109: invokestatic  #46                 // Method java/lang/Double.valueOf:(D)Ljava/lang/Double;
     112: iconst_1      
     113: iconst_1      
     114: invokespecial #5                  // Method enerj/rt/Reference."<init>":(Ljava/lang/Object;ZZ)V
     117: astore        13
     119: getstatic     #2                  // Field enerj/rt/PrecisionRuntimeRoot.impl:Lenerj/rt/PrecisionRuntime;
     122: ldc2_w        #69                 // double 4.296875E-4d
     125: invokestatic  #46                 // Method java/lang/Double.valueOf:(D)Ljava/lang/Double;
     128: iconst_1      
     129: getstatic     #16                 // Field enerj/rt/PrecisionRuntime$MemKind.VARIABLE:Lenerj/rt/PrecisionRuntime$MemKind;
     132: invokeinterface #17,  4           // InterfaceMethod enerj/rt/PrecisionRuntime.storeValue:(Ljava/lang/Object;ZLenerj/rt/PrecisionRuntime$MemKind;)Ljava/lang/Object;
     137: checkcast     #50                 // class java/lang/Double
     140: invokevirtual #51                 // Method java/lang/Double.doubleValue:()D
     143: dstore        14
     145: new           #4                  // class enerj/rt/Reference
     148: dup           
     149: dload         14
     151: invokestatic  #46                 // Method java/lang/Double.valueOf:(D)Ljava/lang/Double;
     154: iconst_1      
     155: iconst_1      
     156: invokespecial #5                  // Method enerj/rt/Reference."<init>":(Ljava/lang/Object;ZZ)V
     159: astore        16
     161: getstatic     #2                  // Field enerj/rt/PrecisionRuntimeRoot.impl:Lenerj/rt/PrecisionRuntime;
     164: aload_2       
     165: iconst_0      
     166: iconst_0      
     167: invokestatic  #20                 // Method java/lang/Integer.valueOf:(I)Ljava/lang/Integer;
     170: invokeinterface #71,  4           // InterfaceMethod enerj/rt/PrecisionRuntime.storeLocal:(Lenerj/rt/Reference;ZLjava/lang/Object;)Ljava/lang/Object;
     175: pop           
     176: getstatic     #2                  // Field enerj/rt/PrecisionRuntimeRoot.impl:Lenerj/rt/PrecisionRuntime;
     179: getstatic     #2                  // Field enerj/rt/PrecisionRuntimeRoot.impl:Lenerj/rt/PrecisionRuntime;
     182: aload_2       
     183: iconst_0      
     184: invokeinterface #9,  3            // InterfaceMethod enerj/rt/PrecisionRuntime.loadLocal:(Lenerj/rt/Reference;Z)Ljava/lang/Object;
     189: checkcast     #22                 // class java/lang/Integer
     192: invokevirtual #23                 // Method java/lang/Integer.intValue:()I
     195: getstatic     #2                  // Field enerj/rt/PrecisionRuntimeRoot.impl:Lenerj/rt/PrecisionRuntime;
     198: aload_0       
     199: ldc           #26                 // String image
     201: iconst_0      
     202: invokeinterface #13,  4           // InterfaceMethod enerj/rt/PrecisionRuntime.loadField:(Ljava/lang/Object;Ljava/lang/String;Z)Ljava/lang/Object;
     207: checkcast     #29                 // class "[[[I"
     210: arraylength   
     211: if_icmpge     218
     214: iconst_1      
     215: goto          219
     218: iconst_0      
     219: invokestatic  #30                 // Method java/lang/Boolean.valueOf:(Z)Ljava/lang/Boolean;
     222: invokeinterface #31,  2           // InterfaceMethod enerj/rt/PrecisionRuntime.countLogicalOp:(Ljava/lang/Object;)Ljava/lang/Object;
     227: checkcast     #32                 // class java/lang/Boolean
     230: invokevirtual #33                 // Method java/lang/Boolean.booleanValue:()Z
     233: ifeq          1196
     236: getstatic     #2                  // Field enerj/rt/PrecisionRuntimeRoot.impl:Lenerj/rt/PrecisionRuntime;
     239: aload         4
     241: iconst_0      
     242: iconst_0      
     243: invokestatic  #20                 // Method java/lang/Integer.valueOf:(I)Ljava/lang/Integer;
     246: invokeinterface #71,  4           // InterfaceMethod enerj/rt/PrecisionRuntime.storeLocal:(Lenerj/rt/Reference;ZLjava/lang/Object;)Ljava/lang/Object;
     251: pop           
     252: getstatic     #2                  // Field enerj/rt/PrecisionRuntimeRoot.impl:Lenerj/rt/PrecisionRuntime;
     255: getstatic     #2                  // Field enerj/rt/PrecisionRuntimeRoot.impl:Lenerj/rt/PrecisionRuntime;
     258: aload         4
     260: iconst_0      
     261: invokeinterface #9,  3            // InterfaceMethod enerj/rt/PrecisionRuntime.loadLocal:(Lenerj/rt/Reference;Z)Ljava/lang/Object;
     266: checkcast     #22                 // class java/lang/Integer
     269: invokevirtual #23                 // Method java/lang/Integer.intValue:()I
     272: getstatic     #2                  // Field enerj/rt/PrecisionRuntimeRoot.impl:Lenerj/rt/PrecisionRuntime;
     275: getstatic     #2                  // Field enerj/rt/PrecisionRuntimeRoot.impl:Lenerj/rt/PrecisionRuntime;
     278: aload_0       
     279: ldc           #26                 // String image
     281: iconst_0      
     282: invokeinterface #13,  4           // InterfaceMethod enerj/rt/PrecisionRuntime.loadField:(Ljava/lang/Object;Ljava/lang/String;Z)Ljava/lang/Object;
     287: getstatic     #2                  // Field enerj/rt/PrecisionRuntimeRoot.impl:Lenerj/rt/PrecisionRuntime;
     290: aload_2       
     291: iconst_0      
     292: invokeinterface #9,  3            // InterfaceMethod enerj/rt/PrecisionRuntime.loadLocal:(Lenerj/rt/Reference;Z)Ljava/lang/Object;
     297: checkcast     #22                 // class java/lang/Integer
     300: invokevirtual #23                 // Method java/lang/Integer.intValue:()I
     303: iconst_0      
     304: invokeinterface #36,  4           // InterfaceMethod enerj/rt/PrecisionRuntime.loadArray:(Ljava/lang/Object;IZ)Ljava/lang/Object;
     309: checkcast     #27                 // class "[[I"
     312: arraylength   
     313: if_icmpge     320
     316: iconst_1      
     317: goto          321
     320: iconst_0      
     321: invokestatic  #30                 // Method java/lang/Boolean.valueOf:(Z)Ljava/lang/Boolean;
     324: invokeinterface #31,  2           // InterfaceMethod enerj/rt/PrecisionRuntime.countLogicalOp:(Ljava/lang/Object;)Ljava/lang/Object;
     329: checkcast     #32                 // class java/lang/Boolean
     332: invokevirtual #33                 // Method java/lang/Boolean.booleanValue:()Z
     335: ifeq          1171
     338: getstatic     #2                  // Field enerj/rt/PrecisionRuntimeRoot.impl:Lenerj/rt/PrecisionRuntime;
     341: aload         7
     343: iconst_1      
     344: getstatic     #2                  // Field enerj/rt/PrecisionRuntimeRoot.impl:Lenerj/rt/PrecisionRuntime;
     347: getstatic     #2                  // Field enerj/rt/PrecisionRuntimeRoot.impl:Lenerj/rt/PrecisionRuntime;
     350: getstatic     #2                  // Field enerj/rt/PrecisionRuntimeRoot.impl:Lenerj/rt/PrecisionRuntime;
     353: getstatic     #2                  // Field enerj/rt/PrecisionRuntimeRoot.impl:Lenerj/rt/PrecisionRuntime;
     356: aload         10
     358: iconst_1      
     359: invokeinterface #9,  3            // InterfaceMethod enerj/rt/PrecisionRuntime.loadLocal:(Lenerj/rt/Reference;Z)Ljava/lang/Object;
     364: checkcast     #50                 // class java/lang/Double
     367: invokevirtual #51                 // Method java/lang/Double.doubleValue:()D
     370: invokestatic  #46                 // Method java/lang/Double.valueOf:(D)Ljava/lang/Double;
     373: getstatic     #2                  // Field enerj/rt/PrecisionRuntimeRoot.impl:Lenerj/rt/PrecisionRuntime;
     376: getstatic     #2                  // Field enerj/rt/PrecisionRuntimeRoot.impl:Lenerj/rt/PrecisionRuntime;
     379: getstatic     #2                  // Field enerj/rt/PrecisionRuntimeRoot.impl:Lenerj/rt/PrecisionRuntime;
     382: getstatic     #2                  // Field enerj/rt/PrecisionRuntimeRoot.impl:Lenerj/rt/PrecisionRuntime;
     385: aload_0       
     386: ldc           #26                 // String image
     388: iconst_0      
     389: invokeinterface #13,  4           // InterfaceMethod enerj/rt/PrecisionRuntime.loadField:(Ljava/lang/Object;Ljava/lang/String;Z)Ljava/lang/Object;
     394: getstatic     #2                  // Field enerj/rt/PrecisionRuntimeRoot.impl:Lenerj/rt/PrecisionRuntime;
     397: aload_2       
     398: iconst_0      
     399: invokeinterface #9,  3            // InterfaceMethod enerj/rt/PrecisionRuntime.loadLocal:(Lenerj/rt/Reference;Z)Ljava/lang/Object;
     404: checkcast     #22                 // class java/lang/Integer
     407: invokevirtual #23                 // Method java/lang/Integer.intValue:()I
     410: iconst_0      
     411: invokeinterface #36,  4           // InterfaceMethod enerj/rt/PrecisionRuntime.loadArray:(Ljava/lang/Object;IZ)Ljava/lang/Object;
     416: getstatic     #2                  // Field enerj/rt/PrecisionRuntimeRoot.impl:Lenerj/rt/PrecisionRuntime;
     419: aload         4
     421: iconst_0      
     422: invokeinterface #9,  3            // InterfaceMethod enerj/rt/PrecisionRuntime.loadLocal:(Lenerj/rt/Reference;Z)Ljava/lang/Object;
     427: checkcast     #22                 // class java/lang/Integer
     430: invokevirtual #23                 // Method java/lang/Integer.intValue:()I
     433: iconst_0      
     434: invokeinterface #36,  4           // InterfaceMethod enerj/rt/PrecisionRuntime.loadArray:(Ljava/lang/Object;IZ)Ljava/lang/Object;
     439: iconst_0      
     440: iconst_1      
     441: invokeinterface #36,  4           // InterfaceMethod enerj/rt/PrecisionRuntime.loadArray:(Ljava/lang/Object;IZ)Ljava/lang/Object;
     446: checkcast     #22                 // class java/lang/Integer
     449: invokevirtual #23                 // Method java/lang/Integer.intValue:()I
     452: invokestatic  #20                 // Method java/lang/Integer.valueOf:(I)Ljava/lang/Integer;
     455: getstatic     #55                 // Field enerj/rt/PrecisionRuntime$ArithOperator.MULTIPLY:Lenerj/rt/PrecisionRuntime$ArithOperator;
     458: getstatic     #48                 // Field enerj/rt/PrecisionRuntime$NumberKind.DOUBLE:Lenerj/rt/PrecisionRuntime$NumberKind;
     461: iconst_1      
     462: invokeinterface #41,  6           // InterfaceMethod enerj/rt/PrecisionRuntime.binaryOp:(Ljava/lang/Number;Ljava/lang/Number;Lenerj/rt/PrecisionRuntime$ArithOperator;Lenerj/rt/PrecisionRuntime$NumberKind;Z)Ljava/lang/Number;
     467: invokevirtual #49                 // Method java/lang/Number.doubleValue:()D
     470: invokestatic  #46                 // Method java/lang/Double.valueOf:(D)Ljava/lang/Double;
     473: getstatic     #2                  // Field enerj/rt/PrecisionRuntimeRoot.impl:Lenerj/rt/PrecisionRuntime;
     476: getstatic     #2                  // Field enerj/rt/PrecisionRuntimeRoot.impl:Lenerj/rt/PrecisionRuntime;
     479: aload         13
     481: iconst_1      
     482: invokeinterface #9,  3            // InterfaceMethod enerj/rt/PrecisionRuntime.loadLocal:(Lenerj/rt/Reference;Z)Ljava/lang/Object;
     487: checkcast     #50                 // class java/lang/Double
     490: invokevirtual #51                 // Method java/lang/Double.doubleValue:()D
     493: invokestatic  #46                 // Method java/lang/Double.valueOf:(D)Ljava/lang/Double;
     496: getstatic     #2                  // Field enerj/rt/PrecisionRuntimeRoot.impl:Lenerj/rt/PrecisionRuntime;
     499: getstatic     #2                  // Field enerj/rt/PrecisionRuntimeRoot.impl:Lenerj/rt/PrecisionRuntime;
     502: getstatic     #2                  // Field enerj/rt/PrecisionRuntimeRoot.impl:Lenerj/rt/PrecisionRuntime;
     505: getstatic     #2                  // Field enerj/rt/PrecisionRuntimeRoot.impl:Lenerj/rt/PrecisionRuntime;
     508: aload_0       
     509: ldc           #26                 // String image
     511: iconst_0      
     512: invokeinterface #13,  4           // InterfaceMethod enerj/rt/PrecisionRuntime.loadField:(Ljava/lang/Object;Ljava/lang/String;Z)Ljava/lang/Object;
     517: getstatic     #2                  // Field enerj/rt/PrecisionRuntimeRoot.impl:Lenerj/rt/PrecisionRuntime;
     520: aload_2       
     521: iconst_0      
     522: invokeinterface #9,  3            // InterfaceMethod enerj/rt/PrecisionRuntime.loadLocal:(Lenerj/rt/Reference;Z)Ljava/lang/Object;
     527: checkcast     #22                 // class java/lang/Integer
     530: invokevirtual #23                 // Method java/lang/Integer.intValue:()I
     533: iconst_0      
     534: invokeinterface #36,  4           // InterfaceMethod enerj/rt/PrecisionRuntime.loadArray:(Ljava/lang/Object;IZ)Ljava/lang/Object;
     539: getstatic     #2                  // Field enerj/rt/PrecisionRuntimeRoot.impl:Lenerj/rt/PrecisionRuntime;
     542: aload         4
     544: iconst_0      
     545: invokeinterface #9,  3            // InterfaceMethod enerj/rt/PrecisionRuntime.loadLocal:(Lenerj/rt/Reference;Z)Ljava/lang/Object;
     550: checkcast     #22                 // class java/lang/Integer
     553: invokevirtual #23                 // Method java/lang/Integer.intValue:()I
     556: iconst_0      
     557: invokeinterface #36,  4           // InterfaceMethod enerj/rt/PrecisionRuntime.loadArray:(Ljava/lang/Object;IZ)Ljava/lang/Object;
     562: iconst_1      
     563: iconst_1      
     564: invokeinterface #36,  4           // InterfaceMethod enerj/rt/PrecisionRuntime.loadArray:(Ljava/lang/Object;IZ)Ljava/lang/Object;
     569: checkcast     #22                 // class java/lang/Integer
     572: invokevirtual #23                 // Method java/lang/Integer.intValue:()I
     575: invokestatic  #20                 // Method java/lang/Integer.valueOf:(I)Ljava/lang/Integer;
     578: getstatic     #55                 // Field enerj/rt/PrecisionRuntime$ArithOperator.MULTIPLY:Lenerj/rt/PrecisionRuntime$ArithOperator;
     581: getstatic     #48                 // Field enerj/rt/PrecisionRuntime$NumberKind.DOUBLE:Lenerj/rt/PrecisionRuntime$NumberKind;
     584: iconst_1      
     585: invokeinterface #41,  6           // InterfaceMethod enerj/rt/PrecisionRuntime.binaryOp:(Ljava/lang/Number;Ljava/lang/Number;Lenerj/rt/PrecisionRuntime$ArithOperator;Lenerj/rt/PrecisionRuntime$NumberKind;Z)Ljava/lang/Number;
     590: invokevirtual #49                 // Method java/lang/Number.doubleValue:()D
     593: invokestatic  #46                 // Method java/lang/Double.valueOf:(D)Ljava/lang/Double;
     596: getstatic     #37                 // Field enerj/rt/PrecisionRuntime$ArithOperator.PLUS:Lenerj/rt/PrecisionRuntime$ArithOperator;
     599: getstatic     #48                 // Field enerj/rt/PrecisionRuntime$NumberKind.DOUBLE:Lenerj/rt/PrecisionRuntime$NumberKind;
     602: iconst_1      
     603: invokeinterface #41,  6           // InterfaceMethod enerj/rt/PrecisionRuntime.binaryOp:(Ljava/lang/Number;Ljava/lang/Number;Lenerj/rt/PrecisionRuntime$ArithOperator;Lenerj/rt/PrecisionRuntime$NumberKind;Z)Ljava/lang/Number;
     608: invokevirtual #49                 // Method java/lang/Number.doubleValue:()D
     611: invokestatic  #46                 // Method java/lang/Double.valueOf:(D)Ljava/lang/Double;
     614: getstatic     #2                  // Field enerj/rt/PrecisionRuntimeRoot.impl:Lenerj/rt/PrecisionRuntime;
     617: getstatic     #2                  // Field enerj/rt/PrecisionRuntimeRoot.impl:Lenerj/rt/PrecisionRuntime;
     620: aload         16
     622: iconst_1      
     623: invokeinterface #9,  3            // InterfaceMethod enerj/rt/PrecisionRuntime.loadLocal:(Lenerj/rt/Reference;Z)Ljava/lang/Object;
     628: checkcast     #50                 // class java/lang/Double
     631: invokevirtual #51                 // Method java/lang/Double.doubleValue:()D
     634: invokestatic  #46                 // Method java/lang/Double.valueOf:(D)Ljava/lang/Double;
     637: getstatic     #2                  // Field enerj/rt/PrecisionRuntimeRoot.impl:Lenerj/rt/PrecisionRuntime;
     640: getstatic     #2                  // Field enerj/rt/PrecisionRuntimeRoot.impl:Lenerj/rt/PrecisionRuntime;
     643: getstatic     #2                  // Field enerj/rt/PrecisionRuntimeRoot.impl:Lenerj/rt/PrecisionRuntime;
     646: getstatic     #2                  // Field enerj/rt/PrecisionRuntimeRoot.impl:Lenerj/rt/PrecisionRuntime;
     649: aload_0       
     650: ldc           #26                 // String image
     652: iconst_0      
     653: invokeinterface #13,  4           // InterfaceMethod enerj/rt/PrecisionRuntime.loadField:(Ljava/lang/Object;Ljava/lang/String;Z)Ljava/lang/Object;
     658: getstatic     #2                  // Field enerj/rt/PrecisionRuntimeRoot.impl:Lenerj/rt/PrecisionRuntime;
     661: aload_2       
     662: iconst_0      
     663: invokeinterface #9,  3            // InterfaceMethod enerj/rt/PrecisionRuntime.loadLocal:(Lenerj/rt/Reference;Z)Ljava/lang/Object;
     668: checkcast     #22                 // class java/lang/Integer
     671: invokevirtual #23                 // Method java/lang/Integer.intValue:()I
     674: iconst_0      
     675: invokeinterface #36,  4           // InterfaceMethod enerj/rt/PrecisionRuntime.loadArray:(Ljava/lang/Object;IZ)Ljava/lang/Object;
     680: getstatic     #2                  // Field enerj/rt/PrecisionRuntimeRoot.impl:Lenerj/rt/PrecisionRuntime;
     683: aload         4
     685: iconst_0      
     686: invokeinterface #9,  3            // InterfaceMethod enerj/rt/PrecisionRuntime.loadLocal:(Lenerj/rt/Reference;Z)Ljava/lang/Object;
     691: checkcast     #22                 // class java/lang/Integer
     694: invokevirtual #23                 // Method java/lang/Integer.intValue:()I
     697: iconst_0      
     698: invokeinterface #36,  4           // InterfaceMethod enerj/rt/PrecisionRuntime.loadArray:(Ljava/lang/Object;IZ)Ljava/lang/Object;
     703: iconst_2      
     704: iconst_1      
     705: invokeinterface #36,  4           // InterfaceMethod enerj/rt/PrecisionRuntime.loadArray:(Ljava/lang/Object;IZ)Ljava/lang/Object;
     710: checkcast     #22                 // class java/lang/Integer
     713: invokevirtual #23                 // Method java/lang/Integer.intValue:()I
     716: invokestatic  #20                 // Method java/lang/Integer.valueOf:(I)Ljava/lang/Integer;
     719: getstatic     #55                 // Field enerj/rt/PrecisionRuntime$ArithOperator.MULTIPLY:Lenerj/rt/PrecisionRuntime$ArithOperator;
     722: getstatic     #48                 // Field enerj/rt/PrecisionRuntime$NumberKind.DOUBLE:Lenerj/rt/PrecisionRuntime$NumberKind;
     725: iconst_1      
     726: invokeinterface #41,  6           // InterfaceMethod enerj/rt/PrecisionRuntime.binaryOp:(Ljava/lang/Number;Ljava/lang/Number;Lenerj/rt/PrecisionRuntime$ArithOperator;Lenerj/rt/PrecisionRuntime$NumberKind;Z)Ljava/lang/Number;
     731: invokevirtual #49                 // Method java/lang/Number.doubleValue:()D
     734: invokestatic  #46                 // Method java/lang/Double.valueOf:(D)Ljava/lang/Double;
     737: getstatic     #37                 // Field enerj/rt/PrecisionRuntime$ArithOperator.PLUS:Lenerj/rt/PrecisionRuntime$ArithOperator;
     740: getstatic     #48                 // Field enerj/rt/PrecisionRuntime$NumberKind.DOUBLE:Lenerj/rt/PrecisionRuntime$NumberKind;
     743: iconst_1      
     744: invokeinterface #41,  6           // InterfaceMethod enerj/rt/PrecisionRuntime.binaryOp:(Ljava/lang/Number;Ljava/lang/Number;Lenerj/rt/PrecisionRuntime$ArithOperator;Lenerj/rt/PrecisionRuntime$NumberKind;Z)Ljava/lang/Number;
     749: invokevirtual #49                 // Method java/lang/Number.doubleValue:()D
     752: invokestatic  #46                 // Method java/lang/Double.valueOf:(D)Ljava/lang/Double;
     755: invokeinterface #71,  4           // InterfaceMethod enerj/rt/PrecisionRuntime.storeLocal:(Lenerj/rt/Reference;ZLjava/lang/Object;)Ljava/lang/Object;
     760: pop           
     761: getstatic     #2                  // Field enerj/rt/PrecisionRuntimeRoot.impl:Lenerj/rt/PrecisionRuntime;
     764: getstatic     #2                  // Field enerj/rt/PrecisionRuntimeRoot.impl:Lenerj/rt/PrecisionRuntime;
     767: getstatic     #2                  // Field enerj/rt/PrecisionRuntimeRoot.impl:Lenerj/rt/PrecisionRuntime;
     770: getstatic     #2                  // Field enerj/rt/PrecisionRuntimeRoot.impl:Lenerj/rt/PrecisionRuntime;
     773: aload_0       
     774: ldc           #26                 // String image
     776: iconst_0      
     777: invokeinterface #13,  4           // InterfaceMethod enerj/rt/PrecisionRuntime.loadField:(Ljava/lang/Object;Ljava/lang/String;Z)Ljava/lang/Object;
     782: getstatic     #2                  // Field enerj/rt/PrecisionRuntimeRoot.impl:Lenerj/rt/PrecisionRuntime;
     785: aload_2       
     786: iconst_0      
     787: invokeinterface #9,  3            // InterfaceMethod enerj/rt/PrecisionRuntime.loadLocal:(Lenerj/rt/Reference;Z)Ljava/lang/Object;
     792: checkcast     #22                 // class java/lang/Integer
     795: invokevirtual #23                 // Method java/lang/Integer.intValue:()I
     798: iconst_0      
     799: invokeinterface #36,  4           // InterfaceMethod enerj/rt/PrecisionRuntime.loadArray:(Ljava/lang/Object;IZ)Ljava/lang/Object;
     804: getstatic     #2                  // Field enerj/rt/PrecisionRuntimeRoot.impl:Lenerj/rt/PrecisionRuntime;
     807: aload         4
     809: iconst_0      
     810: invokeinterface #9,  3            // InterfaceMethod enerj/rt/PrecisionRuntime.loadLocal:(Lenerj/rt/Reference;Z)Ljava/lang/Object;
     815: checkcast     #22                 // class java/lang/Integer
     818: invokevirtual #23                 // Method java/lang/Integer.intValue:()I
     821: iconst_0      
     822: invokeinterface #36,  4           // InterfaceMethod enerj/rt/PrecisionRuntime.loadArray:(Ljava/lang/Object;IZ)Ljava/lang/Object;
     827: iconst_0      
     828: iconst_1      
     829: getstatic     #2                  // Field enerj/rt/PrecisionRuntimeRoot.impl:Lenerj/rt/PrecisionRuntime;
     832: getstatic     #2                  // Field enerj/rt/PrecisionRuntimeRoot.impl:Lenerj/rt/PrecisionRuntime;
     835: aload         7
     837: iconst_1      
     838: invokeinterface #9,  3            // InterfaceMethod enerj/rt/PrecisionRuntime.loadLocal:(Lenerj/rt/Reference;Z)Ljava/lang/Object;
     843: checkcast     #50                 // class java/lang/Double
     846: invokevirtual #51                 // Method java/lang/Double.doubleValue:()D
     849: invokestatic  #46                 // Method java/lang/Double.valueOf:(D)Ljava/lang/Double;
     852: sipush        256
     855: invokestatic  #20                 // Method java/lang/Integer.valueOf:(I)Ljava/lang/Integer;
     858: getstatic     #55                 // Field enerj/rt/PrecisionRuntime$ArithOperator.MULTIPLY:Lenerj/rt/PrecisionRuntime$ArithOperator;
     861: getstatic     #48                 // Field enerj/rt/PrecisionRuntime$NumberKind.DOUBLE:Lenerj/rt/PrecisionRuntime$NumberKind;
     864: iconst_1      
     865: invokeinterface #41,  6           // InterfaceMethod enerj/rt/PrecisionRuntime.binaryOp:(Ljava/lang/Number;Ljava/lang/Number;Lenerj/rt/PrecisionRuntime$ArithOperator;Lenerj/rt/PrecisionRuntime$NumberKind;Z)Ljava/lang/Number;
     870: invokevirtual #49                 // Method java/lang/Number.doubleValue:()D
     873: d2i           
     874: invokestatic  #20                 // Method java/lang/Integer.valueOf:(I)Ljava/lang/Integer;
     877: invokeinterface #35,  5           // InterfaceMethod enerj/rt/PrecisionRuntime.storeArray:(Ljava/lang/Object;IZLjava/lang/Object;)Ljava/lang/Object;
     882: checkcast     #22                 // class java/lang/Integer
     885: invokevirtual #23                 // Method java/lang/Integer.intValue:()I
     888: pop           
     889: getstatic     #2                  // Field enerj/rt/PrecisionRuntimeRoot.impl:Lenerj/rt/PrecisionRuntime;
     892: getstatic     #2                  // Field enerj/rt/PrecisionRuntimeRoot.impl:Lenerj/rt/PrecisionRuntime;
     895: getstatic     #2                  // Field enerj/rt/PrecisionRuntimeRoot.impl:Lenerj/rt/PrecisionRuntime;
     898: getstatic     #2                  // Field enerj/rt/PrecisionRuntimeRoot.impl:Lenerj/rt/PrecisionRuntime;
     901: aload_0       
     902: ldc           #26                 // String image
     904: iconst_0      
     905: invokeinterface #13,  4           // InterfaceMethod enerj/rt/PrecisionRuntime.loadField:(Ljava/lang/Object;Ljava/lang/String;Z)Ljava/lang/Object;
     910: getstatic     #2                  // Field enerj/rt/PrecisionRuntimeRoot.impl:Lenerj/rt/PrecisionRuntime;
     913: aload_2       
     914: iconst_0      
     915: invokeinterface #9,  3            // InterfaceMethod enerj/rt/PrecisionRuntime.loadLocal:(Lenerj/rt/Reference;Z)Ljava/lang/Object;
     920: checkcast     #22                 // class java/lang/Integer
     923: invokevirtual #23                 // Method java/lang/Integer.intValue:()I
     926: iconst_0      
     927: invokeinterface #36,  4           // InterfaceMethod enerj/rt/PrecisionRuntime.loadArray:(Ljava/lang/Object;IZ)Ljava/lang/Object;
     932: getstatic     #2                  // Field enerj/rt/PrecisionRuntimeRoot.impl:Lenerj/rt/PrecisionRuntime;
     935: aload         4
     937: iconst_0      
     938: invokeinterface #9,  3            // InterfaceMethod enerj/rt/PrecisionRuntime.loadLocal:(Lenerj/rt/Reference;Z)Ljava/lang/Object;
     943: checkcast     #22                 // class java/lang/Integer
     946: invokevirtual #23                 // Method java/lang/Integer.intValue:()I
     949: iconst_0      
     950: invokeinterface #36,  4           // InterfaceMethod enerj/rt/PrecisionRuntime.loadArray:(Ljava/lang/Object;IZ)Ljava/lang/Object;
     955: iconst_1      
     956: iconst_1      
     957: getstatic     #2                  // Field enerj/rt/PrecisionRuntimeRoot.impl:Lenerj/rt/PrecisionRuntime;
     960: getstatic     #2                  // Field enerj/rt/PrecisionRuntimeRoot.impl:Lenerj/rt/PrecisionRuntime;
     963: aload         7
     965: iconst_1      
     966: invokeinterface #9,  3            // InterfaceMethod enerj/rt/PrecisionRuntime.loadLocal:(Lenerj/rt/Reference;Z)Ljava/lang/Object;
     971: checkcast     #50                 // class java/lang/Double
     974: invokevirtual #51                 // Method java/lang/Double.doubleValue:()D
     977: invokestatic  #46                 // Method java/lang/Double.valueOf:(D)Ljava/lang/Double;
     980: sipush        256
     983: invokestatic  #20                 // Method java/lang/Integer.valueOf:(I)Ljava/lang/Integer;
     986: getstatic     #55                 // Field enerj/rt/PrecisionRuntime$ArithOperator.MULTIPLY:Lenerj/rt/PrecisionRuntime$ArithOperator;
     989: getstatic     #48                 // Field enerj/rt/PrecisionRuntime$NumberKind.DOUBLE:Lenerj/rt/PrecisionRuntime$NumberKind;
     992: iconst_1      
     993: invokeinterface #41,  6           // InterfaceMethod enerj/rt/PrecisionRuntime.binaryOp:(Ljava/lang/Number;Ljava/lang/Number;Lenerj/rt/PrecisionRuntime$ArithOperator;Lenerj/rt/PrecisionRuntime$NumberKind;Z)Ljava/lang/Number;
     998: invokevirtual #49                 // Method java/lang/Number.doubleValue:()D
    1001: d2i           
    1002: invokestatic  #20                 // Method java/lang/Integer.valueOf:(I)Ljava/lang/Integer;
    1005: invokeinterface #35,  5           // InterfaceMethod enerj/rt/PrecisionRuntime.storeArray:(Ljava/lang/Object;IZLjava/lang/Object;)Ljava/lang/Object;
    1010: checkcast     #22                 // class java/lang/Integer
    1013: invokevirtual #23                 // Method java/lang/Integer.intValue:()I
    1016: pop           
    1017: getstatic     #2                  // Field enerj/rt/PrecisionRuntimeRoot.impl:Lenerj/rt/PrecisionRuntime;
    1020: getstatic     #2                  // Field enerj/rt/PrecisionRuntimeRoot.impl:Lenerj/rt/PrecisionRuntime;
    1023: getstatic     #2                  // Field enerj/rt/PrecisionRuntimeRoot.impl:Lenerj/rt/PrecisionRuntime;
    1026: getstatic     #2                  // Field enerj/rt/PrecisionRuntimeRoot.impl:Lenerj/rt/PrecisionRuntime;
    1029: aload_0       
    1030: ldc           #26                 // String image
    1032: iconst_0      
    1033: invokeinterface #13,  4           // InterfaceMethod enerj/rt/PrecisionRuntime.loadField:(Ljava/lang/Object;Ljava/lang/String;Z)Ljava/lang/Object;
    1038: getstatic     #2                  // Field enerj/rt/PrecisionRuntimeRoot.impl:Lenerj/rt/PrecisionRuntime;
    1041: aload_2       
    1042: iconst_0      
    1043: invokeinterface #9,  3            // InterfaceMethod enerj/rt/PrecisionRuntime.loadLocal:(Lenerj/rt/Reference;Z)Ljava/lang/Object;
    1048: checkcast     #22                 // class java/lang/Integer
    1051: invokevirtual #23                 // Method java/lang/Integer.intValue:()I
    1054: iconst_0      
    1055: invokeinterface #36,  4           // InterfaceMethod enerj/rt/PrecisionRuntime.loadArray:(Ljava/lang/Object;IZ)Ljava/lang/Object;
    1060: getstatic     #2                  // Field enerj/rt/PrecisionRuntimeRoot.impl:Lenerj/rt/PrecisionRuntime;
    1063: aload         4
    1065: iconst_0      
    1066: invokeinterface #9,  3            // InterfaceMethod enerj/rt/PrecisionRuntime.loadLocal:(Lenerj/rt/Reference;Z)Ljava/lang/Object;
    1071: checkcast     #22                 // class java/lang/Integer
    1074: invokevirtual #23                 // Method java/lang/Integer.intValue:()I
    1077: iconst_0      
    1078: invokeinterface #36,  4           // InterfaceMethod enerj/rt/PrecisionRuntime.loadArray:(Ljava/lang/Object;IZ)Ljava/lang/Object;
    1083: iconst_2      
    1084: iconst_1      
    1085: getstatic     #2                  // Field enerj/rt/PrecisionRuntimeRoot.impl:Lenerj/rt/PrecisionRuntime;
    1088: getstatic     #2                  // Field enerj/rt/PrecisionRuntimeRoot.impl:Lenerj/rt/PrecisionRuntime;
    1091: aload         7
    1093: iconst_1      
    1094: invokeinterface #9,  3            // InterfaceMethod enerj/rt/PrecisionRuntime.loadLocal:(Lenerj/rt/Reference;Z)Ljava/lang/Object;
    1099: checkcast     #50                 // class java/lang/Double
    1102: invokevirtual #51                 // Method java/lang/Double.doubleValue:()D
    1105: invokestatic  #46                 // Method java/lang/Double.valueOf:(D)Ljava/lang/Double;
    1108: sipush        256
    1111: invokestatic  #20                 // Method java/lang/Integer.valueOf:(I)Ljava/lang/Integer;
    1114: getstatic     #55                 // Field enerj/rt/PrecisionRuntime$ArithOperator.MULTIPLY:Lenerj/rt/PrecisionRuntime$ArithOperator;
    1117: getstatic     #48                 // Field enerj/rt/PrecisionRuntime$NumberKind.DOUBLE:Lenerj/rt/PrecisionRuntime$NumberKind;
    1120: iconst_1      
    1121: invokeinterface #41,  6           // InterfaceMethod enerj/rt/PrecisionRuntime.binaryOp:(Ljava/lang/Number;Ljava/lang/Number;Lenerj/rt/PrecisionRuntime$ArithOperator;Lenerj/rt/PrecisionRuntime$NumberKind;Z)Ljava/lang/Number;
    1126: invokevirtual #49                 // Method java/lang/Number.doubleValue:()D
    1129: d2i           
    1130: invokestatic  #20                 // Method java/lang/Integer.valueOf:(I)Ljava/lang/Integer;
    1133: invokeinterface #35,  5           // InterfaceMethod enerj/rt/PrecisionRuntime.storeArray:(Ljava/lang/Object;IZLjava/lang/Object;)Ljava/lang/Object;
    1138: checkcast     #22                 // class java/lang/Integer
    1141: invokevirtual #23                 // Method java/lang/Integer.intValue:()I
    1144: pop           
    1145: getstatic     #2                  // Field enerj/rt/PrecisionRuntimeRoot.impl:Lenerj/rt/PrecisionRuntime;
    1148: aload         4
    1150: getstatic     #37                 // Field enerj/rt/PrecisionRuntime$ArithOperator.PLUS:Lenerj/rt/PrecisionRuntime$ArithOperator;
    1153: iconst_1      
    1154: invokestatic  #20                 // Method java/lang/Integer.valueOf:(I)Ljava/lang/Integer;
    1157: iconst_1      
    1158: getstatic     #38                 // Field enerj/rt/PrecisionRuntime$NumberKind.INT:Lenerj/rt/PrecisionRuntime$NumberKind;
    1161: iconst_0      
    1162: invokeinterface #39,  7           // InterfaceMethod enerj/rt/PrecisionRuntime.assignopLocal:(Lenerj/rt/Reference;Lenerj/rt/PrecisionRuntime$ArithOperator;Ljava/lang/Number;ZLenerj/rt/PrecisionRuntime$NumberKind;Z)Ljava/lang/Number;
    1167: pop           
    1168: goto          252
    1171: getstatic     #2                  // Field enerj/rt/PrecisionRuntimeRoot.impl:Lenerj/rt/PrecisionRuntime;
    1174: aload_2       
    1175: getstatic     #37                 // Field enerj/rt/PrecisionRuntime$ArithOperator.PLUS:Lenerj/rt/PrecisionRuntime$ArithOperator;
    1178: iconst_1      
    1179: invokestatic  #20                 // Method java/lang/Integer.valueOf:(I)Ljava/lang/Integer;
    1182: iconst_1      
    1183: getstatic     #38                 // Field enerj/rt/PrecisionRuntime$NumberKind.INT:Lenerj/rt/PrecisionRuntime$NumberKind;
    1186: iconst_0      
    1187: invokeinterface #39,  7           // InterfaceMethod enerj/rt/PrecisionRuntime.assignopLocal:(Lenerj/rt/Reference;Lenerj/rt/PrecisionRuntime$ArithOperator;Ljava/lang/Number;ZLenerj/rt/PrecisionRuntime$NumberKind;Z)Ljava/lang/Number;
    1192: pop           
    1193: goto          176
    1196: return        

  public static void main(java.lang.String[]) throws java.io.IOException;
    Code:
       0: new           #4                  // class enerj/rt/Reference
       3: dup           
       4: aload_0       
       5: iconst_0      
       6: iconst_0      
       7: invokespecial #5                  // Method enerj/rt/Reference."<init>":(Ljava/lang/Object;ZZ)V
      10: astore_1      
      11: getstatic     #2                  // Field enerj/rt/PrecisionRuntimeRoot.impl:Lenerj/rt/PrecisionRuntime;
      14: getstatic     #2                  // Field enerj/rt/PrecisionRuntimeRoot.impl:Lenerj/rt/PrecisionRuntime;
      17: getstatic     #2                  // Field enerj/rt/PrecisionRuntimeRoot.impl:Lenerj/rt/PrecisionRuntime;
      20: invokestatic  #6                  // Method java/lang/Thread.currentThread:()Ljava/lang/Thread;
      23: iconst_0      
      24: bipush        16
      26: iconst_0      
      27: invokeinterface #7,  5            // InterfaceMethod enerj/rt/PrecisionRuntime.beforeCreation:(Ljava/lang/Object;ZII)Z
      32: new           #72                 // class Sobel/RgbImage
      35: dup           
      36: invokespecial #73                 // Method "<init>":()V
      39: invokestatic  #6                  // Method java/lang/Thread.currentThread:()Ljava/lang/Thread;
      42: invokeinterface #15,  4           // InterfaceMethod enerj/rt/PrecisionRuntime.wrappedNew:(ZLjava/lang/Object;Ljava/lang/Object;)Ljava/lang/Object;
      47: iconst_0      
      48: getstatic     #16                 // Field enerj/rt/PrecisionRuntime$MemKind.VARIABLE:Lenerj/rt/PrecisionRuntime$MemKind;
      51: invokeinterface #17,  4           // InterfaceMethod enerj/rt/PrecisionRuntime.storeValue:(Ljava/lang/Object;ZLenerj/rt/PrecisionRuntime$MemKind;)Ljava/lang/Object;
      56: checkcast     #72                 // class Sobel/RgbImage
      59: astore_2      
      60: new           #4                  // class enerj/rt/Reference
      63: dup           
      64: aload_2       
      65: iconst_0      
      66: iconst_0      
      67: invokespecial #5                  // Method enerj/rt/Reference."<init>":(Ljava/lang/Object;ZZ)V
      70: astore_3      
      71: getstatic     #2                  // Field enerj/rt/PrecisionRuntimeRoot.impl:Lenerj/rt/PrecisionRuntime;
      74: aload_3       
      75: iconst_0      
      76: invokeinterface #9,  3            // InterfaceMethod enerj/rt/PrecisionRuntime.loadLocal:(Lenerj/rt/Reference;Z)Ljava/lang/Object;
      81: checkcast     #72                 // class Sobel/RgbImage
      84: getstatic     #2                  // Field enerj/rt/PrecisionRuntimeRoot.impl:Lenerj/rt/PrecisionRuntime;
      87: getstatic     #2                  // Field enerj/rt/PrecisionRuntimeRoot.impl:Lenerj/rt/PrecisionRuntime;
      90: aload_1       
      91: iconst_0      
      92: invokeinterface #9,  3            // InterfaceMethod enerj/rt/PrecisionRuntime.loadLocal:(Lenerj/rt/Reference;Z)Ljava/lang/Object;
      97: iconst_0      
      98: iconst_0      
      99: invokeinterface #36,  4           // InterfaceMethod enerj/rt/PrecisionRuntime.loadArray:(Ljava/lang/Object;IZ)Ljava/lang/Object;
     104: checkcast     #10                 // class java/lang/String
     107: invokevirtual #74                 // Method load:(Ljava/lang/String;)V
     110: getstatic     #2                  // Field enerj/rt/PrecisionRuntimeRoot.impl:Lenerj/rt/PrecisionRuntime;
     113: aload_3       
     114: iconst_0      
     115: invokeinterface #9,  3            // InterfaceMethod enerj/rt/PrecisionRuntime.loadLocal:(Lenerj/rt/Reference;Z)Ljava/lang/Object;
     120: checkcast     #72                 // class Sobel/RgbImage
     123: invokevirtual #75                 // Method makeGrayscale:()V
     126: getstatic     #2                  // Field enerj/rt/PrecisionRuntimeRoot.impl:Lenerj/rt/PrecisionRuntime;
     129: getstatic     #2                  // Field enerj/rt/PrecisionRuntimeRoot.impl:Lenerj/rt/PrecisionRuntime;
     132: iconst_3      
     133: iconst_3      
     134: iconst_3      
     135: multianewarray #29,  3            // class "[[[I"
     139: iconst_3      
     140: iconst_1      
     141: iconst_0      
     142: iconst_4      
     143: invokeinterface #28,  6           // InterfaceMethod enerj/rt/PrecisionRuntime.newArray:(Ljava/lang/Object;IZII)Ljava/lang/Object;
     148: iconst_0      
     149: getstatic     #16                 // Field enerj/rt/PrecisionRuntime$MemKind.VARIABLE:Lenerj/rt/PrecisionRuntime$MemKind;
     152: invokeinterface #17,  4           // InterfaceMethod enerj/rt/PrecisionRuntime.storeValue:(Ljava/lang/Object;ZLenerj/rt/PrecisionRuntime$MemKind;)Ljava/lang/Object;
     157: checkcast     #29                 // class "[[[I"
     160: checkcast     #29                 // class "[[[I"
     163: astore        4
     165: new           #4                  // class enerj/rt/Reference
     168: dup           
     169: aload         4
     171: iconst_0      
     172: iconst_0      
     173: invokespecial #5                  // Method enerj/rt/Reference."<init>":(Ljava/lang/Object;ZZ)V
     176: astore        5
     178: new           #4                  // class enerj/rt/Reference
     181: dup           
     182: aconst_null   
     183: iconst_1      
     184: iconst_1      
     185: invokespecial #5                  // Method enerj/rt/Reference."<init>":(Ljava/lang/Object;ZZ)V
     188: astore        8
     190: getstatic     #2                  // Field enerj/rt/PrecisionRuntimeRoot.impl:Lenerj/rt/PrecisionRuntime;
     193: iconst_0      
     194: invokestatic  #20                 // Method java/lang/Integer.valueOf:(I)Ljava/lang/Integer;
     197: iconst_0      
     198: getstatic     #16                 // Field enerj/rt/PrecisionRuntime$MemKind.VARIABLE:Lenerj/rt/PrecisionRuntime$MemKind;
     201: invokeinterface #17,  4           // InterfaceMethod enerj/rt/PrecisionRuntime.storeValue:(Ljava/lang/Object;ZLenerj/rt/PrecisionRuntime$MemKind;)Ljava/lang/Object;
     206: checkcast     #22                 // class java/lang/Integer
     209: invokevirtual #23                 // Method java/lang/Integer.intValue:()I
     212: istore        9
     214: new           #4                  // class enerj/rt/Reference
     217: dup           
     218: iload         9
     220: invokestatic  #20                 // Method java/lang/Integer.valueOf:(I)Ljava/lang/Integer;
     223: iconst_0      
     224: iconst_1      
     225: invokespecial #5                  // Method enerj/rt/Reference."<init>":(Ljava/lang/Object;ZZ)V
     228: astore        10
     230: getstatic     #2                  // Field enerj/rt/PrecisionRuntimeRoot.impl:Lenerj/rt/PrecisionRuntime;
     233: getstatic     #2                  // Field enerj/rt/PrecisionRuntimeRoot.impl:Lenerj/rt/PrecisionRuntime;
     236: aload         10
     238: iconst_0      
     239: invokeinterface #9,  3            // InterfaceMethod enerj/rt/PrecisionRuntime.loadLocal:(Lenerj/rt/Reference;Z)Ljava/lang/Object;
     244: checkcast     #22                 // class java/lang/Integer
     247: invokevirtual #23                 // Method java/lang/Integer.intValue:()I
     250: getstatic     #2                  // Field enerj/rt/PrecisionRuntimeRoot.impl:Lenerj/rt/PrecisionRuntime;
     253: aload_3       
     254: iconst_0      
     255: invokeinterface #9,  3            // InterfaceMethod enerj/rt/PrecisionRuntime.loadLocal:(Lenerj/rt/Reference;Z)Ljava/lang/Object;
     260: checkcast     #72                 // class Sobel/RgbImage
     263: getfield      #76                 // Field height:I
     266: if_icmpge     273
     269: iconst_1      
     270: goto          274
     273: iconst_0      
     274: invokestatic  #30                 // Method java/lang/Boolean.valueOf:(Z)Ljava/lang/Boolean;
     277: invokeinterface #31,  2           // InterfaceMethod enerj/rt/PrecisionRuntime.countLogicalOp:(Ljava/lang/Object;)Ljava/lang/Object;
     282: checkcast     #32                 // class java/lang/Boolean
     285: invokevirtual #33                 // Method java/lang/Boolean.booleanValue:()Z
     288: ifeq          777
     291: getstatic     #2                  // Field enerj/rt/PrecisionRuntimeRoot.impl:Lenerj/rt/PrecisionRuntime;
     294: iconst_0      
     295: invokestatic  #20                 // Method java/lang/Integer.valueOf:(I)Ljava/lang/Integer;
     298: iconst_0      
     299: getstatic     #16                 // Field enerj/rt/PrecisionRuntime$MemKind.VARIABLE:Lenerj/rt/PrecisionRuntime$MemKind;
     302: invokeinterface #17,  4           // InterfaceMethod enerj/rt/PrecisionRuntime.storeValue:(Ljava/lang/Object;ZLenerj/rt/PrecisionRuntime$MemKind;)Ljava/lang/Object;
     307: checkcast     #22                 // class java/lang/Integer
     310: invokevirtual #23                 // Method java/lang/Integer.intValue:()I
     313: istore        11
     315: new           #4                  // class enerj/rt/Reference
     318: dup           
     319: iload         11
     321: invokestatic  #20                 // Method java/lang/Integer.valueOf:(I)Ljava/lang/Integer;
     324: iconst_0      
     325: iconst_1      
     326: invokespecial #5                  // Method enerj/rt/Reference."<init>":(Ljava/lang/Object;ZZ)V
     329: astore        12
     331: getstatic     #2                  // Field enerj/rt/PrecisionRuntimeRoot.impl:Lenerj/rt/PrecisionRuntime;
     334: getstatic     #2                  // Field enerj/rt/PrecisionRuntimeRoot.impl:Lenerj/rt/PrecisionRuntime;
     337: aload         12
     339: iconst_0      
     340: invokeinterface #9,  3            // InterfaceMethod enerj/rt/PrecisionRuntime.loadLocal:(Lenerj/rt/Reference;Z)Ljava/lang/Object;
     345: checkcast     #22                 // class java/lang/Integer
     348: invokevirtual #23                 // Method java/lang/Integer.intValue:()I
     351: getstatic     #2                  // Field enerj/rt/PrecisionRuntimeRoot.impl:Lenerj/rt/PrecisionRuntime;
     354: aload_3       
     355: iconst_0      
     356: invokeinterface #9,  3            // InterfaceMethod enerj/rt/PrecisionRuntime.loadLocal:(Lenerj/rt/Reference;Z)Ljava/lang/Object;
     361: checkcast     #72                 // class Sobel/RgbImage
     364: getfield      #77                 // Field width:I
     367: if_icmpge     374
     370: iconst_1      
     371: goto          375
     374: iconst_0      
     375: invokestatic  #30                 // Method java/lang/Boolean.valueOf:(Z)Ljava/lang/Boolean;
     378: invokeinterface #31,  2           // InterfaceMethod enerj/rt/PrecisionRuntime.countLogicalOp:(Ljava/lang/Object;)Ljava/lang/Object;
     383: checkcast     #32                 // class java/lang/Boolean
     386: invokevirtual #33                 // Method java/lang/Boolean.booleanValue:()Z
     389: ifeq          751
     392: getstatic     #2                  // Field enerj/rt/PrecisionRuntimeRoot.impl:Lenerj/rt/PrecisionRuntime;
     395: aload_3       
     396: iconst_0      
     397: invokeinterface #9,  3            // InterfaceMethod enerj/rt/PrecisionRuntime.loadLocal:(Lenerj/rt/Reference;Z)Ljava/lang/Object;
     402: checkcast     #72                 // class Sobel/RgbImage
     405: getstatic     #2                  // Field enerj/rt/PrecisionRuntimeRoot.impl:Lenerj/rt/PrecisionRuntime;
     408: aload         12
     410: iconst_0      
     411: invokeinterface #9,  3            // InterfaceMethod enerj/rt/PrecisionRuntime.loadLocal:(Lenerj/rt/Reference;Z)Ljava/lang/Object;
     416: checkcast     #22                 // class java/lang/Integer
     419: invokevirtual #23                 // Method java/lang/Integer.intValue:()I
     422: getstatic     #2                  // Field enerj/rt/PrecisionRuntimeRoot.impl:Lenerj/rt/PrecisionRuntime;
     425: aload         10
     427: iconst_0      
     428: invokeinterface #9,  3            // InterfaceMethod enerj/rt/PrecisionRuntime.loadLocal:(Lenerj/rt/Reference;Z)Ljava/lang/Object;
     433: checkcast     #22                 // class java/lang/Integer
     436: invokevirtual #23                 // Method java/lang/Integer.intValue:()I
     439: getstatic     #2                  // Field enerj/rt/PrecisionRuntimeRoot.impl:Lenerj/rt/PrecisionRuntime;
     442: aload         5
     444: iconst_0      
     445: invokeinterface #9,  3            // InterfaceMethod enerj/rt/PrecisionRuntime.loadLocal:(Lenerj/rt/Reference;Z)Ljava/lang/Object;
     450: checkcast     #29                 // class "[[[I"
     453: invokevirtual #78                 // Method slideWindow:(II[[[I)V
     456: getstatic     #2                  // Field enerj/rt/PrecisionRuntimeRoot.impl:Lenerj/rt/PrecisionRuntime;
     459: aload         8
     461: iconst_1      
     462: getstatic     #2                  // Field enerj/rt/PrecisionRuntimeRoot.impl:Lenerj/rt/PrecisionRuntime;
     465: aload_3       
     466: iconst_0      
     467: invokeinterface #9,  3            // InterfaceMethod enerj/rt/PrecisionRuntime.loadLocal:(Lenerj/rt/Reference;Z)Ljava/lang/Object;
     472: checkcast     #72                 // class Sobel/RgbImage
     475: getstatic     #2                  // Field enerj/rt/PrecisionRuntimeRoot.impl:Lenerj/rt/PrecisionRuntime;
     478: aload         5
     480: iconst_0      
     481: invokeinterface #9,  3            // InterfaceMethod enerj/rt/PrecisionRuntime.loadLocal:(Lenerj/rt/Reference;Z)Ljava/lang/Object;
     486: checkcast     #29                 // class "[[[I"
     489: invokevirtual #79                 // Method sobel:([[[I)D
     492: invokestatic  #46                 // Method java/lang/Double.valueOf:(D)Ljava/lang/Double;
     495: invokeinterface #71,  4           // InterfaceMethod enerj/rt/PrecisionRuntime.storeLocal:(Lenerj/rt/Reference;ZLjava/lang/Object;)Ljava/lang/Object;
     500: pop           
     501: getstatic     #2                  // Field enerj/rt/PrecisionRuntimeRoot.impl:Lenerj/rt/PrecisionRuntime;
     504: getstatic     #2                  // Field enerj/rt/PrecisionRuntimeRoot.impl:Lenerj/rt/PrecisionRuntime;
     507: aload         8
     509: iconst_1      
     510: invokeinterface #9,  3            // InterfaceMethod enerj/rt/PrecisionRuntime.loadLocal:(Lenerj/rt/Reference;Z)Ljava/lang/Object;
     515: checkcast     #50                 // class java/lang/Double
     518: invokevirtual #51                 // Method java/lang/Double.doubleValue:()D
     521: invokestatic  #52                 // Method enerj/lang/Endorsements.endorse:(D)D
     524: d2i           
     525: invokestatic  #20                 // Method java/lang/Integer.valueOf:(I)Ljava/lang/Integer;
     528: iconst_0      
     529: getstatic     #16                 // Field enerj/rt/PrecisionRuntime$MemKind.VARIABLE:Lenerj/rt/PrecisionRuntime$MemKind;
     532: invokeinterface #17,  4           // InterfaceMethod enerj/rt/PrecisionRuntime.storeValue:(Ljava/lang/Object;ZLenerj/rt/PrecisionRuntime$MemKind;)Ljava/lang/Object;
     537: checkcast     #22                 // class java/lang/Integer
     540: invokevirtual #23                 // Method java/lang/Integer.intValue:()I
     543: istore        13
     545: new           #4                  // class enerj/rt/Reference
     548: dup           
     549: iload         13
     551: invokestatic  #20                 // Method java/lang/Integer.valueOf:(I)Ljava/lang/Integer;
     554: iconst_0      
     555: iconst_1      
     556: invokespecial #5                  // Method enerj/rt/Reference."<init>":(Ljava/lang/Object;ZZ)V
     559: astore        14
     561: getstatic     #2                  // Field enerj/rt/PrecisionRuntimeRoot.impl:Lenerj/rt/PrecisionRuntime;
     564: getstatic     #2                  // Field enerj/rt/PrecisionRuntimeRoot.impl:Lenerj/rt/PrecisionRuntime;
     567: aload         14
     569: iconst_0      
     570: invokeinterface #9,  3            // InterfaceMethod enerj/rt/PrecisionRuntime.loadLocal:(Lenerj/rt/Reference;Z)Ljava/lang/Object;
     575: checkcast     #22                 // class java/lang/Integer
     578: invokevirtual #23                 // Method java/lang/Integer.intValue:()I
     581: sipush        256
     584: if_icmplt     591
     587: iconst_1      
     588: goto          592
     591: iconst_0      
     592: invokestatic  #30                 // Method java/lang/Boolean.valueOf:(Z)Ljava/lang/Boolean;
     595: invokeinterface #31,  2           // InterfaceMethod enerj/rt/PrecisionRuntime.countLogicalOp:(Ljava/lang/Object;)Ljava/lang/Object;
     600: checkcast     #32                 // class java/lang/Boolean
     603: invokevirtual #33                 // Method java/lang/Boolean.booleanValue:()Z
     606: ifeq          627
     609: getstatic     #2                  // Field enerj/rt/PrecisionRuntimeRoot.impl:Lenerj/rt/PrecisionRuntime;
     612: aload         14
     614: iconst_0      
     615: sipush        255
     618: invokestatic  #20                 // Method java/lang/Integer.valueOf:(I)Ljava/lang/Integer;
     621: invokeinterface #71,  4           // InterfaceMethod enerj/rt/PrecisionRuntime.storeLocal:(Lenerj/rt/Reference;ZLjava/lang/Object;)Ljava/lang/Object;
     626: pop           
     627: getstatic     #2                  // Field enerj/rt/PrecisionRuntimeRoot.impl:Lenerj/rt/PrecisionRuntime;
     630: getstatic     #2                  // Field enerj/rt/PrecisionRuntimeRoot.impl:Lenerj/rt/PrecisionRuntime;
     633: aload         14
     635: iconst_0      
     636: invokeinterface #9,  3            // InterfaceMethod enerj/rt/PrecisionRuntime.loadLocal:(Lenerj/rt/Reference;Z)Ljava/lang/Object;
     641: checkcast     #22                 // class java/lang/Integer
     644: invokevirtual #23                 // Method java/lang/Integer.intValue:()I
     647: ifge          654
     650: iconst_1      
     651: goto          655
     654: iconst_0      
     655: invokestatic  #30                 // Method java/lang/Boolean.valueOf:(Z)Ljava/lang/Boolean;
     658: invokeinterface #31,  2           // InterfaceMethod enerj/rt/PrecisionRuntime.countLogicalOp:(Ljava/lang/Object;)Ljava/lang/Object;
     663: checkcast     #32                 // class java/lang/Boolean
     666: invokevirtual #33                 // Method java/lang/Boolean.booleanValue:()Z
     669: ifeq          688
     672: getstatic     #2                  // Field enerj/rt/PrecisionRuntimeRoot.impl:Lenerj/rt/PrecisionRuntime;
     675: aload         14
     677: iconst_0      
     678: iconst_0      
     679: invokestatic  #20                 // Method java/lang/Integer.valueOf:(I)Ljava/lang/Integer;
     682: invokeinterface #71,  4           // InterfaceMethod enerj/rt/PrecisionRuntime.storeLocal:(Lenerj/rt/Reference;ZLjava/lang/Object;)Ljava/lang/Object;
     687: pop           
     688: getstatic     #2                  // Field enerj/rt/PrecisionRuntimeRoot.impl:Lenerj/rt/PrecisionRuntime;
     691: ldc_w         #80                 // class java/lang/System
     694: ldc           #81                 // String out
     696: iconst_0      
     697: invokeinterface #13,  4           // InterfaceMethod enerj/rt/PrecisionRuntime.loadField:(Ljava/lang/Object;Ljava/lang/String;Z)Ljava/lang/Object;
     702: checkcast     #82                 // class java/io/PrintStream
     705: getstatic     #2                  // Field enerj/rt/PrecisionRuntimeRoot.impl:Lenerj/rt/PrecisionRuntime;
     708: aload         14
     710: iconst_0      
     711: invokeinterface #9,  3            // InterfaceMethod enerj/rt/PrecisionRuntime.loadLocal:(Lenerj/rt/Reference;Z)Ljava/lang/Object;
     716: checkcast     #22                 // class java/lang/Integer
     719: invokevirtual #23                 // Method java/lang/Integer.intValue:()I
     722: invokevirtual #83                 // Method java/io/PrintStream.println:(I)V
     725: getstatic     #2                  // Field enerj/rt/PrecisionRuntimeRoot.impl:Lenerj/rt/PrecisionRuntime;
     728: aload         12
     730: getstatic     #37                 // Field enerj/rt/PrecisionRuntime$ArithOperator.PLUS:Lenerj/rt/PrecisionRuntime$ArithOperator;
     733: iconst_1      
     734: invokestatic  #20                 // Method java/lang/Integer.valueOf:(I)Ljava/lang/Integer;
     737: iconst_1      
     738: getstatic     #38                 // Field enerj/rt/PrecisionRuntime$NumberKind.INT:Lenerj/rt/PrecisionRuntime$NumberKind;
     741: iconst_0      
     742: invokeinterface #39,  7           // InterfaceMethod enerj/rt/PrecisionRuntime.assignopLocal:(Lenerj/rt/Reference;Lenerj/rt/PrecisionRuntime$ArithOperator;Ljava/lang/Number;ZLenerj/rt/PrecisionRuntime$NumberKind;Z)Ljava/lang/Number;
     747: pop           
     748: goto          331
     751: getstatic     #2                  // Field enerj/rt/PrecisionRuntimeRoot.impl:Lenerj/rt/PrecisionRuntime;
     754: aload         10
     756: getstatic     #37                 // Field enerj/rt/PrecisionRuntime$ArithOperator.PLUS:Lenerj/rt/PrecisionRuntime$ArithOperator;
     759: iconst_1      
     760: invokestatic  #20                 // Method java/lang/Integer.valueOf:(I)Ljava/lang/Integer;
     763: iconst_1      
     764: getstatic     #38                 // Field enerj/rt/PrecisionRuntime$NumberKind.INT:Lenerj/rt/PrecisionRuntime$NumberKind;
     767: iconst_0      
     768: invokeinterface #39,  7           // InterfaceMethod enerj/rt/PrecisionRuntime.assignopLocal:(Lenerj/rt/Reference;Lenerj/rt/PrecisionRuntime$ArithOperator;Ljava/lang/Number;ZLenerj/rt/PrecisionRuntime$NumberKind;Z)Ljava/lang/Number;
     773: pop           
     774: goto          230
     777: return        
}
